{
  "type": "Feature",
  "properties": {
    "gn:admin1_code":"44",
    "gn:asciiname":"Tafani",
    "gn:country_code":"AL",
    "gn:dem":102,
    "gn:feature_class":"P",
    "gn:feature_code":"PPL",
    "gn:name":"Tafani",
    "gn:population":0,
    "gn:timezone":"Europe/Tirane",
    "iso:country":"AL",
    "wof:name":"Tafani",
    "wof:placetype":"locality"
},
  "geometry": {"coordinates":[19.7725,40.98194],"type":"Point"}
}