{
  "type": "Feature",
  "properties": {
    "gn:admin1_code":"44",
    "gn:asciiname":"Mermucaj",
    "gn:cc2":"AL",
    "gn:country_code":"AL",
    "gn:dem":269,
    "gn:feature_class":"P",
    "gn:feature_code":"PPL",
    "gn:name":"Mermu\u00e7aj",
    "gn:population":0,
    "gn:timezone":"Europe/Tirane",
    "iso:country":"AL",
    "name:und_x_variant":[
        "Memu\u00e7aj"
    ],
    "wof:name":"Mermucaj",
    "wof:placetype":"locality"
},
  "geometry": {"coordinates":[19.83333,40.48333],"type":"Point"}
}