{
  "type": "Feature",
  "properties": {
    "gn:admin1_code":"49",
    "gn:asciiname":"Dheu i Lehte",
    "gn:cc2":"AL",
    "gn:country_code":"AL",
    "gn:dem":13,
    "gn:feature_class":"P",
    "gn:feature_code":"PPL",
    "gn:name":"Dheu i Leht\u00eb",
    "gn:population":0,
    "gn:timezone":"Europe/Tirane",
    "iso:country":"AL",
    "name:und_x_variant":[
        "Dheulet",
        "Dhe i Let",
        "Dheu i Let",
        "Dheu i Leht\u00eb"
    ],
    "wof:name":"Dheu i Lehte",
    "wof:placetype":"locality"
},
  "geometry": {"coordinates":[19.60806,41.95556],"type":"Point"}
}