{
  "type": "Feature",
  "properties": {
    "gn:admin1_code":"40",
    "gn:asciiname":"Bregu-Leckes",
    "gn:country_code":"AL",
    "gn:dem":308,
    "gn:feature_class":"P",
    "gn:feature_code":"PPL",
    "gn:name":"Bregu-Leck\u00ebs",
    "gn:population":0,
    "gn:timezone":"Europe/Tirane",
    "iso:country":"AL",
    "wof:name":"Bregu-Leckes",
    "wof:placetype":"locality"
},
  "geometry": {"coordinates":[20.00444,40.87639],"type":"Point"}
}