{
  "type": "Feature",
  "properties": {
    "gn:admin1_code":"49",
    "gn:asciiname":"Gojan",
    "gn:cc2":"AL",
    "gn:country_code":"AL",
    "gn:dem":102,
    "gn:feature_class":"P",
    "gn:feature_code":"PPL",
    "gn:name":"Gojan",
    "gn:population":0,
    "gn:timezone":"Europe/Tirane",
    "iso:country":"AL",
    "name:und_x_variant":[
        "Ura Hozh\u00ebs",
        "Gojani",
        "Gojan"
    ],
    "wof:name":"Gojan",
    "wof:placetype":"locality"
},
  "geometry": {"coordinates":[19.69778,42.02028],"type":"Point"}
}