{
  "type": "Feature",
  "properties": {
    "gn:admin1_code":"42",
    "gn:asciiname":"Bize",
    "gn:cc2":"AL",
    "gn:country_code":"AL",
    "gn:dem":167,
    "gn:feature_class":"P",
    "gn:feature_code":"PPL",
    "gn:name":"Biz\u00eb",
    "gn:population":0,
    "gn:timezone":"Europe/Tirane",
    "iso:country":"AL",
    "name:arg_x_preferred":[
        "Bize"
    ],
    "name:ceb_x_preferred":[
        "Bize"
    ],
    "name:deu_x_preferred":[
        "Bize"
    ],
    "name:fra_x_preferred":[
        "Bize"
    ],
    "name:hye_x_preferred":[
        "\u0532\u056b\u0566"
    ],
    "name:ita_x_preferred":[
        "Bize"
    ],
    "name:kaz_x_preferred":[
        "\u0411\u0456\u0437"
    ],
    "name:nds_x_preferred":[
        "Bize"
    ],
    "name:nld_x_preferred":[
        "Bize"
    ],
    "name:oci_x_preferred":[
        "Bize"
    ],
    "name:pms_x_preferred":[
        "Bize"
    ],
    "name:pol_x_preferred":[
        "Bize"
    ],
    "name:por_x_preferred":[
        "Bize"
    ],
    "name:rus_x_preferred":[
        "\u0411\u0438\u0437"
    ],
    "name:scn_x_preferred":[
        "Bize"
    ],
    "name:slk_x_preferred":[
        "Bize"
    ],
    "name:spa_x_preferred":[
        "Bize"
    ],
    "name:srp_x_preferred":[
        "\u0411\u0438\u0437"
    ],
    "name:swe_x_preferred":[
        "Bize"
    ],
    "name:ukr_x_preferred":[
        "\u0411\u0456\u0437"
    ],
    "name:und_x_variant":[
        "Biz",
        "Biza",
        "Biz\u00eb"
    ],
    "wof:name":"Bize",
    "wof:placetype":"locality"
},
  "geometry": {"coordinates":[19.54722000000001,41.55583],"type":"Point"}
}