{
  "type": "Feature",
  "properties": {
    "gn:admin1_code":"42",
    "gn:asciiname":"Bize",
    "gn:cc2":"AL",
    "gn:country_code":"AL",
    "gn:dem":167,
    "gn:feature_class":"P",
    "gn:feature_code":"PPL",
    "gn:name":"Biz\u00eb",
    "gn:population":0,
    "gn:timezone":"Europe/Tirane",
    "iso:country":"AL",
    "name:und_x_variant":[
        "Biz",
        "Biza",
        "Biz\u00eb"
    ],
    "wof:name":"Bize",
    "wof:placetype":"locality"
},
  "geometry": {"coordinates":[19.54722000000001,41.55583],"type":"Point"}
}