{
  "type": "Feature",
  "properties": {
    "gn:admin1_code":"51",
    "gn:asciiname":"Treblove",
    "gn:cc2":"AL",
    "gn:country_code":"AL",
    "gn:dem":414,
    "gn:feature_class":"P",
    "gn:feature_code":"PPL",
    "gn:name":"Treblov\u00eb",
    "gn:population":0,
    "gn:timezone":"Europe/Tirane",
    "iso:country":"AL",
    "name:und_x_variant":[
        "Trehlov\u00eb",
        "Treblova",
        "Treblov\u00eb"
    ],
    "wof:name":"Treblove",
    "wof:placetype":"locality"
},
  "geometry": {"coordinates":[19.64028,40.48333],"type":"Point"}
}