{
  "type": "Feature",
  "properties": {
    "gn:admin1_code":"40",
    "gn:asciiname":"Mecaj",
    "gn:country_code":"AL",
    "gn:dem":649,
    "gn:feature_class":"P",
    "gn:feature_code":"PPL",
    "gn:name":"Me\u00e7aj",
    "gn:population":0,
    "gn:timezone":"Europe/Tirane",
    "iso:country":"AL",
    "wof:name":"Mecaj",
    "wof:placetype":"locality"
},
  "geometry": {"coordinates":[20.08417,40.50861],"type":"Point"}
}