{
  "type": "Feature",
  "properties": {
    "gn:admin1_code":"44",
    "gn:asciiname":"Mertikaj",
    "gn:country_code":"AL",
    "gn:dem":7,
    "gn:feature_class":"P",
    "gn:feature_code":"PPL",
    "gn:name":"Mertikaj",
    "gn:population":0,
    "gn:timezone":"Europe/Tirane",
    "iso:country":"AL",
    "wof:name":"Mertikaj",
    "wof:placetype":"locality"
},
  "geometry": {"coordinates":[19.625,40.81],"type":"Point"}
}