{
  "type": "Feature",
  "properties": {
    "gn:admin1_code":"44",
    "gn:asciiname":"Agacaj",
    "gn:country_code":"AL",
    "gn:dem":12,
    "gn:feature_class":"P",
    "gn:feature_code":"PPL",
    "gn:name":"Aga\u00e7aj",
    "gn:population":0,
    "gn:timezone":"Europe/Tirane",
    "iso:country":"AL",
    "wof:name":"Agacaj",
    "wof:placetype":"locality"
},
  "geometry": {"coordinates":[19.69806,40.77778],"type":"Point"}
}