{
  "type": "Feature",
  "properties": {
    "gn:admin1_code":"43",
    "gn:asciiname":"Vilan",
    "gn:cc2":"AL",
    "gn:country_code":"AL",
    "gn:dem":1064,
    "gn:feature_class":"P",
    "gn:feature_code":"PPL",
    "gn:name":"Vilan",
    "gn:population":0,
    "gn:timezone":"Europe/Tirane",
    "iso:country":"AL",
    "name:und_x_variant":[
        "Vilani",
        "Vilan"
    ],
    "wof:name":"Vilan",
    "wof:placetype":"locality"
},
  "geometry": {"coordinates":[20.27639,41.08389],"type":"Point"}
}