{
  "type": "Feature",
  "properties": {
    "gn:admin1_code":"43",
    "gn:asciiname":"Vilan",
    "gn:cc2":"AL",
    "gn:country_code":"AL",
    "gn:dem":1064,
    "gn:feature_class":"P",
    "gn:feature_code":"PPL",
    "gn:name":"Vilan",
    "gn:population":0,
    "gn:timezone":"Europe/Tirane",
    "iso:country":"AL",
    "name:ara_x_preferred":[
        "\u0641\u064a\u0644\u0627\u0646"
    ],
    "name:ceb_x_preferred":[
        "Vilan"
    ],
    "name:deu_x_preferred":[
        "Vilan"
    ],
    "name:kat_x_preferred":[
        "\u10d5\u10d8\u10da\u10d0\u10dc\u10d8"
    ],
    "name:nno_x_preferred":[
        "Vilan"
    ],
    "name:pol_x_preferred":[
        "Vilan"
    ],
    "name:swe_x_preferred":[
        "Vilan"
    ],
    "name:und_x_variant":[
        "Vilani"
    ],
    "wof:name":"Vilan",
    "wof:placetype":"locality"
},
  "geometry": {"coordinates":[20.27639,41.08389],"type":"Point"}
}