{
  "type": "Feature",
  "properties": {
    "gn:admin1_code":"43",
    "gn:asciiname":"Garunje",
    "gn:cc2":"AL",
    "gn:country_code":"AL",
    "gn:dem":355,
    "gn:feature_class":"P",
    "gn:feature_code":"PPL",
    "gn:name":"Garunj\u00eb",
    "gn:population":0,
    "gn:timezone":"Europe/Tirane",
    "iso:country":"AL",
    "name:und_x_variant":[
        "Garruja",
        "Garunja e vog\u00ebl",
        "Garujis",
        "Garunja"
    ],
    "wof:name":"Garunje",
    "wof:placetype":"locality"
},
  "geometry": {"coordinates":[19.86667000000001,41.11667],"type":"Point"}
}