{
  "type": "Feature",
  "properties": {
    "gn:admin1_code":"46",
    "gn:admin2_code":"8.0",
    "gn:asciiname":"Mollas",
    "gn:cc2":"AL",
    "gn:country_code":"AL",
    "gn:dem":969,
    "gn:feature_class":"P",
    "gn:feature_code":"PPLA3",
    "gn:name":"Mollas",
    "gn:population":0,
    "gn:timezone":"Europe/Tirane",
    "iso:country":"AL",
    "name:ita_x_preferred":[
        "Mollas"
    ],
    "name:mkd_x_preferred":[
        "\u041c\u0438\u043b\u0435\u0447"
    ],
    "name:msa_x_preferred":[
        "Mollas"
    ],
    "name:pol_x_preferred":[
        "Gmina Mollas"
    ],
    "name:por_x_preferred":[
        "Mollas"
    ],
    "name:tur_x_preferred":[
        "Mollas"
    ],
    "name:und_x_variant":[
        "Mollasi",
        "Mollas"
    ],
    "name:vie_x_preferred":[
        "Mollas"
    ],
    "name:war_x_preferred":[
        "Mollas"
    ],
    "wof:name":"Mollas",
    "wof:placetype":"locality"
},
  "geometry": {"coordinates":[20.67444,40.42556],"type":"Point"}
}