{
  "type": "Feature",
  "properties": {
    "gn:admin1_code":"49",
    "gn:asciiname":"Kreneshdol",
    "gn:country_code":"AL",
    "gn:dem":1175,
    "gn:feature_class":"P",
    "gn:feature_code":"PPL",
    "gn:name":"Kreneshdol",
    "gn:population":0,
    "gn:timezone":"Europe/Tirane",
    "iso:country":"AL",
    "wof:name":"Kreneshdol",
    "wof:placetype":"locality"
},
  "geometry": {"coordinates":[19.555,42.36111],"type":"Point"}
}