{
  "type": "Feature",
  "properties": {
    "gn:admin1_code":"51",
    "gn:asciiname":"Gumenice",
    "gn:cc2":"AL",
    "gn:country_code":"AL",
    "gn:dem":375,
    "gn:feature_class":"P",
    "gn:feature_code":"PPL",
    "gn:name":"Gumenic\u00eb",
    "gn:population":0,
    "gn:timezone":"Europe/Tirane",
    "iso:country":"AL",
    "name:und_x_variant":[
        "Gomenitsa",
        "Gumenica",
        "Gomenizza",
        "Gumenic\u00eb"
    ],
    "wof:name":"Gumenice",
    "wof:placetype":"locality"
},
  "geometry": {"coordinates":[19.60556,40.34139],"type":"Point"}
}