{
  "type": "Feature",
  "properties": {
    "gn:admin1_code":"48",
    "gn:asciiname":"Rrushkull",
    "gn:cc2":"AL",
    "gn:country_code":"AL",
    "gn:dem":241,
    "gn:feature_class":"P",
    "gn:feature_code":"PPL",
    "gn:name":"Rrushkull",
    "gn:population":0,
    "gn:timezone":"Europe/Tirane",
    "iso:country":"AL",
    "name:und_x_variant":[
        "Rrushkulli",
        "Rrushkull"
    ],
    "wof:name":"Rrushkull",
    "wof:placetype":"locality"
},
  "geometry": {"coordinates":[19.90861,41.72861],"type":"Point"}
}