{
  "type": "Feature",
  "properties": {
    "gn:admin1_code":"44",
    "gn:asciiname":"Salaj",
    "gn:cc2":"AL",
    "gn:country_code":"AL",
    "gn:dem":377,
    "gn:feature_class":"P",
    "gn:feature_code":"PPL",
    "gn:name":"Salaj",
    "gn:population":0,
    "gn:timezone":"Europe/Tirane",
    "iso:country":"AL",
    "name:und_x_variant":[
        "Hoxhaj",
        "Salaj"
    ],
    "wof:name":"Salaj",
    "wof:placetype":"locality"
},
  "geometry": {"coordinates":[19.78722,40.62556],"type":"Point"}
}