{
  "type": "Feature",
  "properties": {
    "gn:admin1_code":"46",
    "gn:asciiname":"Radimisht",
    "gn:cc2":"AL",
    "gn:country_code":"AL",
    "gn:dem":884,
    "gn:feature_class":"P",
    "gn:feature_code":"PPL",
    "gn:name":"Radimisht",
    "gn:population":0,
    "gn:timezone":"Europe/Tirane",
    "iso:country":"AL",
    "name:sqi_x_preferred":[
        "Radimisht"
    ],
    "name:und_x_variant":[
        "Radomisht",
        "Radimishti",
        "Radimishta",
        "Radimisht\u00eb",
        "Radimisht"
    ],
    "wof:name":"Radimisht",
    "wof:placetype":"locality"
},
  "geometry": {"coordinates":[20.56833,40.26194],"type":"Point"}
}