{
  "type": "Feature",
  "properties": {
    "gn:country":"AL",
    "gn:fcode":"PPL",
    "gn:population":5,
    "iso:country":"AL",
    "qs:name":"Llang\u00eb",
    "qs:photos_9r":0,
    "qs:photos_sr":0,
    "qs:pop_sr":"1",
    "wof:name":"Llang\u00eb",
    "wof:placetype":"locality",
    "wof:population":5
},
  "geometry": {"coordinates":[20.35222,41.26139],"type":"Point"}
}