{
  "type": "Feature",
  "properties": {
    "gn:admin1_code":"51",
    "gn:admin2_code":"20.0",
    "gn:asciiname":"Aliko",
    "gn:cc2":"AL",
    "gn:country_code":"AL",
    "gn:dem":33,
    "gn:feature_class":"P",
    "gn:feature_code":"PPLA3",
    "gn:name":"Aliko",
    "gn:population":0,
    "gn:timezone":"Europe/Tirane",
    "iso:country":"AL",
    "name:ell_x_preferred":[
        "\u0391\u03bb\u03cd\u03ba\u03bf"
    ],
    "name:fas_x_preferred":[
        "\u0627\u0644\u06cc\u06a9\u0648"
    ],
    "name:ita_x_preferred":[
        "Aliko"
    ],
    "name:msa_x_preferred":[
        "Aliko"
    ],
    "name:pol_x_preferred":[
        "Aliko"
    ],
    "name:por_x_preferred":[
        "Aliko"
    ],
    "name:tur_x_preferred":[
        "Aliko"
    ],
    "name:und_x_variant":[
        "Alikoj\u00eb",
        "Alikaj",
        "Alikon",
        "Alikoja",
        "Alicu"
    ],
    "name:vie_x_preferred":[
        "Aliko"
    ],
    "name:war_x_preferred":[
        "Aliko"
    ],
    "wof:name":"Aliko",
    "wof:placetype":"locality"
},
  "geometry": {"coordinates":[20.07917,39.85861],"type":"Point"}
}