{
  "type": "Feature",
  "properties": {
    "gn:admin1_code":"51",
    "gn:admin2_code":"20.0",
    "gn:asciiname":"Aliko",
    "gn:cc2":"AL",
    "gn:country_code":"AL",
    "gn:dem":33,
    "gn:feature_class":"P",
    "gn:feature_code":"PPLA3",
    "gn:name":"Aliko",
    "gn:population":0,
    "gn:timezone":"Europe/Tirane",
    "iso:country":"AL",
    "name:und_x_variant":[
        "Alikoj\u00eb",
        "Alikaj",
        "Alikon",
        "Alikoja",
        "Alicu",
        "Aliko"
    ],
    "wof:name":"Aliko",
    "wof:placetype":"locality"
},
  "geometry": {"coordinates":[20.07917,39.85861],"type":"Point"}
}