{
  "type": "Feature",
  "properties": {
    "gn:admin1_code":"49",
    "gn:asciiname":"Gropat e Selces",
    "gn:country_code":"AL",
    "gn:dem":1114,
    "gn:feature_class":"P",
    "gn:feature_code":"PPL",
    "gn:name":"Gropat e Selc\u00ebs",
    "gn:population":0,
    "gn:timezone":"Europe/Tirane",
    "iso:country":"AL",
    "name:und_x_variant":[
        "Gropat e Selc\u00ebs"
    ],
    "wof:name":"Gropat e Selces",
    "wof:placetype":"locality"
},
  "geometry": {"coordinates":[19.69056,42.53778],"type":"Point"}
}