{
  "type": "Feature",
  "properties": {
    "gn:admin1_code":"41",
    "gn:asciiname":"Val",
    "gn:cc2":"AL",
    "gn:country_code":"AL",
    "gn:dem":990,
    "gn:feature_class":"P",
    "gn:feature_code":"PPL",
    "gn:name":"Val",
    "gn:population":0,
    "gn:timezone":"Europe/Tirane",
    "iso:country":"AL",
    "name:ceb_x_preferred":[
        "Val"
    ],
    "name:ces_x_preferred":[
        "Val"
    ],
    "name:fas_x_preferred":[
        "\u0648\u0644"
    ],
    "name:fra_x_preferred":[
        "Val"
    ],
    "name:glg_x_preferred":[
        "Val"
    ],
    "name:jpn_x_preferred":[
        "Val"
    ],
    "name:nld_x_preferred":[
        "Val"
    ],
    "name:pol_x_preferred":[
        "Val"
    ],
    "name:por_x_preferred":[
        "Val"
    ],
    "name:rus_x_preferred":[
        "\u0412\u044d\u043b"
    ],
    "name:slk_x_preferred":[
        "Val"
    ],
    "name:slv_x_preferred":[
        "Val"
    ],
    "name:swe_x_preferred":[
        "Val"
    ],
    "name:und_x_variant":[
        "Val\u00eb",
        "Vali"
    ],
    "name:zho_x_preferred":[
        "Val"
    ],
    "wof:name":"Val",
    "wof:placetype":"locality"
},
  "geometry": {"coordinates":[20.16111,41.40278],"type":"Point"}
}