{
  "type": "Feature",
  "properties": {
    "gn:admin1_code":"41",
    "gn:asciiname":"Val",
    "gn:cc2":"AL",
    "gn:country_code":"AL",
    "gn:dem":990,
    "gn:feature_class":"P",
    "gn:feature_code":"PPL",
    "gn:name":"Val",
    "gn:population":0,
    "gn:timezone":"Europe/Tirane",
    "iso:country":"AL",
    "name:und_x_variant":[
        "Val\u00eb",
        "Vali",
        "Val"
    ],
    "wof:name":"Val",
    "wof:placetype":"locality"
},
  "geometry": {"coordinates":[20.16111,41.40278],"type":"Point"}
}