{
  "type": "Feature",
  "properties": {
    "gn:admin1_code":"45",
    "gn:asciiname":"Beduqas",
    "gn:cc2":"AL",
    "gn:country_code":"AL",
    "gn:dem":251,
    "gn:feature_class":"P",
    "gn:feature_code":"PPL",
    "gn:name":"Beduqas",
    "gn:population":0,
    "gn:timezone":"Europe/Tirane",
    "iso:country":"AL",
    "name:und_x_variant":[
        "Bedyqasi",
        "Bedyqas",
        "Beduqas"
    ],
    "wof:name":"Beduqas",
    "wof:placetype":"locality"
},
  "geometry": {"coordinates":[20.18472,40.32972],"type":"Point"}
}