{
  "type": "Feature",
  "properties": {
    "gn:admin1_code":"46",
    "gn:asciiname":"Dishnice",
    "gn:cc2":"AL",
    "gn:country_code":"AL",
    "gn:dem":877,
    "gn:feature_class":"P",
    "gn:feature_code":"PPLA3",
    "gn:name":"Dishnic\u00eb",
    "gn:population":0,
    "gn:timezone":"Europe/Tirane",
    "iso:country":"AL",
    "name:und_x_variant":[
        "Tishnica",
        "Dishnica",
        "Deshnica",
        "Dishnic\u00eb"
    ],
    "wof:name":"Dishnice",
    "wof:placetype":"locality"
},
  "geometry": {"coordinates":[20.81361,40.65139],"type":"Point"}
}