{
  "type": "Feature",
  "properties": {
    "gn:admin1_code":"51",
    "gn:asciiname":"Dukati i Ri",
    "gn:cc2":"AL",
    "gn:country_code":"AL",
    "gn:dem":148,
    "gn:feature_class":"P",
    "gn:feature_code":"PPL",
    "gn:name":"Dukati i Ri",
    "gn:population":0,
    "gn:timezone":"Europe/Tirane",
    "iso:country":"AL",
    "name:und_x_variant":[
        "Dukat i Ri",
        "Dukati i Ri"
    ],
    "wof:name":"Dukati i Ri",
    "wof:placetype":"locality"
},
  "geometry": {"coordinates":[19.50694,40.27111],"type":"Point"}
}