{
  "type": "Feature",
  "properties": {
    "gn:admin1_code":"41",
    "gn:asciiname":"Gjergas",
    "gn:cc2":"AL",
    "gn:country_code":"AL",
    "gn:dem":475,
    "gn:feature_class":"P",
    "gn:feature_code":"PPL",
    "gn:name":"Gjergas",
    "gn:population":0,
    "gn:timezone":"Europe/Tirane",
    "iso:country":"AL",
    "name:und_x_variant":[
        "Gjergasi",
        "Gjergas"
    ],
    "wof:name":"Gjergas",
    "wof:placetype":"locality"
},
  "geometry": {"coordinates":[19.89361,41.60417],"type":"Point"}
}