{
  "type": "Feature",
  "properties": {
    "gn:admin1_code":"51",
    "gn:asciiname":"Pirg",
    "gn:country_code":"AL",
    "gn:dem":545,
    "gn:feature_class":"P",
    "gn:feature_code":"PPL",
    "gn:name":"Pirg",
    "gn:population":0,
    "gn:timezone":"Europe/Tirane",
    "iso:country":"AL",
    "name:ita_x_preferred":[
        "Pirg"
    ],
    "name:msa_x_preferred":[
        "Pirg"
    ],
    "name:pol_x_preferred":[
        "Gmina Pirg"
    ],
    "name:por_x_preferred":[
        "Pirg"
    ],
    "name:spa_x_preferred":[
        "Pirg"
    ],
    "name:tur_x_preferred":[
        "Pirg"
    ],
    "name:und_x_variant":[
        "Pirgu",
        "Pirg"
    ],
    "name:vie_x_preferred":[
        "Pirg"
    ],
    "name:war_x_preferred":[
        "Pirg"
    ],
    "wof:name":"Pirg",
    "wof:placetype":"locality"
},
  "geometry": {"coordinates":[19.62639,40.25],"type":"Point"}
}