{
  "type": "Feature",
  "properties": {
    "gn:admin1_code":"46",
    "gn:asciiname":"Qinam-Radovicke",
    "gn:cc2":"AL",
    "gn:country_code":"AL",
    "gn:dem":783,
    "gn:feature_class":"P",
    "gn:feature_code":"PPL",
    "gn:name":"Qinam-Radovick\u00eb",
    "gn:population":0,
    "gn:timezone":"Europe/Tirane",
    "iso:country":"AL",
    "name:und_x_variant":[
        "Qinam-Radovicka",
        "Qinam i Radovick\u00ebs",
        "Qinami i Radovick\u00ebs",
        "Qinam-Radovick\u00eb"
    ],
    "wof:name":"Qinam-Radovicke",
    "wof:placetype":"locality"
},
  "geometry": {"coordinates":[20.49028,40.40889],"type":"Point"}
}