{
  "type": "Feature",
  "properties": {
    "gn:admin1_code":"47",
    "gn:asciiname":"Lushaj",
    "gn:cc2":"AL",
    "gn:country_code":"AL",
    "gn:dem":1057,
    "gn:feature_class":"P",
    "gn:feature_code":"PPL",
    "gn:name":"Lushaj",
    "gn:population":0,
    "gn:timezone":"Europe/Tirane",
    "iso:country":"AL",
    "name:und_x_variant":[
        "Llugaj",
        "Lukai",
        "Lukaj",
        "Lluga",
        "Lushaj"
    ],
    "wof:name":"Lushaj",
    "wof:placetype":"locality"
},
  "geometry": {"coordinates":[20.19361,42.44306],"type":"Point"}
}