{
  "type": "Feature",
  "properties": {
    "gn:admin1_code":"44",
    "gn:asciiname":"Xhaferrapaj",
    "gn:country_code":"AL",
    "gn:dem":360,
    "gn:feature_class":"P",
    "gn:feature_code":"PPL",
    "gn:name":"Xhaferrapaj",
    "gn:population":0,
    "gn:timezone":"Europe/Tirane",
    "iso:country":"AL",
    "wof:name":"Xhaferrapaj",
    "wof:placetype":"locality"
},
  "geometry": {"coordinates":[19.81639,40.5775],"type":"Point"}
}