{
  "type": "Feature",
  "properties": {
    "gn:admin1_code":"47",
    "gn:asciiname":"San Sula",
    "gn:cc2":"AL",
    "gn:country_code":"AL",
    "gn:dem":523,
    "gn:feature_class":"P",
    "gn:feature_code":"PPL",
    "gn:name":"San Sula",
    "gn:population":0,
    "gn:timezone":"Europe/Tirane",
    "iso:country":"AL",
    "name:und_x_variant":[
        "San Sulja"
    ],
    "wof:name":"San Sula",
    "wof:placetype":"locality"
},
  "geometry": {"coordinates":[20.45,42.11667],"type":"Point"}
}