{
  "type": "Feature",
  "properties": {
    "gn:admin1_code":"47",
    "gn:asciiname":"Mazrek",
    "gn:cc2":"AL",
    "gn:country_code":"AL",
    "gn:dem":349,
    "gn:feature_class":"P",
    "gn:feature_code":"PPL",
    "gn:name":"Mazrek",
    "gn:population":0,
    "gn:timezone":"Europe/Tirane",
    "iso:country":"AL",
    "name:ceb_x_preferred":[
        "Mazrek"
    ],
    "name:sqi_x_preferred":[
        "Mazrek"
    ],
    "name:swe_x_preferred":[
        "Mazrek"
    ],
    "name:und_x_variant":[
        "Mazreku"
    ],
    "wof:name":"Mazrek",
    "wof:placetype":"locality"
},
  "geometry": {"coordinates":[20.36806,42.18944000000001],"type":"Point"}
}