{
  "type": "Feature",
  "properties": {
    "gn:admin1_code":"49",
    "gn:asciiname":"Samrisht",
    "gn:cc2":"AL",
    "gn:country_code":"AL",
    "gn:dem":4,
    "gn:feature_class":"P",
    "gn:feature_code":"PPL",
    "gn:name":"Samrisht",
    "gn:population":0,
    "gn:timezone":"Europe/Tirane",
    "iso:country":"AL",
    "name:und_x_variant":[
        "Samrishi",
        "Samric",
        "Samrish",
        "Samrisht\u2019 i Sip\u00ebrm\u00eb",
        "Samrishti",
        "Samrisht i Sip\u00ebrm",
        "Samrish i Sip\u00ebrm",
        "Samrishi i Siper",
        "Samerishti i Sip\u00ebrme",
        "Samrishti i Sip\u00ebrm",
        "Samarisht",
        "Samrishti i Sip\u00ebrm\u00eb",
        "Samrisht"
    ],
    "wof:name":"Samrisht",
    "wof:placetype":"locality"
},
  "geometry": {"coordinates":[19.39778,42.00222],"type":"Point"}
}