{
  "type": "Feature",
  "properties": {
    "gn:admin1_code":"44",
    "gn:asciiname":"Likaj",
    "gn:country_code":"AL",
    "gn:dem":14,
    "gn:feature_class":"P",
    "gn:feature_code":"PPL",
    "gn:name":"Likaj",
    "gn:population":0,
    "gn:timezone":"Europe/Tirane",
    "iso:country":"AL",
    "wof:name":"Likaj",
    "wof:placetype":"locality"
},
  "geometry": {"coordinates":[19.73583,40.85111],"type":"Point"}
}