{
  "type": "Feature",
  "properties": {
    "gn:admin1_code":"44",
    "gn:asciiname":"Povelce",
    "gn:cc2":"AL",
    "gn:country_code":"AL",
    "gn:dem":1,
    "gn:feature_class":"P",
    "gn:feature_code":"PPL",
    "gn:name":"Povel\u00e7e",
    "gn:population":0,
    "gn:timezone":"Europe/Tirane",
    "iso:country":"AL",
    "name:und_x_variant":[
        "N. B. Povel\u00e7\u00eb",
        "Povel\u00e7e"
    ],
    "wof:name":"Povelce",
    "wof:placetype":"locality"
},
  "geometry": {"coordinates":[19.42083,40.72889],"type":"Point"}
}