{
  "type": "Feature",
  "properties": {
    "gn:admin1_code":"42",
    "gn:asciiname":"Virjon",
    "gn:cc2":"AL",
    "gn:country_code":"AL",
    "gn:dem":137,
    "gn:feature_class":"P",
    "gn:feature_code":"PPL",
    "gn:name":"Virjon",
    "gn:population":0,
    "gn:timezone":"Europe/Tirane",
    "iso:country":"AL",
    "name:und_x_variant":[
        "Verjon",
        "Verjani",
        "Verjan",
        "Virion",
        "Virjoni",
        "Virjon"
    ],
    "wof:name":"Virjon",
    "wof:placetype":"locality"
},
  "geometry": {"coordinates":[19.78611,41.4525],"type":"Point"}
}