{
  "type": "Feature",
  "properties": {
    "gn:admin1_code":"50",
    "gn:asciiname":"Kumbardhe",
    "gn:cc2":"AL",
    "gn:country_code":"AL",
    "gn:dem":1009,
    "gn:feature_class":"P",
    "gn:feature_code":"PPL",
    "gn:name":"Kumbardh\u00eb",
    "gn:population":0,
    "gn:timezone":"Europe/Tirane",
    "iso:country":"AL",
    "name:und_x_variant":[
        "Kumarza"
    ],
    "wof:name":"Kumbardhe",
    "wof:placetype":"locality"
},
  "geometry": {"coordinates":[19.85,41.45],"type":"Point"}
}