{
  "type": "Feature",
  "properties": {
    "gn:admin1_code":"40",
    "gn:asciiname":"Gostencke",
    "gn:cc2":"AL",
    "gn:country_code":"AL",
    "gn:dem":990,
    "gn:feature_class":"P",
    "gn:feature_code":"PPL",
    "gn:name":"Gostenck\u00eb",
    "gn:population":0,
    "gn:timezone":"Europe/Tirane",
    "iso:country":"AL",
    "name:und_x_variant":[
        "Gostencka",
        "Gostanzca",
        "Gostinck\u00eb",
        "Gostenska",
        "Gostenck\u00eb"
    ],
    "wof:name":"Gostencke",
    "wof:placetype":"locality"
},
  "geometry": {"coordinates":[20.31806,40.54972],"type":"Point"}
}