{
  "type": "Feature",
  "properties": {
    "gn:country":"AL",
    "gn:fcode":"PPL",
    "gn:population":5,
    "iso:country":"AL",
    "name:und_x_variant":[
        "Okshtun i Vog\u00ebl"
    ],
    "qs:name":"Okshtuni i Vog\u00ebl",
    "qs:photos_9r":0,
    "qs:photos_sr":0,
    "qs:pop_sr":"1",
    "wof:name":"Okshtuni i Vog\u00ebl",
    "wof:placetype":"locality",
    "wof:population":5
},
  "geometry": {"coordinates":[20.3475,41.38528],"type":"Point"}
}