{
  "type": "Feature",
  "properties": {
    "gn:admin1_code":"49",
    "gn:asciiname":"Plezhe",
    "gn:cc2":"AL",
    "gn:country_code":"AL",
    "gn:dem":16,
    "gn:feature_class":"P",
    "gn:feature_code":"PPL",
    "gn:name":"Plezh\u00eb",
    "gn:population":0,
    "gn:timezone":"Europe/Tirane",
    "iso:country":"AL",
    "name:und_x_variant":[
        "Plezha",
        "Plesh\u00eb",
        "Ple\u0161 e Zadrims",
        "Plesha",
        "Plesh e Zadrim\u00ebs",
        "Plezh\u00eb"
    ],
    "wof:name":"Plezhe",
    "wof:placetype":"locality"
},
  "geometry": {"coordinates":[19.55389,41.96972],"type":"Point"}
}