{
  "type": "Feature",
  "properties": {
    "gn:admin1_code":"51",
    "gn:asciiname":"Gjashte",
    "gn:cc2":"AL",
    "gn:country_code":"AL",
    "gn:dem":132,
    "gn:feature_class":"P",
    "gn:feature_code":"PPL",
    "gn:name":"Gjasht\u00eb",
    "gn:population":0,
    "gn:timezone":"Europe/Tirane",
    "iso:country":"AL",
    "name:und_x_variant":[
        "Gjastha",
        "Metogjashta",
        "Gjiashte",
        "Gjashta",
        "Giasta",
        "Gjasht\u00eb"
    ],
    "wof:name":"Gjashte",
    "wof:placetype":"locality"
},
  "geometry": {"coordinates":[20.025,39.87472],"type":"Point"}
}