{
  "type": "Feature",
  "properties": {
    "gn:admin1_code":"47",
    "gn:asciiname":"Dobrune",
    "gn:cc2":"AL",
    "gn:country_code":"AL",
    "gn:dem":667,
    "gn:feature_class":"P",
    "gn:feature_code":"PPL",
    "gn:name":"Dobrun\u00eb",
    "gn:population":0,
    "gn:timezone":"Europe/Tirane",
    "iso:country":"AL",
    "name:und_x_variant":[
        "Dobruna",
        "Dobrunna",
        "Dobrun\u00eb"
    ],
    "wof:name":"Dobrune",
    "wof:placetype":"locality"
},
  "geometry": {"coordinates":[20.4225,42.27139],"type":"Point"}
}