{
  "type": "Feature",
  "properties": {
    "gn:admin1_code":"45",
    "gn:asciiname":"Kurtjez",
    "gn:cc2":"AL",
    "gn:country_code":"AL",
    "gn:dem":509,
    "gn:feature_class":"P",
    "gn:feature_code":"PPL",
    "gn:name":"Kurtjez",
    "gn:population":0,
    "gn:timezone":"Europe/Tirane",
    "iso:country":"AL",
    "name:und_x_variant":[
        "Kurtez\u00eb",
        "Kurtic\u00eb",
        "Kurtez",
        "Kurtjeza",
        "Kurteza",
        "Kurtezi",
        "Kurtjez"
    ],
    "wof:name":"Kurtjez",
    "wof:placetype":"locality"
},
  "geometry": {"coordinates":[20.01806,40.42667],"type":"Point"}
}