{
  "type": "Feature",
  "properties": {
    "gn:admin1_code":"43",
    "gn:asciiname":"Lubinje",
    "gn:cc2":"AL",
    "gn:country_code":"AL",
    "gn:dem":500,
    "gn:feature_class":"P",
    "gn:feature_code":"PPL",
    "gn:name":"Lubinj\u00eb",
    "gn:population":0,
    "gn:timezone":"Europe/Tirane",
    "iso:country":"AL",
    "name:und_x_variant":[
        "Murriza",
        "Lubinja",
        "Lubin",
        "Lubinj\u00eb"
    ],
    "wof:name":"Lubinje",
    "wof:placetype":"locality"
},
  "geometry": {"coordinates":[20.13833,40.85833],"type":"Point"}
}