{
  "type": "Feature",
  "properties": {
    "gn:admin1_code":"48",
    "gn:asciiname":"Sanxhak",
    "gn:cc2":"AL",
    "gn:country_code":"AL",
    "gn:dem":29,
    "gn:feature_class":"P",
    "gn:feature_code":"PPL",
    "gn:name":"Sanxhak",
    "gn:population":0,
    "gn:timezone":"Europe/Tirane",
    "iso:country":"AL",
    "name:und_x_variant":[
        "Sanxhaku",
        "Sanxhak"
    ],
    "wof:name":"Sanxhak",
    "wof:placetype":"locality"
},
  "geometry": {"coordinates":[19.71611,41.62139000000001],"type":"Point"}
}