{
  "type": "Feature",
  "properties": {
    "gn:admin1_code":"50",
    "gn:asciiname":"Linze",
    "gn:cc2":"AL",
    "gn:country_code":"AL",
    "gn:dem":312,
    "gn:feature_class":"P",
    "gn:feature_code":"PPL",
    "gn:name":"Linz\u00eb",
    "gn:population":0,
    "gn:timezone":"Europe/Tirane",
    "iso:country":"AL",
    "name:und_x_variant":[
        "Lin\u00ebz",
        "Linza",
        "Linz\u00eb"
    ],
    "wof:name":"Linze",
    "wof:placetype":"locality"
},
  "geometry": {"coordinates":[19.88306,41.34861],"type":"Point"}
}