{
  "type": "Feature",
  "properties": {
    "gn:country":"AL",
    "gn:fcode":"PPL",
    "gn:pop":4,
    "iso:country":"AL",
    "name:eng_x_preferred":[
        "Novosel\u00eb"
    ],
    "name:fra_x_preferred":[
        "Novosel\u00eb"
    ],
    "name:ita_x_preferred":[
        "Novosel\u00eb"
    ],
    "name:mkd_x_preferred":[
        "\u041d\u043e\u0432\u043e \u0421\u0435\u043b\u043e"
    ],
    "name:msa_x_preferred":[
        "Novosel\u00eb"
    ],
    "name:nld_x_preferred":[
        "Novosel\u00eb"
    ],
    "name:pol_x_preferred":[
        "Novosela"
    ],
    "name:por_x_preferred":[
        "Novosel\u00eb"
    ],
    "name:sqi_x_preferred":[
        "Komuna Novosel\u00eb"
    ],
    "name:tur_x_preferred":[
        "Novosela"
    ],
    "name:unk_x_variant":[
        "Novosella"
    ],
    "name:vie_x_preferred":[
        "Novosel\u00eb"
    ],
    "name:war_x_preferred":[
        "Novosel\u00eb"
    ],
    "qs:name":"Novosel\u00eb",
    "qs:photos_9r":0,
    "qs:photos_sr":0,
    "qs:pop_sr":"1",
    "wd:wordcount":76,
    "wof:name":"Novosel\u00eb",
    "wof:placetype":"locality",
    "wof:population":4
},
  "geometry": {"coordinates":[20.58806,41.98278],"type":"Point"}
}