{
  "type": "Feature",
  "properties": {
    "gn:country":"AL",
    "gn:fcode":"PPL",
    "gn:pop":4,
    "iso:country":"AL",
    "name:unk_x_variant":[
        "Novosella"
    ],
    "qs:name":"Novosel\u00eb",
    "qs:photos_9r":0,
    "qs:photos_sr":0,
    "qs:pop_sr":"1",
    "wd:wordcount":76,
    "wof:name":"Novosel\u00eb",
    "wof:placetype":"locality",
    "wof:population":4
},
  "geometry": {"coordinates":[20.58806,41.98278],"type":"Point"}
}