{
  "type": "Feature",
  "properties": {
    "gn:admin1_code":"43",
    "gn:asciiname":"Cestije",
    "gn:cc2":"AL",
    "gn:country_code":"AL",
    "gn:dem":163,
    "gn:feature_class":"P",
    "gn:feature_code":"PPL",
    "gn:name":"\u00c7estije",
    "gn:population":0,
    "gn:timezone":"Europe/Tirane",
    "iso:country":"AL",
    "name:und_x_variant":[
        "Haxhijai",
        "\u00c7estia",
        "Haxhialian",
        "\u00c7esti",
        "Haxhialiani",
        "Haxhilian",
        "Haxhi Alijani",
        "Haxhialjani",
        "Haxhialiaj",
        "Haxhijas",
        "\u00c7estije"
    ],
    "wof:name":"Cestije",
    "wof:placetype":"locality"
},
  "geometry": {"coordinates":[19.87583,40.91333],"type":"Point"}
}