{
  "type": "Feature",
  "properties": {
    "gn:admin1_code":"41",
    "gn:asciiname":"Radovesh",
    "gn:cc2":"AL",
    "gn:country_code":"AL",
    "gn:dem":879,
    "gn:feature_class":"P",
    "gn:feature_code":"PPL",
    "gn:name":"Radovesh",
    "gn:population":0,
    "gn:timezone":"Europe/Tirane",
    "iso:country":"AL",
    "name:und_x_variant":[
        "Radoveshi",
        "Ranga",
        "Radovesh"
    ],
    "wof:name":"Radovesh",
    "wof:placetype":"locality"
},
  "geometry": {"coordinates":[20.47278,41.44694000000001],"type":"Point"}
}