{
  "type": "Feature",
  "properties": {
    "gn:admin1_code":"48",
    "gn:asciiname":"Krajn",
    "gn:cc2":"AL",
    "gn:country_code":"AL",
    "gn:dem":77,
    "gn:feature_class":"P",
    "gn:feature_code":"PPL",
    "gn:name":"Krajn",
    "gn:population":0,
    "gn:timezone":"Europe/Tirane",
    "iso:country":"AL",
    "name:und_x_variant":[
        "Kranji",
        "Krajni",
        "Krajn"
    ],
    "wof:name":"Krajn",
    "wof:placetype":"locality"
},
  "geometry": {"coordinates":[19.67389,41.91139],"type":"Point"}
}