{
  "type": "Feature",
  "properties": {
    "gn:admin1_code":"40",
    "gn:asciiname":"Pashtraj",
    "gn:cc2":"AL",
    "gn:country_code":"AL",
    "gn:dem":291,
    "gn:feature_class":"P",
    "gn:feature_code":"PPL",
    "gn:name":"Pashtraj",
    "gn:population":0,
    "gn:timezone":"Europe/Tirane",
    "iso:country":"AL",
    "name:sqi_x_preferred":[
        "Pashtraj"
    ],
    "name:und_x_variant":[
        "Pashtran",
        "Pashtram",
        "Pashtranj",
        "Pashtrani"
    ],
    "wof:name":"Pashtraj",
    "wof:placetype":"locality"
},
  "geometry": {"coordinates":[19.96639,40.81389],"type":"Point"}
}