{
  "type": "Feature",
  "properties": {
    "gn:admin1_code":"42",
    "gn:asciiname":"Guzaj",
    "gn:country_code":"AL",
    "gn:dem":19,
    "gn:feature_class":"P",
    "gn:feature_code":"PPL",
    "gn:name":"Guzaj",
    "gn:population":0,
    "gn:timezone":"Europe/Tirane",
    "iso:country":"AL",
    "wof:name":"Guzaj",
    "wof:placetype":"locality"
},
  "geometry": {"coordinates":[19.57472000000001,41.37194],"type":"Point"}
}