{
  "type": "Feature",
  "properties": {
    "gn:admin1_code":"49",
    "gn:asciiname":"Shpor",
    "gn:cc2":"AL",
    "gn:country_code":"AL",
    "gn:dem":194,
    "gn:feature_class":"P",
    "gn:feature_code":"PPL",
    "gn:name":"Shpor",
    "gn:population":0,
    "gn:timezone":"Europe/Tirane",
    "iso:country":"AL",
    "name:und_x_variant":[
        "Shpor\u00eb",
        "Shpori",
        "Shpor"
    ],
    "wof:name":"Shpor",
    "wof:placetype":"locality"
},
  "geometry": {"coordinates":[19.67333,42.08139],"type":"Point"}
}