{
  "type": "Feature",
  "properties": {
    "gn:admin1_code":"41",
    "gn:asciiname":"Gjorica e Poshtme",
    "gn:cc2":"AL",
    "gn:country_code":"AL",
    "gn:dem":451,
    "gn:feature_class":"P",
    "gn:feature_code":"PPL",
    "gn:name":"Gjorica e Poshtme",
    "gn:population":0,
    "gn:timezone":"Europe/Tirane",
    "iso:country":"AL",
    "name:mkd_x_preferred":[
        "\u0414\u043e\u043b\u043d\u0430 \u0413\u043e\u0440\u0438\u0446\u0430"
    ],
    "name:und_x_variant":[
        "Gjorica e Posht\u00ebme",
        "Gjoric\u00eb e Poshtme",
        "Gjoric\u00eb e Posht\u00ebr",
        "Gjoric\u00eb e Posht\u00ebme",
        "Gjorica e Poshtme"
    ],
    "wof:name":"Gjorica e Poshtme",
    "wof:placetype":"locality"
},
  "geometry": {"coordinates":[20.45389,41.54833],"type":"Point"}
}