{
  "type": "Feature",
  "properties": {
    "gn:admin1_code":"47",
    "gn:asciiname":"Prahlisht",
    "gn:cc2":"AL",
    "gn:country_code":"AL",
    "gn:dem":921,
    "gn:feature_class":"P",
    "gn:feature_code":"PPL",
    "gn:name":"Prahlisht",
    "gn:population":0,
    "gn:timezone":"Europe/Tirane",
    "iso:country":"AL",
    "name:und_x_variant":[
        "Pralishti",
        "Praklishti",
        "Pralisht",
        "Praklisht",
        "Prahlisht"
    ],
    "wof:name":"Prahlisht",
    "wof:placetype":"locality"
},
  "geometry": {"coordinates":[20.37806,41.85],"type":"Point"}
}