{
  "type": "Feature",
  "properties": {
    "gn:admin1_code":"43",
    "gn:asciiname":"Haspiraj",
    "gn:cc2":"AL",
    "gn:country_code":"AL",
    "gn:dem":344,
    "gn:feature_class":"P",
    "gn:feature_code":"PPL",
    "gn:name":"Haspiraj",
    "gn:population":0,
    "gn:timezone":"Europe/Tirane",
    "iso:country":"AL",
    "name:und_x_variant":[
        "Pirej",
        "Haspiraj"
    ],
    "wof:name":"Haspiraj",
    "wof:placetype":"locality"
},
  "geometry": {"coordinates":[19.83694,41.10222],"type":"Point"}
}