{
  "type": "Feature",
  "properties": {
    "gn:admin1_code":"43",
    "gn:admin2_code":"13.0",
    "gn:asciiname":"Rajce",
    "gn:cc2":"AL",
    "gn:country_code":"AL",
    "gn:dem":694,
    "gn:feature_class":"P",
    "gn:feature_code":"PPLA3",
    "gn:name":"Rajc\u00eb",
    "gn:population":0,
    "gn:timezone":"Europe/Tirane",
    "iso:country":"AL",
    "name:deu_x_preferred":[
        "Rrajca"
    ],
    "name:ita_x_preferred":[
        "Rrajc\u00eb"
    ],
    "name:mkd_x_preferred":[
        "\u0420\u0430\u0458\u0447\u0435"
    ],
    "name:msa_x_preferred":[
        "Rrajc\u00eb"
    ],
    "name:pol_x_preferred":[
        "Gmina Rajc\u00eb"
    ],
    "name:por_x_preferred":[
        "Rrajc\u00eb"
    ],
    "name:spa_x_preferred":[
        "Rrajc\u00eb"
    ],
    "name:tur_x_preferred":[
        "Rrajca"
    ],
    "name:und_x_variant":[
        "Sula",
        "Raica",
        "Rajca",
        "Rajc\u00eb"
    ],
    "name:vie_x_preferred":[
        "Rrajc\u00eb"
    ],
    "name:war_x_preferred":[
        "Rrajc\u00eb"
    ],
    "wof:name":"Rajce",
    "wof:placetype":"locality"
},
  "geometry": {"coordinates":[20.57639,41.09028],"type":"Point"}
}