{
  "type": "Feature",
  "properties": {
    "gn:admin1_code":"46",
    "gn:asciiname":"Gur",
    "gn:cc2":"AL",
    "gn:country_code":"AL",
    "gn:dem":975,
    "gn:feature_class":"P",
    "gn:feature_code":"PPL",
    "gn:name":"Gur",
    "gn:population":0,
    "gn:timezone":"Europe/Tirane",
    "iso:country":"AL",
    "name:und_x_variant":[
        "Tresk\u00eb Egurrit",
        "Guri",
        "Gur"
    ],
    "wof:name":"Gur",
    "wof:placetype":"locality"
},
  "geometry": {"coordinates":[20.49556,40.45],"type":"Point"}
}