{
  "type": "Feature",
  "properties": {
    "gn:admin1_code":"47",
    "gn:asciiname":"Moriq",
    "gn:country_code":"AL",
    "gn:dem":737,
    "gn:feature_class":"P",
    "gn:feature_code":"PPL",
    "gn:name":"Moriq",
    "gn:population":0,
    "gn:timezone":"Europe/Tirane",
    "iso:country":"AL",
    "wof:name":"Moriq",
    "wof:placetype":"locality"
},
  "geometry": {"coordinates":[20.52583,42.17972],"type":"Point"}
}