{
  "type": "Feature",
  "properties": {
    "gn:admin1_code":"48",
    "gn:asciiname":"Gernac",
    "gn:cc2":"AL",
    "gn:country_code":"AL",
    "gn:dem":761,
    "gn:feature_class":"P",
    "gn:feature_code":"PPL",
    "gn:name":"G\u00ebrnac",
    "gn:population":0,
    "gn:timezone":"Europe/Tirane",
    "iso:country":"AL",
    "name:und_x_variant":[
        "Garnaci",
        "G\u00ebrnec",
        "Germec",
        "Gernaci",
        "Garnac",
        "German",
        "G\u00ebrnac"
    ],
    "wof:name":"Gernac",
    "wof:placetype":"locality"
},
  "geometry": {"coordinates":[19.82,41.58361],"type":"Point"}
}