{
  "type": "Feature",
  "properties": {
    "gn:admin1_code":"40",
    "gn:asciiname":"Gume",
    "gn:cc2":"AL",
    "gn:country_code":"AL",
    "gn:dem":471,
    "gn:feature_class":"P",
    "gn:feature_code":"PPL",
    "gn:name":"Gum\u00eb",
    "gn:population":0,
    "gn:timezone":"Europe/Tirane",
    "iso:country":"AL",
    "name:und_x_variant":[
        "Gumanj",
        "Gumar",
        "Guma",
        "Gum\u00eb"
    ],
    "wof:name":"Gume",
    "wof:placetype":"locality"
},
  "geometry": {"coordinates":[20.04111,40.50306],"type":"Point"}
}