{
  "type": "Feature",
  "properties": {
    "gn:admin1_code":"48",
    "gn:asciiname":"Tene",
    "gn:country_code":"AL",
    "gn:dem":394,
    "gn:feature_class":"P",
    "gn:feature_code":"PPL",
    "gn:name":"Ten\u00eb",
    "gn:population":0,
    "gn:timezone":"Europe/Tirane",
    "iso:country":"AL",
    "wof:name":"Tene",
    "wof:placetype":"locality"
},
  "geometry": {"coordinates":[19.96222,41.78917],"type":"Point"}
}