{
  "type": "Feature",
  "properties": {
    "gn:admin1_code":"41",
    "gn:asciiname":"Ploshtan",
    "gn:cc2":"AL",
    "gn:country_code":"AL",
    "gn:dem":1236,
    "gn:feature_class":"P",
    "gn:feature_code":"PPL",
    "gn:name":"Ploshtan",
    "gn:population":0,
    "gn:timezone":"Europe/Tirane",
    "iso:country":"AL",
    "name:und_x_variant":[
        "Ploshtani",
        "Plostan",
        "Ploshtan"
    ],
    "wof:name":"Ploshtan",
    "wof:placetype":"locality"
},
  "geometry": {"coordinates":[20.45528,41.84472],"type":"Point"}
}