{
  "type": "Feature",
  "properties": {
    "gn:admin1_code":"43",
    "gn:asciiname":"Verri",
    "gn:cc2":"AL",
    "gn:country_code":"AL",
    "gn:dem":610,
    "gn:feature_class":"P",
    "gn:feature_code":"PPL",
    "gn:name":"V\u00ebrri",
    "gn:population":0,
    "gn:timezone":"Europe/Tirane",
    "iso:country":"AL",
    "name:und_x_variant":[
        "V\u00ebrrin",
        "V\u00ebrrija",
        "V\u00ebrrini",
        "Vrija",
        "Vrri\u00eb",
        "V\u00ebrri"
    ],
    "wof:name":"Verri",
    "wof:placetype":"locality"
},
  "geometry": {"coordinates":[20.21444,41.26917],"type":"Point"}
}