{
  "type": "Feature",
  "properties": {
    "gn:admin1_code":"49",
    "gn:asciiname":"Rapshe",
    "gn:cc2":"AL",
    "gn:country_code":"AL",
    "gn:dem":737,
    "gn:feature_class":"P",
    "gn:feature_code":"PPL",
    "gn:name":"Rapsh\u00eb",
    "gn:population":0,
    "gn:timezone":"Europe/Tirane",
    "iso:country":"AL",
    "name:und_x_variant":[
        "Rap\u0161a",
        "Rrapsh",
        "Rapsh",
        "Rrap\u00ebsha",
        "Rapsha",
        "Rapsh\u00eb"
    ],
    "wof:name":"Rapshe",
    "wof:placetype":"locality"
},
  "geometry": {"coordinates":[19.49167000000001,42.39889],"type":"Point"}
}