{
  "type": "Feature",
  "properties": {
    "gn:admin1_code":"44",
    "gn:asciiname":"Gobolesh",
    "gn:cc2":"AL",
    "gn:country_code":"AL",
    "gn:dem":8,
    "gn:feature_class":"P",
    "gn:feature_code":"PPL",
    "gn:name":"Gobolesh",
    "gn:population":0,
    "gn:timezone":"Europe/Tirane",
    "iso:country":"AL",
    "name:und_x_variant":[
        "Shpatz\u2019 e Godoleshit",
        "Godoleshi",
        "Shpatza e Godoleshit",
        "Goboleshi",
        "Godolesh",
        "Godole\u0161",
        "Gobolesh"
    ],
    "wof:name":"Gobolesh",
    "wof:placetype":"locality"
},
  "geometry": {"coordinates":[19.66861,40.84139],"type":"Point"}
}