{
  "type": "Feature",
  "properties": {
    "gn:admin1_code":"43",
    "gn:asciiname":"Kolnekas",
    "gn:cc2":"AL",
    "gn:country_code":"AL",
    "gn:dem":610,
    "gn:feature_class":"P",
    "gn:feature_code":"PPL",
    "gn:name":"Kolnekas",
    "gn:population":0,
    "gn:timezone":"Europe/Tirane",
    "iso:country":"AL",
    "name:und_x_variant":[
        "Kontnekas",
        "Kolnekas"
    ],
    "wof:name":"Kolnekas",
    "wof:placetype":"locality"
},
  "geometry": {"coordinates":[20.55028,41.02556],"type":"Point"}
}