{
  "type": "Feature",
  "properties": {
    "gn:admin1_code":"50",
    "gn:asciiname":"Zashtik",
    "gn:country_code":"AL",
    "gn:dem":15,
    "gn:feature_class":"P",
    "gn:feature_code":"PPL",
    "gn:name":"Zashtik",
    "gn:population":0,
    "gn:timezone":"Europe/Tirane",
    "iso:country":"AL",
    "wof:name":"Zashtik",
    "wof:placetype":"locality"
},
  "geometry": {"coordinates":[19.56111,41.08972],"type":"Point"}
}