{
  "type": "Feature",
  "properties": {
    "gn:admin1_code":"46",
    "gn:asciiname":"Bubuq",
    "gn:cc2":"AL",
    "gn:country_code":"AL",
    "gn:dem":1116,
    "gn:feature_class":"P",
    "gn:feature_code":"PPL",
    "gn:name":"Bubuq",
    "gn:population":0,
    "gn:timezone":"Europe/Tirane",
    "iso:country":"AL",
    "name:und_x_variant":[
        "Bubuqi",
        "Bubuq"
    ],
    "wof:name":"Bubuq",
    "wof:placetype":"locality"
},
  "geometry": {"coordinates":[20.67222000000001,40.77306],"type":"Point"}
}