{
  "type": "Feature",
  "properties": {
    "gn:admin1_code":"41",
    "gn:asciiname":"Kllobcisht",
    "gn:cc2":"AL",
    "gn:country_code":"AL",
    "gn:dem":698,
    "gn:feature_class":"P",
    "gn:feature_code":"PPL",
    "gn:name":"Kllob\u00e7isht",
    "gn:population":0,
    "gn:timezone":"Europe/Tirane",
    "iso:country":"AL",
    "name:und_x_variant":[
        "Clobucishta",
        "Kllobogjishta",
        "Klobu\u00e7ishte",
        "Kllob\u00e7ishti",
        "Kllobogjisht\u00eb",
        "Kllobu\u00e7jishta",
        "Kllobo\u00e7ishta",
        "Kllop\u00e7ishti",
        "Kllop\u00e7isht",
        "Kllob\u00e7isht"
    ],
    "wof:name":"Kllobcisht",
    "wof:placetype":"locality"
},
  "geometry": {"coordinates":[20.51056,41.56944],"type":"Point"}
}