{
  "type": "Feature",
  "properties": {
    "gn:admin1_code":"40",
    "gn:asciiname":"Corogjaf",
    "gn:cc2":"AL",
    "gn:country_code":"AL",
    "gn:dem":790,
    "gn:feature_class":"P",
    "gn:feature_code":"PPL",
    "gn:name":"\u00c7orogjaf",
    "gn:population":0,
    "gn:timezone":"Europe/Tirane",
    "iso:country":"AL",
    "name:und_x_variant":[
        "\u00c7oroqaf",
        "\u00c7orrogjaf",
        "Cioroghiaf",
        "\u00c7orrogjafi",
        "\u00c7orogjafi",
        "\u00c7orogjaf"
    ],
    "wof:name":"Corogjaf",
    "wof:placetype":"locality"
},
  "geometry": {"coordinates":[20.005,40.53167],"type":"Point"}
}