{
  "type": "Feature",
  "properties": {
    "gn:admin1_code":"50",
    "gn:asciiname":"Radhesh",
    "gn:cc2":"AL",
    "gn:country_code":"AL",
    "gn:dem":349,
    "gn:feature_class":"P",
    "gn:feature_code":"PPL",
    "gn:name":"Radhesh",
    "gn:population":0,
    "gn:timezone":"Europe/Tirane",
    "iso:country":"AL",
    "name:und_x_variant":[
        "Rodhesh",
        "Rradhesh",
        "Radheshi",
        "Rradheshi",
        "Radhesh"
    ],
    "wof:name":"Radhesh",
    "wof:placetype":"locality"
},
  "geometry": {"coordinates":[19.83,41.43417],"type":"Point"}
}