{
  "type": "Feature",
  "properties": {
    "gn:admin1_code":"51",
    "gn:asciiname":"Qesarat",
    "gn:cc2":"AL",
    "gn:country_code":"AL",
    "gn:dem":188,
    "gn:feature_class":"P",
    "gn:feature_code":"PPL",
    "gn:name":"Qesarat",
    "gn:population":0,
    "gn:timezone":"Europe/Tirane",
    "iso:country":"AL",
    "name:und_x_variant":[
        "Qesarati",
        "Qeserati",
        "Qesaret",
        "Qesarai",
        "Qesarat"
    ],
    "wof:name":"Qesarat",
    "wof:placetype":"locality"
},
  "geometry": {"coordinates":[20.18861,39.78111],"type":"Point"}
}