{
  "type": "Feature",
  "properties": {
    "gn:admin1_code":"46",
    "gn:asciiname":"Kodras",
    "gn:cc2":"AL",
    "gn:country_code":"AL",
    "gn:dem":940,
    "gn:feature_class":"P",
    "gn:feature_code":"PPL",
    "gn:name":"Kodras",
    "gn:population":0,
    "gn:timezone":"Europe/Tirane",
    "iso:country":"AL",
    "name:und_x_variant":[
        "Kodra",
        "Kodrazi",
        "Kosdras",
        "Kodrasi",
        "Kodras"
    ],
    "wof:name":"Kodras",
    "wof:placetype":"locality"
},
  "geometry": {"coordinates":[20.64083,40.33333],"type":"Point"}
}