{
  "type": "Feature",
  "properties": {
    "gn:admin1_code":"49",
    "gn:asciiname":"Gurre",
    "gn:cc2":"AL",
    "gn:country_code":"AL",
    "gn:dem":666,
    "gn:feature_class":"P",
    "gn:feature_code":"PPL",
    "gn:name":"Gurr\u00eb",
    "gn:population":0,
    "gn:timezone":"Europe/Tirane",
    "iso:country":"AL",
    "name:und_x_variant":[
        "Gurra",
        "Gurr\u00eb"
    ],
    "wof:name":"Gurre",
    "wof:placetype":"locality"
},
  "geometry": {"coordinates":[19.77056,42.2475],"type":"Point"}
}