{
  "type": "Feature",
  "properties": {
    "gn:admin1_code":"40",
    "gn:asciiname":"Kullah",
    "gn:cc2":"AL",
    "gn:country_code":"AL",
    "gn:dem":78,
    "gn:feature_class":"P",
    "gn:feature_code":"PPL",
    "gn:name":"Kullah",
    "gn:population":0,
    "gn:timezone":"Europe/Tirane",
    "iso:country":"AL",
    "name:und_x_variant":[
        "Kullau",
        "Kullah"
    ],
    "wof:name":"Kullah",
    "wof:placetype":"neighbourhood"
},
  "geometry": {"coordinates":[19.99528,40.69083],"type":"Point"}
}