{
  "type": "Feature",
  "properties": {
    "gn:admin1_code":"41",
    "gn:asciiname":"Cerjan",
    "gn:cc2":"AL",
    "gn:country_code":"AL",
    "gn:dem":1289,
    "gn:feature_class":"P",
    "gn:feature_code":"PPL",
    "gn:name":"Cerjan",
    "gn:population":0,
    "gn:timezone":"Europe/Tirane",
    "iso:country":"AL",
    "name:und_x_variant":[
        "Selanaj",
        "\u010cerijan",
        "Cerjani",
        "Gerjani",
        "Cerjan"
    ],
    "wof:name":"Cerjan",
    "wof:placetype":"locality"
},
  "geometry": {"coordinates":[20.48333,41.71333],"type":"Point"}
}