{
  "type": "Feature",
  "properties": {
    "gn:admin1_code":"51",
    "gn:admin2_code":"20.0",
    "gn:asciiname":"Lukove",
    "gn:cc2":"AL",
    "gn:country_code":"AL",
    "gn:dem":229,
    "gn:feature_class":"P",
    "gn:feature_code":"PPLA3",
    "gn:name":"Lukov\u00eb",
    "gn:population":0,
    "gn:timezone":"Europe/Tirane",
    "iso:country":"AL",
    "name:mkd_x_preferred":[
        "\u041b\u0443\u043a\u043e\u0432\u043e"
    ],
    "name:und_x_variant":[
        "Lucova",
        "Lukova",
        "Lukovo",
        "Lukov\u00eb"
    ],
    "wof:name":"Lukove",
    "wof:placetype":"locality"
},
  "geometry": {"coordinates":[19.91389,39.99222],"type":"Point"}
}