{
  "type": "Feature",
  "properties": {
    "gn:admin1_code":"49",
    "gn:asciiname":"Dush",
    "gn:cc2":"AL",
    "gn:country_code":"AL",
    "gn:dem":580,
    "gn:feature_class":"P",
    "gn:feature_code":"PPL",
    "gn:name":"Dush",
    "gn:population":0,
    "gn:timezone":"Europe/Tirane",
    "iso:country":"AL",
    "name:und_x_variant":[
        "Dusi-Eper",
        "Dush i Ep\u00ebr",
        "Dushi",
        "Dush i Ep\u00ebrm",
        "Dushi i Ep\u00ebrm\u00eb",
        "Dush"
    ],
    "wof:name":"Dush",
    "wof:placetype":"locality"
},
  "geometry": {"coordinates":[19.80333,42.0425],"type":"Point"}
}