{
  "type": "Feature",
  "properties": {
    "gn:admin1_code":"48",
    "gn:admin2_code":"16.0",
    "gn:asciiname":"Kthella e Eperme",
    "gn:cc2":"AL",
    "gn:country_code":"AL",
    "gn:dem":600,
    "gn:feature_class":"P",
    "gn:feature_code":"PPLA3",
    "gn:name":"Kthella e Ep\u00ebrme",
    "gn:population":0,
    "gn:timezone":"Europe/Tirane",
    "iso:country":"AL",
    "name:und_x_variant":[
        "Kthell\u00eb e Ep\u00ebrme",
        "Kethella e Eper",
        "Kthella Ep\u00ebr",
        "Kthell\u00eb e Ep\u00ebr",
        "Ktell\u00eb e eper",
        "Kthell\u00eb e Sip\u00ebrme",
        "Kthella e ep\u00ebr",
        "Kthella e Ep\u00ebrme"
    ],
    "wof:name":"Kthella e Eperme",
    "wof:placetype":"locality"
},
  "geometry": {"coordinates":[20.05889,41.81194],"type":"Point"}
}