{
  "type": "Feature",
  "properties": {
    "gn:admin1_code":"43",
    "gn:asciiname":"Ballollorve",
    "gn:country_code":"AL",
    "gn:dem":586,
    "gn:feature_class":"P",
    "gn:feature_code":"PPL",
    "gn:name":"Ballollorve",
    "gn:population":0,
    "gn:timezone":"Europe/Tirane",
    "iso:country":"AL",
    "name:mkd_x_preferred":[
        "\u0411\u0435\u043b\u043e\u0432\u0440\u0432"
    ],
    "wof:name":"Ballollorve",
    "wof:placetype":"locality"
},
  "geometry": {"coordinates":[20.56917,41.06694],"type":"Point"}
}