{
  "type": "Feature",
  "properties": {
    "gn:admin1_code":"50",
    "gn:asciiname":"Shermine",
    "gn:cc2":"AL",
    "gn:country_code":"AL",
    "gn:dem":577,
    "gn:feature_class":"P",
    "gn:feature_code":"PPL",
    "gn:name":"Sh\u00ebrmin\u00eb",
    "gn:population":0,
    "gn:timezone":"Europe/Tirane",
    "iso:country":"AL",
    "name:und_x_variant":[
        "Sh\u00ebmini",
        "Shurmi",
        "Shermina",
        "Sh\u00ebrmin",
        "Sh\u00ebrmi",
        "Shermini"
    ],
    "wof:name":"Shermine",
    "wof:placetype":"locality"
},
  "geometry": {"coordinates":[19.89806,41.36306],"type":"Point"}
}