{
  "type": "Feature",
  "properties": {
    "gn:admin1_code":"49",
    "gn:asciiname":"Shtrina te Palajt",
    "gn:cc2":"AL",
    "gn:country_code":"AL",
    "gn:dem":854,
    "gn:feature_class":"P",
    "gn:feature_code":"PPL",
    "gn:name":"Shtrina te Palajt",
    "gn:population":0,
    "gn:timezone":"Europe/Tirane",
    "iso:country":"AL",
    "name:und_x_variant":[
        "Shtrina e Palajve",
        "Shtrina te Palajt"
    ],
    "wof:name":"Shtrina te Palajt",
    "wof:placetype":"locality"
},
  "geometry": {"coordinates":[19.75972,42.20528],"type":"Point"}
}