{
  "type": "Feature",
  "properties": {
    "gn:admin1_code":"41",
    "gn:asciiname":"Dodaj",
    "gn:country_code":"AL",
    "gn:dem":966,
    "gn:feature_class":"P",
    "gn:feature_code":"PPL",
    "gn:name":"Dodaj",
    "gn:population":0,
    "gn:timezone":"Europe/Tirane",
    "iso:country":"AL",
    "wof:name":"Dodaj",
    "wof:placetype":"locality"
},
  "geometry": {"coordinates":[20.235,41.87667],"type":"Point"}
}