{
  "type": "Feature",
  "properties": {
    "gn:admin1_code":"40",
    "gn:asciiname":"Vodeza e Siperme",
    "gn:cc2":"AL",
    "gn:country_code":"AL",
    "gn:dem":292,
    "gn:feature_class":"P",
    "gn:feature_code":"PPL",
    "gn:name":"Vod\u00ebza e Sip\u00ebrme",
    "gn:population":0,
    "gn:timezone":"Europe/Tirane",
    "iso:country":"AL",
    "name:und_x_variant":[
        "Vod\u00ebz\u00eb e Sip\u00ebrme",
        "Vodez e Sip\u00ebrme",
        "Vod\u00ebz",
        "Vod\u00ebza e Sip\u00ebrme"
    ],
    "wof:name":"Vodeza e Siperme",
    "wof:placetype":"locality"
},
  "geometry": {"coordinates":[19.98694,40.765],"type":"Point"}
}