{
  "type": "Feature",
  "properties": {
    "gn:admin1_code":"41",
    "gn:asciiname":"Gur-Lure",
    "gn:cc2":"AL",
    "gn:country_code":"AL",
    "gn:dem":868,
    "gn:feature_class":"P",
    "gn:feature_code":"PPL",
    "gn:name":"Gur-Lur\u00eb",
    "gn:population":0,
    "gn:timezone":"Europe/Tirane",
    "iso:country":"AL",
    "name:und_x_variant":[
        "Gur i Lur\u00ebs",
        "Gur\u00eb-Lur\u00eb",
        "Gur\u00eb-Lura",
        "Guri",
        "Gur",
        "Gur-Lur\u00eb"
    ],
    "wof:name":"Gur-Lure",
    "wof:placetype":"locality"
},
  "geometry": {"coordinates":[20.22417,41.75806],"type":"Point"}
}