{
  "type": "Feature",
  "properties": {
    "gn:admin1_code":"43",
    "gn:asciiname":"Xibrake",
    "gn:cc2":"AL",
    "gn:country_code":"AL",
    "gn:dem":189,
    "gn:feature_class":"P",
    "gn:feature_code":"PPL",
    "gn:name":"Xibrak\u00eb",
    "gn:population":0,
    "gn:timezone":"Europe/Tirane",
    "iso:country":"AL",
    "name:und_x_variant":[
        "Cib\u00ebrrak\u00eb",
        "Xibrrak\u00eb",
        "\u00c7ib\u00ebrraka",
        "Xhibrraka",
        "Xibraka",
        "Xiberraka",
        "Zibraca",
        "Xibrak\u00eb"
    ],
    "wof:name":"Xibrake",
    "wof:placetype":"locality"
},
  "geometry": {"coordinates":[20.19944,41.16694],"type":"Point"}
}