{
  "type": "Feature",
  "properties": {
    "gn:admin1_code":"40",
    "gn:asciiname":"Kapinove",
    "gn:cc2":"AL",
    "gn:country_code":"AL",
    "gn:dem":1018,
    "gn:feature_class":"P",
    "gn:feature_code":"PPL",
    "gn:name":"Kapinov\u00eb",
    "gn:population":0,
    "gn:timezone":"Europe/Tirane",
    "iso:country":"AL",
    "name:und_x_variant":[
        "Capinova",
        "Kapinova",
        "Kapinonov\u00eb",
        "Kapinov\u00eb"
    ],
    "wof:name":"Kapinove",
    "wof:placetype":"locality"
},
  "geometry": {"coordinates":[20.36361,40.54194],"type":"Point"}
}