{
  "type": "Feature",
  "properties": {
    "gn:admin1_code":"47",
    "gn:asciiname":"Vlahen",
    "gn:cc2":"AL",
    "gn:country_code":"AL",
    "gn:dem":660,
    "gn:feature_class":"P",
    "gn:feature_code":"PPL",
    "gn:name":"Vlah\u00ebn",
    "gn:population":0,
    "gn:timezone":"Europe/Tirane",
    "iso:country":"AL",
    "name:und_x_variant":[
        "Vilagna",
        "Vlhana",
        "Vlah\u00ebn\u00eb",
        "Vlahena",
        "Vlana",
        "Vlahn\u00eb",
        "Vlah\u00ebn"
    ],
    "wof:name":"Vlahen",
    "wof:placetype":"locality"
},
  "geometry": {"coordinates":[20.45639,42.23778],"type":"Point"}
}