{
  "type": "Feature",
  "properties": {
    "gn:admin1_code":"49",
    "gn:asciiname":"Tamare",
    "gn:cc2":"AL",
    "gn:country_code":"AL",
    "gn:dem":264,
    "gn:feature_class":"P",
    "gn:feature_code":"PPL",
    "gn:name":"Tamar\u00eb",
    "gn:population":0,
    "gn:timezone":"Europe/Tirane",
    "iso:country":"AL",
    "name:und_x_variant":[
        "Tamara",
        "Tamar\u00eb"
    ],
    "wof:name":"Tamare",
    "wof:placetype":"locality"
},
  "geometry": {"coordinates":[19.5625,42.46333],"type":"Point"}
}