{
  "type": "Feature",
  "properties": {
    "gn:admin1_code":"46",
    "gn:asciiname":"Guri i Bardhe",
    "gn:cc2":"AL",
    "gn:country_code":"AL",
    "gn:dem":1047,
    "gn:feature_class":"P",
    "gn:feature_code":"PPL",
    "gn:name":"Guri i Bardh\u00eb",
    "gn:population":0,
    "gn:timezone":"Europe/Tirane",
    "iso:country":"AL",
    "name:und_x_variant":[
        "Gur\u00ebbardh\u00eb",
        "Gur\u00ebbardhi",
        "Guri i Bardh\u00eb"
    ],
    "wof:name":"Guri i Bardhe",
    "wof:placetype":"locality"
},
  "geometry": {"coordinates":[20.55694,40.88528],"type":"Point"}
}