{
  "type": "Feature",
  "properties": {
    "gn:admin1_code":"44",
    "gn:asciiname":"Lavdan",
    "gn:cc2":"AL",
    "gn:country_code":"AL",
    "gn:dem":222,
    "gn:feature_class":"P",
    "gn:feature_code":"PPL",
    "gn:name":"Lavdan",
    "gn:population":0,
    "gn:timezone":"Europe/Tirane",
    "iso:country":"AL",
    "name:und_x_variant":[
        "Lavdani",
        "Ljavdanj",
        "Lavdaj",
        "Lavdanj",
        "Lavdan"
    ],
    "wof:name":"Lavdan",
    "wof:placetype":"locality"
},
  "geometry": {"coordinates":[19.74306,40.60917],"type":"Point"}
}