{
  "type": "Feature",
  "properties": {
    "gn:admin1_code":"41",
    "gn:asciiname":"Kokerdhok",
    "gn:cc2":"AL",
    "gn:country_code":"AL",
    "gn:dem":148,
    "gn:feature_class":"P",
    "gn:feature_code":"PPL",
    "gn:name":"Kok\u00ebrdhok",
    "gn:population":0,
    "gn:timezone":"Europe/Tirane",
    "iso:country":"AL",
    "name:und_x_variant":[
        "Kok\u00ebrlloku",
        "Kokordhoku",
        "Kok\u00ebrdhoku",
        "Kok\u00ebrllok",
        "Kok\u00ebrdhok"
    ],
    "wof:name":"Kokerdhok",
    "wof:placetype":"locality"
},
  "geometry": {"coordinates":[19.90194,41.67333],"type":"Point"}
}