{
  "type": "Feature",
  "properties": {
    "gn:admin1_code":"49",
    "gn:asciiname":"Gomsiqja e Re",
    "gn:cc2":"AL",
    "gn:country_code":"AL",
    "gn:dem":97,
    "gn:feature_class":"P",
    "gn:feature_code":"PPL",
    "gn:name":"Gomsiqja e Re",
    "gn:population":0,
    "gn:timezone":"Europe/Tirane",
    "iso:country":"AL",
    "name:und_x_variant":[
        "Gomsiqia",
        "Gomsiqja",
        "Gem\u0161i\u0107e",
        "Gomsiqeja",
        "Gomsiq\u00eb e Re",
        "Gomsiqe",
        "Gemshic",
        "Gomsiqa e Re",
        "Gomsiqja e Re"
    ],
    "wof:name":"Gomsiqja e Re",
    "wof:placetype":"locality"
},
  "geometry": {"coordinates":[19.68083,42.02722],"type":"Point"}
}