{
  "type": "Feature",
  "properties": {
    "gn:admin1_code":"44",
    "gn:asciiname":"Bitaj",
    "gn:cc2":"AL",
    "gn:country_code":"AL",
    "gn:dem":25,
    "gn:feature_class":"P",
    "gn:feature_code":"PPL",
    "gn:name":"Bitaj",
    "gn:population":0,
    "gn:timezone":"Europe/Tirane",
    "iso:country":"AL",
    "name:und_x_variant":[
        "Bitanj",
        "Bitan",
        "Bitani",
        "Bicaj",
        "Bitaj"
    ],
    "wof:name":"Bitaj",
    "wof:placetype":"locality"
},
  "geometry": {"coordinates":[19.59056,40.84778],"type":"Point"}
}