{
  "type": "Feature",
  "properties": {
    "gn:admin1_code":"50",
    "gn:asciiname":"Perpunje",
    "gn:cc2":"AL",
    "gn:country_code":"AL",
    "gn:dem":564,
    "gn:feature_class":"P",
    "gn:feature_code":"PPL",
    "gn:name":"P\u00ebrpunje",
    "gn:population":0,
    "gn:timezone":"Europe/Tirane",
    "iso:country":"AL",
    "name:und_x_variant":[
        "P\u00ebrpuj\u00eb",
        "Parpun\u2019\u00eb",
        "P\u00ebrpuja",
        "Parpunj\u00eb",
        "P\u00ebrpun\u00eb",
        "Perp\u00fbj",
        "P\u00ebrpunje"
    ],
    "wof:name":"Perpunje",
    "wof:placetype":"locality"
},
  "geometry": {"coordinates":[20.02389,41.31472],"type":"Point"}
}