{
  "type": "Feature",
  "properties": {
    "gn:country":"AL",
    "gn:fcode":"PPL",
    "gn:pop":1113,
    "iso:country":"AL",
    "name:dut_x_preferred":[
        "Vukatan\u00eb"
    ],
    "name:eng_x_preferred":[
        "Vukatan\u00eb"
    ],
    "name:sqi_x_colloquial":[
        "Vukatan"
    ],
    "name:sqi_x_historical":[
        "Vukatan"
    ],
    "name:swe_x_preferred":[
        "Vukatan\u00eb"
    ],
    "name:unk_x_variant":[
        "Vukatana"
    ],
    "qs:name":"Vukatan\u00eb",
    "qs:photos_9r":0,
    "qs:photos_sr":0,
    "qs:pop_sr":"3",
    "wd:wordcount":81,
    "wof:name":"Vukatan\u00eb",
    "wof:placetype":"locality",
    "wof:population":1113
},
  "geometry": {"coordinates":[19.54778,42.02806],"type":"Point"}
}