{
  "type": "Feature",
  "properties": {
    "gn:admin1_code":"48",
    "gn:asciiname":"Patalej",
    "gn:cc2":"AL",
    "gn:country_code":"AL",
    "gn:dem":85,
    "gn:feature_class":"P",
    "gn:feature_code":"PPL",
    "gn:name":"Patalej",
    "gn:population":0,
    "gn:timezone":"Europe/Tirane",
    "iso:country":"AL",
    "name:und_x_variant":[
        "Patale",
        "Palalej",
        "Partallaj",
        "Patalaj",
        "Patalej"
    ],
    "wof:name":"Patalej",
    "wof:placetype":"locality"
},
  "geometry": {"coordinates":[19.67417,41.7925],"type":"Point"}
}