{
  "type": "Feature",
  "properties": {
    "gn:admin1_code":"49",
    "gn:asciiname":"Aliaj",
    "gn:country_code":"AL",
    "gn:dem":83,
    "gn:feature_class":"P",
    "gn:feature_code":"PPL",
    "gn:name":"Aliaj",
    "gn:population":0,
    "gn:timezone":"Europe/Tirane",
    "iso:country":"AL",
    "name:ceb_x_preferred":[
        "Aliaj"
    ],
    "name:sqi_x_preferred":[
        "Aliaj"
    ],
    "name:swe_x_preferred":[
        "Aliaj"
    ],
    "wof:name":"Aliaj",
    "wof:placetype":"locality"
},
  "geometry": {"coordinates":[19.4275,42.25667],"type":"Point"}
}