{
  "type": "Feature",
  "properties": {
    "gn:admin1_code":"44",
    "gn:admin2_code":"14.0",
    "gn:asciiname":"Fier-Shegan",
    "gn:cc2":"AL",
    "gn:country_code":"AL",
    "gn:dem":19,
    "gn:feature_class":"P",
    "gn:feature_code":"PPLA3",
    "gn:name":"Fier-Shegan",
    "gn:population":0,
    "gn:timezone":"Europe/Tirane",
    "iso:country":"AL",
    "name:ita_x_preferred":[
        "Fier-Shegan"
    ],
    "name:msa_x_preferred":[
        "Fier-Shegan"
    ],
    "name:pol_x_preferred":[
        "Gmina Fier-Shegan"
    ],
    "name:por_x_preferred":[
        "Fier-Shegan"
    ],
    "name:spa_x_preferred":[
        "Fier-Shegan"
    ],
    "name:tur_x_preferred":[
        "Fier-Shegan"
    ],
    "name:und_x_variant":[
        "Fieri Shegani",
        "Fier Shegeni",
        "Fier-Shegani"
    ],
    "name:vie_x_preferred":[
        "Fier Shegan"
    ],
    "name:war_x_preferred":[
        "Fier-Shegan"
    ],
    "wof:name":"Fier-Shegan",
    "wof:placetype":"locality"
},
  "geometry": {"coordinates":[19.78528,40.86722],"type":"Point"}
}