{
  "type": "Feature",
  "properties": {
    "gn:admin1_code":"41",
    "gn:asciiname":"Karice",
    "gn:cc2":"AL",
    "gn:country_code":"AL",
    "gn:dem":302,
    "gn:feature_class":"P",
    "gn:feature_code":"PPL",
    "gn:name":"Karic\u00eb",
    "gn:population":0,
    "gn:timezone":"Europe/Tirane",
    "iso:country":"AL",
    "name:und_x_variant":[
        "Karrica",
        "Karica",
        "Karic\u00eb"
    ],
    "wof:name":"Karice",
    "wof:placetype":"locality"
},
  "geometry": {"coordinates":[19.94472,41.61556],"type":"Point"}
}