{
  "type": "Feature",
  "properties": {
    "gn:admin1_code":"40",
    "gn:asciiname":"Vendresha e Madhe",
    "gn:cc2":"AL",
    "gn:country_code":"AL",
    "gn:dem":681,
    "gn:feature_class":"P",
    "gn:feature_code":"PPL",
    "gn:name":"Vendresha e Madhe",
    "gn:population":0,
    "gn:timezone":"Europe/Tirane",
    "iso:country":"AL",
    "name:fas_x_preferred":[
        "\u0648\u0646\u062f\u0631\u0634 \u0622\u0645\u062f\u0647"
    ],
    "name:und_x_variant":[
        "V\u00ebndresh\u00eb",
        "V\u00ebndresha",
        "Vendresh\u00eb e Madhe",
        "Vendresha e Madhe"
    ],
    "wof:name":"Vendresha e Madhe",
    "wof:placetype":"locality"
},
  "geometry": {"coordinates":[20.14361,40.50278],"type":"Point"}
}