{
  "type": "Feature",
  "properties": {
    "gn:admin1_code":"44",
    "gn:asciiname":"Buzaj",
    "gn:country_code":"AL",
    "gn:dem":24,
    "gn:feature_class":"P",
    "gn:feature_code":"PPL",
    "gn:name":"Buzaj",
    "gn:population":0,
    "gn:timezone":"Europe/Tirane",
    "iso:country":"AL",
    "wof:name":"Buzaj",
    "wof:placetype":"locality"
},
  "geometry": {"coordinates":[19.78361,40.85917],"type":"Point"}
}