{
  "type": "Feature",
  "properties": {
    "gn:admin1_code":"46",
    "gn:asciiname":"Buqeze",
    "gn:cc2":"AL",
    "gn:country_code":"AL",
    "gn:dem":704,
    "gn:feature_class":"P",
    "gn:feature_code":"PPL",
    "gn:name":"Buqez\u00eb",
    "gn:population":0,
    "gn:timezone":"Europe/Tirane",
    "iso:country":"AL",
    "name:und_x_variant":[
        "Buqez",
        "Buqeza",
        "Buqez\u00eb"
    ],
    "wof:name":"Buqeze",
    "wof:placetype":"locality"
},
  "geometry": {"coordinates":[20.63056,41.05],"type":"Point"}
}