{
  "type": "Feature",
  "properties": {
    "gn:admin1_code":"45",
    "gn:asciiname":"Malas",
    "gn:cc2":"AL",
    "gn:country_code":"AL",
    "gn:dem":712,
    "gn:feature_class":"P",
    "gn:feature_code":"PPL",
    "gn:name":"Malas",
    "gn:population":0,
    "gn:timezone":"Europe/Tirane",
    "iso:country":"AL",
    "name:ceb_x_preferred":[
        "Malas"
    ],
    "name:deu_x_preferred":[
        "Malas"
    ],
    "name:und_x_variant":[
        "Bubsi i Dyt\u00eb",
        "Bub\u00ebsi II",
        "Bub\u00ebsi i Dyt\u00eb",
        "Bub\u00ebs i Dyt\u00eb"
    ],
    "wof:name":"Malas",
    "wof:placetype":"locality"
},
  "geometry": {"coordinates":[20.09444,40.48917],"type":"Point"}
}