{
  "type": "Feature",
  "properties": {
    "gn:admin1_code":"44",
    "gn:asciiname":"Stojk",
    "gn:cc2":"AL",
    "gn:country_code":"AL",
    "gn:dem":3,
    "gn:feature_class":"P",
    "gn:feature_code":"PPL",
    "gn:name":"Stojk",
    "gn:population":0,
    "gn:timezone":"Europe/Tirane",
    "iso:country":"AL",
    "name:und_x_variant":[
        "Stojku",
        "Stojk"
    ],
    "wof:name":"Stojk",
    "wof:placetype":"locality"
},
  "geometry": {"coordinates":[19.51556,40.74861],"type":"Point"}
}