{
  "type": "Feature",
  "properties": {
    "gn:admin1_code":"40",
    "gn:asciiname":"Barc",
    "gn:cc2":"AL",
    "gn:country_code":"AL",
    "gn:dem":809,
    "gn:feature_class":"P",
    "gn:feature_code":"PPL",
    "gn:name":"Bar\u00e7",
    "gn:population":0,
    "gn:timezone":"Europe/Tirane",
    "iso:country":"AL",
    "name:hun_x_preferred":[
        "Bar\u00e7"
    ],
    "name:und_x_variant":[
        "Bar\u00e7 i Posht\u00ebm",
        "Bar\u00e7i",
        "Bar\u00e7"
    ],
    "wof:name":"Barc",
    "wof:placetype":"locality"
},
  "geometry": {"coordinates":[20.31194,40.61833],"type":"Point"}
}