{
  "type": "Feature",
  "properties": {
    "gn:admin1_code":"49",
    "gn:asciiname":"Grumas",
    "gn:country_code":"AL",
    "gn:dem":695,
    "gn:feature_class":"P",
    "gn:feature_code":"PPL",
    "gn:name":"Grumas",
    "gn:population":0,
    "gn:timezone":"Europe/Tirane",
    "iso:country":"AL",
    "wof:name":"Grumas",
    "wof:placetype":"locality"
},
  "geometry": {"coordinates":[19.78944,42.37806],"type":"Point"}
}