{
  "type": "Feature",
  "properties": {
    "gn:admin1_code":"41",
    "gn:admin2_code":"2.0",
    "gn:asciiname":"Kastriot",
    "gn:cc2":"AL",
    "gn:country_code":"AL",
    "gn:dem":562,
    "gn:feature_class":"P",
    "gn:feature_code":"PPLA3",
    "gn:name":"Kastriot",
    "gn:population":0,
    "gn:timezone":"Europe/Tirane",
    "iso:country":"AL",
    "name:ceb_x_preferred":[
        "Kastriot"
    ],
    "name:nld_x_preferred":[
        "Kastriot"
    ],
    "name:por_x_preferred":[
        "Kastriot"
    ],
    "name:srp_x_preferred":[
        "\u041a\u0430\u0441\u0442\u0440\u0438\u043e\u0442"
    ],
    "name:swe_x_preferred":[
        "Kastriot"
    ],
    "name:und_x_variant":[
        "Kastrioti",
        "Kastriota"
    ],
    "wof:name":"Kastriot",
    "wof:placetype":"locality"
},
  "geometry": {"coordinates":[20.37722,41.72944],"type":"Point"}
}