{
  "type": "Feature",
  "properties": {
    "gn:admin1_code":"50",
    "gn:asciiname":"Kakunje",
    "gn:cc2":"AL",
    "gn:country_code":"AL",
    "gn:dem":474,
    "gn:feature_class":"P",
    "gn:feature_code":"PPL",
    "gn:name":"Kakunj\u00eb",
    "gn:population":0,
    "gn:timezone":"Europe/Tirane",
    "iso:country":"AL",
    "name:und_x_variant":[
        "Kaku",
        "Kakunja",
        "Kokunj\u00eb",
        "Kakuj\u00eb",
        "Kakuja",
        "Kakunj\u00eb"
    ],
    "wof:name":"Kakunje",
    "wof:placetype":"locality"
},
  "geometry": {"coordinates":[19.86778,41.16611],"type":"Point"}
}