{
  "type": "Feature",
  "properties": {
    "gn:admin1_code":"43",
    "gn:asciiname":"Kuqan",
    "gn:cc2":"AL",
    "gn:country_code":"AL",
    "gn:dem":108,
    "gn:feature_class":"P",
    "gn:feature_code":"PPL",
    "gn:name":"Kuqan",
    "gn:population":0,
    "gn:timezone":"Europe/Tirane",
    "iso:country":"AL",
    "name:und_x_variant":[
        "Cukian",
        "Kugani",
        "Kuqani",
        "Kuqan"
    ],
    "wof:name":"Kuqan",
    "wof:placetype":"locality"
},
  "geometry": {"coordinates":[20.05639,41.06306],"type":"Point"}
}