{
  "type": "Feature",
  "properties": {
    "gn:admin1_code":"41",
    "gn:asciiname":"Shullan",
    "gn:cc2":"AL",
    "gn:country_code":"AL",
    "gn:dem":693,
    "gn:feature_class":"P",
    "gn:feature_code":"PPL",
    "gn:name":"Shullan",
    "gn:population":0,
    "gn:timezone":"Europe/Tirane",
    "iso:country":"AL",
    "name:und_x_variant":[
        "Shull\u00eb",
        "Shulani",
        "Shulla",
        "Shullani",
        "Shullan"
    ],
    "wof:name":"Shullan",
    "wof:placetype":"locality"
},
  "geometry": {"coordinates":[20.42611,41.82972],"type":"Point"}
}