{
  "type": "Feature",
  "properties": {
    "gn:admin1_code":"46",
    "gn:asciiname":"Cervenake",
    "gn:cc2":"AL",
    "gn:country_code":"AL",
    "gn:dem":1139,
    "gn:feature_class":"P",
    "gn:feature_code":"PPL",
    "gn:name":"\u00c7ervenak\u00eb",
    "gn:population":0,
    "gn:timezone":"Europe/Tirane",
    "iso:country":"AL",
    "name:mkd_x_preferred":[
        "\u0427\u0435\u0440\u0432\u0435\u043d\u0430\u043a"
    ],
    "name:mkd_x_variant":[
        "\u0427\u0435\u0440\u0432\u0435\u043d\u0430\u043a\u0430"
    ],
    "name:und_x_variant":[
        "\u00c7ervenak",
        "\u00c7ervenaka",
        "\u00c7ervenaku",
        "Cerdermeake",
        "\u00c7ervenak\u00eb"
    ],
    "wof:name":"Cervenake",
    "wof:placetype":"locality"
},
  "geometry": {"coordinates":[20.60722,40.945],"type":"Point"}
}