{
  "type": "Feature",
  "properties": {
    "gn:admin1_code":"45",
    "gn:asciiname":"Fushe",
    "gn:country_code":"AL",
    "gn:dem":293,
    "gn:feature_class":"P",
    "gn:feature_code":"PPL",
    "gn:name":"Fush\u00eb",
    "gn:population":0,
    "gn:timezone":"Europe/Tirane",
    "iso:country":"AL",
    "wof:name":"Fushe",
    "wof:placetype":"locality"
},
  "geometry": {"coordinates":[20.13639,40.38056],"type":"Point"}
}