{
  "type": "Feature",
  "properties": {
    "gn:admin1_code":"41",
    "gn:admin2_code":"15.0",
    "gn:asciiname":"Xiber-Murrize",
    "gn:cc2":"AL",
    "gn:country_code":"AL",
    "gn:dem":842,
    "gn:feature_class":"P",
    "gn:feature_code":"PPLA3",
    "gn:name":"Xib\u00ebr-Murriz\u00eb",
    "gn:population":0,
    "gn:timezone":"Europe/Tirane",
    "iso:country":"AL",
    "name:und_x_variant":[
        "Murriz\u00eb",
        "Xib\u00ebr-Murriz",
        "Xib\u00ebr-Murr",
        "Xib\u00ebr-Muriz\u00eb",
        "Xib\u00ebrr-Murriz\u00eb",
        "Zib\u00ebr-Muriz\u00eb",
        "Xib\u00ebr",
        "Xib\u00ebr-Murriza",
        "Xibri",
        "Xib\u00ebr-Murrizia",
        "Xiber-Muriza",
        "Xib\u00ebr-Murriz\u00eb"
    ],
    "wof:name":"Xiber-Murrize",
    "wof:placetype":"locality"
},
  "geometry": {"coordinates":[20.02556,41.45472],"type":"Point"}
}