{
  "type": "Feature",
  "properties": {
    "gn:admin1_code":"45",
    "gn:asciiname":"Lotonjaj",
    "gn:country_code":"AL",
    "gn:dem":321,
    "gn:feature_class":"P",
    "gn:feature_code":"PPL",
    "gn:name":"Lotonjaj",
    "gn:population":0,
    "gn:timezone":"Europe/Tirane",
    "iso:country":"AL",
    "wof:name":"Lotonjaj",
    "wof:placetype":"locality"
},
  "geometry": {"coordinates":[20.15,40.38806],"type":"Point"}
}