{
  "type": "Feature",
  "properties": {
    "gn:admin1_code":"40",
    "gn:asciiname":"Banaj",
    "gn:cc2":"AL",
    "gn:country_code":"AL",
    "gn:dem":25,
    "gn:feature_class":"P",
    "gn:feature_code":"PPL",
    "gn:name":"Banaj",
    "gn:population":2500,
    "gn:timezone":"Europe/Tirane",
    "iso:country":"AL",
    "name:ceb_x_preferred":[
        "Banaj"
    ],
    "name:mkd_x_preferred":[
        "\u0411\u0430\u043d\u0430\u0458"
    ],
    "name:sqi_x_preferred":[
        "Banaj"
    ],
    "name:swe_x_preferred":[
        "Banaj"
    ],
    "name:tur_x_preferred":[
        "Banaj"
    ],
    "name:und_x_variant":[
        "Bananj",
        "Banani",
        "Banaj",
        "Beran"
    ],
    "wof:name":"Banaj",
    "wof:placetype":"locality",
    "wof:population":2500
},
  "geometry": {"coordinates":[19.83917000000001,40.82472],"type":"Point"}
}