{
  "type": "Feature",
  "properties": {
    "gn:admin1_code":"47",
    "gn:asciiname":"Kryemadh",
    "gn:cc2":"AL",
    "gn:country_code":"AL",
    "gn:dem":542,
    "gn:feature_class":"P",
    "gn:feature_code":"PPL",
    "gn:name":"Kryemadh",
    "gn:population":0,
    "gn:timezone":"Europe/Tirane",
    "iso:country":"AL",
    "name:und_x_variant":[
        "Kryemadh\u00eb",
        "Kryemadhi",
        "Krymadhi",
        "Kryemadh"
    ],
    "wof:name":"Kryemadh",
    "wof:placetype":"locality"
},
  "geometry": {"coordinates":[20.29528,42.09083],"type":"Point"}
}