{
  "type": "Feature",
  "properties": {
    "gn:admin1_code":"44",
    "gn:asciiname":"Zhelizhan",
    "gn:cc2":"AL",
    "gn:country_code":"AL",
    "gn:dem":14,
    "gn:feature_class":"P",
    "gn:feature_code":"PPL",
    "gn:name":"Zhelizhan",
    "gn:population":0,
    "gn:timezone":"Europe/Tirane",
    "iso:country":"AL",
    "name:und_x_variant":[
        "Zhelezhani",
        "\u017deli\u017ean",
        "Zhelizhani",
        "Zhelizhan"
    ],
    "wof:name":"Zhelizhan",
    "wof:placetype":"locality"
},
  "geometry": {"coordinates":[19.75333,40.82639],"type":"Point"}
}