{
  "type": "Feature",
  "properties": {
    "gn:country":"AL",
    "gn:fcode":"PPLA2",
    "gn:pop":24825,
    "iso:country":"AL",
    "name:alb_x_preferred":[
        "La\u00e7i"
    ],
    "name:bul_x_preferred":[
        "\u041b\u044f\u0447"
    ],
    "name:cat_x_preferred":[
        "La\u00e7"
    ],
    "name:chi_x_preferred":[
        "\u62c9\u5947"
    ],
    "name:cze_x_preferred":[
        "La\u00e7"
    ],
    "name:dan_x_preferred":[
        "La\u00e7"
    ],
    "name:diq_x_preferred":[
        "La\u00e7"
    ],
    "name:dut_x_preferred":[
        "La\u00e7"
    ],
    "name:eng_x_preferred":[
        "La\u00e7"
    ],
    "name:fin_x_preferred":[
        "La\u00e7"
    ],
    "name:fre_x_preferred":[
        "La\u00e7"
    ],
    "name:ger_x_preferred":[
        "La\u00e7"
    ],
    "name:gre_x_preferred":[
        "laci"
    ],
    "name:hun_x_preferred":[
        "La\u00e7"
    ],
    "name:ita_x_preferred":[
        "La\u00e7"
    ],
    "name:kor_x_preferred":[
        "\ub77c\uce58"
    ],
    "name:lit_x_preferred":[
        "Lia\u010dis"
    ],
    "name:mac_x_preferred":[
        "\u041b\u0430\u0447"
    ],
    "name:mkd_x_preferred":[
        "\u041b\u0430\u0447"
    ],
    "name:oci_x_preferred":[
        "La\u00e7"
    ],
    "name:pol_x_preferred":[
        "La\u00e7"
    ],
    "name:por_x_preferred":[
        "La\u00e7"
    ],
    "name:rum_x_preferred":[
        "La\u00e7"
    ],
    "name:rup_x_preferred":[
        "La\u00e7"
    ],
    "name:rus_x_preferred":[
        "\u041b\u0430\u043a"
    ],
    "name:slo_x_preferred":[
        "La\u00e7"
    ],
    "name:spa_x_preferred":[
        "La\u00e7"
    ],
    "name:srp_x_preferred":[
        "\u041b\u0430\u0447"
    ],
    "name:swe_x_preferred":[
        "La\u00e7"
    ],
    "name:tat_x_preferred":[
        "\u041b\u0430\u0447"
    ],
    "name:tur_x_preferred":[
        "La\u00e7"
    ],
    "name:ukr_x_preferred":[
        "\u041b\u0430\u0447\u0456"
    ],
    "name:unk_x_variant":[
        "La\u00e7i"
    ],
    "name:urd_x_preferred":[
        "\u0644\u0627\u0633\u06cc"
    ],
    "name:vie_x_preferred":[
        "La\u00e7"
    ],
    "name:vol_x_preferred":[
        "La\u00e7i"
    ],
    "name:war_x_preferred":[
        "La\u00e7"
    ],
    "name:zho_x_preferred":[
        "\u62c9\u5947"
    ],
    "qs:name":"La\u00e7",
    "qs:photos_9r":0,
    "qs:photos_sr":0,
    "qs:pop_sr":"7",
    "wd:wordcount":104,
    "wof:name":"La\u00e7",
    "wof:placetype":"locality",
    "wof:population":24825
},
  "geometry": {"coordinates":[19.71306,41.63556],"type":"Point"}
}