{
  "type": "Feature",
  "properties": {
    "gn:admin1_code":"43",
    "gn:asciiname":"Lumas",
    "gn:cc2":"AL",
    "gn:country_code":"AL",
    "gn:dem":100,
    "gn:feature_class":"P",
    "gn:feature_code":"PPL",
    "gn:name":"Lumas",
    "gn:population":0,
    "gn:timezone":"Europe/Tirane",
    "iso:country":"AL",
    "name:hye_x_preferred":[
        "\u053c\u0578\u0582\u0574\u0561\u057d"
    ],
    "name:ita_x_preferred":[
        "Lumas"
    ],
    "name:msa_x_preferred":[
        "Lumas"
    ],
    "name:nno_x_preferred":[
        "Lumas"
    ],
    "name:pol_x_preferred":[
        "Gmina Lumas"
    ],
    "name:por_x_preferred":[
        "Lumas"
    ],
    "name:spa_x_preferred":[
        "Lumas"
    ],
    "name:tur_x_preferred":[
        "Lumas"
    ],
    "name:und_x_variant":[
        "Lumac",
        "Lumasi",
        "Lumaz"
    ],
    "name:vie_x_preferred":[
        "Lumas"
    ],
    "name:war_x_preferred":[
        "Lumas"
    ],
    "wof:name":"Lumas",
    "wof:placetype":"locality"
},
  "geometry": {"coordinates":[20.00972,40.96889],"type":"Point"}
}