{
  "type": "Feature",
  "properties": {
    "gn:admin1_code":"43",
    "gn:asciiname":"Lumas",
    "gn:cc2":"AL",
    "gn:country_code":"AL",
    "gn:dem":100,
    "gn:feature_class":"P",
    "gn:feature_code":"PPL",
    "gn:name":"Lumas",
    "gn:population":0,
    "gn:timezone":"Europe/Tirane",
    "iso:country":"AL",
    "name:und_x_variant":[
        "Lumac",
        "Lumasi",
        "Lumaz",
        "Lumas"
    ],
    "wof:name":"Lumas",
    "wof:placetype":"locality"
},
  "geometry": {"coordinates":[20.00972,40.96889],"type":"Point"}
}