{
  "type": "Feature",
  "properties": {
    "gn:admin1_code":"45",
    "gn:asciiname":"Koncke",
    "gn:cc2":"AL",
    "gn:country_code":"AL",
    "gn:dem":928,
    "gn:feature_class":"P",
    "gn:feature_code":"PPL",
    "gn:name":"Konck\u00eb",
    "gn:population":0,
    "gn:timezone":"Europe/Tirane",
    "iso:country":"AL",
    "name:und_x_variant":[
        "Koncka",
        "Konck\u00eb"
    ],
    "wof:name":"Koncke",
    "wof:placetype":"locality"
},
  "geometry": {"coordinates":[20.27889,40.19417],"type":"Point"}
}