{
  "type": "Feature",
  "properties": {
    "gn:country":"AL",
    "gn:fcode":"PPL",
    "gn:population":5,
    "iso:country":"AL",
    "name:eng_x_preferred":[
        "Verri"
    ],
    "name:nld_x_preferred":[
        "Verri"
    ],
    "name:und_x_variant":[
        "Veri Prevalli"
    ],
    "name:uzb_x_preferred":[
        "Verri"
    ],
    "qs:name":"V\u00ebrri",
    "qs:photos_9r":0,
    "qs:photos_sr":0,
    "qs:pop_sr":"1",
    "wd:wordcount":51,
    "wof:name":"V\u00ebrri",
    "wof:placetype":"locality",
    "wof:population":5
},
  "geometry": {"coordinates":[20.30889,41.30056],"type":"Point"}
}