{
  "type": "Feature",
  "properties": {
    "gn:admin1_code":"41",
    "gn:asciiname":"Hotesh",
    "gn:cc2":"AL",
    "gn:country_code":"AL",
    "gn:dem":535,
    "gn:feature_class":"P",
    "gn:feature_code":"PPL",
    "gn:name":"Hotesh",
    "gn:population":0,
    "gn:timezone":"Europe/Tirane",
    "iso:country":"AL",
    "name:und_x_variant":[
        "Koteshi",
        "Shtosciaj",
        "Hoteshi",
        "Hotesh"
    ],
    "wof:name":"Hotesh",
    "wof:placetype":"locality"
},
  "geometry": {"coordinates":[20.4025,41.63111],"type":"Point"}
}