{
  "type": "Feature",
  "properties": {
    "gn:admin1_code":"45",
    "gn:asciiname":"Leuse",
    "gn:cc2":"AL",
    "gn:country_code":"AL",
    "gn:dem":436,
    "gn:feature_class":"P",
    "gn:feature_code":"PPL",
    "gn:name":"Leus\u00eb",
    "gn:population":0,
    "gn:timezone":"Europe/Tirane",
    "iso:country":"AL",
    "name:und_x_variant":[
        "Eleusa",
        "Lous\u00eb",
        "Leusa",
        "Lusja",
        "Leus\u00eb"
    ],
    "wof:name":"Leuse",
    "wof:placetype":"locality"
},
  "geometry": {"coordinates":[20.35583,40.21944000000001],"type":"Point"}
}