{
  "type": "Feature",
  "properties": {
    "gn:admin1_code":"40",
    "gn:asciiname":"Vishanj",
    "gn:cc2":"AL",
    "gn:country_code":"AL",
    "gn:dem":952,
    "gn:feature_class":"P",
    "gn:feature_code":"PPL",
    "gn:name":"Vishanj",
    "gn:population":0,
    "gn:timezone":"Europe/Tirane",
    "iso:country":"AL",
    "name:und_x_variant":[
        "Vishanij",
        "Vishanji",
        "Vashani",
        "Vishani",
        "Vishanj"
    ],
    "wof:name":"Vishanj",
    "wof:placetype":"locality"
},
  "geometry": {"coordinates":[20.32222,40.62472],"type":"Point"}
}