{
  "type": "Feature",
  "properties": {
    "gn:admin1_code":"51",
    "gn:asciiname":"Lefter Talo",
    "gn:cc2":"AL",
    "gn:country_code":"AL",
    "gn:dem":64,
    "gn:feature_class":"P",
    "gn:feature_code":"PPL",
    "gn:name":"Lefter Talo",
    "gn:population":0,
    "gn:timezone":"Europe/Tirane",
    "iso:country":"AL",
    "name:und_x_variant":[
        "Lefter Taloja",
        "Haidaraga",
        "Haderagaj",
        "Had\u00ebraga",
        "Had\u00ebr Ago",
        "Lefter Talo"
    ],
    "wof:name":"Lefter Talo",
    "wof:placetype":"locality"
},
  "geometry": {"coordinates":[20.10028,39.79],"type":"Point"}
}