{
  "type": "Feature",
  "properties": {
    "gn:admin1_code":"48",
    "gn:asciiname":"Mashterkor",
    "gn:cc2":"AL",
    "gn:country_code":"AL",
    "gn:dem":313,
    "gn:feature_class":"P",
    "gn:feature_code":"PPL",
    "gn:name":"Masht\u00ebrkor",
    "gn:population":0,
    "gn:timezone":"Europe/Tirane",
    "iso:country":"AL",
    "name:und_x_variant":[
        "Mast\u00ebrkora",
        "Mashterkora",
        "Mashtrokora",
        "Masht\u00ebrkori",
        "Mashtrokor\u00eb",
        "Masht\u00ebrkor"
    ],
    "wof:name":"Mashterkor",
    "wof:placetype":"locality"
},
  "geometry": {"coordinates":[20.07278,41.87417],"type":"Point"}
}