{
  "type": "Feature",
  "properties": {
    "gn:admin1_code":"42",
    "gn:asciiname":"Lalez",
    "gn:cc2":"AL",
    "gn:country_code":"AL",
    "gn:dem":204,
    "gn:feature_class":"P",
    "gn:feature_code":"PPL",
    "gn:name":"Lal\u00ebz",
    "gn:population":0,
    "gn:timezone":"Europe/Tirane",
    "iso:country":"AL",
    "name:und_x_variant":[
        "Lals",
        "Lalzi",
        "Lalze-Rotull",
        "Lales",
        "Lales-rrotull",
        "Lalz",
        "Lal\u00ebzi",
        "Lalz\u00eb",
        "Lalza",
        "Lal\u00ebz"
    ],
    "wof:name":"Lalez",
    "wof:placetype":"locality"
},
  "geometry": {"coordinates":[19.56806,41.53194000000001],"type":"Point"}
}