{
  "type": "Feature",
  "properties": {
    "gn:admin1_code":"49",
    "gn:asciiname":"Lekaj",
    "gn:cc2":"AL",
    "gn:country_code":"AL",
    "gn:dem":690,
    "gn:feature_class":"P",
    "gn:feature_code":"PPL",
    "gn:name":"Lekaj",
    "gn:population":0,
    "gn:timezone":"Europe/Tirane",
    "iso:country":"AL",
    "name:ita_x_preferred":[
        "Lekaj"
    ],
    "name:msa_x_preferred":[
        "Lekaj"
    ],
    "name:por_x_preferred":[
        "Lekaj"
    ],
    "name:tur_x_preferred":[
        "Lekaj"
    ],
    "name:und_x_variant":[
        "Lecaj",
        "Lekaj"
    ],
    "name:vie_x_preferred":[
        "Lekaj"
    ],
    "name:war_x_preferred":[
        "Lekaj"
    ],
    "wof:name":"Lekaj",
    "wof:placetype":"locality"
},
  "geometry": {"coordinates":[19.79472,42.32194000000001],"type":"Point"}
}