{
  "type": "Feature",
  "properties": {
    "gn:admin1_code":"51",
    "gn:asciiname":"Mirteo",
    "gn:country_code":"AL",
    "gn:dem":1030,
    "gn:feature_class":"P",
    "gn:feature_code":"PPL",
    "gn:name":"Mirteo",
    "gn:population":0,
    "gn:timezone":"Europe/Tirane",
    "iso:country":"AL",
    "wof:name":"Mirteo",
    "wof:placetype":"locality"
},
  "geometry": {"coordinates":[19.76694,40.14583],"type":"Point"}
}