{
  "type": "Feature",
  "properties": {
    "gn:admin1_code":"45",
    "gn:asciiname":"Mamaj",
    "gn:country_code":"AL",
    "gn:dem":260,
    "gn:feature_class":"P",
    "gn:feature_code":"PPL",
    "gn:name":"Mamaj",
    "gn:population":0,
    "gn:timezone":"Europe/Tirane",
    "iso:country":"AL",
    "wof:name":"Mamaj",
    "wof:placetype":"locality"
},
  "geometry": {"coordinates":[20.0025,40.3125],"type":"Point"}
}