{
  "type": "Feature",
  "properties": {
    "gn:admin1_code":"50",
    "gn:asciiname":"Vorrozen",
    "gn:cc2":"AL",
    "gn:country_code":"AL",
    "gn:dem":21,
    "gn:feature_class":"P",
    "gn:feature_code":"PPL",
    "gn:name":"Vorrozen",
    "gn:population":0,
    "gn:timezone":"Europe/Tirane",
    "iso:country":"AL",
    "name:sqi_x_preferred":[
        "Vorrozen"
    ],
    "name:und_x_variant":[
        "Vorazen",
        "Vorrezaj",
        "Vorezaj",
        "Vorrozeni",
        "Vorez\u00eb",
        "Vorrazeni",
        "Vorozeni",
        "Vorrazen",
        "Vorosen",
        "Vorozen",
        "Vorrozen"
    ],
    "wof:name":"Vorrozen",
    "wof:placetype":"locality"
},
  "geometry": {"coordinates":[19.56472,41.14528],"type":"Point"}
}