{
  "type": "Feature",
  "properties": {
    "gn:admin1_code":"45",
    "gn:asciiname":"Bokollar",
    "gn:cc2":"AL",
    "gn:country_code":"AL",
    "gn:dem":353,
    "gn:feature_class":"P",
    "gn:feature_code":"PPL",
    "gn:name":"Bokollar",
    "gn:population":0,
    "gn:timezone":"Europe/Tirane",
    "iso:country":"AL",
    "name:und_x_variant":[
        "Bakollar",
        "Bokollar"
    ],
    "wof:name":"Bokollar",
    "wof:placetype":"locality"
},
  "geometry": {"coordinates":[20.14833,40.35389],"type":"Point"}
}