{
  "type": "Feature",
  "properties": {
    "gn:admin1_code":"47",
    "gn:asciiname":"Jah Salih",
    "gn:cc2":"AL",
    "gn:country_code":"AL",
    "gn:dem":319,
    "gn:feature_class":"P",
    "gn:feature_code":"PPL",
    "gn:name":"Jah Salih",
    "gn:population":0,
    "gn:timezone":"Europe/Tirane",
    "iso:country":"AL",
    "name:und_x_variant":[
        "Jaho Salihi",
        "Jah-Salihu",
        "Jah-Salihi",
        "Jah Salih"
    ],
    "wof:name":"Jah Salih",
    "wof:placetype":"locality"
},
  "geometry": {"coordinates":[20.10583,42.35889],"type":"Point"}
}