{
  "type": "Feature",
  "properties": {
    "gn:admin1_code":"51",
    "gn:asciiname":"Nje Maj",
    "gn:cc2":"AL",
    "gn:country_code":"AL",
    "gn:dem":82,
    "gn:feature_class":"P",
    "gn:feature_code":"PPL",
    "gn:name":"Nj\u00eb Maj",
    "gn:population":0,
    "gn:timezone":"Europe/Tirane",
    "iso:country":"AL",
    "name:und_x_variant":[
        "1 (Nj\u00eb) Maj",
        "1 Maj",
        "Nj\u00eb Maj"
    ],
    "wof:name":"Nje Maj",
    "wof:placetype":"locality"
},
  "geometry": {"coordinates":[19.76222000000001,40.11],"type":"Point"}
}