{
  "type": "Feature",
  "properties": {
    "gn:admin1_code":"47",
    "gn:asciiname":"Nome",
    "gn:cc2":"AL",
    "gn:country_code":"AL",
    "gn:dem":770,
    "gn:feature_class":"P",
    "gn:feature_code":"PPL",
    "gn:name":"Nom\u00eb",
    "gn:population":0,
    "gn:timezone":"Europe/Tirane",
    "iso:country":"AL",
    "name:und_x_variant":[
        "Domaj"
    ],
    "wof:name":"Nome",
    "wof:placetype":"locality"
},
  "geometry": {"coordinates":[20.26667,41.88333],"type":"Point"}
}