{
  "type": "Feature",
  "properties": {
    "gn:admin1_code":"47",
    "gn:asciiname":"Nome",
    "gn:cc2":"AL",
    "gn:country_code":"AL",
    "gn:dem":770,
    "gn:feature_class":"P",
    "gn:feature_code":"PPL",
    "gn:name":"Nom\u00eb",
    "gn:population":0,
    "gn:timezone":"Europe/Tirane",
    "iso:country":"AL",
    "name:ceb_x_preferred":[
        "Nome"
    ],
    "name:ces_x_preferred":[
        "Nome"
    ],
    "name:deu_x_preferred":[
        "Nome"
    ],
    "name:fra_x_preferred":[
        "Nome"
    ],
    "name:heb_x_preferred":[
        "\u05e0\u05d5\u05dd"
    ],
    "name:ind_x_preferred":[
        "Nome"
    ],
    "name:ita_x_preferred":[
        "Nome"
    ],
    "name:lim_x_preferred":[
        "Nome"
    ],
    "name:nld_x_preferred":[
        "Nome"
    ],
    "name:nor_x_preferred":[
        "Nome"
    ],
    "name:oci_x_preferred":[
        "N\u00f2me"
    ],
    "name:pol_x_preferred":[
        "Nome"
    ],
    "name:por_x_preferred":[
        "Nome"
    ],
    "name:ron_x_preferred":[
        "Nome"
    ],
    "name:srp_x_preferred":[
        "\u041d\u043e\u0443\u043c"
    ],
    "name:swe_x_preferred":[
        "Nome"
    ],
    "name:und_x_variant":[
        "Domaj"
    ],
    "name:vol_x_preferred":[
        "Nome"
    ],
    "wof:name":"Nome",
    "wof:placetype":"locality"
},
  "geometry": {"coordinates":[20.26667,41.88333],"type":"Point"}
}