{
  "type": "Feature",
  "properties": {
    "gn:admin1_code":"42",
    "gn:asciiname":"Rromanat",
    "gn:cc2":"AL",
    "gn:country_code":"AL",
    "gn:dem":55,
    "gn:feature_class":"P",
    "gn:feature_code":"PPL",
    "gn:name":"Rromanat",
    "gn:population":0,
    "gn:timezone":"Europe/Tirane",
    "iso:country":"AL",
    "name:und_x_variant":[
        "Romanotok",
        "Rumanat",
        "Romanat",
        "Rrumanati",
        "Romanati",
        "Rromanat"
    ],
    "wof:name":"Rromanat",
    "wof:placetype":"locality"
},
  "geometry": {"coordinates":[19.59528,41.28278],"type":"Point"}
}