{
  "type": "Feature",
  "properties": {
    "gn:admin1_code":"49",
    "gn:asciiname":"Pulaj",
    "gn:country_code":"AL",
    "gn:dem":2,
    "gn:feature_class":"P",
    "gn:feature_code":"PPL",
    "gn:name":"Pulaj",
    "gn:population":0,
    "gn:timezone":"Europe/Tirane",
    "iso:country":"AL",
    "wof:name":"Pulaj",
    "wof:placetype":"locality"
},
  "geometry": {"coordinates":[19.38417,41.87722],"type":"Point"}
}