{
  "type": "Feature",
  "properties": {
    "gn:admin1_code":"43",
    "gn:asciiname":"Ferhataj",
    "gn:country_code":"AL",
    "gn:dem":182,
    "gn:feature_class":"P",
    "gn:feature_code":"PPL",
    "gn:name":"Ferhataj",
    "gn:population":0,
    "gn:timezone":"Europe/Tirane",
    "iso:country":"AL",
    "wof:name":"Ferhataj",
    "wof:placetype":"locality"
},
  "geometry": {"coordinates":[19.835,40.98278],"type":"Point"}
}