{
  "type": "Feature",
  "properties": {
    "gn:admin1_code":"43",
    "gn:asciiname":"Bletez",
    "gn:cc2":"AL",
    "gn:country_code":"AL",
    "gn:dem":732,
    "gn:feature_class":"P",
    "gn:feature_code":"PPL",
    "gn:name":"Blet\u00ebz",
    "gn:population":0,
    "gn:timezone":"Europe/Tirane",
    "iso:country":"AL",
    "name:und_x_variant":[
        "Sh\u00ebmberdhej i Sip\u00ebrm",
        "Blet\u00ebza",
        "Shemerdhenj i Sip\u00ebrm",
        "Shemberdhej i Siperme",
        "Sh\u00ebmb\u00ebrthej i Sip\u00ebrm",
        "Sh\u00ebmberdhenj i Sip\u00ebrm",
        "Sh\u00ebmerdhej i Siperm",
        "Blet\u00ebz"
    ],
    "wof:name":"Bletez",
    "wof:placetype":"locality"
},
  "geometry": {"coordinates":[20.2675,40.76861],"type":"Point"}
}