{
  "type": "Feature",
  "properties": {
    "gn:gn_country":"AL",
    "gn:gn_fcode":"PPLA3",
    "gn:gn_pop":11026,
    "gn:population":11026,
    "iso:country":"AL",
    "name:alb_x_preferred":[
        "Kamza"
    ],
    "name:bul_x_preferred":[
        "\u041a\u0430\u043c\u0437\u0430"
    ],
    "name:chi_x_preferred":[
        "\u5361\u59c6\u624e"
    ],
    "name:dut_x_preferred":[
        "Kam\u00ebz"
    ],
    "name:eng_x_preferred":[
        "Kam\u00ebz"
    ],
    "name:fre_x_preferred":[
        "Kamza"
    ],
    "name:ger_x_preferred":[
        "Kamza"
    ],
    "name:ita_x_preferred":[
        "Kam\u00ebz"
    ],
    "name:lit_x_preferred":[
        "Kamz\u0117"
    ],
    "name:mac_x_preferred":[
        "\u041a\u0430\u043c\u0437\u0430"
    ],
    "name:mkd_x_preferred":[
        "\u041a\u0430\u043c\u0437\u0430"
    ],
    "name:pol_x_preferred":[
        "Kamza"
    ],
    "name:por_x_preferred":[
        "Kam\u00ebz"
    ],
    "name:rum_x_preferred":[
        "Kamza"
    ],
    "name:rup_x_preferred":[
        "Kamza"
    ],
    "name:sco_x_preferred":[
        "Kam\u00ebz"
    ],
    "name:spa_x_preferred":[
        "Kam\u00ebz"
    ],
    "name:swe_x_preferred":[
        "Kam\u00ebz"
    ],
    "name:tat_x_preferred":[
        "\u041a\u0430\u043c\u0437\u0430"
    ],
    "name:tur_x_preferred":[
        "Kamza"
    ],
    "name:unk_x_variant":[
        "Camza"
    ],
    "name:urd_x_preferred":[
        "\u06a9\u0627\u0645\u0632\u0627"
    ],
    "name:vie_x_preferred":[
        "Kam\u00ebz"
    ],
    "name:war_x_preferred":[
        "Kam\u00ebz"
    ],
    "name:zho_x_preferred":[
        "\u5361\u59c6\u624e"
    ],
    "qs_pg:aaroncc":"AL",
    "qs_pg:gn_country":"AL",
    "qs_pg:gn_fcode":"PPLA3",
    "qs_pg:gn_pop":11026,
    "qs_pg:name":"Kam\u00ebz",
    "qs_pg:photos_9r":0,
    "qs_pg:photos_sr":0,
    "qs_pg:pop_sr":6,
    "qs_pg:qs_pg_placetype":"locality",
    "wof:name":"Kam\u00ebz",
    "wof:placetype":"locality",
    "wof:population":11026
},
  "geometry": {"coordinates":[19.76028,41.38167],"type":"Point"}
}