{
  "type": "Feature",
  "properties": {
    "gn:country":"AL",
    "gn:fcode":"PPLA3",
    "gn:population":11026,
    "iso:country":"AL",
    "name:ara_x_preferred":[
        "\u0643\u0627\u0645\u0632\u0627"
    ],
    "name:arz_x_preferred":[
        "\u0643\u0627\u0645\u0632\u0627"
    ],
    "name:ast_x_preferred":[
        "Kam\u00ebz"
    ],
    "name:bul_x_preferred":[
        "\u041a\u0430\u043c\u0437\u0430"
    ],
    "name:bul_x_variant":[
        "\u041a\u0430\u043c\u0430\u0437"
    ],
    "name:ceb_x_preferred":[
        "Kam\u00ebz"
    ],
    "name:ces_x_preferred":[
        "Kam\u00ebz"
    ],
    "name:dan_x_preferred":[
        "Kam\u00ebz"
    ],
    "name:deu_x_preferred":[
        "Kamza"
    ],
    "name:ell_x_preferred":[
        "\u039a\u03ac\u03bc\u03b6\u03b1"
    ],
    "name:eng_x_preferred":[
        "Kam\u00ebz"
    ],
    "name:est_x_preferred":[
        "Kam\u00ebz"
    ],
    "name:fra_x_preferred":[
        "Kamza"
    ],
    "name:hun_x_preferred":[
        "Kamza"
    ],
    "name:hye_x_preferred":[
        "\u053f\u0561\u0574\u0566\u0561"
    ],
    "name:ita_x_preferred":[
        "Kam\u00ebz"
    ],
    "name:lav_x_preferred":[
        "Kamza"
    ],
    "name:lit_x_preferred":[
        "Kamz\u0117"
    ],
    "name:mkd_x_preferred":[
        "\u041a\u0430\u043c\u0437\u0430"
    ],
    "name:nld_x_preferred":[
        "Kam\u00ebz"
    ],
    "name:nno_x_preferred":[
        "Kam\u00ebz"
    ],
    "name:nob_x_preferred":[
        "Kam\u00ebz"
    ],
    "name:pol_x_preferred":[
        "Kamza"
    ],
    "name:por_x_preferred":[
        "Kam\u00ebz"
    ],
    "name:ron_x_preferred":[
        "Kamza"
    ],
    "name:rup_x_preferred":[
        "Kamza"
    ],
    "name:rus_x_preferred":[
        "\u041a\u0430\u043c\u0437\u0430"
    ],
    "name:sco_x_preferred":[
        "Kam\u00ebz"
    ],
    "name:spa_x_preferred":[
        "Kam\u00ebz"
    ],
    "name:sqi_x_preferred":[
        "Kamza"
    ],
    "name:swe_x_preferred":[
        "Kam\u00ebz"
    ],
    "name:tat_x_preferred":[
        "\u041a\u0430\u043c\u0437\u0430"
    ],
    "name:tur_x_preferred":[
        "Kamza"
    ],
    "name:ukr_x_preferred":[
        "\u041a\u0430\u043c\u0437\u0430"
    ],
    "name:und_x_variant":[
        "Camza"
    ],
    "name:urd_x_preferred":[
        "\u06a9\u0627\u0645\u0632\u0627"
    ],
    "name:vie_x_preferred":[
        "Kam\u00ebz"
    ],
    "name:war_x_preferred":[
        "Kam\u00ebz"
    ],
    "name:zho_x_preferred":[
        "\u5361\u59c6\u624e"
    ],
    "qs_pg:aaroncc":"AL",
    "qs_pg:gn_country":"AL",
    "qs_pg:gn_fcode":"PPLA3",
    "qs_pg:gn_pop":11026,
    "qs_pg:name":"Kam\u00ebz",
    "qs_pg:photos_9r":0,
    "qs_pg:photos_sr":0,
    "qs_pg:pop_sr":6,
    "qs_pg:qs_pg_placetype":"locality",
    "wof:name":"Kam\u00ebz",
    "wof:placetype":"locality",
    "wof:population":11026
},
  "geometry": {"coordinates":[19.76028,41.38167],"type":"Point"}
}