{
  "type": "Feature",
  "properties": {
    "gn:admin1_code":"47",
    "gn:asciiname":"Sefollj",
    "gn:country_code":"AL",
    "gn:dem":560,
    "gn:feature_class":"P",
    "gn:feature_code":"PPL",
    "gn:name":"Sefollj",
    "gn:population":0,
    "gn:timezone":"Europe/Tirane",
    "iso:country":"AL",
    "wof:name":"Sefollj",
    "wof:placetype":"locality"
},
  "geometry": {"coordinates":[20.37639,42.14889],"type":"Point"}
}