{
  "type": "Feature",
  "properties": {
    "gn:admin1_code":"49",
    "gn:asciiname":"Ivanaj",
    "gn:cc2":"AL",
    "gn:country_code":"AL",
    "gn:dem":58,
    "gn:feature_class":"P",
    "gn:feature_code":"PPL",
    "gn:name":"Ivanaj",
    "gn:population":0,
    "gn:timezone":"Europe/Tirane",
    "iso:country":"AL",
    "name:ceb_x_preferred":[
        "Ivanaj"
    ],
    "name:sqi_x_preferred":[
        "Ivanaj"
    ],
    "name:swe_x_preferred":[
        "Ivanaj"
    ],
    "name:und_x_variant":[
        "Bajza",
        "Jvanaj",
        "Bajz\u00eb"
    ],
    "wof:name":"Ivanaj",
    "wof:placetype":"locality"
},
  "geometry": {"coordinates":[19.43778,42.28528],"type":"Point"}
}