{
  "type": "Feature",
  "properties": {
    "gn:admin1_code":"49",
    "gn:asciiname":"Markolaj",
    "gn:country_code":"AL",
    "gn:dem":146,
    "gn:feature_class":"P",
    "gn:feature_code":"PPL",
    "gn:name":"Markolaj",
    "gn:population":0,
    "gn:timezone":"Europe/Tirane",
    "iso:country":"AL",
    "wof:name":"Markolaj",
    "wof:placetype":"locality"
},
  "geometry": {"coordinates":[19.71944,42.06694],"type":"Point"}
}