{
  "type": "Feature",
  "properties": {
    "gn:admin1_code":"45",
    "gn:asciiname":"Bylysh",
    "gn:cc2":"AL",
    "gn:country_code":"AL",
    "gn:dem":437,
    "gn:feature_class":"P",
    "gn:feature_code":"PPL",
    "gn:name":"Bylysh",
    "gn:population":0,
    "gn:timezone":"Europe/Tirane",
    "iso:country":"AL",
    "name:und_x_variant":[
        "Bylyshi",
        "Bylysh"
    ],
    "wof:name":"Bylysh",
    "wof:placetype":"locality"
},
  "geometry": {"coordinates":[20.00417,40.36056],"type":"Point"}
}