{
  "type": "Feature",
  "properties": {
    "gn:admin1_code":"40",
    "gn:asciiname":"Vite",
    "gn:country_code":"AL",
    "gn:dem":501,
    "gn:feature_class":"P",
    "gn:feature_code":"PPL",
    "gn:name":"Vit\u00eb",
    "gn:population":0,
    "gn:timezone":"Europe/Tirane",
    "iso:country":"AL",
    "wof:name":"Vite",
    "wof:placetype":"locality"
},
  "geometry": {"coordinates":[20.03833,40.77167],"type":"Point"}
}