{
  "type": "Feature",
  "properties": {
    "gn:admin1_code":"44",
    "gn:asciiname":"Karbunara e Madhe",
    "gn:cc2":"AL",
    "gn:country_code":"AL",
    "gn:dem":38,
    "gn:feature_class":"P",
    "gn:feature_code":"PPL",
    "gn:name":"Karbunara e Madhe",
    "gn:population":0,
    "gn:timezone":"Europe/Tirane",
    "iso:country":"AL",
    "name:und_x_variant":[
        "Karbunar\u00eb e Sip\u00ebrme",
        "Karbunara e Sip\u00ebrme",
        "Karbunar\u00eb e Madhe",
        "Karbunara e Madhe"
    ],
    "wof:name":"Karbunara e Madhe",
    "wof:placetype":"locality"
},
  "geometry": {"coordinates":[19.74083,40.9275],"type":"Point"}
}