{
  "type": "Feature",
  "properties": {
    "gn:admin1_code":"40",
    "gn:asciiname":"Panarit",
    "gn:cc2":"AL",
    "gn:country_code":"AL",
    "gn:dem":566,
    "gn:feature_class":"P",
    "gn:feature_code":"PPL",
    "gn:name":"Panarit",
    "gn:population":0,
    "gn:timezone":"Europe/Tirane",
    "iso:country":"AL",
    "name:sqi_x_preferred":[
        "Panariti"
    ],
    "name:und_x_variant":[
        "Panariti",
        "Panarit"
    ],
    "name:urd_x_preferred":[
        "\u067e\u0627\u0646\u0627\u0631\u062a"
    ],
    "wof:name":"Panarit",
    "wof:placetype":"locality"
},
  "geometry": {"coordinates":[20.02667000000001,40.49639000000001],"type":"Point"}
}