{
  "type": "Feature",
  "properties": {
    "gn:admin1_code":"51",
    "gn:asciiname":"Bletez",
    "gn:cc2":"AL",
    "gn:country_code":"AL",
    "gn:dem":274,
    "gn:feature_class":"P",
    "gn:feature_code":"PPL",
    "gn:name":"Blet\u00ebz",
    "gn:population":0,
    "gn:timezone":"Europe/Tirane",
    "iso:country":"AL",
    "name:und_x_variant":[
        "Bleds",
        "Blet\u00ebz"
    ],
    "wof:name":"Bletez",
    "wof:placetype":"locality"
},
  "geometry": {"coordinates":[19.76583,40.20222],"type":"Point"}
}