{
  "type": "Feature",
  "properties": {
    "gn:admin1_code":"44",
    "gn:asciiname":"Baltez",
    "gn:cc2":"AL",
    "gn:country_code":"AL",
    "gn:dem":5,
    "gn:feature_class":"P",
    "gn:feature_code":"PPL",
    "gn:name":"Balt\u00ebz",
    "gn:population":0,
    "gn:timezone":"Europe/Tirane",
    "iso:country":"AL",
    "name:und_x_variant":[
        "Balt\u00ebz\u00eb",
        "Balt\u00ebza",
        "Balt\u00ebz"
    ],
    "wof:name":"Baltez",
    "wof:placetype":"locality"
},
  "geometry": {"coordinates":[19.53889,40.75528],"type":"Point"}
}