{
  "type": "Feature",
  "properties": {
    "gn:admin1_code":"43",
    "gn:asciiname":"Banje",
    "gn:cc2":"AL",
    "gn:country_code":"AL",
    "gn:dem":125,
    "gn:feature_class":"P",
    "gn:feature_code":"PPL",
    "gn:name":"Banj\u00eb",
    "gn:population":0,
    "gn:timezone":"Europe/Tirane",
    "iso:country":"AL",
    "name:und_x_variant":[
        "Banja",
        "B\u00ebnja",
        "Banj\u00eb"
    ],
    "wof:name":"Banje",
    "wof:placetype":"locality"
},
  "geometry": {"coordinates":[20.05861,40.96556],"type":"Point"}
}