{
  "type": "Feature",
  "properties": {
    "gn:admin1_code":"45",
    "gn:asciiname":"Humelice",
    "gn:cc2":"AL",
    "gn:country_code":"AL",
    "gn:dem":307,
    "gn:feature_class":"P",
    "gn:feature_code":"PPL",
    "gn:name":"Humelic\u00eb",
    "gn:population":0,
    "gn:timezone":"Europe/Tirane",
    "iso:country":"AL",
    "name:und_x_variant":[
        "Humelizza",
        "Humelica",
        "Humalica",
        "Humelic\u00eb"
    ],
    "wof:name":"Humelice",
    "wof:placetype":"locality"
},
  "geometry": {"coordinates":[20.07694,40.1625],"type":"Point"}
}