{
  "type": "Feature",
  "properties": {
    "gn:admin1_code":"49",
    "gn:asciiname":"Kokaj",
    "gn:cc2":"AL",
    "gn:country_code":"AL",
    "gn:dem":412,
    "gn:feature_class":"P",
    "gn:feature_code":"PPL",
    "gn:name":"Kokaj",
    "gn:population":0,
    "gn:timezone":"Europe/Tirane",
    "iso:country":"AL",
    "name:und_x_variant":[
        "Kokay",
        "Kokaj"
    ],
    "wof:name":"Kokaj",
    "wof:placetype":"locality"
},
  "geometry": {"coordinates":[19.53083,42.27444000000001],"type":"Point"}
}