{
  "type": "Feature",
  "properties": {
    "gn:admin1_code":"41",
    "gn:asciiname":"Kuben",
    "gn:cc2":"AL",
    "gn:country_code":"AL",
    "gn:dem":441,
    "gn:feature_class":"P",
    "gn:feature_code":"PPL",
    "gn:name":"Kuben",
    "gn:population":0,
    "gn:timezone":"Europe/Tirane",
    "iso:country":"AL",
    "name:ceb_x_preferred":[
        "Kuben"
    ],
    "name:nor_x_preferred":[
        "Kuben"
    ],
    "name:swe_x_preferred":[
        "Kuben"
    ],
    "name:und_x_variant":[
        "Kubeni",
        "Kuben"
    ],
    "wof:name":"Kuben",
    "wof:placetype":"locality"
},
  "geometry": {"coordinates":[20.36,41.69333],"type":"Point"}
}