{
  "type": "Feature",
  "properties": {
    "gn:admin1_code":"46",
    "gn:asciiname":"Laktesh",
    "gn:cc2":"AL",
    "gn:country_code":"AL",
    "gn:dem":880,
    "gn:feature_class":"P",
    "gn:feature_code":"PPL",
    "gn:name":"Laktesh",
    "gn:population":0,
    "gn:timezone":"Europe/Tirane",
    "iso:country":"AL",
    "name:und_x_variant":[
        "Lakteshi",
        "Laktesh"
    ],
    "wof:name":"Laktesh",
    "wof:placetype":"locality"
},
  "geometry": {"coordinates":[20.47556,40.97361],"type":"Point"}
}