{
  "type": "Feature",
  "properties": {
    "gn:admin1_code":"43",
    "gn:asciiname":"Jatesh",
    "gn:cc2":"AL",
    "gn:country_code":"AL",
    "gn:dem":334,
    "gn:feature_class":"P",
    "gn:feature_code":"PPL",
    "gn:name":"Jatesh",
    "gn:population":0,
    "gn:timezone":"Europe/Tirane",
    "iso:country":"AL",
    "name:und_x_variant":[
        "Teshi",
        "Jateshi",
        "Jatesh"
    ],
    "wof:name":"Jatesh",
    "wof:placetype":"locality"
},
  "geometry": {"coordinates":[19.98111,41.10222],"type":"Point"}
}