{
  "type": "Feature",
  "properties": {
    "gn:admin1_code":"40",
    "gn:asciiname":"Boje",
    "gn:cc2":"AL",
    "gn:country_code":"AL",
    "gn:dem":345,
    "gn:feature_class":"P",
    "gn:feature_code":"PPL",
    "gn:name":"Boj\u00eb",
    "gn:population":0,
    "gn:timezone":"Europe/Tirane",
    "iso:country":"AL",
    "name:und_x_variant":[
        "Boja",
        "Bojaj",
        "Boj\u00eb"
    ],
    "wof:name":"Boje",
    "wof:placetype":"locality"
},
  "geometry": {"coordinates":[20.02194,40.69056],"type":"Point"}
}