{
  "type": "Feature",
  "properties": {
    "gn:admin1_code":"48",
    "gn:admin2_code":"12.0",
    "gn:asciiname":"Gjader, Dajc",
    "gn:country_code":"AL",
    "gn:dem":6,
    "gn:feature_class":"P",
    "gn:feature_code":"PPL",
    "gn:name":"Gjad\u00ebr, Dajc",
    "gn:population":0,
    "gn:timezone":"Europe/Tirane",
    "iso:country":"AL",
    "name:sqi_x_preferred":[
        "Gjad\u00ebr"
    ],
    "name:und_x_variant":[
        "Dadri",
        "Gjad\u00ebri",
        "Gjadri",
        "Gjad\u00ebr"
    ],
    "wof:name":"Gjader, Dajc",
    "wof:placetype":"locality"
},
  "geometry": {"coordinates":[19.59139,41.88],"type":"Point"}
}