{
  "type": "Feature",
  "properties": {
    "gn:admin1_code":"44",
    "gn:asciiname":"Makaj",
    "gn:country_code":"AL",
    "gn:dem":2,
    "gn:feature_class":"P",
    "gn:feature_code":"PPL",
    "gn:name":"Makaj",
    "gn:population":0,
    "gn:timezone":"Europe/Tirane",
    "iso:country":"AL",
    "wof:name":"Makaj",
    "wof:placetype":"locality"
},
  "geometry": {"coordinates":[19.52111,40.75528],"type":"Point"}
}