{
  "type": "Feature",
  "properties": {
    "iso:country":"AL",
    "name:und_x_variant":[
        "Bogdani i Posht\u00ebm"
    ],
    "qs:gn_country":"AL",
    "qs:gn_fcode":"PPL",
    "qs:gn_pop":0,
    "qs:name":"Bogdan i Posht\u00ebm",
    "qs:name_adm0":"Shqip\u00ebri",
    "qs:name_adm1":"Berat",
    "qs:photos":3,
    "qs:photos_1k":1,
    "qs:photos_9k":1,
    "qs:photos_9r":1,
    "qs:photos_all":3,
    "qs:photos_sr":1,
    "qs:placetype":"Suburb",
    "qs:pop_sr":"0",
    "qs:woe_adm0":23424742,
    "wof:name":"Bogdan i Posht\u00ebm",
    "wof:placetype":"neighbourhood"
},
  "geometry": {"coordinates":[20.04333,40.71306],"type":"Point"}
}