{
  "type": "Feature",
  "properties": {
    "gn:admin1_code":"49",
    "gn:asciiname":"Zhupe",
    "gn:cc2":"AL",
    "gn:country_code":"AL",
    "gn:dem":70,
    "gn:feature_class":"P",
    "gn:feature_code":"PPL",
    "gn:name":"Zhup\u00eb",
    "gn:population":0,
    "gn:timezone":"Europe/Tirane",
    "iso:country":"AL",
    "name:und_x_variant":[
        "\u017dub",
        "Zhupa",
        "Zhub"
    ],
    "wof:name":"Zhupe",
    "wof:placetype":"locality"
},
  "geometry": {"coordinates":[19.62111,42.08528],"type":"Point"}
}