{
  "type": "Feature",
  "properties": {
    "gn:admin1_code":"48",
    "gn:asciiname":"Rasfik",
    "gn:cc2":"AL",
    "gn:country_code":"AL",
    "gn:dem":56,
    "gn:feature_class":"P",
    "gn:feature_code":"PPL",
    "gn:name":"Rasfik",
    "gn:population":0,
    "gn:timezone":"Europe/Tirane",
    "iso:country":"AL",
    "name:und_x_variant":[
        "Rrasfiku",
        "Prasfik",
        "Rrasfik",
        "Rasfiku",
        "Rasfik"
    ],
    "wof:name":"Rasfik",
    "wof:placetype":"locality"
},
  "geometry": {"coordinates":[19.76222000000001,41.72556],"type":"Point"}
}