{
  "type": "Feature",
  "properties": {
    "gn:admin1_code":"43",
    "gn:asciiname":"Gjashaj",
    "gn:country_code":"AL",
    "gn:dem":132,
    "gn:feature_class":"P",
    "gn:feature_code":"PPL",
    "gn:name":"Gjashaj",
    "gn:population":0,
    "gn:timezone":"Europe/Tirane",
    "iso:country":"AL",
    "wof:name":"Gjashaj",
    "wof:placetype":"locality"
},
  "geometry": {"coordinates":[19.88917,40.96278],"type":"Point"}
}