{
  "type": "Feature",
  "properties": {
    "gn:admin1_code":"41",
    "gn:asciiname":"Vinjoll",
    "gn:cc2":"AL",
    "gn:country_code":"AL",
    "gn:dem":615,
    "gn:feature_class":"P",
    "gn:feature_code":"PPL",
    "gn:name":"Vinjoll",
    "gn:population":0,
    "gn:timezone":"Europe/Tirane",
    "iso:country":"AL",
    "name:und_x_variant":[
        "Vinjall",
        "Vinjolli",
        "Vignali",
        "Vinjolla",
        "Vinjoll"
    ],
    "wof:name":"Vinjoll",
    "wof:placetype":"locality"
},
  "geometry": {"coordinates":[20.14222,41.62611],"type":"Point"}
}