{
  "type": "Feature",
  "properties": {
    "gn:admin1_code":"41",
    "gn:asciiname":"Limjan",
    "gn:cc2":"AL",
    "gn:country_code":"AL",
    "gn:dem":906,
    "gn:feature_class":"P",
    "gn:feature_code":"PPL",
    "gn:name":"Limjan",
    "gn:population":0,
    "gn:timezone":"Europe/Tirane",
    "iso:country":"AL",
    "name:und_x_variant":[
        "Limjani",
        "Limjan"
    ],
    "wof:name":"Limjan",
    "wof:placetype":"locality"
},
  "geometry": {"coordinates":[20.41,41.73833],"type":"Point"}
}