{
  "type": "Feature",
  "properties": {
    "gn:admin1_code":"51",
    "gn:asciiname":"Peshkepi",
    "gn:cc2":"AL",
    "gn:country_code":"AL",
    "gn:dem":59,
    "gn:feature_class":"P",
    "gn:feature_code":"PPL",
    "gn:name":"Peshk\u00ebpi",
    "gn:population":0,
    "gn:timezone":"Europe/Tirane",
    "iso:country":"AL",
    "name:und_x_variant":[
        "Peshkupi",
        "Piscupi",
        "Peshkep",
        "Peshk\u00ebpia",
        "Peshk\u00ebpi"
    ],
    "wof:name":"Peshkepi",
    "wof:placetype":"locality"
},
  "geometry": {"coordinates":[19.58556,40.47278],"type":"Point"}
}