{
  "type": "Feature",
  "properties": {
    "gn:admin1_code":"40",
    "gn:asciiname":"Bardhaj",
    "gn:country_code":"AL",
    "gn:dem":114,
    "gn:feature_class":"P",
    "gn:feature_code":"PPL",
    "gn:name":"Bardhaj",
    "gn:population":0,
    "gn:timezone":"Europe/Tirane",
    "iso:country":"AL",
    "wof:name":"Bardhaj",
    "wof:placetype":"locality"
},
  "geometry": {"coordinates":[19.97667,40.805],"type":"Point"}
}