{
  "type": "Feature",
  "properties": {
    "gn:admin1_code":"48",
    "gn:asciiname":"Kulme",
    "gn:country_code":"AL",
    "gn:dem":253,
    "gn:feature_class":"P",
    "gn:feature_code":"PPL",
    "gn:name":"Kulme",
    "gn:population":0,
    "gn:timezone":"Europe/Tirane",
    "iso:country":"AL",
    "wof:name":"Kulme",
    "wof:placetype":"locality"
},
  "geometry": {"coordinates":[19.81556,41.77139],"type":"Point"}
}