{
  "type": "Feature",
  "properties": {
    "gn:admin1_code":"40",
    "gn:asciiname":"Grepcke",
    "gn:cc2":"AL",
    "gn:country_code":"AL",
    "gn:dem":532,
    "gn:feature_class":"P",
    "gn:feature_code":"PPL",
    "gn:name":"Grepck\u00eb",
    "gn:population":0,
    "gn:timezone":"Europe/Tirane",
    "iso:country":"AL",
    "name:mkd_x_preferred":[
        "\u0413\u0440\u0435\u043f\u0446\u043a\u0430"
    ],
    "name:sqi_x_preferred":[
        "Grepcka"
    ],
    "name:tur_x_preferred":[
        "Grepcka"
    ],
    "name:und_x_variant":[
        "Krepsk\u00eb",
        "Grepck\u00eb-Dor\u00ebz",
        "Grepc\u00eb-Dor\u00ebzi",
        "Grepcka",
        "Gralisk\u00eb",
        "Grepsa",
        "Grepck\u00eb-Dorezi",
        "Grepck\u00eb"
    ],
    "wof:name":"Grepcke",
    "wof:placetype":"locality"
},
  "geometry": {"coordinates":[20.24528,40.47056],"type":"Point"}
}