{
  "type": "Feature",
  "properties": {
    "gn:admin1_code":"46",
    "gn:asciiname":"Qershize",
    "gn:country_code":"AL",
    "gn:dem":809,
    "gn:feature_class":"P",
    "gn:feature_code":"PPL",
    "gn:name":"Qershiz\u00eb",
    "gn:population":0,
    "gn:timezone":"Europe/Tirane",
    "iso:country":"AL",
    "wof:name":"Qershize",
    "wof:placetype":"locality"
},
  "geometry": {"coordinates":[20.71667,40.85],"type":"Point"}
}