{
  "type": "Feature",
  "properties": {
    "gn:admin1_code":"48",
    "gn:asciiname":"Delbnisht",
    "gn:cc2":"AL",
    "gn:country_code":"AL",
    "gn:dem":237,
    "gn:feature_class":"P",
    "gn:feature_code":"PPL",
    "gn:name":"Delbnisht",
    "gn:population":0,
    "gn:timezone":"Europe/Tirane",
    "iso:country":"AL",
    "name:und_x_variant":[
        "Selidelbinishti",
        "Dkelpnishte",
        "Selite-Delbinishtaj",
        "Delbnishtaj",
        "Dhelpnishte",
        "Delbnishti",
        "Delbini\u0161t",
        "Delbenisht",
        "Delbenishti",
        "Delbinisht",
        "Delbinishtaj",
        "Delbinishti",
        "Delbnisht"
    ],
    "wof:name":"Delbnisht",
    "wof:placetype":"locality"
},
  "geometry": {"coordinates":[19.73528,41.64833],"type":"Point"}
}