{
  "type": "Feature",
  "properties": {
    "gn:admin1_code":"43",
    "gn:asciiname":"Satlaket",
    "gn:country_code":"AL",
    "gn:dem":179,
    "gn:feature_class":"P",
    "gn:feature_code":"PPL",
    "gn:name":"Satlaket",
    "gn:population":0,
    "gn:timezone":"Europe/Tirane",
    "iso:country":"AL",
    "wof:name":"Satlaket",
    "wof:placetype":"locality"
},
  "geometry": {"coordinates":[19.9425,40.94139000000001],"type":"Point"}
}