{
  "type": "Feature",
  "properties": {
    "gn:admin1_code":"50",
    "gn:asciiname":"Rromanat",
    "gn:cc2":"AL",
    "gn:country_code":"AL",
    "gn:dem":144,
    "gn:feature_class":"P",
    "gn:feature_code":"PPL",
    "gn:name":"Rromanat",
    "gn:population":0,
    "gn:timezone":"Europe/Tirane",
    "iso:country":"AL",
    "name:und_x_variant":[
        "Gurkuqi",
        "Romanat",
        "Rahmanti",
        "Rumanatej"
    ],
    "wof:name":"Rromanat",
    "wof:placetype":"locality"
},
  "geometry": {"coordinates":[19.63333,41.23333],"type":"Point"}
}