{
  "type": "Feature",
  "properties": {
    "gn:admin1_code":"50",
    "gn:asciiname":"Selite",
    "gn:cc2":"AL",
    "gn:country_code":"AL",
    "gn:dem":114,
    "gn:feature_class":"P",
    "gn:feature_code":"PPL",
    "gn:name":"Selit\u00eb",
    "gn:population":0,
    "gn:timezone":"Europe/Tirane",
    "iso:country":"AL",
    "name:und_x_variant":[
        "Selita e Vog\u00ebl",
        "Selit\u00eb e Vog\u00ebl",
        "Selit\u00eb"
    ],
    "wof:name":"Selite",
    "wof:placetype":"locality"
},
  "geometry": {"coordinates":[19.775,41.31083],"type":"Point"}
}