{
  "type": "Feature",
  "properties": {
    "gn:admin1_code":"43",
    "gn:asciiname":"Zgjupe-Koder",
    "gn:cc2":"AL",
    "gn:country_code":"AL",
    "gn:dem":215,
    "gn:feature_class":"P",
    "gn:feature_code":"PPL",
    "gn:name":"Zgjup\u00eb-Kod\u00ebr",
    "gn:population":0,
    "gn:timezone":"Europe/Tirane",
    "iso:country":"AL",
    "name:und_x_variant":[
        "Qerret",
        "Zgjup\u00eb-Kod\u00ebr"
    ],
    "wof:name":"Zgjupe-Koder",
    "wof:placetype":"locality"
},
  "geometry": {"coordinates":[20.14806,40.90111],"type":"Point"}
}