{
  "type": "Feature",
  "properties": {
    "gn:admin1_code":"48",
    "gn:admin2_code":"12.0",
    "gn:asciiname":"Zejmen",
    "gn:cc2":"AL",
    "gn:country_code":"AL",
    "gn:dem":8,
    "gn:feature_class":"P",
    "gn:feature_code":"PPLA3",
    "gn:name":"Zejmen",
    "gn:population":0,
    "gn:timezone":"Europe/Tirane",
    "iso:country":"AL",
    "name:und_x_variant":[
        "Zojmendi",
        "Zejmeni",
        "Zojmen",
        "Zejmani",
        "Zejmen"
    ],
    "wof:name":"Zejmen",
    "wof:placetype":"locality"
},
  "geometry": {"coordinates":[19.68917,41.70778],"type":"Point"}
}