{
  "type": "Feature",
  "properties": {
    "gn:admin1_code":"45",
    "gn:admin2_code":"17.0",
    "gn:asciiname":"Piskove",
    "gn:cc2":"AL",
    "gn:country_code":"AL",
    "gn:dem":202,
    "gn:feature_class":"P",
    "gn:feature_code":"PPLA3",
    "gn:name":"Piskov\u00eb",
    "gn:population":0,
    "gn:timezone":"Europe/Tirane",
    "iso:country":"AL",
    "name:und_x_variant":[
        "Piskova",
        "Piskov\u00eb"
    ],
    "wof:name":"Piskove",
    "wof:placetype":"locality"
},
  "geometry": {"coordinates":[20.2725,40.27917],"type":"Point"}
}