{
  "type": "Feature",
  "properties": {
    "gn:admin1_code":"42",
    "gn:asciiname":"Shkallnur",
    "gn:cc2":"AL",
    "gn:country_code":"AL",
    "gn:dem":15,
    "gn:feature_class":"P",
    "gn:feature_code":"PPL",
    "gn:name":"Shkallnur",
    "gn:population":0,
    "gn:timezone":"Europe/Tirane",
    "iso:country":"AL",
    "name:und_x_variant":[
        "Shkallnueri",
        "Shkallnuri",
        "Shkallnuer",
        "Shkallngur",
        "\u0160kalngur",
        "Skalgrah",
        "Shkallnduer",
        "Shkallnur"
    ],
    "wof:name":"Shkallnur",
    "wof:placetype":"locality"
},
  "geometry": {"coordinates":[19.51694,41.29028],"type":"Point"}
}