{
  "type": "Feature",
  "properties": {
    "gn:admin1_code":"43",
    "gn:asciiname":"Gurras",
    "gn:cc2":"AL",
    "gn:country_code":"AL",
    "gn:dem":132,
    "gn:feature_class":"P",
    "gn:feature_code":"PPL",
    "gn:name":"Gurras",
    "gn:population":0,
    "gn:timezone":"Europe/Tirane",
    "iso:country":"AL",
    "name:und_x_variant":[
        "Gurasi",
        "Guraz",
        "Gurrasi",
        "Guras",
        "Guri-zi",
        "Gurazi",
        "Gurrsi",
        "Gurras"
    ],
    "wof:name":"Gurras",
    "wof:placetype":"locality"
},
  "geometry": {"coordinates":[19.95167,40.91972],"type":"Point"}
}