{
  "type": "Feature",
  "properties": {
    "gn:admin1_code":"49",
    "gn:asciiname":"Prangull",
    "gn:cc2":"AL",
    "gn:country_code":"AL",
    "gn:dem":522,
    "gn:feature_class":"P",
    "gn:feature_code":"PPL",
    "gn:name":"Prangull",
    "gn:population":0,
    "gn:timezone":"Europe/Tirane",
    "iso:country":"AL",
    "name:und_x_variant":[
        "Prangulli",
        "Markndonaj",
        "Prangull"
    ],
    "wof:name":"Prangull",
    "wof:placetype":"locality"
},
  "geometry": {"coordinates":[19.71472,42.23194],"type":"Point"}
}