{
  "type": "Feature",
  "properties": {
    "gn:admin1_code":"44",
    "gn:asciiname":"Arapaj",
    "gn:cc2":"AL",
    "gn:country_code":"AL",
    "gn:dem":12,
    "gn:feature_class":"P",
    "gn:feature_code":"PPL",
    "gn:name":"Arapaj",
    "gn:population":0,
    "gn:timezone":"Europe/Tirane",
    "iso:country":"AL",
    "name:sco_x_preferred":[
        "Arapaj"
    ],
    "name:sqi_x_preferred":[
        "Arapaj"
    ],
    "name:swe_x_preferred":[
        "Arapaj"
    ],
    "name:tur_x_preferred":[
        "Arapaj"
    ],
    "name:ukr_x_preferred":[
        "\u0410\u0440\u0430\u043f\u0430\u0439"
    ],
    "name:und_x_variant":[
        "Arapaj \u00c7omleka",
        "Arapan"
    ],
    "wof:name":"Arapaj",
    "wof:placetype":"locality"
},
  "geometry": {"coordinates":[19.72083,40.805],"type":"Point"}
}