{
  "type": "Feature",
  "properties": {
    "gn:admin1_code":"47",
    "gn:asciiname":"Stoberte",
    "gn:cc2":"AL",
    "gn:country_code":"AL",
    "gn:dem":854,
    "gn:feature_class":"P",
    "gn:feature_code":"PPL",
    "gn:name":"Stobert\u00eb",
    "gn:population":0,
    "gn:timezone":"Europe/Tirane",
    "iso:country":"AL",
    "name:und_x_variant":[
        "Stoberta",
        "Stobert\u00eb"
    ],
    "wof:name":"Stoberte",
    "wof:placetype":"locality"
},
  "geometry": {"coordinates":[20.25222,42.31472],"type":"Point"}
}