{
  "type": "Feature",
  "properties": {
    "gn:admin1_code":"42",
    "gn:asciiname":"Borake",
    "gn:cc2":"AL",
    "gn:country_code":"AL",
    "gn:dem":42,
    "gn:feature_class":"P",
    "gn:feature_code":"PPL",
    "gn:name":"Borak\u00eb",
    "gn:population":0,
    "gn:timezone":"Europe/Tirane",
    "iso:country":"AL",
    "name:und_x_variant":[
        "Boraka",
        "Barak",
        "Barake",
        "Borakaj",
        "Barakaj",
        "Bakaj",
        "Borak\u00eb"
    ],
    "wof:name":"Borake",
    "wof:placetype":"locality"
},
  "geometry": {"coordinates":[19.55972,41.35694],"type":"Point"}
}