{
  "type": "Feature",
  "properties": {
    "gn:admin1_code":"49",
    "gn:asciiname":"Cesme e Koplikut",
    "gn:cc2":"AL",
    "gn:country_code":"AL",
    "gn:dem":27,
    "gn:feature_class":"P",
    "gn:feature_code":"PPL",
    "gn:name":"\u00c7esme e Koplikut",
    "gn:population":0,
    "gn:timezone":"Europe/Tirane",
    "iso:country":"AL",
    "name:und_x_variant":[
        "\u00c7ezmja e Koplikut"
    ],
    "wof:name":"Cesme e Koplikut",
    "wof:placetype":"locality"
},
  "geometry": {"coordinates":[19.46,42.18139],"type":"Point"}
}