{
  "type": "Feature",
  "properties": {
    "gn:admin1_code":"43",
    "gn:asciiname":"Ciflik",
    "gn:country_code":"AL",
    "gn:dem":315,
    "gn:feature_class":"P",
    "gn:feature_code":"PPL",
    "gn:name":"\u00c7iflik",
    "gn:population":0,
    "gn:timezone":"Europe/Tirane",
    "iso:country":"AL",
    "wof:name":"Ciflik",
    "wof:placetype":"locality"
},
  "geometry": {"coordinates":[20.16056,40.83],"type":"Point"}
}