{
  "type": "Feature",
  "properties": {
    "gn:admin1_code":"46",
    "gn:asciiname":"Stropcke",
    "gn:cc2":"AL",
    "gn:country_code":"AL",
    "gn:dem":870,
    "gn:feature_class":"P",
    "gn:feature_code":"PPL",
    "gn:name":"Stropck\u00eb",
    "gn:population":0,
    "gn:timezone":"Europe/Tirane",
    "iso:country":"AL",
    "name:mkd_x_preferred":[
        "\u0421\u0442\u0440\u043e\u043f\u0435\u043a\u0430"
    ],
    "name:mkd_x_variant":[
        "\u0421\u0442\u0440\u043e\u043f\u0438\u0446\u0430"
    ],
    "name:und_x_variant":[
        "Stropcka",
        "Stropoke",
        "Stropeku",
        "Stropeka",
        "Stropk\u00eb",
        "Stropck\u00eb"
    ],
    "wof:name":"Stropcke",
    "wof:placetype":"locality"
},
  "geometry": {"coordinates":[20.68306,40.85306],"type":"Point"}
}