{
  "type": "Feature",
  "properties": {
    "gn:admin1_code":"43",
    "gn:asciiname":"Gjevor",
    "gn:cc2":"AL",
    "gn:country_code":"AL",
    "gn:dem":241,
    "gn:feature_class":"P",
    "gn:feature_code":"PPL",
    "gn:name":"Gjevor",
    "gn:population":0,
    "gn:timezone":"Europe/Tirane",
    "iso:country":"AL",
    "name:und_x_variant":[
        "\u00d0avort",
        "Gjevori",
        "Gjavuri",
        "Gjavueri",
        "Gjevuri",
        "Gjevur",
        "Gjevor"
    ],
    "wof:name":"Gjevor",
    "wof:placetype":"locality"
},
  "geometry": {"coordinates":[19.78083,41.06556],"type":"Point"}
}