{
  "type": "Feature",
  "properties": {
    "gn:admin1_code":"43",
    "gn:asciiname":"Dufshan",
    "gn:cc2":"AL",
    "gn:country_code":"AL",
    "gn:dem":460,
    "gn:feature_class":"P",
    "gn:feature_code":"PPL",
    "gn:name":"Dufshan",
    "gn:population":0,
    "gn:timezone":"Europe/Tirane",
    "iso:country":"AL",
    "name:und_x_variant":[
        "Dufshani",
        "Dufshan"
    ],
    "wof:name":"Dufshan",
    "wof:placetype":"locality"
},
  "geometry": {"coordinates":[20.12111,40.87833],"type":"Point"}
}