{
  "type": "Feature",
  "properties": {
    "gn:admin1_code":"43",
    "gn:admin2_code":"4.0",
    "gn:asciiname":"Mollas",
    "gn:cc2":"AL",
    "gn:country_code":"AL",
    "gn:dem":110,
    "gn:feature_class":"P",
    "gn:feature_code":"PPLA3",
    "gn:name":"Mollas",
    "gn:population":0,
    "gn:timezone":"Europe/Tirane",
    "iso:country":"AL",
    "name:ita_x_preferred":[
        "Mollas"
    ],
    "name:msa_x_preferred":[
        "Mollas"
    ],
    "name:pol_x_preferred":[
        "Gmina Mollas"
    ],
    "name:por_x_preferred":[
        "Mollas"
    ],
    "name:spa_x_preferred":[
        "Mollas"
    ],
    "name:tur_x_preferred":[
        "Mollas"
    ],
    "name:und_x_variant":[
        "Motas",
        "Maulas",
        "Mollasi"
    ],
    "name:vie_x_preferred":[
        "Mollas"
    ],
    "name:war_x_preferred":[
        "Mollas"
    ],
    "wof:name":"Mollas",
    "wof:placetype":"locality"
},
  "geometry": {"coordinates":[20.00361,40.92694],"type":"Point"}
}