{
  "type": "Feature",
  "properties": {
    "gn:admin1_code":"49",
    "gn:asciiname":"Mushan",
    "gn:cc2":"AL",
    "gn:country_code":"AL",
    "gn:dem":5,
    "gn:feature_class":"P",
    "gn:feature_code":"PPL",
    "gn:name":"Mushan",
    "gn:population":0,
    "gn:timezone":"Europe/Tirane",
    "iso:country":"AL",
    "name:ceb_x_preferred":[
        "Mushan"
    ],
    "name:swe_x_preferred":[
        "Mushan"
    ],
    "name:und_x_variant":[
        "Mushani",
        "Muzhan",
        "Mu\u017ean"
    ],
    "wof:name":"Mushan",
    "wof:placetype":"locality"
},
  "geometry": {"coordinates":[19.435,41.97889],"type":"Point"}
}