{
  "type": "Feature",
  "properties": {
    "gn:admin1_code":"44",
    "gn:admin2_code":"37.0",
    "gn:asciiname":"Kalenje",
    "gn:cc2":"AL",
    "gn:country_code":"AL",
    "gn:dem":508,
    "gn:feature_class":"P",
    "gn:feature_code":"PPLA3",
    "gn:name":"Kalenj\u00eb",
    "gn:population":0,
    "gn:timezone":"Europe/Tirane",
    "iso:country":"AL",
    "name:und_x_variant":[
        "Kahlenja",
        "Kalenja",
        "Kalenj",
        "Kalenj\u00eb"
    ],
    "wof:name":"Kalenje",
    "wof:placetype":"locality"
},
  "geometry": {"coordinates":[19.77833,40.59],"type":"Point"}
}