{
  "type": "Feature",
  "properties": {
    "gn:admin1_code":"40",
    "gn:asciiname":"Prokop",
    "gn:cc2":"AL",
    "gn:country_code":"AL",
    "gn:dem":582,
    "gn:feature_class":"P",
    "gn:feature_code":"PPL",
    "gn:name":"Prokop",
    "gn:population":0,
    "gn:timezone":"Europe/Tirane",
    "iso:country":"AL",
    "name:bos_x_preferred":[
        "Prokop"
    ],
    "name:ceb_x_preferred":[
        "Prokop"
    ],
    "name:ces_x_preferred":[
        "Prokop"
    ],
    "name:deu_x_preferred":[
        "Prokop"
    ],
    "name:ita_x_preferred":[
        "Prokop"
    ],
    "name:nds_x_preferred":[
        "Prokop"
    ],
    "name:swe_x_preferred":[
        "Prokop"
    ],
    "name:und_x_variant":[
        "Prokopi"
    ],
    "wof:name":"Prokop",
    "wof:placetype":"locality"
},
  "geometry": {"coordinates":[19.88,40.6725],"type":"Point"}
}