{
  "type": "Feature",
  "properties": {
    "gn:admin1_code":"48",
    "gn:asciiname":"Skuraj",
    "gn:cc2":"AL",
    "gn:country_code":"AL",
    "gn:dem":95,
    "gn:feature_class":"P",
    "gn:feature_code":"PPL",
    "gn:name":"Skuraj",
    "gn:population":0,
    "gn:timezone":"Europe/Tirane",
    "iso:country":"AL",
    "name:und_x_variant":[
        "Scuraji",
        "Scuraj",
        "Skurajvit",
        "Skurraj",
        "Skorovot",
        "Skuraj"
    ],
    "wof:name":"Skuraj",
    "wof:placetype":"locality"
},
  "geometry": {"coordinates":[19.79639,41.68861],"type":"Point"}
}