{
  "type": "Feature",
  "properties": {
    "gn:admin1_code":"46",
    "gn:asciiname":"Marjan",
    "gn:cc2":"AL",
    "gn:country_code":"AL",
    "gn:dem":1048,
    "gn:feature_class":"P",
    "gn:feature_code":"PPL",
    "gn:name":"Marjan",
    "gn:population":0,
    "gn:timezone":"Europe/Tirane",
    "iso:country":"AL",
    "name:ceb_x_preferred":[
        "Marjan"
    ],
    "name:deu_x_preferred":[
        "Marjan"
    ],
    "name:fas_x_preferred":[
        "\u0645\u0631\u062c\u0627\u0646"
    ],
    "name:fra_x_preferred":[
        "Marjan"
    ],
    "name:swe_x_preferred":[
        "Marjan"
    ],
    "name:und_x_variant":[
        "Mariani",
        "Marjani",
        "Marjan"
    ],
    "wof:name":"Marjan",
    "wof:placetype":"locality"
},
  "geometry": {"coordinates":[20.62667,40.76194],"type":"Point"}
}