{
  "type": "Feature",
  "properties": {
    "gn:admin1_code":"51",
    "gn:asciiname":"Alopul",
    "gn:cc2":"AL",
    "gn:country_code":"AL",
    "gn:dem":698,
    "gn:feature_class":"P",
    "gn:feature_code":"PPL",
    "gn:name":"Alopul",
    "gn:population":0,
    "gn:timezone":"Europe/Tirane",
    "iso:country":"AL",
    "name:und_x_variant":[
        "Alopuli",
        "Alopul"
    ],
    "wof:name":"Alopul",
    "wof:placetype":"locality"
},
  "geometry": {"coordinates":[20.26944,39.83528],"type":"Point"}
}