{
  "type": "Feature",
  "properties": {
    "gn:admin1_code":"49",
    "gn:asciiname":"Meshqerre",
    "gn:cc2":"AL",
    "gn:country_code":"AL",
    "gn:dem":76,
    "gn:feature_class":"P",
    "gn:feature_code":"PPL",
    "gn:name":"M\u00ebshqerr\u00eb",
    "gn:population":0,
    "gn:timezone":"Europe/Tirane",
    "iso:country":"AL",
    "name:sqi_x_preferred":[
        "Mushqerra"
    ],
    "name:und_x_variant":[
        "Dud\u011b",
        "M\u00ebshqerra",
        "M\u00ebshqerr\u00eb"
    ],
    "wof:name":"Meshqerre",
    "wof:placetype":"locality"
},
  "geometry": {"coordinates":[19.50333,42.17611],"type":"Point"}
}