{
  "type": "Feature",
  "properties": {
    "gn:admin1_code":"51",
    "gn:asciiname":"Metoq",
    "gn:cc2":"AL",
    "gn:country_code":"AL",
    "gn:dem":18,
    "gn:feature_class":"P",
    "gn:feature_code":"PPL",
    "gn:name":"Metoq",
    "gn:population":0,
    "gn:timezone":"Europe/Tirane",
    "iso:country":"AL",
    "name:und_x_variant":[
        "Metogjashta",
        "Metohi",
        "Metoqi"
    ],
    "wof:name":"Metoq",
    "wof:placetype":"locality"
},
  "geometry": {"coordinates":[20.04556,39.88333],"type":"Point"}
}