{
  "type": "Feature",
  "properties": {
    "gn:admin1_code":"44",
    "gn:asciiname":"Vidhishte",
    "gn:cc2":"AL",
    "gn:country_code":"AL",
    "gn:dem":25,
    "gn:feature_class":"P",
    "gn:feature_code":"PPL",
    "gn:name":"Vidhisht\u00eb",
    "gn:population":0,
    "gn:timezone":"Europe/Tirane",
    "iso:country":"AL",
    "name:und_x_variant":[
        "Vidhishta",
        "Vivishta",
        "Vidhisht\u00eb"
    ],
    "wof:name":"Vidhishte",
    "wof:placetype":"locality"
},
  "geometry": {"coordinates":[19.69778,40.71861],"type":"Point"}
}