{
  "type": "Feature",
  "properties": {
    "gn:admin1_code":"40",
    "gn:asciiname":"Turanet",
    "gn:country_code":"AL",
    "gn:dem":617,
    "gn:feature_class":"P",
    "gn:feature_code":"PPL",
    "gn:name":"Turan\u00ebt",
    "gn:population":0,
    "gn:timezone":"Europe/Tirane",
    "iso:country":"AL",
    "wof:name":"Turanet",
    "wof:placetype":"locality"
},
  "geometry": {"coordinates":[20.07778,40.77639],"type":"Point"}
}