{
  "type": "Feature",
  "properties": {
    "gn:admin1_code":"48",
    "gn:asciiname":"Prosek",
    "gn:cc2":"AL",
    "gn:country_code":"AL",
    "gn:dem":257,
    "gn:feature_class":"P",
    "gn:feature_code":"PPL",
    "gn:name":"Prosek",
    "gn:population":0,
    "gn:timezone":"Europe/Tirane",
    "iso:country":"AL",
    "name:bul_x_preferred":[
        "\u041f\u0440\u043e\u0441\u0435\u043a"
    ],
    "name:mkd_x_preferred":[
        "\u041f\u0440\u043e\u0441\u0435\u043a"
    ],
    "name:por_x_preferred":[
        "Prosek"
    ],
    "name:spa_x_preferred":[
        "Prosek"
    ],
    "name:und_x_variant":[
        "Proseca",
        "Proseku"
    ],
    "wof:name":"Prosek",
    "wof:placetype":"locality"
},
  "geometry": {"coordinates":[19.94861,41.74556],"type":"Point"}
}