{
  "type": "Feature",
  "properties": {
    "gn:admin1_code":"47",
    "gn:asciiname":"Brenoge",
    "gn:cc2":"AL",
    "gn:country_code":"AL",
    "gn:dem":427,
    "gn:feature_class":"P",
    "gn:feature_code":"PPL",
    "gn:name":"Brenog\u00eb",
    "gn:population":0,
    "gn:timezone":"Europe/Tirane",
    "iso:country":"AL",
    "name:und_x_variant":[
        "Brahog",
        "Branog",
        "Branag\u00eb",
        "Branag",
        "Brenog\u00eb"
    ],
    "wof:name":"Brenoge",
    "wof:placetype":"locality"
},
  "geometry": {"coordinates":[20.31417,42.15889],"type":"Point"}
}