{
  "type": "Feature",
  "properties": {
    "gn:country":"AL",
    "gn:fcode":"PPLA3",
    "gn:population":2604,
    "iso:country":"AL",
    "name:bul_x_preferred":[
        "\u041e\u0440\u0438\u043a\u0443\u043c"
    ],
    "name:ceb_x_preferred":[
        "Bashkia e Orikumit"
    ],
    "name:ces_x_preferred":[
        "Orikumi"
    ],
    "name:deu_x_preferred":[
        "Orikum"
    ],
    "name:eng_x_preferred":[
        "Orikum"
    ],
    "name:fra_x_preferred":[
        "Orikum"
    ],
    "name:hun_x_preferred":[
        "Orikum"
    ],
    "name:ita_x_preferred":[
        "Orikum"
    ],
    "name:mkd_x_preferred":[
        "\u041e\u0440\u0438\u043a\u0443\u043c"
    ],
    "name:nld_x_preferred":[
        "Orikum"
    ],
    "name:pol_x_preferred":[
        "Orikum"
    ],
    "name:por_x_preferred":[
        "Orikum"
    ],
    "name:ron_x_preferred":[
        "Orikum"
    ],
    "name:rus_x_preferred":[
        "\u041e\u0440\u0438\u043a\u0443\u043c"
    ],
    "name:sqi_x_preferred":[
        "Orikumi"
    ],
    "name:swe_x_preferred":[
        "Bashkia e Orikumit"
    ],
    "name:tat_x_preferred":[
        "\u041e\u0440\u0438\u043a\u0443\u043c"
    ],
    "name:tur_x_preferred":[
        "Orikum"
    ],
    "name:ukr_x_preferred":[
        "\u041e\u0440\u0456\u043a\u0443\u043c"
    ],
    "name:vie_x_preferred":[
        "Orikum"
    ],
    "name:war_x_preferred":[
        "Orikum"
    ],
    "name:zho_x_preferred":[
        "\u5967\u91cc\u5eab\u59c6"
    ],
    "qs:gn_pop":0,
    "qs:name":"Orikum",
    "qs:name_adm0":"Shqip\u00ebri",
    "qs:name_adm1":"Vlor\u00eb",
    "qs:photos":52,
    "qs:photos_1k":11,
    "qs:photos_9k":1,
    "qs:photos_9r":2,
    "qs:photos_all":52,
    "qs:photos_sr":2,
    "qs:placetype":"Town",
    "qs:pop_sr":"0",
    "qs:woe_adm0":23424742,
    "wd:wordcount":107,
    "wof:name":"Orikum",
    "wof:placetype":"locality",
    "wof:population":2604
},
  "geometry": {"coordinates":[19.4661425,40.326262],"type":"Point"}
}