{
  "type": "Feature",
  "properties": {
    "gn:admin1_code":"48",
    "gn:asciiname":"Zheje",
    "gn:cc2":"AL",
    "gn:country_code":"AL",
    "gn:dem":35,
    "gn:feature_class":"P",
    "gn:feature_code":"PPL",
    "gn:name":"Zhej\u00eb",
    "gn:population":0,
    "gn:timezone":"Europe/Tirane",
    "iso:country":"AL",
    "name:und_x_variant":[
        "Zhej",
        "Zhej\u00ebs",
        "Zheji",
        "Zheja",
        "Zhej\u00eb"
    ],
    "wof:name":"Zheje",
    "wof:placetype":"locality"
},
  "geometry": {"coordinates":[19.71972,41.59306],"type":"Point"}
}