{
  "type": "Feature",
  "properties": {
    "gn:admin1_code":"43",
    "gn:asciiname":"Borove",
    "gn:cc2":"AL",
    "gn:country_code":"AL",
    "gn:dem":927,
    "gn:feature_class":"P",
    "gn:feature_code":"PPL",
    "gn:name":"Borov\u00eb",
    "gn:population":0,
    "gn:timezone":"Europe/Tirane",
    "iso:country":"AL",
    "name:mkd_x_preferred":[
        "\u0411\u043e\u0440\u043e\u0432\u043e"
    ],
    "name:und_x_variant":[
        "Brinjasi",
        "Borova",
        "Borov\u00eb"
    ],
    "wof:name":"Borove",
    "wof:placetype":"locality"
},
  "geometry": {"coordinates":[20.42806,41.35111],"type":"Point"}
}