{
  "type": "Feature",
  "properties": {
    "gn:admin1_code":"46",
    "gn:asciiname":"Nevicisht",
    "gn:cc2":"AL",
    "gn:country_code":"AL",
    "gn:dem":909,
    "gn:feature_class":"P",
    "gn:feature_code":"PPL",
    "gn:name":"Nevi\u00e7isht",
    "gn:population":0,
    "gn:timezone":"Europe/Tirane",
    "iso:country":"AL",
    "name:und_x_variant":[
        "Neviciste",
        "Nevi\u00e7ishta",
        "Nevi\u00e7ishti",
        "Nevi\u00e7isht"
    ],
    "wof:name":"Nevicisht",
    "wof:placetype":"locality"
},
  "geometry": {"coordinates":[20.82583,40.65944],"type":"Point"}
}