{
  "type": "Feature",
  "properties": {
    "gn:admin1_code":"43",
    "gn:asciiname":"Cestije",
    "gn:country_code":"AL",
    "gn:dem":151,
    "gn:feature_class":"P",
    "gn:feature_code":"PPL",
    "gn:name":"\u00c7estije",
    "gn:population":0,
    "gn:timezone":"Europe/Tirane",
    "iso:country":"AL",
    "wof:name":"Cestije",
    "wof:placetype":"locality"
},
  "geometry": {"coordinates":[19.86389,40.90833],"type":"Point"}
}