{
  "type": "Feature",
  "properties": {
    "gn:admin1_code":"48",
    "gn:admin2_code":"12.0",
    "gn:asciiname":"Kallmeti i Madh",
    "gn:cc2":"AL",
    "gn:country_code":"AL",
    "gn:dem":61,
    "gn:feature_class":"P",
    "gn:feature_code":"PPLA3",
    "gn:name":"Kallmeti i Madh",
    "gn:population":0,
    "gn:timezone":"Europe/Tirane",
    "iso:country":"AL",
    "name:und_x_variant":[
        "Calmeti",
        "Kallmeti i Math",
        "Kallmet i Math",
        "Kallheti i Math",
        "Kalmet",
        "Kallmeti",
        "Kallmet",
        "Kallmet i Madh",
        "Kallmeti i Madh"
    ],
    "wof:name":"Kallmeti i Madh",
    "wof:placetype":"locality"
},
  "geometry": {"coordinates":[19.68694,41.84889],"type":"Point"}
}