{
  "type": "Feature",
  "properties": {
    "gn:admin1_code":"45",
    "gn:asciiname":"Kakoz",
    "gn:cc2":"AL",
    "gn:country_code":"AL",
    "gn:dem":360,
    "gn:feature_class":"P",
    "gn:feature_code":"PPL",
    "gn:name":"Kakoz",
    "gn:population":0,
    "gn:timezone":"Europe/Tirane",
    "iso:country":"AL",
    "name:und_x_variant":[
        "Cacossi",
        "Kakos",
        "Kokos",
        "Kakozi",
        "Kakoz"
    ],
    "wof:name":"Kakoz",
    "wof:placetype":"locality"
},
  "geometry": {"coordinates":[20.15306,40.16472],"type":"Point"}
}