{
  "type": "Feature",
  "properties": {
    "gn:admin1_code":"44",
    "gn:asciiname":"Bishtqethem",
    "gn:cc2":"AL",
    "gn:country_code":"AL",
    "gn:dem":10,
    "gn:feature_class":"P",
    "gn:feature_code":"PPL",
    "gn:name":"Bishtqeth\u00ebm",
    "gn:population":0,
    "gn:timezone":"Europe/Tirane",
    "iso:country":"AL",
    "name:und_x_variant":[
        "Lagje e Stanit",
        "Bishqeth\u00ebmi",
        "Bishqetmi",
        "Bishgethun",
        "Bishqethun",
        "Bishtqethuni",
        "Bishqethuni",
        "Bishqeth\u00ebm",
        "Bishkesmi",
        "Bishqethdni",
        "Bishqethmi",
        "Bishqemthi",
        "Bishtqeth\u00ebm"
    ],
    "wof:name":"Bishtqethem",
    "wof:placetype":"locality"
},
  "geometry": {"coordinates":[19.65889,40.86722],"type":"Point"}
}