{
  "type": "Feature",
  "properties": {
    "gn:admin1_code":"51",
    "gn:asciiname":"Fushe-Verri",
    "gn:cc2":"AL",
    "gn:country_code":"AL",
    "gn:dem":188,
    "gn:feature_class":"P",
    "gn:feature_code":"PPL",
    "gn:name":"Fush\u00eb-V\u00ebrri",
    "gn:population":0,
    "gn:timezone":"Europe/Tirane",
    "iso:country":"AL",
    "name:und_x_variant":[
        "Fush\u00eb-V\u00ebrri\u00eb",
        "Fush\u00eb-V\u00ebrrij\u00eb",
        "Fush\u00eb-V\u00ebrrinja",
        "Fush\u00eb-V\u00ebrija",
        "Fush\u00eb-V\u00ebrrija",
        "Fush\u00eb-V\u00ebrria",
        "Fush\u00eb-Vrinja",
        "Fush\u00eb-V\u00ebrri"
    ],
    "wof:name":"Fushe-Verri",
    "wof:placetype":"locality"
},
  "geometry": {"coordinates":[19.99889,39.99972],"type":"Point"}
}