{
  "type": "Feature",
  "properties": {
    "gn:admin1_code":"49",
    "gn:asciiname":"Malas",
    "gn:country_code":"AL",
    "gn:dem":85,
    "gn:feature_class":"P",
    "gn:feature_code":"PPL",
    "gn:name":"Malas",
    "gn:population":0,
    "gn:timezone":"Europe/Tirane",
    "iso:country":"AL",
    "name:ceb_x_preferred":[
        "Malas"
    ],
    "name:deu_x_preferred":[
        "Malas"
    ],
    "wof:name":"Malas",
    "wof:placetype":"locality"
},
  "geometry": {"coordinates":[19.69917,42.08528],"type":"Point"}
}