{
  "type": "Feature",
  "properties": {
    "gn:admin1_code":"43",
    "gn:asciiname":"Hyre",
    "gn:cc2":"AL",
    "gn:country_code":"AL",
    "gn:dem":319,
    "gn:feature_class":"P",
    "gn:feature_code":"PPL",
    "gn:name":"Hyre",
    "gn:population":0,
    "gn:timezone":"Europe/Tirane",
    "iso:country":"AL",
    "name:und_x_variant":[
        "Helej",
        "Hyre"
    ],
    "wof:name":"Hyre",
    "wof:placetype":"locality"
},
  "geometry": {"coordinates":[19.74222,41.08778],"type":"Point"}
}