{
  "type": "Feature",
  "properties": {
    "gn:country":"AL",
    "gn:fcode":"PPLA3",
    "gn:population":1349,
    "iso:country":"AL",
    "name:bul_x_preferred":[
        "\u041a\u043e\u043d\u0438\u0441\u043f\u043e\u043b"
    ],
    "name:cat_x_preferred":[
        "Konispol"
    ],
    "name:ces_x_preferred":[
        "Konispol"
    ],
    "name:deu_x_preferred":[
        "Konispol"
    ],
    "name:ell_x_preferred":[
        "Konispolis"
    ],
    "name:ell_x_variant":[
        "Konispoli",
        "\u039a\u03bf\u03bd\u03af\u03c3\u03c0\u03bf\u03bb\u03b7"
    ],
    "name:eng_x_preferred":[
        "Konispol"
    ],
    "name:fas_x_preferred":[
        "\u06a9\u0648\u0646\u06cc\u0633\u067e\u0648\u0644"
    ],
    "name:fin_x_preferred":[
        "Konispol"
    ],
    "name:fra_x_preferred":[
        "Konispol"
    ],
    "name:hun_x_preferred":[
        "Konispol"
    ],
    "name:hye_x_preferred":[
        "\u053f\u0578\u0576\u056b\u057d\u057a\u0578\u056c"
    ],
    "name:ita_x_preferred":[
        "Konispol"
    ],
    "name:jpn_x_preferred":[
        "\u30b3\u30cb\u30b9\u30dd"
    ],
    "name:mkd_x_preferred":[
        "\u041a\u043e\u043d\u0438\u0441\u043f\u043e\u043b"
    ],
    "name:nld_x_preferred":[
        "Konispol"
    ],
    "name:oci_x_preferred":[
        "Konispol"
    ],
    "name:pol_x_preferred":[
        "Konispol"
    ],
    "name:por_x_preferred":[
        "Konispol"
    ],
    "name:ron_x_preferred":[
        "Konispol"
    ],
    "name:rus_x_preferred":[
        "\u041a\u043e\u043d\u0438\u0441\u043f\u043e\u043b\u044c"
    ],
    "name:slk_x_preferred":[
        "Konispol"
    ],
    "name:spa_x_preferred":[
        "Konispol"
    ],
    "name:sqi_x_preferred":[
        "Konispol"
    ],
    "name:sqi_x_variant":[
        "Konispoli"
    ],
    "name:swe_x_preferred":[
        "Konispoli"
    ],
    "name:tat_x_preferred":[
        "\u041a\u043e\u043d\u0438\u0441\u043f\u043e\u043b"
    ],
    "name:tur_x_preferred":[
        "Konispol"
    ],
    "name:ukr_x_preferred":[
        "\u041a\u043e\u043d\u0456\u0441\u043f\u043e\u043b\u044c"
    ],
    "name:und_x_variant":[
        "Conispolis"
    ],
    "name:vie_x_preferred":[
        "Konispol"
    ],
    "name:war_x_preferred":[
        "Konispol"
    ],
    "name:zho_x_preferred":[
        "\u79d1\u5c3c\u65af\u6ce2\u5c14"
    ],
    "qs_pg:aaroncc":"AL",
    "qs_pg:gn_country":"AL",
    "qs_pg:gn_fcode":"PPLA3",
    "qs_pg:gn_pop":1349,
    "qs_pg:name":"Konispol",
    "qs_pg:photos_9r":0,
    "qs_pg:photos_sr":0,
    "qs_pg:pop_sr":3,
    "qs_pg:qs_pg_placetype":"locality",
    "wof:name":"Konispol",
    "wof:placetype":"locality",
    "wof:population":1349
},
  "geometry": {"coordinates":[20.18139,39.65889],"type":"Point"}
}