{
  "type": "Feature",
  "properties": {
    "gn:country":"AL",
    "gn:fcode":"PPLA3",
    "gn:population":4,
    "iso:country":"AL",
    "name:cat_x_preferred":[
        "Ul\u00ebz"
    ],
    "name:deu_x_preferred":[
        "Ulza"
    ],
    "name:eng_x_preferred":[
        "Ul\u00ebz"
    ],
    "name:fas_x_preferred":[
        "\u0627\u0648\u0644\u0632"
    ],
    "name:fra_x_preferred":[
        "Ul\u00ebz"
    ],
    "name:hun_x_preferred":[
        "Ulza"
    ],
    "name:ita_x_preferred":[
        "Ul\u00ebz"
    ],
    "name:msa_x_preferred":[
        "Ul\u00ebz"
    ],
    "name:nld_x_preferred":[
        "Ul\u00ebz"
    ],
    "name:nno_x_preferred":[
        "Ul\u00ebz"
    ],
    "name:pol_x_preferred":[
        "Gmina Ul\u00ebz"
    ],
    "name:por_x_preferred":[
        "Ul\u00ebz"
    ],
    "name:ron_x_preferred":[
        "Ulza"
    ],
    "name:spa_x_preferred":[
        "Ul\u00ebz"
    ],
    "name:sqi_x_preferred":[
        "Komuna Ul\u00ebz"
    ],
    "name:tat_x_preferred":[
        "\u0423\u043b\u044b\u0437"
    ],
    "name:tur_x_preferred":[
        "Ulza"
    ],
    "name:und_x_variant":[
        "Ul\u00ebza"
    ],
    "name:vie_x_preferred":[
        "Ul\u00ebz"
    ],
    "name:war_x_preferred":[
        "Ul\u00ebz"
    ],
    "qs:name":"Ul\u00ebz",
    "qs:photos_9r":0,
    "qs:photos_sr":0,
    "qs:pop_sr":"1",
    "wd:wordcount":69,
    "wof:name":"Ul\u00ebz",
    "wof:placetype":"locality",
    "wof:population":4
},
  "geometry": {"coordinates":[19.89333,41.68278],"type":"Point"}
}