{
  "type": "Feature",
  "properties": {
    "gn:admin1_code":"51",
    "gn:asciiname":"Blerimas",
    "gn:cc2":"AL",
    "gn:country_code":"AL",
    "gn:dem":47,
    "gn:feature_class":"P",
    "gn:feature_code":"PPL",
    "gn:name":"Blerimas",
    "gn:population":0,
    "gn:timezone":"Europe/Tirane",
    "iso:country":"AL",
    "name:und_x_variant":[
        "Sajan",
        "Blerime",
        "Shijan",
        "Blerimasi",
        "Shian",
        "Shen-Jan",
        "Saiant",
        "Shijani",
        "Blerimas"
    ],
    "wof:name":"Blerimas",
    "wof:placetype":"locality"
},
  "geometry": {"coordinates":[20.04083,39.91833],"type":"Point"}
}