{
  "type": "Feature",
  "properties": {
    "gn:admin1_code":"48",
    "gn:asciiname":"Gryke-Manati",
    "gn:cc2":"AL",
    "gn:country_code":"AL",
    "gn:dem":28,
    "gn:feature_class":"P",
    "gn:feature_code":"PPL",
    "gn:name":"Gryk\u00eb-Manati",
    "gn:population":0,
    "gn:timezone":"Europe/Tirane",
    "iso:country":"AL",
    "name:und_x_variant":[
        "Grik",
        "Gryk\u2019 e Kolshit",
        "Gryk\u00eb-Manatia",
        "Gryk\u00eb e Manatis\u00eb",
        "Gryka e Manatis\u00eb",
        "Gryk\u00eb",
        "Gryla e Manatise",
        "Gryk\u00eb-Manati"
    ],
    "wof:name":"Gryke-Manati",
    "wof:placetype":"locality"
},
  "geometry": {"coordinates":[19.675,41.77861],"type":"Point"}
}