{
  "type": "Feature",
  "properties": {
    "gn:admin1_code":"42",
    "gn:asciiname":"Borce",
    "gn:cc2":"AL",
    "gn:country_code":"AL",
    "gn:dem":32,
    "gn:feature_class":"P",
    "gn:feature_code":"PPL",
    "gn:name":"Bor\u00e7\u00eb",
    "gn:population":0,
    "gn:timezone":"Europe/Tirane",
    "iso:country":"AL",
    "name:und_x_variant":[
        "Borca",
        "Bor\u010d",
        "Bor\u00e7e-Kuqelini",
        "Borc-Zuqllimej",
        "Bor\u00e7-Kuqlinaj",
        "Bor\u00e7 e Kuqullini",
        "Bor\u00e7\u00eb"
    ],
    "wof:name":"Borce",
    "wof:placetype":"locality"
},
  "geometry": {"coordinates":[19.56278,41.41944],"type":"Point"}
}