{
  "type": "Feature",
  "properties": {
    "gn:admin1_code":"42",
    "gn:asciiname":"Borce",
    "gn:cc2":"AL",
    "gn:country_code":"AL",
    "gn:dem":32,
    "gn:feature_class":"P",
    "gn:feature_code":"PPL",
    "gn:name":"Bor\u00e7\u00eb",
    "gn:population":0,
    "gn:timezone":"Europe/Tirane",
    "iso:country":"AL",
    "name:arg_x_preferred":[
        "Borza"
    ],
    "name:cat_x_preferred":[
        "B\u00f2r\u00e7a"
    ],
    "name:ceb_x_preferred":[
        "Borce"
    ],
    "name:dan_x_preferred":[
        "Borce"
    ],
    "name:deu_x_preferred":[
        "Borce"
    ],
    "name:eus_x_preferred":[
        "Borce"
    ],
    "name:fra_x_preferred":[
        "Borce"
    ],
    "name:hun_x_preferred":[
        "Borce"
    ],
    "name:ita_x_preferred":[
        "Borce"
    ],
    "name:kaz_x_preferred":[
        "\u0411\u043e\u0440\u0441"
    ],
    "name:lat_x_preferred":[
        "Borce"
    ],
    "name:mlg_x_preferred":[
        "Borce"
    ],
    "name:msa_x_preferred":[
        "Borce"
    ],
    "name:nld_x_preferred":[
        "Borce"
    ],
    "name:oci_x_preferred":[
        "B\u00f2r\u00e7a"
    ],
    "name:pms_x_preferred":[
        "Borce"
    ],
    "name:pol_x_preferred":[
        "Borce"
    ],
    "name:por_x_preferred":[
        "Borce"
    ],
    "name:ron_x_preferred":[
        "Borce"
    ],
    "name:rus_x_preferred":[
        "\u0411\u043e\u0440\u0441"
    ],
    "name:slk_x_preferred":[
        "Borce"
    ],
    "name:spa_x_preferred":[
        "Borce"
    ],
    "name:srp_x_preferred":[
        "\u0411\u043e\u0440\u0441"
    ],
    "name:swe_x_preferred":[
        "Borce"
    ],
    "name:ukr_x_preferred":[
        "\u0411\u043e\u0440\u0441"
    ],
    "name:und_x_variant":[
        "Borca",
        "Bor\u010d",
        "Bor\u00e7e-Kuqelini",
        "Borc-Zuqllimej",
        "Bor\u00e7-Kuqlinaj",
        "Bor\u00e7 e Kuqullini",
        "Bor\u00e7\u00eb"
    ],
    "name:uzb_x_preferred":[
        "Borce"
    ],
    "name:vie_x_preferred":[
        "Borce"
    ],
    "name:vol_x_preferred":[
        "Borce"
    ],
    "name:war_x_preferred":[
        "Borce"
    ],
    "name:zho_x_preferred":[
        "\u535a\u5c14\u65af"
    ],
    "wof:name":"Borce",
    "wof:placetype":"locality"
},
  "geometry": {"coordinates":[19.56278,41.41944],"type":"Point"}
}