{
  "type": "Feature",
  "properties": {
    "gn:admin1_code":"44",
    "gn:asciiname":"Peshtani i Vogel",
    "gn:cc2":"AL",
    "gn:country_code":"AL",
    "gn:dem":126,
    "gn:feature_class":"P",
    "gn:feature_code":"PPL",
    "gn:name":"Peshtani i Vog\u00ebl",
    "gn:population":0,
    "gn:timezone":"Europe/Tirane",
    "iso:country":"AL",
    "name:und_x_variant":[
        "Peshtan i Vog\u00ebl",
        "Pe\u0161tan i Vogl",
        "Peshtan i Madh",
        "Peshtani i Vog\u00ebl"
    ],
    "wof:name":"Peshtani i Vogel",
    "wof:placetype":"locality"
},
  "geometry": {"coordinates":[19.52361,40.6825],"type":"Point"}
}