{
  "type": "Feature",
  "properties": {
    "gn:admin1_code":"49",
    "gn:asciiname":"Buhot",
    "gn:cc2":"AL",
    "gn:country_code":"AL",
    "gn:dem":386,
    "gn:feature_class":"P",
    "gn:feature_code":"PPL",
    "gn:name":"Buhot",
    "gn:population":0,
    "gn:timezone":"Europe/Tirane",
    "iso:country":"AL",
    "name:und_x_variant":[
        "Buhoti",
        "Bohoti",
        "B\u00ebhot",
        "Bohot",
        "Buhot"
    ],
    "wof:name":"Buhot",
    "wof:placetype":"locality"
},
  "geometry": {"coordinates":[19.93917,42.05778],"type":"Point"}
}