{
  "type": "Feature",
  "properties": {
    "gn:admin1_code":"48",
    "gn:asciiname":"Perlikaj",
    "gn:country_code":"AL",
    "gn:dem":477,
    "gn:feature_class":"P",
    "gn:feature_code":"PPL",
    "gn:name":"Perlikaj",
    "gn:population":0,
    "gn:timezone":"Europe/Tirane",
    "iso:country":"AL",
    "wof:name":"Perlikaj",
    "wof:placetype":"locality"
},
  "geometry": {"coordinates":[20.03056,41.73833],"type":"Point"}
}