{
  "type": "Feature",
  "properties": {
    "gn:admin1_code":"08",
    "gn:asciiname":"Dokollarre",
    "gn:country_code":"AL",
    "gn:dem":977,
    "gn:feature_class":"P",
    "gn:feature_code":"PPL",
    "gn:name":"Dokollarre",
    "gn:population":0,
    "gn:timezone":"Europe/Tirane",
    "iso:country":"AL",
    "wof:name":"Dokollarre",
    "wof:placetype":"locality"
},
  "geometry": {"coordinates":[20.66412,40.32751],"type":"Point"}
}