{
  "type": "Feature",
  "properties": {
    "gn:admin1_code":"44",
    "gn:asciiname":"Bufaj",
    "gn:country_code":"AL",
    "gn:dem":12,
    "gn:feature_class":"P",
    "gn:feature_code":"PPL",
    "gn:name":"Bufaj",
    "gn:population":0,
    "gn:timezone":"Europe/Tirane",
    "iso:country":"AL",
    "wof:name":"Bufaj",
    "wof:placetype":"locality"
},
  "geometry": {"coordinates":[19.70194,40.82806],"type":"Point"}
}