{
  "type": "Feature",
  "properties": {
    "gn:admin1_code":"46",
    "gn:asciiname":"Radat",
    "gn:cc2":"AL",
    "gn:country_code":"AL",
    "gn:dem":890,
    "gn:feature_class":"P",
    "gn:feature_code":"PPL",
    "gn:name":"Radat",
    "gn:population":0,
    "gn:timezone":"Europe/Tirane",
    "iso:country":"AL",
    "name:und_x_variant":[
        "Radati",
        "Radat"
    ],
    "wof:name":"Radat",
    "wof:placetype":"locality"
},
  "geometry": {"coordinates":[20.66278,40.13583],"type":"Point"}
}