{
  "type": "Feature",
  "properties": {
    "gn:admin1_code":"44",
    "gn:asciiname":"Ballan",
    "gn:cc2":"AL",
    "gn:country_code":"AL",
    "gn:dem":294,
    "gn:feature_class":"P",
    "gn:feature_code":"PPL",
    "gn:name":"Ballan",
    "gn:population":0,
    "gn:timezone":"Europe/Tirane",
    "iso:country":"AL",
    "name:und_x_variant":[
        "Ballani",
        "Ballan"
    ],
    "wof:name":"Ballan",
    "wof:placetype":"locality"
},
  "geometry": {"coordinates":[19.71806,40.56222],"type":"Point"}
}