{
  "type": "Feature",
  "properties": {
    "gn:admin1_code":"40",
    "gn:asciiname":"Pellumbas",
    "gn:cc2":"AL",
    "gn:country_code":"AL",
    "gn:dem":224,
    "gn:feature_class":"P",
    "gn:feature_code":"PPL",
    "gn:name":"P\u00ebllumbas",
    "gn:population":0,
    "gn:timezone":"Europe/Tirane",
    "iso:country":"AL",
    "name:sqi_x_preferred":[
        "P\u00ebllumbas"
    ],
    "name:und_x_variant":[
        "Simuren",
        "P\u00ebllumbasi",
        "S\u00ebmuraj",
        "S\u00ebmurani",
        "S\u00ebmuranj",
        "Semurraj",
        "Semuranji",
        "Smuranji",
        "P\u00ebllumbas"
    ],
    "wof:name":"Pellumbas",
    "wof:placetype":"locality"
},
  "geometry": {"coordinates":[20.00972,40.8175],"type":"Point"}
}