{
  "type": "Feature",
  "properties": {
    "gn:admin1_code":"49",
    "gn:asciiname":"Nareaj",
    "gn:country_code":"AL",
    "gn:dem":554,
    "gn:feature_class":"P",
    "gn:feature_code":"PPL",
    "gn:name":"Nareaj",
    "gn:population":0,
    "gn:timezone":"Europe/Tirane",
    "iso:country":"AL",
    "wof:name":"Nareaj",
    "wof:placetype":"locality"
},
  "geometry": {"coordinates":[19.78083,42.24611],"type":"Point"}
}