{
  "type": "Feature",
  "properties": {
    "gn:admin1_code":"42",
    "gn:asciiname":"Sukth-Vendas",
    "gn:cc2":"AL",
    "gn:country_code":"AL",
    "gn:dem":26,
    "gn:feature_class":"P",
    "gn:feature_code":"PPL",
    "gn:name":"Sukth-Vendas",
    "gn:population":0,
    "gn:timezone":"Europe/Tirane",
    "iso:country":"AL",
    "name:und_x_variant":[
        "Sukthi-V\u00ebndas",
        "Sukth",
        "Sukth V\u00ebndasi",
        "Sukth-Vendas"
    ],
    "wof:name":"Sukth-Vendas",
    "wof:placetype":"locality"
},
  "geometry": {"coordinates":[19.62306,41.52639],"type":"Point"}
}