{
  "type": "Feature",
  "properties": {
    "gn:admin1_code":"49",
    "gn:asciiname":"Babot",
    "gn:cc2":"AL",
    "gn:country_code":"AL",
    "gn:dem":207,
    "gn:feature_class":"P",
    "gn:feature_code":"PPL",
    "gn:name":"Babot",
    "gn:population":0,
    "gn:timezone":"Europe/Tirane",
    "iso:country":"AL",
    "name:und_x_variant":[
        "Babat",
        "Baboti",
        "Boboti",
        "Bobot",
        "Babot"
    ],
    "wof:name":"Babot",
    "wof:placetype":"locality"
},
  "geometry": {"coordinates":[19.40111,42.05694],"type":"Point"}
}