{
  "type": "Feature",
  "properties": {
    "gn:admin1_code":"41",
    "gn:asciiname":"Bllata e Eperme",
    "gn:cc2":"AL",
    "gn:country_code":"AL",
    "gn:dem":586,
    "gn:feature_class":"P",
    "gn:feature_code":"PPL",
    "gn:name":"Bllata e Ep\u00ebrme",
    "gn:population":0,
    "gn:timezone":"Europe/Tirane",
    "iso:country":"AL",
    "name:und_x_variant":[
        "Gornje Blato",
        "Bllat\u00eb e Ep\u00ebrme",
        "Bllata e Ep\u00eb",
        "Bllat\u00eb e Ep\u00ebr",
        "Bllat\u00eb e Sip\u00ebrme",
        "Bllata e Ep\u00ebrme"
    ],
    "wof:name":"Bllata e Eperme",
    "wof:placetype":"locality"
},
  "geometry": {"coordinates":[20.48944,41.56278],"type":"Point"}
}