{
  "type": "Feature",
  "properties": {
    "gn:admin1_code":"49",
    "gn:asciiname":"Thelloje",
    "gn:country_code":"AL",
    "gn:dem":124,
    "gn:feature_class":"P",
    "gn:feature_code":"PPL",
    "gn:name":"Thelloj\u00eb",
    "gn:population":0,
    "gn:timezone":"Europe/Tirane",
    "iso:country":"AL",
    "wof:name":"Thelloje",
    "wof:placetype":"locality"
},
  "geometry": {"coordinates":[19.62556,42.10444],"type":"Point"}
}