{
  "type": "Feature",
  "properties": {
    "gn:admin1_code":"45",
    "gn:asciiname":"Limar",
    "gn:cc2":"AL",
    "gn:country_code":"AL",
    "gn:dem":723,
    "gn:feature_class":"P",
    "gn:feature_code":"PPL",
    "gn:name":"Limar",
    "gn:population":0,
    "gn:timezone":"Europe/Tirane",
    "iso:country":"AL",
    "name:und_x_variant":[
        "Limari",
        "Limar"
    ],
    "wof:name":"Limar",
    "wof:placetype":"locality"
},
  "geometry": {"coordinates":[20.17444,40.26083],"type":"Point"}
}