{
  "type": "Feature",
  "properties": {
    "gn:admin1_code":"48",
    "gn:asciiname":"Gurth-Spac",
    "gn:cc2":"AL",
    "gn:country_code":"AL",
    "gn:dem":949,
    "gn:feature_class":"P",
    "gn:feature_code":"PPL",
    "gn:name":"Gurth-Spa\u00e7",
    "gn:population":0,
    "gn:timezone":"Europe/Tirane",
    "iso:country":"AL",
    "name:und_x_variant":[
        "Gurthi Spa\u00e7it",
        "Gurthi i Spa\u00e7it",
        "Gurth-Spa\u00e7"
    ],
    "wof:name":"Gurth-Spac",
    "wof:placetype":"locality"
},
  "geometry": {"coordinates":[20.06917,41.91833],"type":"Point"}
}