{
  "type": "Feature",
  "properties": {
    "gn:admin1_code":"51",
    "gn:asciiname":"Dukat",
    "gn:cc2":"AL",
    "gn:country_code":"AL",
    "gn:dem":438,
    "gn:feature_class":"P",
    "gn:feature_code":"PPL",
    "gn:name":"Dukat",
    "gn:population":0,
    "gn:timezone":"Europe/Tirane",
    "iso:country":"AL",
    "name:und_x_variant":[
        "Dukati",
        "Dukat-Fshat",
        "Ducati",
        "Dukat"
    ],
    "wof:name":"Dukat",
    "wof:placetype":"locality"
},
  "geometry": {"coordinates":[19.56722,40.25056],"type":"Point"}
}