{
  "type": "Feature",
  "properties": {
    "gn:admin1_code":"51",
    "gn:asciiname":"Dukat",
    "gn:cc2":"AL",
    "gn:country_code":"AL",
    "gn:dem":438,
    "gn:feature_class":"P",
    "gn:feature_code":"PPL",
    "gn:name":"Dukat",
    "gn:population":0,
    "gn:timezone":"Europe/Tirane",
    "iso:country":"AL",
    "name:ceb_x_preferred":[
        "Dukat"
    ],
    "name:ces_x_preferred":[
        "Duk\u00e1t"
    ],
    "name:deu_x_preferred":[
        "Dukat"
    ],
    "name:fra_x_preferred":[
        "Dukat"
    ],
    "name:hrv_x_preferred":[
        "Dukat"
    ],
    "name:hun_x_preferred":[
        "Dukat"
    ],
    "name:nld_x_preferred":[
        "Dukat"
    ],
    "name:slv_x_preferred":[
        "Dukat"
    ],
    "name:srp_x_preferred":[
        "\u0414\u0443\u043a\u0430\u0442"
    ],
    "name:swe_x_preferred":[
        "Dukat"
    ],
    "name:und_x_variant":[
        "Dukati",
        "Dukat-Fshat",
        "Ducati"
    ],
    "wof:name":"Dukat",
    "wof:placetype":"locality"
},
  "geometry": {"coordinates":[19.56722,40.25056],"type":"Point"}
}