{
  "type": "Feature",
  "properties": {
    "gn:admin1_code":"46",
    "gn:asciiname":"Polje",
    "gn:cc2":"AL",
    "gn:country_code":"AL",
    "gn:dem":735,
    "gn:feature_class":"P",
    "gn:feature_code":"PPL",
    "gn:name":"Polje",
    "gn:population":0,
    "gn:timezone":"Europe/Tirane",
    "iso:country":"AL",
    "name:mkd_x_preferred":[
        "\u041b\u0435\u0448\u043d\u0430"
    ],
    "name:und_x_variant":[
        "Leskij\u00eb",
        "Le\u0161ija",
        "Polje"
    ],
    "wof:name":"Polje",
    "wof:placetype":"locality"
},
  "geometry": {"coordinates":[20.64,40.97417],"type":"Point"}
}