{
  "type": "Feature",
  "properties": {
    "gn:admin1_code":"43",
    "gn:asciiname":"Tudan",
    "gn:cc2":"AL",
    "gn:country_code":"AL",
    "gn:dem":278,
    "gn:feature_class":"P",
    "gn:feature_code":"PPL",
    "gn:name":"Tudan",
    "gn:population":0,
    "gn:timezone":"Europe/Tirane",
    "iso:country":"AL",
    "name:ron_x_preferred":[
        "Tudan"
    ],
    "name:und_x_variant":[
        "Tudani",
        "Tudaji",
        "Tudan"
    ],
    "wof:name":"Tudan",
    "wof:placetype":"locality"
},
  "geometry": {"coordinates":[20.08528,41.06028],"type":"Point"}
}