{
  "type": "Feature",
  "properties": {
    "gn:admin1_code":"49",
    "gn:asciiname":"Pog",
    "gn:cc2":"AL",
    "gn:country_code":"AL",
    "gn:dem":501,
    "gn:feature_class":"P",
    "gn:feature_code":"PPL",
    "gn:name":"Pog",
    "gn:population":0,
    "gn:timezone":"Europe/Tirane",
    "iso:country":"AL",
    "name:und_x_variant":[
        "Pog\u00eb",
        "Poga",
        "Pogu",
        "Pog"
    ],
    "wof:name":"Pog",
    "wof:placetype":"locality"
},
  "geometry": {"coordinates":[19.69694,42.26583],"type":"Point"}
}