{
  "type": "Feature",
  "properties": {
    "gn:admin1_code":"45",
    "gn:asciiname":"Barme",
    "gn:cc2":"AL",
    "gn:country_code":"AL",
    "gn:dem":588,
    "gn:feature_class":"P",
    "gn:feature_code":"PPL",
    "gn:name":"Barm\u00eb",
    "gn:population":0,
    "gn:timezone":"Europe/Tirane",
    "iso:country":"AL",
    "name:und_x_variant":[
        "Barma",
        "Barm\u00eb"
    ],
    "wof:name":"Barme",
    "wof:placetype":"locality"
},
  "geometry": {"coordinates":[20.04639,40.49361],"type":"Point"}
}