{
  "type": "Feature",
  "properties": {
    "gn:admin1_code":"43",
    "gn:admin2_code":"38.0",
    "gn:asciiname":"Gjocaj",
    "gn:cc2":"AL",
    "gn:country_code":"AL",
    "gn:dem":33,
    "gn:feature_class":"P",
    "gn:feature_code":"PPLA3",
    "gn:name":"Gjo\u00e7aj",
    "gn:population":0,
    "gn:timezone":"Europe/Tirane",
    "iso:country":"AL",
    "name:und_x_variant":[
        "Gjocej",
        "\u00d0jocaj",
        "Gjo\u00e7aj"
    ],
    "wof:name":"Gjocaj",
    "wof:placetype":"locality"
},
  "geometry": {"coordinates":[19.72389,41.02556],"type":"Point"}
}