{
  "type": "Feature",
  "properties": {
    "gn:admin1_code":"49",
    "gn:asciiname":"Velinaj",
    "gn:country_code":"AL",
    "gn:dem":12,
    "gn:feature_class":"P",
    "gn:feature_code":"PPL",
    "gn:name":"Velinaj",
    "gn:population":0,
    "gn:timezone":"Europe/Tirane",
    "iso:country":"AL",
    "name:fas_x_preferred":[
        "\u0648\u0644\u06cc\u0646\u062c"
    ],
    "wof:name":"Velinaj",
    "wof:placetype":"locality"
},
  "geometry": {"coordinates":[19.41778,42.0225],"type":"Point"}
}