{
  "type": "Feature",
  "properties": {
    "gn:admin1_code":"50",
    "gn:asciiname":"Kolaj",
    "gn:country_code":"AL",
    "gn:dem":290,
    "gn:feature_class":"P",
    "gn:feature_code":"PPL",
    "gn:name":"Kolaj",
    "gn:population":0,
    "gn:timezone":"Europe/Tirane",
    "iso:country":"AL",
    "wof:name":"Kolaj",
    "wof:placetype":"locality"
},
  "geometry": {"coordinates":[19.66667,41.21667],"type":"Point"}
}