{
  "type": "Feature",
  "properties": {
    "gn:admin1_code":"40",
    "gn:asciiname":"Bersake",
    "gn:cc2":"AL",
    "gn:country_code":"AL",
    "gn:dem":969,
    "gn:feature_class":"P",
    "gn:feature_code":"PPL",
    "gn:name":"Bersak\u00eb",
    "gn:population":0,
    "gn:timezone":"Europe/Tirane",
    "iso:country":"AL",
    "name:und_x_variant":[
        "Birsak\u00eb",
        "Bisaca",
        "Bersak\u00eb"
    ],
    "wof:name":"Bersake",
    "wof:placetype":"locality"
},
  "geometry": {"coordinates":[20.35361,40.52417],"type":"Point"}
}