{
  "type": "Feature",
  "properties": {
    "gn:admin1_code":"40",
    "gn:asciiname":"Melove",
    "gn:cc2":"AL",
    "gn:country_code":"AL",
    "gn:dem":977,
    "gn:feature_class":"P",
    "gn:feature_code":"PPL",
    "gn:name":"Melov\u00eb",
    "gn:population":0,
    "gn:timezone":"Europe/Tirane",
    "iso:country":"AL",
    "name:und_x_variant":[
        "Milov\u00eb",
        "Milova",
        "Melova",
        "Melov\u00eb"
    ],
    "wof:name":"Melove",
    "wof:placetype":"locality"
},
  "geometry": {"coordinates":[20.28472,40.58528],"type":"Point"}
}