{
  "type": "Feature",
  "properties": {
    "gn:admin1_code":"45",
    "gn:admin2_code":"6.0",
    "gn:asciiname":"Odrie",
    "gn:cc2":"AL",
    "gn:country_code":"AL",
    "gn:dem":286,
    "gn:feature_class":"P",
    "gn:feature_code":"PPLA3",
    "gn:name":"Odrie",
    "gn:population":0,
    "gn:timezone":"Europe/Tirane",
    "iso:country":"AL",
    "name:ces_x_preferred":[
        "Odrie"
    ],
    "name:ita_x_preferred":[
        "Odrie"
    ],
    "name:msa_x_preferred":[
        "Odrie"
    ],
    "name:pol_x_preferred":[
        "Gmina Odrie"
    ],
    "name:por_x_preferred":[
        "Odrie"
    ],
    "name:spa_x_preferred":[
        "Odrie"
    ],
    "name:tur_x_preferred":[
        "Odrie"
    ],
    "name:und_x_variant":[
        "Odria"
    ],
    "name:vie_x_preferred":[
        "Odrie"
    ],
    "name:war_x_preferred":[
        "Odrie"
    ],
    "wof:name":"Odrie",
    "wof:placetype":"locality"
},
  "geometry": {"coordinates":[20.16667,40.13333],"type":"Point"}
}