{
  "type": "Feature",
  "properties": {
    "gn:admin1_code":"51",
    "gn:asciiname":"Sharaj",
    "gn:country_code":"AL",
    "gn:dem":296,
    "gn:feature_class":"P",
    "gn:feature_code":"PPL",
    "gn:name":"Sharaj",
    "gn:population":0,
    "gn:timezone":"Europe/Tirane",
    "iso:country":"AL",
    "wof:name":"Sharaj",
    "wof:placetype":"locality"
},
  "geometry": {"coordinates":[19.66,40.41556],"type":"Point"}
}