{
  "type": "Feature",
  "properties": {
    "gn:admin1_code":"44",
    "gn:asciiname":"Stan",
    "gn:cc2":"AL",
    "gn:country_code":"AL",
    "gn:dem":295,
    "gn:feature_class":"P",
    "gn:feature_code":"PPL",
    "gn:name":"Stan",
    "gn:population":0,
    "gn:timezone":"Europe/Tirane",
    "iso:country":"AL",
    "name:und_x_variant":[
        "Stani",
        "Stan"
    ],
    "wof:name":"Stan",
    "wof:placetype":"locality"
},
  "geometry": {"coordinates":[19.71389,40.61333],"type":"Point"}
}