{
  "type": "Feature",
  "properties": {
    "gn:admin1_code":"44",
    "gn:asciiname":"Stan",
    "gn:cc2":"AL",
    "gn:country_code":"AL",
    "gn:dem":295,
    "gn:feature_class":"P",
    "gn:feature_code":"PPL",
    "gn:name":"Stan",
    "gn:population":0,
    "gn:timezone":"Europe/Tirane",
    "iso:country":"AL",
    "name:bos_x_preferred":[
        "Stan"
    ],
    "name:ceb_x_preferred":[
        "Stan"
    ],
    "name:ces_x_preferred":[
        "Stan"
    ],
    "name:deu_x_preferred":[
        "Stan"
    ],
    "name:fra_x_preferred":[
        "Stan"
    ],
    "name:heb_x_preferred":[
        "\u05e1\u05d8\u05df"
    ],
    "name:ita_x_preferred":[
        "Stan"
    ],
    "name:jpn_x_preferred":[
        "\u30b9\u30bf\u30f3"
    ],
    "name:nld_x_preferred":[
        "Stan"
    ],
    "name:pol_x_preferred":[
        "Stan"
    ],
    "name:por_x_preferred":[
        "Stan"
    ],
    "name:ron_x_preferred":[
        "Stan"
    ],
    "name:slk_x_preferred":[
        "Stan"
    ],
    "name:spa_x_preferred":[
        "Stan"
    ],
    "name:swe_x_preferred":[
        "Stan"
    ],
    "name:ukr_x_preferred":[
        "\u0421\u0442\u0430\u043d"
    ],
    "name:und_x_variant":[
        "Stani"
    ],
    "wof:name":"Stan",
    "wof:placetype":"locality"
},
  "geometry": {"coordinates":[19.71389,40.61333],"type":"Point"}
}