{
  "type": "Feature",
  "properties": {
    "gn:admin1_code":"49",
    "gn:asciiname":"Megulle",
    "gn:cc2":"AL",
    "gn:country_code":"AL",
    "gn:dem":655,
    "gn:feature_class":"P",
    "gn:feature_code":"PPL",
    "gn:name":"M\u00ebgull\u00eb",
    "gn:population":0,
    "gn:timezone":"Europe/Tirane",
    "iso:country":"AL",
    "name:und_x_variant":[
        "Mgul\u00eb",
        "Mengull\u00eb",
        "Megule",
        "M\u00ebgulla",
        "Mgull\u00eb",
        "M\u00ebngulla",
        "Mgulla",
        "M\u00ebgull\u00eb"
    ],
    "wof:name":"Megulle",
    "wof:placetype":"locality"
},
  "geometry": {"coordinates":[19.68333,42.26861],"type":"Point"}
}