{
  "type": "Feature",
  "properties": {
    "gn:admin1_code":"44",
    "gn:asciiname":"Vlosh",
    "gn:cc2":"AL",
    "gn:country_code":"AL",
    "gn:dem":223,
    "gn:feature_class":"P",
    "gn:feature_code":"PPL",
    "gn:name":"Vlosh",
    "gn:population":0,
    "gn:timezone":"Europe/Tirane",
    "iso:country":"AL",
    "name:und_x_variant":[
        "Vloshi",
        "Vljo\u0161",
        "Vlijoshi",
        "Vlosh"
    ],
    "wof:name":"Vlosh",
    "wof:placetype":"locality"
},
  "geometry": {"coordinates":[19.7675,40.67972],"type":"Point"}
}