{
  "type": "Feature",
  "properties": {
    "gn:admin1_code":"43",
    "gn:asciiname":"Terbac",
    "gn:cc2":"AL",
    "gn:country_code":"AL",
    "gn:dem":508,
    "gn:feature_class":"P",
    "gn:feature_code":"PPL",
    "gn:name":"T\u00ebrba\u00e7",
    "gn:population":0,
    "gn:timezone":"Europe/Tirane",
    "iso:country":"AL",
    "name:und_x_variant":[
        "Krushnaja",
        "T\u00ebrbaci",
        "T\u00ebrba\u00e7"
    ],
    "wof:name":"Terbac",
    "wof:placetype":"locality"
},
  "geometry": {"coordinates":[19.94444,41.15889],"type":"Point"}
}