{
  "type": "Feature",
  "properties": {
    "gn:admin1_code":"48",
    "gn:asciiname":"Balldren",
    "gn:cc2":"AL",
    "gn:country_code":"AL",
    "gn:dem":2,
    "gn:feature_class":"P",
    "gn:feature_code":"PPL",
    "gn:name":"Balldren",
    "gn:population":0,
    "gn:timezone":"Europe/Tirane",
    "iso:country":"AL",
    "name:und_x_variant":[
        "Sh\u2019 Prende",
        "Baldrin",
        "Baldre",
        "Baldren",
        "Baldreen",
        "Balldreni",
        "Balldren",
        "Balldre"
    ],
    "wof:name":"Balldren",
    "wof:placetype":"locality"
},
  "geometry": {"coordinates":[19.63472,41.80944],"type":"Point"}
}