{
  "type": "Feature",
  "properties": {
    "gn:admin1_code":"51",
    "gn:asciiname":"Radhime",
    "gn:cc2":"AL",
    "gn:country_code":"AL",
    "gn:dem":179,
    "gn:feature_class":"P",
    "gn:feature_code":"PPL",
    "gn:name":"Radhim\u00eb",
    "gn:population":0,
    "gn:timezone":"Europe/Tirane",
    "iso:country":"AL",
    "name:mkd_x_preferred":[
        "\u0420\u0430\u0434\u0438\u043c\u0430"
    ],
    "name:und_x_variant":[
        "Ralima",
        "Radhima",
        "Rradhima",
        "Rradhim\u00eb",
        "Radima",
        "Radhim\u00eb"
    ],
    "wof:name":"Radhime",
    "wof:placetype":"locality"
},
  "geometry": {"coordinates":[19.49417,40.37194],"type":"Point"}
}