{
  "type": "Feature",
  "properties": {
    "gn:admin1_code":"45",
    "gn:asciiname":"Liqeth",
    "gn:cc2":"AL",
    "gn:country_code":"AL",
    "gn:dem":719,
    "gn:feature_class":"P",
    "gn:feature_code":"PPL",
    "gn:name":"Liqeth",
    "gn:population":0,
    "gn:timezone":"Europe/Tirane",
    "iso:country":"AL",
    "name:und_x_variant":[
        "Liqethi",
        "Liqeth"
    ],
    "wof:name":"Liqeth",
    "wof:placetype":"locality"
},
  "geometry": {"coordinates":[20.06861,40.48306],"type":"Point"}
}