{
  "type": "Feature",
  "properties": {
    "gn:admin1_code":"43",
    "gn:asciiname":"Hardhias",
    "gn:cc2":"AL",
    "gn:country_code":"AL",
    "gn:dem":186,
    "gn:feature_class":"P",
    "gn:feature_code":"PPL",
    "gn:name":"Hardhias",
    "gn:population":0,
    "gn:timezone":"Europe/Tirane",
    "iso:country":"AL",
    "name:und_x_variant":[
        "Hurdha e But\u00eb",
        "Hardhija e But",
        "Hardhi e But\u00eb",
        "Hardhias"
    ],
    "wof:name":"Hardhias",
    "wof:placetype":"locality"
},
  "geometry": {"coordinates":[19.84444,40.93417],"type":"Point"}
}