{
  "type": "Feature",
  "properties": {
    "gn:admin1_code":"46",
    "gn:asciiname":"Osoje",
    "gn:cc2":"AL",
    "gn:country_code":"AL",
    "gn:dem":951,
    "gn:feature_class":"P",
    "gn:feature_code":"PPL",
    "gn:name":"Osoj\u00eb",
    "gn:population":0,
    "gn:timezone":"Europe/Tirane",
    "iso:country":"AL",
    "name:und_x_variant":[
        "Osoja",
        "Paravanas",
        "Osoj\u00eb"
    ],
    "wof:name":"Osoje",
    "wof:placetype":"locality"
},
  "geometry": {"coordinates":[20.495,40.665],"type":"Point"}
}