{
  "type": "Feature",
  "properties": {
    "gn:admin1_code":"40",
    "gn:asciiname":"Licollar",
    "gn:cc2":"AL",
    "gn:country_code":"AL",
    "gn:dem":962,
    "gn:feature_class":"P",
    "gn:feature_code":"PPL",
    "gn:name":"Li\u00e7ollar",
    "gn:population":0,
    "gn:timezone":"Europe/Tirane",
    "iso:country":"AL",
    "name:und_x_variant":[
        "Li\u00e7ollar\u00eb",
        "Li\u00e7ollar"
    ],
    "wof:name":"Licollar",
    "wof:placetype":"locality"
},
  "geometry": {"coordinates":[20.365,40.40333],"type":"Point"}
}