{
  "type": "Feature",
  "properties": {
    "gn:admin1_code":"41",
    "gn:asciiname":"Cidhne",
    "gn:cc2":"AL",
    "gn:country_code":"AL",
    "gn:dem":661,
    "gn:feature_class":"P",
    "gn:feature_code":"PPL",
    "gn:name":"\u00c7idhn\u00eb",
    "gn:population":0,
    "gn:timezone":"Europe/Tirane",
    "iso:country":"AL",
    "name:und_x_variant":[
        "Qidhna e Poshtme",
        "Cidhnaeposhi",
        "Qidhn\u00eb e Poshtme",
        "\u00c7idhna e Posht\u00ebme",
        "Qillna e Posht\u00ebme",
        "\u00c7idhn\u00eb e Posht\u00ebme",
        "\u00c7idhna",
        "\u00c7idh\u00ebn",
        "\u00c7idhn\u00eb"
    ],
    "wof:name":"Cidhne",
    "wof:placetype":"locality"
},
  "geometry": {"coordinates":[20.26806,41.7525],"type":"Point"}
}