{
  "type": "Feature",
  "properties": {
    "gn:admin1_code":"49",
    "gn:asciiname":"Luarze",
    "gn:cc2":"AL",
    "gn:country_code":"AL",
    "gn:dem":17,
    "gn:feature_class":"P",
    "gn:feature_code":"PPL",
    "gn:name":"Luarz\u00eb",
    "gn:population":0,
    "gn:timezone":"Europe/Tirane",
    "iso:country":"AL",
    "name:und_x_variant":[
        "Luarazi",
        "Luars",
        "Luarz",
        "Luar\u00ebz",
        "Luarzi",
        "Luarz\u00eb"
    ],
    "wof:name":"Luarze",
    "wof:placetype":"locality"
},
  "geometry": {"coordinates":[19.385,41.92194],"type":"Point"}
}