{
  "type": "Feature",
  "properties": {
    "gn:admin1_code":"41",
    "gn:asciiname":"Deshat",
    "gn:cc2":"AL",
    "gn:country_code":"AL",
    "gn:dem":729,
    "gn:feature_class":"P",
    "gn:feature_code":"PPL",
    "gn:name":"Deshat",
    "gn:population":0,
    "gn:timezone":"Europe/Tirane",
    "iso:country":"AL",
    "name:und_x_variant":[
        "Deshati",
        "Deshat"
    ],
    "wof:name":"Deshat",
    "wof:placetype":"locality"
},
  "geometry": {"coordinates":[20.41528,41.71194000000001],"type":"Point"}
}