{
  "type": "Feature",
  "properties": {
    "gn:admin1_code":"45",
    "gn:asciiname":"Allkomenaj",
    "gn:cc2":"AL",
    "gn:country_code":"AL",
    "gn:dem":677,
    "gn:feature_class":"P",
    "gn:feature_code":"PPL",
    "gn:name":"Allkomenaj",
    "gn:population":0,
    "gn:timezone":"Europe/Tirane",
    "iso:country":"AL",
    "name:und_x_variant":[
        "Komimaj",
        "Allkomemanj",
        "Alkomenaj",
        "Allkomemaj",
        "Alkomemaj",
        "Allkomenaj"
    ],
    "wof:name":"Allkomenaj",
    "wof:placetype":"locality"
},
  "geometry": {"coordinates":[19.90417,40.50944000000001],"type":"Point"}
}