{
  "type": "Feature",
  "properties": {
    "gn:admin1_code":"48",
    "gn:asciiname":"Tarazh",
    "gn:cc2":"AL",
    "gn:country_code":"AL",
    "gn:dem":108,
    "gn:feature_class":"P",
    "gn:feature_code":"PPL",
    "gn:name":"Tarazh",
    "gn:population":0,
    "gn:timezone":"Europe/Tirane",
    "iso:country":"AL",
    "name:und_x_variant":[
        "Tarazhi",
        "Tarazh"
    ],
    "wof:name":"Tarazh",
    "wof:placetype":"locality"
},
  "geometry": {"coordinates":[19.89167,41.75972],"type":"Point"}
}