{
  "type": "Feature",
  "properties": {
    "gn:admin1_code":"40",
    "gn:asciiname":"Velagosht",
    "gn:cc2":"AL",
    "gn:country_code":"AL",
    "gn:dem":347,
    "gn:feature_class":"P",
    "gn:feature_code":"PPL",
    "gn:name":"Velagosht",
    "gn:population":0,
    "gn:timezone":"Europe/Tirane",
    "iso:country":"AL",
    "name:und_x_variant":[
        "Bardhanj",
        "Velagasht",
        "Velagoshti",
        "Velegosht",
        "Velagozhdi",
        "Velegoshti",
        "Velagosht"
    ],
    "wof:name":"Velagosht",
    "wof:placetype":"locality"
},
  "geometry": {"coordinates":[19.9675,40.83694000000001],"type":"Point"}
}