{
  "type": "Feature",
  "properties": {
    "gn:admin1_code":"45",
    "gn:asciiname":"Arreza e Vogel",
    "gn:cc2":"AL",
    "gn:country_code":"AL",
    "gn:dem":710,
    "gn:feature_class":"P",
    "gn:feature_code":"PPL",
    "gn:name":"Arr\u00ebza e Vog\u00ebl",
    "gn:population":0,
    "gn:timezone":"Europe/Tirane",
    "iso:country":"AL",
    "name:und_x_variant":[
        "Arza e Posht\u00ebr",
        "Arza di Sotto",
        "Arz\u00eb e Posht\u00ebr",
        "Arr\u00ebz\u00eb e Vog\u00ebl",
        "Arr\u00ebz e Vog\u00ebl",
        "Arza e Posht\u00ebme",
        "Arr\u00ebza e Vog\u00ebl"
    ],
    "wof:name":"Arreza e Vogel",
    "wof:placetype":"locality"
},
  "geometry": {"coordinates":[20.05444,40.42],"type":"Point"}
}