{
  "type": "Feature",
  "properties": {
    "gn:admin1_code":"45",
    "gn:asciiname":"Krine",
    "gn:cc2":"AL",
    "gn:country_code":"AL",
    "gn:dem":425,
    "gn:feature_class":"P",
    "gn:feature_code":"PPL",
    "gn:name":"Krin\u00eb",
    "gn:population":0,
    "gn:timezone":"Europe/Tirane",
    "iso:country":"AL",
    "name:und_x_variant":[
        "Crina",
        "Krina",
        "Krin\u00eb"
    ],
    "wof:name":"Krine",
    "wof:placetype":"locality"
},
  "geometry": {"coordinates":[20.20139,40.09972],"type":"Point"}
}