{
  "type": "Feature",
  "properties": {
    "gn:admin1_code":"47",
    "gn:asciiname":"Pakisht",
    "gn:cc2":"AL",
    "gn:country_code":"AL",
    "gn:dem":1146,
    "gn:feature_class":"P",
    "gn:feature_code":"PPL",
    "gn:name":"Pakisht",
    "gn:population":0,
    "gn:timezone":"Europe/Tirane",
    "iso:country":"AL",
    "name:und_x_variant":[
        "Pakishta",
        "Paki\u0161",
        "Pakisha",
        "Pakisht\u00eb",
        "Pakishti",
        "Pakish",
        "Pakisht"
    ],
    "wof:name":"Pakisht",
    "wof:placetype":"locality"
},
  "geometry": {"coordinates":[20.56917,42.05167],"type":"Point"}
}