{
  "type": "Feature",
  "properties": {
    "gn:admin1_code":"46",
    "gn:asciiname":"Hodallar",
    "gn:cc2":"AL",
    "gn:country_code":"AL",
    "gn:dem":1222,
    "gn:feature_class":"P",
    "gn:feature_code":"PPL",
    "gn:name":"Hodallar",
    "gn:population":0,
    "gn:timezone":"Europe/Tirane",
    "iso:country":"AL",
    "name:und_x_variant":[
        "Malalar",
        "Malear",
        "Mal\u00eblar",
        "Hodollar",
        "Hodallar"
    ],
    "wof:name":"Hodallar",
    "wof:placetype":"locality"
},
  "geometry": {"coordinates":[20.71417000000001,40.34417],"type":"Point"}
}