{
  "type": "Feature",
  "properties": {
    "gn:admin1_code":"40",
    "gn:asciiname":"Kulleni",
    "gn:cc2":"AL",
    "gn:country_code":"AL",
    "gn:dem":87,
    "gn:feature_class":"P",
    "gn:feature_code":"PPL",
    "gn:name":"Kulleni",
    "gn:population":0,
    "gn:timezone":"Europe/Tirane",
    "iso:country":"AL",
    "name:und_x_variant":[
        "Muhove",
        "Kulleni"
    ],
    "wof:name":"Kulleni",
    "wof:placetype":"locality"
},
  "geometry": {"coordinates":[19.96361,40.86861],"type":"Point"}
}