{
  "type": "Feature",
  "properties": {
    "gn:admin1_code":"45",
    "gn:asciiname":"Kervacaj",
    "gn:country_code":"AL",
    "gn:dem":328,
    "gn:feature_class":"P",
    "gn:feature_code":"PPL",
    "gn:name":"K\u00ebrvacaj",
    "gn:population":0,
    "gn:timezone":"Europe/Tirane",
    "iso:country":"AL",
    "wof:name":"Kervacaj",
    "wof:placetype":"locality"
},
  "geometry": {"coordinates":[19.99639,40.38861],"type":"Point"}
}