{
  "type": "Feature",
  "properties": {
    "gn:admin1_code":"49",
    "gn:asciiname":"Shkoze",
    "gn:cc2":"AL",
    "gn:country_code":"AL",
    "gn:dem":451,
    "gn:feature_class":"P",
    "gn:feature_code":"PPL",
    "gn:name":"Shkoz\u00eb",
    "gn:population":0,
    "gn:timezone":"Europe/Tirane",
    "iso:country":"AL",
    "name:und_x_variant":[
        "Shdoza",
        "Shkoza",
        "Scoza",
        "Shkoz\u00eb"
    ],
    "wof:name":"Shkoze",
    "wof:placetype":"locality"
},
  "geometry": {"coordinates":[19.99444,42.00028],"type":"Point"}
}