{
  "type": "Feature",
  "properties": {
    "gn:admin1_code":"47",
    "gn:asciiname":"Mamez",
    "gn:cc2":"AL",
    "gn:country_code":"AL",
    "gn:dem":495,
    "gn:feature_class":"P",
    "gn:feature_code":"PPL",
    "gn:name":"Mam\u00ebz",
    "gn:population":0,
    "gn:timezone":"Europe/Tirane",
    "iso:country":"AL",
    "name:und_x_variant":[
        "Mamza",
        "Mamezi",
        "Mam\u00ebza",
        "Mamz",
        "Mam\u00ebz"
    ],
    "wof:name":"Mamez",
    "wof:placetype":"locality"
},
  "geometry": {"coordinates":[20.37139,42.06139],"type":"Point"}
}