{
  "type": "Feature",
  "properties": {
    "gn:admin1_code":"51",
    "gn:admin2_code":"27.0",
    "gn:asciiname":"Vranisht",
    "gn:cc2":"AL",
    "gn:country_code":"AL",
    "gn:dem":327,
    "gn:feature_class":"P",
    "gn:feature_code":"PPLA3",
    "gn:name":"Vranisht",
    "gn:population":0,
    "gn:timezone":"Europe/Tirane",
    "iso:country":"AL",
    "name:mkd_x_preferred":[
        "\u0412\u0440\u0430\u043d\u0438\u0448\u0442\u0430"
    ],
    "name:und_x_variant":[
        "Vranishti",
        "Vranisht\u00eb",
        "Vranishta",
        "Vranisht"
    ],
    "wof:name":"Vranisht",
    "wof:placetype":"locality"
},
  "geometry": {"coordinates":[19.69083,40.20972],"type":"Point"}
}