{
  "type": "Feature",
  "properties": {
    "gn:admin1_code":"46",
    "gn:asciiname":"Protopape",
    "gn:cc2":"AL",
    "gn:country_code":"AL",
    "gn:dem":966,
    "gn:feature_class":"P",
    "gn:feature_code":"PPL",
    "gn:name":"Protopap\u00eb",
    "gn:population":0,
    "gn:timezone":"Europe/Tirane",
    "iso:country":"AL",
    "name:und_x_variant":[
        "Kodrasi",
        "Protopapaj",
        "Kodras",
        "Protopapa",
        "Protopap\u00eb"
    ],
    "wof:name":"Protopape",
    "wof:placetype":"locality"
},
  "geometry": {"coordinates":[20.45444,40.65611],"type":"Point"}
}