{
  "type": "Feature",
  "properties": {
    "gn:admin1_code":"49",
    "gn:asciiname":"Dushman",
    "gn:cc2":"AL",
    "gn:country_code":"AL",
    "gn:dem":416,
    "gn:feature_class":"P",
    "gn:feature_code":"PPL",
    "gn:name":"Dushman",
    "gn:population":0,
    "gn:timezone":"Europe/Tirane",
    "iso:country":"AL",
    "name:und_x_variant":[
        "Dushmani",
        "Dushman"
    ],
    "wof:name":"Dushman",
    "wof:placetype":"locality"
},
  "geometry": {"coordinates":[19.86833,42.15833],"type":"Point"}
}