{
  "type": "Feature",
  "properties": {
    "gn:admin1_code":"43",
    "gn:asciiname":"Spathar",
    "gn:cc2":"AL",
    "gn:country_code":"AL",
    "gn:dem":512,
    "gn:feature_class":"P",
    "gn:feature_code":"PPL",
    "gn:name":"Spathar",
    "gn:population":0,
    "gn:timezone":"Europe/Tirane",
    "iso:country":"AL",
    "name:mkd_x_preferred":[
        "\u0421\u043f\u0430\u0442\u0430\u0440"
    ],
    "name:und_x_variant":[
        "Spathari",
        "Spathara",
        "Spathar\u00eb",
        "Spathar"
    ],
    "wof:name":"Spathar",
    "wof:placetype":"locality"
},
  "geometry": {"coordinates":[20.33,41.15944],"type":"Point"}
}