{
  "type": "Feature",
  "properties": {
    "gn:admin1_code":"41",
    "gn:asciiname":"Sina e Eperme",
    "gn:cc2":"AL",
    "gn:country_code":"AL",
    "gn:dem":625,
    "gn:feature_class":"P",
    "gn:feature_code":"PPL",
    "gn:name":"Sina e Ep\u00ebrme",
    "gn:population":0,
    "gn:timezone":"Europe/Tirane",
    "iso:country":"AL",
    "name:und_x_variant":[
        "\u00c7idhn\u00eb e Ep\u00ebr",
        "Sina e Eper",
        "Sin\u00eb e Ep\u00ebrme",
        "Sinja-Ep\u00ebr",
        "Sin\u00eb-Ep\u00ebr",
        "Sina e Ep\u00ebrme"
    ],
    "wof:name":"Sina e Eperme",
    "wof:placetype":"locality"
},
  "geometry": {"coordinates":[20.2775,41.73028],"type":"Point"}
}