{
  "type": "Feature",
  "properties": {
    "gn:admin1_code":"49",
    "gn:admin2_code":"21.0",
    "gn:asciiname":"Rruplaj",
    "gn:country_code":"AL",
    "gn:dem":3,
    "gn:feature_class":"P",
    "gn:feature_code":"PPL",
    "gn:name":"Rruplaj",
    "gn:population":0,
    "gn:timezone":"Europe/Tirane",
    "iso:country":"AL",
    "wof:name":"Rruplaj",
    "wof:placetype":"locality"
},
  "geometry": {"coordinates":[19.52886,41.98673],"type":"Point"}
}