{
  "type": "Feature",
  "properties": {
    "gn:admin1_code":"43",
    "gn:asciiname":"Guri i Zi",
    "gn:cc2":"AL",
    "gn:country_code":"AL",
    "gn:dem":625,
    "gn:feature_class":"P",
    "gn:feature_code":"PPL",
    "gn:name":"Guri i Zi",
    "gn:population":0,
    "gn:timezone":"Europe/Tirane",
    "iso:country":"AL",
    "name:und_x_variant":[
        "Gur-zij",
        "Gur i Zi",
        "Guri i Zi"
    ],
    "wof:name":"Guri i Zi",
    "wof:placetype":"locality"
},
  "geometry": {"coordinates":[20.10444,41.20833],"type":"Point"}
}