{
  "type": "Feature",
  "properties": {
    "gn:admin1_code":"46",
    "gn:asciiname":"Gjirakare",
    "gn:cc2":"AL",
    "gn:country_code":"AL",
    "gn:dem":860,
    "gn:feature_class":"P",
    "gn:feature_code":"PPL",
    "gn:name":"Gjirakar\u00eb",
    "gn:population":0,
    "gn:timezone":"Europe/Tirane",
    "iso:country":"AL",
    "name:und_x_variant":[
        "Zirakara",
        "Gjinakare",
        "Gjerakara",
        "Gjerekar\u00eb",
        "Gjirokar\u00eb",
        "Gjierakare",
        "Gjirokara",
        "Gjerakar\u00eb",
        "Gjirakar\u00eb"
    ],
    "wof:name":"Gjirakare",
    "wof:placetype":"locality"
},
  "geometry": {"coordinates":[20.52417,40.22472],"type":"Point"}
}