{
  "type": "Feature",
  "properties": {
    "gn:admin1_code":"43",
    "gn:asciiname":"Mollagjesh",
    "gn:cc2":"AL",
    "gn:country_code":"AL",
    "gn:dem":783,
    "gn:feature_class":"P",
    "gn:feature_code":"PPL",
    "gn:name":"Mollagjesh",
    "gn:population":0,
    "gn:timezone":"Europe/Tirane",
    "iso:country":"AL",
    "name:und_x_variant":[
        "Molla Gjecit",
        "Mollagjeshi",
        "Mollagjesh"
    ],
    "wof:name":"Mollagjesh",
    "wof:placetype":"locality"
},
  "geometry": {"coordinates":[20.03472,41.22194],"type":"Point"}
}