{
  "type": "Feature",
  "properties": {
    "gn:admin1_code":"45",
    "gn:asciiname":"Corenisht",
    "gn:cc2":"AL",
    "gn:country_code":"AL",
    "gn:dem":265,
    "gn:feature_class":"P",
    "gn:feature_code":"PPL",
    "gn:name":"\u00c7orenisht",
    "gn:population":0,
    "gn:timezone":"Europe/Tirane",
    "iso:country":"AL",
    "name:und_x_variant":[
        "\u00c7orenishti",
        "\u00c7orenisht"
    ],
    "wof:name":"Corenisht",
    "wof:placetype":"locality"
},
  "geometry": {"coordinates":[20.16472000000001,40.33917],"type":"Point"}
}