{
  "type": "Feature",
  "properties": {
    "gn:admin1_code":"49",
    "gn:asciiname":"Mazrek",
    "gn:cc2":"AL",
    "gn:country_code":"AL",
    "gn:dem":276,
    "gn:feature_class":"P",
    "gn:feature_code":"PPL",
    "gn:name":"Mazrek",
    "gn:population":0,
    "gn:timezone":"Europe/Tirane",
    "iso:country":"AL",
    "name:und_x_variant":[
        "Mazreku",
        "Mazrreku",
        "Mazrrek",
        "Mazrek"
    ],
    "wof:name":"Mazrek",
    "wof:placetype":"locality"
},
  "geometry": {"coordinates":[19.66222,42.08806],"type":"Point"}
}