{
  "type": "Feature",
  "properties": {
    "gn:admin1_code":"44",
    "gn:asciiname":"Toshkez",
    "gn:cc2":"AL",
    "gn:country_code":"AL",
    "gn:dem":15,
    "gn:feature_class":"P",
    "gn:feature_code":"PPL",
    "gn:name":"Toshk\u00ebz",
    "gn:population":0,
    "gn:timezone":"Europe/Tirane",
    "iso:country":"AL",
    "name:und_x_variant":[
        "Toshk\u00ebz\u00eb",
        "Toshk\u00ebzi",
        "Toshkazi",
        "Toshk\u00ebsi",
        "Toshk\u00ebza",
        "Toshk\u00ebsa",
        "Toshk\u00ebz"
    ],
    "wof:name":"Toshkez",
    "wof:placetype":"locality"
},
  "geometry": {"coordinates":[19.75417,40.84139],"type":"Point"}
}