{
  "type": "Feature",
  "properties": {
    "gn:admin1_code":"41",
    "gn:asciiname":"Trene",
    "gn:cc2":"AL",
    "gn:country_code":"AL",
    "gn:dem":715,
    "gn:feature_class":"P",
    "gn:feature_code":"PPL",
    "gn:name":"Tren\u00eb",
    "gn:population":0,
    "gn:timezone":"Europe/Tirane",
    "iso:country":"AL",
    "name:und_x_variant":[
        "Trena",
        "Tren",
        "Tren\u00eb"
    ],
    "wof:name":"Trene",
    "wof:placetype":"locality"
},
  "geometry": {"coordinates":[20.43444,41.655],"type":"Point"}
}