{
  "type": "Feature",
  "properties": {
    "gn:admin1_code":"43",
    "gn:asciiname":"Kalaj",
    "gn:cc2":"AL",
    "gn:country_code":"AL",
    "gn:dem":904,
    "gn:feature_class":"P",
    "gn:feature_code":"PPL",
    "gn:name":"Kalaj",
    "gn:population":0,
    "gn:timezone":"Europe/Tirane",
    "iso:country":"AL",
    "name:fas_x_preferred":[
        "\u06a9\u0627\u0644\u062c"
    ],
    "name:und_x_variant":[
        "Kolaj",
        "Kalaj"
    ],
    "wof:name":"Kalaj",
    "wof:placetype":"locality"
},
  "geometry": {"coordinates":[20.38639,40.83222],"type":"Point"}
}