{
  "type": "Feature",
  "properties": {
    "gn:admin1_code":"46",
    "gn:asciiname":"Polene",
    "gn:cc2":"AL",
    "gn:country_code":"AL",
    "gn:dem":1041,
    "gn:feature_class":"P",
    "gn:feature_code":"PPL",
    "gn:name":"Polen\u00eb",
    "gn:population":0,
    "gn:timezone":"Europe/Tirane",
    "iso:country":"AL",
    "name:bos_x_preferred":[
        "Polene"
    ],
    "name:ceb_x_preferred":[
        "Polene"
    ],
    "name:hrv_x_preferred":[
        "Polene"
    ],
    "name:pol_x_preferred":[
        "Polene"
    ],
    "name:ron_x_preferred":[
        "Polene"
    ],
    "name:slv_x_preferred":[
        "Polene"
    ],
    "name:ukr_x_preferred":[
        "\u041f\u043e\u043b\u0435\u043d\u0435"
    ],
    "name:und_x_variant":[
        "Polena",
        "Polen\u00eb"
    ],
    "wof:name":"Polene",
    "wof:placetype":"locality"
},
  "geometry": {"coordinates":[20.53806,40.31694],"type":"Point"}
}