{
  "type": "Feature",
  "properties": {
    "gn:admin1_code":"49",
    "gn:admin2_code":"19.0",
    "gn:asciiname":"Qafemal",
    "gn:cc2":"AL",
    "gn:country_code":"AL",
    "gn:dem":754,
    "gn:feature_class":"P",
    "gn:feature_code":"PPLA3",
    "gn:name":"Qaf\u00ebmal",
    "gn:population":0,
    "gn:timezone":"Europe/Tirane",
    "iso:country":"AL",
    "name:und_x_variant":[
        "Chafamalit",
        "Qafamal",
        "Qaf\u00eb e Malit",
        "Qaf\u00eb Mali",
        "Qaf Mali",
        "Qaf Mal",
        "Qafa e Malit",
        "Qaf\u00ebmal"
    ],
    "wof:name":"Qafemal",
    "wof:placetype":"locality"
},
  "geometry": {"coordinates":[20.09056,42.09333],"type":"Point"}
}