{
  "type": "Feature",
  "properties": {
    "gn:admin1_code":"43",
    "gn:asciiname":"Progem",
    "gn:cc2":"AL",
    "gn:country_code":"AL",
    "gn:dem":226,
    "gn:feature_class":"P",
    "gn:feature_code":"PPL",
    "gn:name":"Progem",
    "gn:population":0,
    "gn:timezone":"Europe/Tirane",
    "iso:country":"AL",
    "name:und_x_variant":[
        "Progni",
        "Progeni",
        "Prog\u00ebn",
        "Prog\u00ebmi",
        "Prog\u00ebm",
        "Proger",
        "Progem"
    ],
    "wof:name":"Progem",
    "wof:placetype":"locality"
},
  "geometry": {"coordinates":[19.76222000000001,41.06056],"type":"Point"}
}