{
  "type": "Feature",
  "properties": {
    "gn:admin1_code":"46",
    "gn:asciiname":"Vranisht",
    "gn:cc2":"AL",
    "gn:country_code":"AL",
    "gn:dem":911,
    "gn:feature_class":"P",
    "gn:feature_code":"PPL",
    "gn:name":"Vranisht",
    "gn:population":0,
    "gn:timezone":"Europe/Tirane",
    "iso:country":"AL",
    "name:und_x_variant":[
        "Vraneshte",
        "Vranishti",
        "Vranishte",
        "Vranishta",
        "Vranisht"
    ],
    "wof:name":"Vranisht",
    "wof:placetype":"locality"
},
  "geometry": {"coordinates":[20.91028,40.66556],"type":"Point"}
}