{
  "type": "Feature",
  "properties": {
    "gn:admin1_code":"44",
    "gn:asciiname":"Imsht",
    "gn:cc2":"AL",
    "gn:country_code":"AL",
    "gn:dem":13,
    "gn:feature_class":"P",
    "gn:feature_code":"PPL",
    "gn:name":"Imsht",
    "gn:population":0,
    "gn:timezone":"Europe/Tirane",
    "iso:country":"AL",
    "name:und_x_variant":[
        "Sheqit",
        "Imsht-Sheqi",
        "Imsht\u00eb-Sheq",
        "Imshta-Sheqi",
        "Imshti",
        "Imsht"
    ],
    "wof:name":"Imsht",
    "wof:placetype":"locality"
},
  "geometry": {"coordinates":[19.69694,40.78944],"type":"Point"}
}