{
  "type": "Feature",
  "properties": {
    "gn:admin1_code":"42",
    "gn:asciiname":"Shetaj",
    "gn:cc2":"AL",
    "gn:country_code":"AL",
    "gn:dem":151,
    "gn:feature_class":"P",
    "gn:feature_code":"PPL",
    "gn:name":"Shetaj",
    "gn:population":0,
    "gn:timezone":"Europe/Tirane",
    "iso:country":"AL",
    "name:und_x_variant":[
        "Scetaj",
        "\u0160etaj",
        "Schataj",
        "Shetaj"
    ],
    "wof:name":"Shetaj",
    "wof:placetype":"locality"
},
  "geometry": {"coordinates":[19.49083,41.55778],"type":"Point"}
}