{
  "type": "Feature",
  "properties": {
    "gn:admin1_code":"51",
    "gn:asciiname":"Karbunare",
    "gn:cc2":"AL",
    "gn:country_code":"AL",
    "gn:dem":114,
    "gn:feature_class":"P",
    "gn:feature_code":"PPL",
    "gn:name":"Karbunar\u00eb",
    "gn:population":0,
    "gn:timezone":"Europe/Tirane",
    "iso:country":"AL",
    "name:und_x_variant":[
        "Carbunara",
        "Karabunara",
        "Carbonara",
        "Kambunar",
        "Karbunari",
        "Karbunar",
        "Karbunara",
        "Karbunar\u00eb"
    ],
    "wof:name":"Karbunare",
    "wof:placetype":"locality"
},
  "geometry": {"coordinates":[19.70278,40.51806],"type":"Point"}
}