{
  "type": "Feature",
  "properties": {
    "gn:admin1_code":"44",
    "gn:asciiname":"Kupas",
    "gn:cc2":"AL",
    "gn:country_code":"AL",
    "gn:dem":157,
    "gn:feature_class":"P",
    "gn:feature_code":"PPL",
    "gn:name":"Kupas",
    "gn:population":0,
    "gn:timezone":"Europe/Tirane",
    "iso:country":"AL",
    "name:und_x_variant":[
        "Kupa",
        "Balaj Kupas",
        "Kupast",
        "Balan Kupasi",
        "Kupasi",
        "Kupas"
    ],
    "wof:name":"Kupas",
    "wof:placetype":"locality"
},
  "geometry": {"coordinates":[19.79167,40.95806],"type":"Point"}
}