{
  "type": "Feature",
  "properties": {
    "gn:admin1_code":"49",
    "gn:asciiname":"Arrez",
    "gn:cc2":"AL",
    "gn:country_code":"AL",
    "gn:dem":362,
    "gn:feature_class":"P",
    "gn:feature_code":"PPL",
    "gn:name":"Arr\u00ebz",
    "gn:population":0,
    "gn:timezone":"Europe/Tirane",
    "iso:country":"AL",
    "name:und_x_variant":[
        "Arr\u00ebz\u00eb",
        "Arr\u00ebz"
    ],
    "wof:name":"Arrez",
    "wof:placetype":"locality"
},
  "geometry": {"coordinates":[19.86944,42.15361],"type":"Point"}
}