{
  "type": "Feature",
  "properties": {
    "gn:admin1_code":"43",
    "gn:admin2_code":"7.0",
    "gn:asciiname":"Kukur",
    "gn:cc2":"AL",
    "gn:country_code":"AL",
    "gn:dem":797,
    "gn:feature_class":"P",
    "gn:feature_code":"PPLA3",
    "gn:name":"Kukur",
    "gn:population":0,
    "gn:timezone":"Europe/Tirane",
    "iso:country":"AL",
    "name:ita_x_preferred":[
        "Kukur"
    ],
    "name:msa_x_preferred":[
        "Kukur"
    ],
    "name:pol_x_preferred":[
        "Gmina Kukur"
    ],
    "name:por_x_preferred":[
        "Kukur"
    ],
    "name:spa_x_preferred":[
        "Kukur"
    ],
    "name:tur_x_preferred":[
        "Kukur"
    ],
    "name:und_x_variant":[
        "Kukuri",
        "Kuk\u00ebr",
        "Kuk\u00ebri"
    ],
    "name:vie_x_preferred":[
        "Kukur"
    ],
    "name:war_x_preferred":[
        "Kukur"
    ],
    "wof:name":"Kukur",
    "wof:placetype":"locality"
},
  "geometry": {"coordinates":[20.36361,40.86778],"type":"Point"}
}