{
  "type": "Feature",
  "properties": {
    "gn:admin1_code":"41",
    "gn:admin2_code":"2.0",
    "gn:asciiname":"Pilafe",
    "gn:country_code":"AL",
    "gn:dem":657,
    "gn:feature_class":"P",
    "gn:feature_code":"PPL",
    "gn:name":"Pilafe",
    "gn:population":0,
    "gn:timezone":"Europe/Tirane",
    "iso:country":"AL",
    "wof:name":"Pilafe",
    "wof:placetype":"locality"
},
  "geometry": {"coordinates":[20.41194,41.69389],"type":"Point"}
}