{
  "type": "Feature",
  "properties": {
    "gn:admin1_code":"49",
    "gn:asciiname":"Alavane",
    "gn:cc2":"AL",
    "gn:country_code":"AL",
    "gn:dem":763,
    "gn:feature_class":"P",
    "gn:feature_code":"PPL",
    "gn:name":"Alavane",
    "gn:population":0,
    "gn:timezone":"Europe/Tirane",
    "iso:country":"AL",
    "name:und_x_variant":[
        "Alavan",
        "Alavane"
    ],
    "wof:name":"Alavane",
    "wof:placetype":"locality"
},
  "geometry": {"coordinates":[19.64611,42.24278],"type":"Point"}
}