{
  "type": "Feature",
  "properties": {
    "gn:admin1_code":"43",
    "gn:asciiname":"Rmath",
    "gn:cc2":"AL",
    "gn:country_code":"AL",
    "gn:dem":1092,
    "gn:feature_class":"P",
    "gn:feature_code":"PPL",
    "gn:name":"Rmath",
    "gn:population":0,
    "gn:timezone":"Europe/Tirane",
    "iso:country":"AL",
    "name:und_x_variant":[
        "Irmathi",
        "Remeth",
        "Irmath",
        "Rmathi",
        "Ormadhi",
        "Ormath",
        "Irmath Ver\u00e7a",
        "Rmath"
    ],
    "wof:name":"Rmath",
    "wof:placetype":"locality"
},
  "geometry": {"coordinates":[20.38528,40.81917],"type":"Point"}
}