{
  "type": "Feature",
  "properties": {
    "gn:admin1_code":"41",
    "gn:asciiname":"Blat",
    "gn:country_code":"AL",
    "gn:dem":192,
    "gn:feature_class":"P",
    "gn:feature_code":"PPL",
    "gn:name":"Blat",
    "gn:population":0,
    "gn:timezone":"Europe/Tirane",
    "iso:country":"AL",
    "name:heb_x_preferred":[
        "\u05d1\u05dc\u05d8"
    ],
    "name:ita_x_preferred":[
        "Blat"
    ],
    "name:lit_x_preferred":[
        "Blatas"
    ],
    "name:por_x_preferred":[
        "Blat"
    ],
    "name:ukr_x_preferred":[
        "\u0411\u043b\u0430\u0442"
    ],
    "wof:name":"Blat",
    "wof:placetype":"locality"
},
  "geometry": {"coordinates":[19.93,41.655],"type":"Point"}
}