{
  "type": "Feature",
  "properties": {
    "gn:admin1_code":"46",
    "gn:asciiname":"Qete",
    "gn:country_code":"AL",
    "gn:dem":434,
    "gn:feature_class":"P",
    "gn:feature_code":"PPL",
    "gn:name":"Qet\u00eb",
    "gn:population":0,
    "gn:timezone":"Europe/Tirane",
    "iso:country":"AL",
    "wof:name":"Qete",
    "wof:placetype":"locality"
},
  "geometry": {"coordinates":[20.33111,40.73444],"type":"Point"}
}