{
  "type": "Feature",
  "properties": {
    "gn:admin1_code":"48",
    "gn:asciiname":"Ndershegas",
    "gn:cc2":"AL",
    "gn:country_code":"AL",
    "gn:dem":157,
    "gn:feature_class":"P",
    "gn:feature_code":"PPL",
    "gn:name":"Nd\u00ebrshegas",
    "gn:population":0,
    "gn:timezone":"Europe/Tirane",
    "iso:country":"AL",
    "name:und_x_variant":[
        "\u0160egas",
        "Shegas"
    ],
    "wof:name":"Ndershegas",
    "wof:placetype":"locality"
},
  "geometry": {"coordinates":[19.71444,41.66861],"type":"Point"}
}