{
  "type": "Feature",
  "properties": {
    "gn:admin1_code":"49",
    "gn:asciiname":"Dragoc",
    "gn:country_code":"AL",
    "gn:dem":62,
    "gn:feature_class":"P",
    "gn:feature_code":"PPL",
    "gn:name":"Drago\u00e7",
    "gn:population":0,
    "gn:timezone":"Europe/Tirane",
    "iso:country":"AL",
    "name:und_x_variant":[
        "Drago\u00e7i",
        "Drago\u00e7"
    ],
    "wof:name":"Dragoc",
    "wof:placetype":"locality"
},
  "geometry": {"coordinates":[19.56111,42.12194],"type":"Point"}
}