{
  "type": "Feature",
  "properties": {
    "gn:admin1_code":"47",
    "gn:asciiname":"Matmilj",
    "gn:cc2":"AL",
    "gn:country_code":"AL",
    "gn:dem":586,
    "gn:feature_class":"P",
    "gn:feature_code":"PPL",
    "gn:name":"Matmilj",
    "gn:population":0,
    "gn:timezone":"Europe/Tirane",
    "iso:country":"AL",
    "name:und_x_variant":[
        "Matmilje",
        "Matmilj"
    ],
    "wof:name":"Matmilj",
    "wof:placetype":"locality"
},
  "geometry": {"coordinates":[20.4825,42.07694],"type":"Point"}
}