{
  "type": "Feature",
  "properties": {
    "gn:admin1_code":"40",
    "gn:admin2_code":"22.0",
    "gn:asciiname":"Bogove",
    "gn:cc2":"AL",
    "gn:country_code":"AL",
    "gn:dem":197,
    "gn:feature_class":"P",
    "gn:feature_code":"PPLA3",
    "gn:name":"Bogov\u00eb",
    "gn:population":0,
    "gn:timezone":"Europe/Tirane",
    "iso:country":"AL",
    "name:ita_x_preferred":[
        "Bogov\u00eb"
    ],
    "name:msa_x_preferred":[
        "Bogov\u00eb"
    ],
    "name:nno_x_preferred":[
        "Bogov\u00eb"
    ],
    "name:pol_x_preferred":[
        "Gmina Bogov\u00eb"
    ],
    "name:por_x_preferred":[
        "Bogov\u00eb"
    ],
    "name:spa_x_preferred":[
        "Bogov\u00eb"
    ],
    "name:tur_x_preferred":[
        "Bogova"
    ],
    "name:vie_x_preferred":[
        "Bogov\u00eb"
    ],
    "name:war_x_preferred":[
        "Bogov\u00eb"
    ],
    "wof:name":"Bogove",
    "wof:placetype":"locality"
},
  "geometry": {"coordinates":[20.15,40.57111],"type":"Point"}
}