{
  "type": "Feature",
  "properties": {
    "gn:admin1_code":"42",
    "gn:asciiname":"Manskur",
    "gn:cc2":"AL",
    "gn:country_code":"AL",
    "gn:dem":119,
    "gn:feature_class":"P",
    "gn:feature_code":"PPL",
    "gn:name":"Manskur",
    "gn:population":0,
    "gn:timezone":"Europe/Tirane",
    "iso:country":"AL",
    "name:und_x_variant":[
        "Manskuri",
        "Manzkuri",
        "Manskuria",
        "Manskurija",
        "Manskuri\u00eb",
        "Menskuri",
        "Manskur"
    ],
    "wof:name":"Manskur",
    "wof:placetype":"locality"
},
  "geometry": {"coordinates":[19.54917,41.2875],"type":"Point"}
}