{
  "type": "Feature",
  "properties": {
    "gn:admin1_code":"46",
    "gn:asciiname":"Beras",
    "gn:cc2":"AL",
    "gn:country_code":"AL",
    "gn:dem":933,
    "gn:feature_class":"P",
    "gn:feature_code":"PPL",
    "gn:name":"Beras",
    "gn:population":0,
    "gn:timezone":"Europe/Tirane",
    "iso:country":"AL",
    "name:und_x_variant":[
        "Beresi",
        "Berasi",
        "Beras"
    ],
    "wof:name":"Beras",
    "wof:placetype":"locality"
},
  "geometry": {"coordinates":[20.67167,40.75556],"type":"Point"}
}