{
  "type": "Feature",
  "properties": {
    "gn:admin1_code":"41",
    "gn:asciiname":"Kraste",
    "gn:cc2":"AL",
    "gn:country_code":"AL",
    "gn:dem":1112,
    "gn:feature_class":"P",
    "gn:feature_code":"PPL",
    "gn:name":"Krast\u00eb",
    "gn:population":0,
    "gn:timezone":"Europe/Tirane",
    "iso:country":"AL",
    "name:ceb_x_preferred":[
        "Krast\u00eb"
    ],
    "name:deu_x_preferred":[
        "Krasta"
    ],
    "name:mkd_x_preferred":[
        "\u041a\u0440\u0430\u0441\u0442\u0430"
    ],
    "name:ron_x_preferred":[
        "Krasta"
    ],
    "name:rus_x_preferred":[
        "\u041a\u0440\u0430\u0441\u0442\u0430"
    ],
    "name:spa_x_preferred":[
        "Kraste"
    ],
    "name:sqi_x_preferred":[
        "Krasta"
    ],
    "name:swe_x_preferred":[
        "Krast\u00eb"
    ],
    "name:tur_x_preferred":[
        "Krasta"
    ],
    "name:ukr_x_preferred":[
        "\u041a\u0440\u0430\u0441\u0442\u0430"
    ],
    "name:und_x_variant":[
        "Krasta",
        "Krast\u00eb"
    ],
    "wof:name":"Kraste",
    "wof:placetype":"locality"
},
  "geometry": {"coordinates":[20.205,41.4225],"type":"Point"}
}