{
  "type": "Feature",
  "properties": {
    "gn:admin1_code":"40",
    "gn:admin2_code":"34.0",
    "gn:asciiname":"Perondi",
    "gn:cc2":"AL",
    "gn:country_code":"AL",
    "gn:dem":41,
    "gn:feature_class":"P",
    "gn:feature_code":"PPLA3",
    "gn:name":"Perondi",
    "gn:population":0,
    "gn:timezone":"Europe/Tirane",
    "iso:country":"AL",
    "name:ita_x_preferred":[
        "Perondi"
    ],
    "name:msa_x_preferred":[
        "Perondi"
    ],
    "name:nno_x_preferred":[
        "Perondi"
    ],
    "name:pol_x_preferred":[
        "Gmina Perondi"
    ],
    "name:por_x_preferred":[
        "Perondi"
    ],
    "name:spa_x_preferred":[
        "Perondi"
    ],
    "name:tur_x_preferred":[
        "Perondi"
    ],
    "name:und_x_variant":[
        "Perhondia",
        "Perhond",
        "Perhondi",
        "Perondija",
        "Perondia",
        "Perhondija"
    ],
    "name:vie_x_preferred":[
        "Perondi"
    ],
    "name:war_x_preferred":[
        "Perondi"
    ],
    "wof:name":"Perondi",
    "wof:placetype":"locality"
},
  "geometry": {"coordinates":[19.92306,40.77889],"type":"Point"}
}