{
  "type": "Feature",
  "properties": {
    "gn:admin1_code":"46",
    "gn:asciiname":"Poceste",
    "gn:cc2":"AL",
    "gn:country_code":"AL",
    "gn:dem":888,
    "gn:feature_class":"P",
    "gn:feature_code":"PPL",
    "gn:name":"Pocest\u00eb",
    "gn:population":0,
    "gn:timezone":"Europe/Tirane",
    "iso:country":"AL",
    "name:mkd_x_preferred":[
        "\u041f\u043e\u0447\u0435\u0441\u0442\u0438"
    ],
    "name:und_x_variant":[
        "Hocisht\u00eb",
        "Pocest",
        "Pocesta",
        "Pocest\u00eb"
    ],
    "wof:name":"Poceste",
    "wof:placetype":"locality"
},
  "geometry": {"coordinates":[20.71556,40.68222],"type":"Point"}
}