{
  "type": "Feature",
  "properties": {
    "gn:admin1_code":"44",
    "gn:asciiname":"Jazxhias",
    "gn:cc2":"AL",
    "gn:country_code":"AL",
    "gn:dem":170,
    "gn:feature_class":"P",
    "gn:feature_code":"PPL",
    "gn:name":"Jazxhias",
    "gn:population":0,
    "gn:timezone":"Europe/Tirane",
    "iso:country":"AL",
    "name:und_x_variant":[
        "Cugarsi",
        "Jazaxhiasi",
        "Jazexhiaj",
        "Jazixhije",
        "Jazixhias",
        "Jazexhijasi",
        "Jazexhiasi",
        "Jazxhijasi",
        "Jazexhias",
        "Jazexhijas",
        "Jazdije",
        "Jazexhiosi",
        "Jazxhias"
    ],
    "wof:name":"Jazxhias",
    "wof:placetype":"locality"
},
  "geometry": {"coordinates":[19.75972,41.00444],"type":"Point"}
}