{
  "type": "Feature",
  "properties": {
    "gn:admin1_code":"47",
    "gn:asciiname":"Kepenek",
    "gn:cc2":"AL",
    "gn:country_code":"AL",
    "gn:dem":505,
    "gn:feature_class":"P",
    "gn:feature_code":"PPL",
    "gn:name":"Kepenek",
    "gn:population":0,
    "gn:timezone":"Europe/Tirane",
    "iso:country":"AL",
    "name:und_x_variant":[
        "Kepeneku",
        "Kepenik",
        "Kepenek"
    ],
    "wof:name":"Kepenek",
    "wof:placetype":"locality"
},
  "geometry": {"coordinates":[20.27306,42.27361],"type":"Point"}
}