{
  "type": "Feature",
  "properties": {
    "gn:admin1_code":"46",
    "gn:asciiname":"Shkoze",
    "gn:cc2":"AL",
    "gn:country_code":"AL",
    "gn:dem":921,
    "gn:feature_class":"P",
    "gn:feature_code":"PPL",
    "gn:name":"Shkoz\u00eb",
    "gn:population":0,
    "gn:timezone":"Europe/Tirane",
    "iso:country":"AL",
    "name:und_x_variant":[
        "Shkoza",
        "Shkoz\u00eb"
    ],
    "wof:name":"Shkoze",
    "wof:placetype":"locality"
},
  "geometry": {"coordinates":[20.68444,40.73639],"type":"Point"}
}