{
  "type": "Feature",
  "properties": {
    "gn:admin1_code":"49",
    "gn:asciiname":"Plan",
    "gn:cc2":"AL",
    "gn:country_code":"AL",
    "gn:dem":679,
    "gn:feature_class":"P",
    "gn:feature_code":"PPL",
    "gn:name":"Plan",
    "gn:population":0,
    "gn:timezone":"Europe/Tirane",
    "iso:country":"AL",
    "name:ara_x_preferred":[
        "\u062e\u0637\u0629"
    ],
    "name:aze_x_preferred":[
        "Plan"
    ],
    "name:ben_x_preferred":[
        "\u09aa\u09b0\u09bf\u0995\u09b2\u09cd\u09aa\u09a8\u09be"
    ],
    "name:ces_x_preferred":[
        "Pl\u00e1n"
    ],
    "name:est_x_preferred":[
        "Plaan"
    ],
    "name:fas_x_preferred":[
        "\u0637\u0631\u062d"
    ],
    "name:gag_x_preferred":[
        "Plan"
    ],
    "name:hat_x_preferred":[
        "Program"
    ],
    "name:heb_x_preferred":[
        "\u05ea\u05d5\u05db\u05e0\u05d9\u05ea \u05e4\u05e2\u05d5\u05dc\u05d4"
    ],
    "name:hin_x_preferred":[
        "\u092f\u094b\u091c\u0928\u093e"
    ],
    "name:hrv_x_preferred":[
        "Plan"
    ],
    "name:ind_x_preferred":[
        "Rencana"
    ],
    "name:ita_x_preferred":[
        "Piano"
    ],
    "name:kan_x_preferred":[
        "\u0caf\u0ccb\u0c9c\u0ca8\u0cc6"
    ],
    "name:kir_x_preferred":[
        "\u041f\u043b\u0430\u043d"
    ],
    "name:mkd_x_preferred":[
        "\u041f\u043b\u0430\u043d"
    ],
    "name:tha_x_preferred":[
        "\u0e41\u0e1c\u0e19"
    ],
    "name:tur_x_preferred":[
        "Plan"
    ],
    "name:und_x_variant":[
        "Plani",
        "Pland\u00eb",
        "Plan"
    ],
    "name:uzb_x_preferred":[
        "Reja"
    ],
    "name:vie_x_preferred":[
        "K\u1ebf ho\u1ea1ch"
    ],
    "wof:name":"Plan",
    "wof:placetype":"locality"
},
  "geometry": {"coordinates":[19.69028,42.28944],"type":"Point"}
}