{
  "type": "Feature",
  "properties": {
    "gn:admin1_code":"49",
    "gn:asciiname":"Plan",
    "gn:cc2":"AL",
    "gn:country_code":"AL",
    "gn:dem":679,
    "gn:feature_class":"P",
    "gn:feature_code":"PPL",
    "gn:name":"Plan",
    "gn:population":0,
    "gn:timezone":"Europe/Tirane",
    "iso:country":"AL",
    "name:und_x_variant":[
        "Plani",
        "Pland\u00eb",
        "Plan"
    ],
    "wof:name":"Plan",
    "wof:placetype":"locality"
},
  "geometry": {"coordinates":[19.69028,42.28944],"type":"Point"}
}