{
  "type": "Feature",
  "properties": {
    "gn:admin1_code":"41",
    "gn:asciiname":"Mallunxe",
    "gn:cc2":"AL",
    "gn:country_code":"AL",
    "gn:dem":313,
    "gn:feature_class":"P",
    "gn:feature_code":"PPL",
    "gn:name":"Mallunx\u00eb",
    "gn:population":0,
    "gn:timezone":"Europe/Tirane",
    "iso:country":"AL",
    "name:und_x_variant":[
        "Mallanxa",
        "Mallonza",
        "Mallunz\u00eb",
        "Mallunca",
        "Mallunxa",
        "Mallux\u00eb",
        "Mallunx\u00eb"
    ],
    "wof:name":"Mallunxe",
    "wof:placetype":"locality"
},
  "geometry": {"coordinates":[20.05722,41.59639],"type":"Point"}
}