{
  "type": "Feature",
  "properties": {
    "gn:admin1_code":"48",
    "gn:asciiname":"Katundi i Vjeter",
    "gn:cc2":"AL",
    "gn:country_code":"AL",
    "gn:dem":522,
    "gn:feature_class":"P",
    "gn:feature_code":"PPL",
    "gn:name":"Katundi i Vjet\u00ebr",
    "gn:population":0,
    "gn:timezone":"Europe/Tirane",
    "iso:country":"AL",
    "name:und_x_variant":[
        "Katund i Vjet\u00ebr",
        "Katundi i Vjet\u00ebr"
    ],
    "wof:name":"Katundi i Vjeter",
    "wof:placetype":"locality"
},
  "geometry": {"coordinates":[19.80722,41.6725],"type":"Point"}
}