{
  "type": "Feature",
  "properties": {
    "gn:admin1_code":"48",
    "gn:asciiname":"Ndershene",
    "gn:cc2":"AL",
    "gn:country_code":"AL",
    "gn:dem":937,
    "gn:feature_class":"P",
    "gn:feature_code":"PPL",
    "gn:name":"Nd\u00ebrshen\u00eb",
    "gn:population":0,
    "gn:timezone":"Europe/Tirane",
    "iso:country":"AL",
    "name:und_x_variant":[
        "Nd\u00ebrshen",
        "Ndershen\u00ebs",
        "Nd\u00ebrshena",
        "Nersheni",
        "Nd\u00ebrshen\u00eb"
    ],
    "wof:name":"Ndershene",
    "wof:placetype":"locality"
},
  "geometry": {"coordinates":[20.08694,41.82944000000001],"type":"Point"}
}