{
  "type": "Feature",
  "properties": {
    "gn:admin1_code":"47",
    "gn:asciiname":"Vas-Spas",
    "gn:cc2":"AL",
    "gn:country_code":"AL",
    "gn:dem":279,
    "gn:feature_class":"P",
    "gn:feature_code":"PPL",
    "gn:name":"Vas-Spas",
    "gn:population":0,
    "gn:timezone":"Europe/Tirane",
    "iso:country":"AL",
    "name:und_x_variant":[
        "Vaspasi",
        "Va i Spasit",
        "Vas-Spasi",
        "Va-Spasi"
    ],
    "wof:name":"Vas-Spas",
    "wof:placetype":"locality"
},
  "geometry": {"coordinates":[20.26333,42.17944],"type":"Point"}
}