{
  "type": "Feature",
  "properties": {
    "gn:admin1_code":"41",
    "gn:asciiname":"Okshatine",
    "gn:cc2":"AL",
    "gn:country_code":"AL",
    "gn:dem":507,
    "gn:feature_class":"P",
    "gn:feature_code":"PPL",
    "gn:name":"Okshatin\u00eb",
    "gn:population":0,
    "gn:timezone":"Europe/Tirane",
    "iso:country":"AL",
    "name:und_x_variant":[
        "Okshatin",
        "Okshetina",
        "Okshatina",
        "Okshatin\u00eb"
    ],
    "wof:name":"Okshatine",
    "wof:placetype":"locality"
},
  "geometry": {"coordinates":[20.42639,41.56583],"type":"Point"}
}