{
  "type": "Feature",
  "properties": {
    "gn:admin1_code":"46",
    "gn:asciiname":"Koshnice",
    "gn:cc2":"AL",
    "gn:country_code":"AL",
    "gn:dem":975,
    "gn:feature_class":"P",
    "gn:feature_code":"PPL",
    "gn:name":"Koshnic\u00eb",
    "gn:population":0,
    "gn:timezone":"Europe/Tirane",
    "iso:country":"AL",
    "name:und_x_variant":[
        "Koshnica",
        "Koshnic\u00eb"
    ],
    "wof:name":"Koshnice",
    "wof:placetype":"locality"
},
  "geometry": {"coordinates":[20.91722,40.53028],"type":"Point"}
}