{
  "type": "Feature",
  "properties": {
    "iso:country":"AL",
    "name:und_x_variant":[
        "Bogdani i Sip\u00ebrm"
    ],
    "qs:gn_country":"AL",
    "qs:gn_fcode":"PPL",
    "qs:gn_pop":0,
    "qs:name":"Bogdan i Sip\u00ebrm",
    "qs:name_adm0":"Shqip\u00ebri",
    "qs:name_adm1":"Berat",
    "qs:photos":18,
    "qs:photos_1k":4,
    "qs:photos_9k":1,
    "qs:photos_9r":1,
    "qs:photos_all":18,
    "qs:photos_sr":1,
    "qs:placetype":"Suburb",
    "qs:pop_sr":"0",
    "qs:woe_adm0":23424742,
    "wof:name":"Bogdan i Sip\u00ebrm",
    "wof:placetype":"neighbourhood"
},
  "geometry": {"coordinates":[20.06611,40.72222],"type":"Point"}
}