{
  "type": "Feature",
  "properties": {
    "gn:admin1_code":"45",
    "gn:asciiname":"Valare",
    "gn:cc2":"AL",
    "gn:country_code":"AL",
    "gn:dem":198,
    "gn:feature_class":"P",
    "gn:feature_code":"PPL",
    "gn:name":"Valare",
    "gn:population":0,
    "gn:timezone":"Europe/Tirane",
    "iso:country":"AL",
    "name:und_x_variant":[
        "Valarea",
        "Valare"
    ],
    "wof:name":"Valare",
    "wof:placetype":"locality"
},
  "geometry": {"coordinates":[20.13417,40.12556],"type":"Point"}
}