{
  "type": "Feature",
  "properties": {
    "gn:admin1_code":"41",
    "gn:asciiname":"Vernice",
    "gn:cc2":"AL",
    "gn:country_code":"AL",
    "gn:dem":830,
    "gn:feature_class":"P",
    "gn:feature_code":"PPL",
    "gn:name":"Vernic\u00eb",
    "gn:population":0,
    "gn:timezone":"Europe/Tirane",
    "iso:country":"AL",
    "name:bul_x_preferred":[
        "\u0412\u0440\u044a\u0431\u043d\u0438\u0446\u0430"
    ],
    "name:mkd_x_preferred":[
        "\u0412\u0440\u043d\u0438\u0446\u0430"
    ],
    "name:sqi_x_preferred":[
        "V\u00ebrnic\u00eb"
    ],
    "name:und_x_variant":[
        "Vbrnic\u00eb",
        "V\u00ebrenic\u00eb",
        "V\u00ebrnica",
        "Vernic\u00eb"
    ],
    "wof:name":"Vernice",
    "wof:placetype":"locality"
},
  "geometry": {"coordinates":[20.52722,41.42333],"type":"Point"}
}