{
  "type": "Feature",
  "properties": {
    "gn:admin1_code":"51",
    "gn:asciiname":"Fushe Brrati",
    "gn:cc2":"AL",
    "gn:country_code":"AL",
    "gn:dem":350,
    "gn:feature_class":"P",
    "gn:feature_code":"PPL",
    "gn:name":"Fush\u00eb Brrati",
    "gn:population":0,
    "gn:timezone":"Europe/Tirane",
    "iso:country":"AL",
    "name:und_x_variant":[
        "Fush\u00eb Brati",
        "Fush\u00eb Brrati"
    ],
    "wof:name":"Fushe Brrati",
    "wof:placetype":"locality"
},
  "geometry": {"coordinates":[19.80917,40.17472],"type":"Point"}
}