{
  "type": "Feature",
  "properties": {
    "gn:admin1_code":"46",
    "gn:asciiname":"Mesicca",
    "gn:country_code":"AL",
    "gn:dem":927,
    "gn:feature_class":"P",
    "gn:feature_code":"PPL",
    "gn:name":"Mesicca",
    "gn:population":0,
    "gn:timezone":"Europe/Tirane",
    "iso:country":"AL",
    "name:und_x_variant":[
        "Mesi\u00e7ka",
        "Mesicca",
        "Misick\u00eb",
        "M\u00ebsi\u00e7k\u00eb"
    ],
    "wof:name":"Mesicca",
    "wof:placetype":"locality"
},
  "geometry": {"coordinates":[20.58,40.35278],"type":"Point"}
}