{
  "type": "Feature",
  "properties": {
    "gn:admin1_code":"45",
    "gn:asciiname":"Rapcke",
    "gn:cc2":"AL",
    "gn:country_code":"AL",
    "gn:dem":372,
    "gn:feature_class":"P",
    "gn:feature_code":"PPL",
    "gn:name":"Rapck\u00eb",
    "gn:population":0,
    "gn:timezone":"Europe/Tirane",
    "iso:country":"AL",
    "name:und_x_variant":[
        "Rapoke",
        "Repcka",
        "Rapisca",
        "Rapcka",
        "Rapsk\u00eb",
        "Rapck\u00eb"
    ],
    "wof:name":"Rapcke",
    "wof:placetype":"locality"
},
  "geometry": {"coordinates":[20.27222,40.2625],"type":"Point"}
}