{
  "type": "Feature",
  "properties": {
    "gn:admin1_code":"50",
    "gn:admin2_code":"33.0",
    "gn:asciiname":"Luzi i Vogel",
    "gn:cc2":"AL",
    "gn:country_code":"AL",
    "gn:dem":15,
    "gn:feature_class":"P",
    "gn:feature_code":"PPLA3",
    "gn:name":"Luzi i Vog\u00ebl",
    "gn:population":0,
    "gn:timezone":"Europe/Tirane",
    "iso:country":"AL",
    "name:und_x_variant":[
        "Luz i Vog\u00ebl",
        "Ljuz i vogel",
        "Luzi i Vog\u00ebl"
    ],
    "wof:name":"Luzi i Vogel",
    "wof:placetype":"locality"
},
  "geometry": {"coordinates":[19.57389,41.1275],"type":"Point"}
}