{
  "type": "Feature",
  "properties": {
    "gn:country":"AL",
    "gn:fcode":"PPL",
    "gn:pop":5,
    "iso:country":"AL",
    "name:unk_x_variant":[
        "Shugyrku"
    ],
    "qs:name":"Shugyrk",
    "qs:photos_9r":0,
    "qs:photos_sr":0,
    "qs:pop_sr":"1",
    "wof:name":"Shugyrk",
    "wof:placetype":"locality",
    "wof:population":5
},
  "geometry": {"coordinates":[19.93028,41.44],"type":"Point"}
}