{
  "type": "Feature",
  "properties": {
    "gn:admin1_code":"43",
    "gn:asciiname":"Ulem",
    "gn:cc2":"AL",
    "gn:country_code":"AL",
    "gn:dem":548,
    "gn:feature_class":"P",
    "gn:feature_code":"PPL",
    "gn:name":"Ul\u00ebm",
    "gn:population":0,
    "gn:timezone":"Europe/Tirane",
    "iso:country":"AL",
    "name:und_x_variant":[
        "Ulm\u00eb",
        "Ul\u00ebm\u00eb",
        "Ulema",
        "Ulaj",
        "Ulma",
        "Ul\u00ebm"
    ],
    "wof:name":"Ulem",
    "wof:placetype":"locality"
},
  "geometry": {"coordinates":[19.98333,41.15],"type":"Point"}
}