{
  "type": "Feature",
  "properties": {
    "gn:admin1_code":"41",
    "gn:asciiname":"Urxalle",
    "gn:cc2":"AL",
    "gn:country_code":"AL",
    "gn:dem":612,
    "gn:feature_class":"P",
    "gn:feature_code":"PPL",
    "gn:name":"Urxall\u00eb",
    "gn:population":0,
    "gn:timezone":"Europe/Tirane",
    "iso:country":"AL",
    "name:und_x_variant":[
        "Urzalli",
        "Urzall",
        "Urxall\u00eb"
    ],
    "wof:name":"Urxalle",
    "wof:placetype":"locality"
},
  "geometry": {"coordinates":[20.07194,41.68944000000001],"type":"Point"}
}