{
  "type": "Feature",
  "properties": {
    "gn:admin1_code":"44",
    "gn:asciiname":"Murriz",
    "gn:cc2":"AL",
    "gn:country_code":"AL",
    "gn:dem":144,
    "gn:feature_class":"P",
    "gn:feature_code":"PPL",
    "gn:name":"Murriz",
    "gn:population":0,
    "gn:timezone":"Europe/Tirane",
    "iso:country":"AL",
    "name:und_x_variant":[
        "Muris-Peqini",
        "Murriz-Peqini",
        "Murriz-Peqin",
        "Muriz",
        "Murrizi",
        "Muriz Peqini",
        "Muriz-Peqin",
        "Murriz"
    ],
    "wof:name":"Murriz",
    "wof:placetype":"locality"
},
  "geometry": {"coordinates":[19.80167,40.94139000000001],"type":"Point"}
}