{
  "type": "Feature",
  "properties": {
    "gn:admin1_code":"48",
    "gn:asciiname":"Lestere",
    "gn:country_code":"AL",
    "gn:dem":478,
    "gn:feature_class":"P",
    "gn:feature_code":"PPL",
    "gn:name":"Lester\u00eb",
    "gn:population":0,
    "gn:timezone":"Europe/Tirane",
    "iso:country":"AL",
    "wof:name":"Lestere",
    "wof:placetype":"locality"
},
  "geometry": {"coordinates":[19.75194,41.6225],"type":"Point"}
}