{
  "type": "Feature",
  "properties": {
    "gn:admin1_code":"43",
    "gn:asciiname":"Lukan",
    "gn:cc2":"AL",
    "gn:country_code":"AL",
    "gn:dem":641,
    "gn:feature_class":"P",
    "gn:feature_code":"PPL",
    "gn:name":"Lukan",
    "gn:population":0,
    "gn:timezone":"Europe/Tirane",
    "iso:country":"AL",
    "name:und_x_variant":[
        "Lukanj",
        "Lukani",
        "Lukan"
    ],
    "wof:name":"Lukan",
    "wof:placetype":"locality"
},
  "geometry": {"coordinates":[20.15806,41.02778],"type":"Point"}
}