{
  "type": "Feature",
  "properties": {
    "gn:admin1_code":"40",
    "gn:asciiname":"Frasher",
    "gn:cc2":"AL",
    "gn:country_code":"AL",
    "gn:dem":58,
    "gn:feature_class":"P",
    "gn:feature_code":"PPL",
    "gn:name":"Frash\u00ebr",
    "gn:population":0,
    "gn:timezone":"Europe/Tirane",
    "iso:country":"AL",
    "name:und_x_variant":[
        "Frash\u00ebri Qelepir",
        "Frash\u00ebri",
        "Frashari",
        "Frash\u00ebr"
    ],
    "wof:name":"Frasher",
    "wof:placetype":"locality"
},
  "geometry": {"coordinates":[19.94528,40.86528],"type":"Point"}
}