{
  "type": "Feature",
  "properties": {
    "gn:admin1_code":"49",
    "gn:asciiname":"Mlloje",
    "gn:cc2":"AL",
    "gn:country_code":"AL",
    "gn:dem":95,
    "gn:feature_class":"P",
    "gn:feature_code":"PPL",
    "gn:name":"Mlloj\u00eb",
    "gn:population":0,
    "gn:timezone":"Europe/Tirane",
    "iso:country":"AL",
    "name:und_x_variant":[
        "Mlloja",
        "Mloja",
        "M\u00eblloja",
        "Mjlloj\u00eb",
        "Mlloj\u00eb"
    ],
    "wof:name":"Mlloje",
    "wof:placetype":"locality"
},
  "geometry": {"coordinates":[19.68,42.07306],"type":"Point"}
}