{
  "type": "Feature",
  "properties": {
    "gn:admin1_code":"47",
    "gn:asciiname":"Kollovoz",
    "gn:cc2":"AL",
    "gn:country_code":"AL",
    "gn:dem":1501,
    "gn:feature_class":"P",
    "gn:feature_code":"PPL",
    "gn:name":"Kollovoz",
    "gn:population":0,
    "gn:timezone":"Europe/Tirane",
    "iso:country":"AL",
    "name:hye_x_preferred":[
        "\u053f\u0578\u056c\u0578\u057e\u0578\u0566"
    ],
    "name:rus_x_preferred":[
        "\u041a\u043e\u043b\u043b\u043e\u0432\u043e\u0437"
    ],
    "name:sqi_x_preferred":[
        "Kollovozi"
    ],
    "name:ukr_x_preferred":[
        "\u041a\u043e\u043b\u043e\u0432\u043e\u0437"
    ],
    "name:und_x_variant":[
        "Kallovozi",
        "Kollovos",
        "Kolovoz",
        "Kollovoz"
    ],
    "wof:name":"Kollovoz",
    "wof:placetype":"locality"
},
  "geometry": {"coordinates":[20.54694,41.99722],"type":"Point"}
}