{
  "type": "Feature",
  "properties": {
    "gn:admin1_code":"46",
    "gn:asciiname":"Burimas",
    "gn:cc2":"AL",
    "gn:country_code":"AL",
    "gn:dem":843,
    "gn:feature_class":"P",
    "gn:feature_code":"PPL",
    "gn:name":"Burimas",
    "gn:population":0,
    "gn:timezone":"Europe/Tirane",
    "iso:country":"AL",
    "name:mkd_x_preferred":[
        "\u0413\u043e\u043b\u043e \u0411\u0440\u0434\u043e"
    ],
    "name:sqi_x_preferred":[
        "Burimas"
    ],
    "name:und_x_variant":[
        "Kollob\u00ebrda",
        "Goloberd\u00eb",
        "Goloberda",
        "Burimi",
        "Gollob\u00ebrdha",
        "Golloberda",
        "Gollob\u00ebrd\u00eb",
        "Burimas"
    ],
    "wof:name":"Burimas",
    "wof:placetype":"locality"
},
  "geometry": {"coordinates":[20.89111,40.71833],"type":"Point"}
}