{
  "type": "Feature",
  "properties": {
    "gn:admin1_code":"45",
    "gn:asciiname":"Toc",
    "gn:cc2":"AL",
    "gn:country_code":"AL",
    "gn:dem":325,
    "gn:feature_class":"P",
    "gn:feature_code":"PPL",
    "gn:name":"To\u00e7",
    "gn:population":0,
    "gn:timezone":"Europe/Tirane",
    "iso:country":"AL",
    "name:und_x_variant":[
        "Toki",
        "To\u00e7i",
        "To\u00e7"
    ],
    "wof:name":"Toc",
    "wof:placetype":"locality"
},
  "geometry": {"coordinates":[19.87472,40.41167],"type":"Point"}
}