{
  "type": "Feature",
  "properties": {
    "gn:admin1_code":"45",
    "gn:asciiname":"Psar",
    "gn:cc2":"AL",
    "gn:country_code":"AL",
    "gn:dem":616,
    "gn:feature_class":"P",
    "gn:feature_code":"PPL",
    "gn:name":"Psar",
    "gn:population":0,
    "gn:timezone":"Europe/Tirane",
    "iso:country":"AL",
    "name:und_x_variant":[
        "Psari",
        "Psar"
    ],
    "wof:name":"Psar",
    "wof:placetype":"locality"
},
  "geometry": {"coordinates":[20.10139,40.39889],"type":"Point"}
}