{
  "type": "Feature",
  "properties": {
    "gn:admin1_code":"50",
    "gn:asciiname":"Kanaparaj",
    "gn:cc2":"AL",
    "gn:country_code":"AL",
    "gn:dem":144,
    "gn:feature_class":"P",
    "gn:feature_code":"PPL",
    "gn:name":"Kanaparaj",
    "gn:population":0,
    "gn:timezone":"Europe/Tirane",
    "iso:country":"AL",
    "name:und_x_variant":[
        "Konaparej",
        "Kanaparej",
        "Kanaparaj"
    ],
    "wof:name":"Kanaparaj",
    "wof:placetype":"locality"
},
  "geometry": {"coordinates":[19.56833,41.2275],"type":"Point"}
}