{
  "type": "Feature",
  "properties": {
    "gn:country":"AL",
    "gn:fcode":"PPLA3",
    "gn:pop":2438,
    "iso:country":"AL",
    "name:alb_x_preferred":[
        "Fush\u00eb-Arr\u00ebz"
    ],
    "name:bul_x_preferred":[
        "\u0424\u0443\u0448\u0430-\u0410\u0440\u0430\u0437"
    ],
    "name:chi_x_preferred":[
        "\u5bcc\u820d\u963f\u52d2\u8332"
    ],
    "name:dut_x_preferred":[
        "Fush\u00eb-Arr\u00ebz"
    ],
    "name:eng_x_preferred":[
        "Fush\u00eb-Arr\u00ebz"
    ],
    "name:fre_x_preferred":[
        "Fush\u00eb-Arr\u00ebz"
    ],
    "name:ger_x_preferred":[
        "Fush\u00eb-Arr\u00ebz"
    ],
    "name:ita_x_preferred":[
        "Fush\u00eb Arr\u00ebz"
    ],
    "name:mac_x_preferred":[
        "\u0424\u0443\u0448\u0430-\u0410\u0440\u0430\u0437"
    ],
    "name:may_x_preferred":[
        "Fush\u00eb-Arr\u00ebz"
    ],
    "name:pol_x_preferred":[
        "Gmina Fush\u00eb-Arr\u00ebz"
    ],
    "name:por_x_preferred":[
        "Fush\u00eb-Arr\u00ebz"
    ],
    "name:rum_x_preferred":[
        "Fush\u00eb-Arrez"
    ],
    "name:rus_x_preferred":[
        "\u0424\u0443\u0448\u0430-\u0410\u0440\u0440\u0435\u0441"
    ],
    "name:spa_x_preferred":[
        "Fush\u00eb-Arr\u00ebz"
    ],
    "name:tat_x_preferred":[
        "\u0424\u0443\u0448\u0430-\u0410\u0440\u0440\u044b\u0437"
    ],
    "name:tur_x_preferred":[
        "Fush\u00eb-Arr\u00ebz"
    ],
    "name:unk_x_variant":[
        "Arr\u00ebs"
    ],
    "name:vie_x_preferred":[
        "Fush\u00eb Arr\u00ebz"
    ],
    "name:war_x_preferred":[
        "Fush\u00eb-Arr\u00ebz"
    ],
    "qs:name":"Fush\u00eb-Arr\u00ebz",
    "qs:photos_9r":0,
    "qs:photos_sr":0,
    "qs:pop_sr":"4",
    "wd:wordcount":118,
    "wof:name":"Fush\u00eb-Arr\u00ebz",
    "wof:placetype":"locality",
    "wof:population":2438
},
  "geometry": {"coordinates":[20.01667,42.06222],"type":"Point"}
}