{
  "type": "Feature",
  "properties": {
    "gn:country":"AL",
    "gn:fcode":"PPLA3",
    "gn:population":2438,
    "iso:country":"AL",
    "name:bul_x_preferred":[
        "\u0424\u0443\u0448\u0430-\u0410\u0440\u0430\u0437"
    ],
    "name:deu_x_preferred":[
        "Fush\u00eb-Arr\u00ebz"
    ],
    "name:ell_x_preferred":[
        "\u03a6\u03bf\u03c5\u03c3\u03ad-\u0391\u03c1\u03ad\u03b6"
    ],
    "name:eng_x_preferred":[
        "Fush\u00eb-Arr\u00ebz"
    ],
    "name:fra_x_preferred":[
        "Fush\u00eb-Arr\u00ebz"
    ],
    "name:hun_x_preferred":[
        "Fush\u00eb-Arr\u00ebz"
    ],
    "name:ita_x_preferred":[
        "Fush\u00eb Arr\u00ebz"
    ],
    "name:mkd_x_preferred":[
        "\u0424\u0443\u0448\u0430-\u0410\u0440\u0430\u0437"
    ],
    "name:mkd_x_variant":[
        "\u0410\u0440\u0430\u0441\u043a\u043e \u041f\u043e\u043b\u0435"
    ],
    "name:msa_x_preferred":[
        "Fush\u00eb-Arr\u00ebz"
    ],
    "name:nld_x_preferred":[
        "Fush\u00eb-Arr\u00ebz"
    ],
    "name:pol_x_preferred":[
        "Gmina Fush\u00eb-Arr\u00ebz"
    ],
    "name:por_x_preferred":[
        "Fush\u00eb-Arr\u00ebz"
    ],
    "name:ron_x_preferred":[
        "Fush\u00eb-Arrez"
    ],
    "name:rus_x_preferred":[
        "\u0424\u0443\u0448\u0430-\u0410\u0440\u0440\u0435\u0441"
    ],
    "name:spa_x_preferred":[
        "Fush\u00eb-Arr\u00ebz"
    ],
    "name:sqi_x_preferred":[
        "Fush\u00eb-Arr\u00ebz"
    ],
    "name:tat_x_preferred":[
        "\u0424\u0443\u0448\u0430-\u0410\u0440\u0440\u044b\u0437"
    ],
    "name:tur_x_preferred":[
        "Fush\u00eb-Arr\u00ebz"
    ],
    "name:und_x_variant":[
        "Arr\u00ebs"
    ],
    "name:vie_x_preferred":[
        "Fush\u00eb Arr\u00ebz"
    ],
    "name:war_x_preferred":[
        "Fush\u00eb-Arr\u00ebz"
    ],
    "name:zho_x_preferred":[
        "\u5bcc\u820d\u963f\u52d2\u8332"
    ],
    "qs:name":"Fush\u00eb-Arr\u00ebz",
    "qs:photos_9r":0,
    "qs:photos_sr":0,
    "qs:pop_sr":"4",
    "wd:wordcount":118,
    "wof:name":"Fush\u00eb-Arr\u00ebz",
    "wof:placetype":"locality",
    "wof:population":2438
},
  "geometry": {"coordinates":[20.01667,42.06222],"type":"Point"}
}