{
  "type": "Feature",
  "properties": {
    "gn:admin1_code":"44",
    "gn:asciiname":"Sopez",
    "gn:cc2":"AL",
    "gn:country_code":"AL",
    "gn:dem":8,
    "gn:feature_class":"P",
    "gn:feature_code":"PPL",
    "gn:name":"Sop\u00ebz",
    "gn:population":0,
    "gn:timezone":"Europe/Tirane",
    "iso:country":"AL",
    "name:und_x_variant":[
        "Sopesa",
        "Sopez\u00eb",
        "Sop\u00ebza",
        "Sop\u00ebz"
    ],
    "wof:name":"Sopez",
    "wof:placetype":"locality"
},
  "geometry": {"coordinates":[19.63528,40.90917],"type":"Point"}
}