{
  "type": "Feature",
  "properties": {
    "gn:admin1_code":"44",
    "gn:asciiname":"Metaj",
    "gn:cc2":"AL",
    "gn:country_code":"AL",
    "gn:dem":5,
    "gn:feature_class":"P",
    "gn:feature_code":"PPL",
    "gn:name":"Metaj",
    "gn:population":0,
    "gn:timezone":"Europe/Tirane",
    "iso:country":"AL",
    "name:und_x_variant":[
        "Metanji",
        "Metani",
        "Metajn",
        "Metaj"
    ],
    "wof:name":"Metaj",
    "wof:placetype":"locality"
},
  "geometry": {"coordinates":[19.52444,40.82917],"type":"Point"}
}