{
  "type": "Feature",
  "properties": {
    "gn:admin1_code":"45",
    "gn:asciiname":"Dracove",
    "gn:cc2":"AL",
    "gn:country_code":"AL",
    "gn:dem":401,
    "gn:feature_class":"P",
    "gn:feature_code":"PPL",
    "gn:name":"Dra\u00e7ov\u00eb",
    "gn:population":0,
    "gn:timezone":"Europe/Tirane",
    "iso:country":"AL",
    "name:und_x_variant":[
        "Dra\u00e7ova",
        "Drashova",
        "Dracevo",
        "Dra\u00e7ov\u00eb"
    ],
    "wof:name":"Dracove",
    "wof:placetype":"locality"
},
  "geometry": {"coordinates":[20.4875,40.12917],"type":"Point"}
}