{
  "type": "Feature",
  "properties": {
    "gn:admin1_code":"49",
    "gn:asciiname":"Qershis e Palajt",
    "gn:cc2":"AL",
    "gn:country_code":"AL",
    "gn:dem":855,
    "gn:feature_class":"P",
    "gn:feature_code":"PPL",
    "gn:name":"Qershis e Palajt",
    "gn:population":0,
    "gn:timezone":"Europe/Tirane",
    "iso:country":"AL",
    "name:und_x_variant":[
        "Qershisa e Palajve",
        "Qershis e Palajt"
    ],
    "wof:name":"Qershis e Palajt",
    "wof:placetype":"locality"
},
  "geometry": {"coordinates":[19.76278,42.19194],"type":"Point"}
}