{
  "type": "Feature",
  "properties": {
    "gn:admin1_code":"44",
    "gn:asciiname":"Sop",
    "gn:cc2":"AL",
    "gn:country_code":"AL",
    "gn:dem":3,
    "gn:feature_class":"P",
    "gn:feature_code":"PPL",
    "gn:name":"Sop",
    "gn:population":0,
    "gn:timezone":"Europe/Tirane",
    "iso:country":"AL",
    "name:cat_x_preferred":[
        "Pa xopat"
    ],
    "name:spa_x_preferred":[
        "Sop"
    ],
    "name:und_x_variant":[
        "Sopi",
        "Apollont\u00eb"
    ],
    "wof:name":"Sop",
    "wof:placetype":"locality"
},
  "geometry": {"coordinates":[19.4575,40.71889],"type":"Point"}
}