{
  "type": "Feature",
  "properties": {
    "gn:admin1_code":"50",
    "gn:asciiname":"Luzi i Madh",
    "gn:cc2":"AL",
    "gn:country_code":"AL",
    "gn:dem":15,
    "gn:feature_class":"P",
    "gn:feature_code":"PPL",
    "gn:name":"Luzi i Madh",
    "gn:population":0,
    "gn:timezone":"Europe/Tirane",
    "iso:country":"AL",
    "name:und_x_variant":[
        "Ljuz i Mal",
        "Luz i Madh",
        "Luz\u2019-i math",
        "Luzi i Madh"
    ],
    "wof:name":"Luzi i Madh",
    "wof:placetype":"locality"
},
  "geometry": {"coordinates":[19.58083,41.11111],"type":"Point"}
}