{
  "type": "Feature",
  "properties": {
    "gn:admin1_code":"41",
    "gn:asciiname":"Mustafaj",
    "gn:cc2":"AL",
    "gn:country_code":"AL",
    "gn:dem":893,
    "gn:feature_class":"P",
    "gn:feature_code":"PPL",
    "gn:name":"Mustafaj",
    "gn:population":0,
    "gn:timezone":"Europe/Tirane",
    "iso:country":"AL",
    "name:und_x_variant":[
        "Mustaf\u00eb",
        "Mustafaj"
    ],
    "wof:name":"Mustafaj",
    "wof:placetype":"locality"
},
  "geometry": {"coordinates":[20.31222,41.77611],"type":"Point"}
}