{
  "type": "Feature",
  "properties": {
    "gn:admin1_code":"43",
    "gn:asciiname":"Vozjan",
    "gn:cc2":"AL",
    "gn:country_code":"AL",
    "gn:dem":962,
    "gn:feature_class":"P",
    "gn:feature_code":"PPL",
    "gn:name":"Vozjan",
    "gn:population":0,
    "gn:timezone":"Europe/Tirane",
    "iso:country":"AL",
    "name:und_x_variant":[
        "Vozian",
        "Voziani",
        "Vozjan"
    ],
    "wof:name":"Vozjan",
    "wof:placetype":"locality"
},
  "geometry": {"coordinates":[20.25917,41.05722],"type":"Point"}
}