{
  "type": "Feature",
  "properties": {
    "gn:admin1_code":"44",
    "gn:asciiname":"Suku i Poshtem",
    "gn:cc2":"AL",
    "gn:country_code":"AL",
    "gn:dem":11,
    "gn:feature_class":"P",
    "gn:feature_code":"PPL",
    "gn:name":"Suku i Posht\u00ebm",
    "gn:population":0,
    "gn:timezone":"Europe/Tirane",
    "iso:country":"AL",
    "name:und_x_variant":[
        "Suk i Posht\u00ebm",
        "Suku i Posht\u00ebm"
    ],
    "wof:name":"Suku i Poshtem",
    "wof:placetype":"locality"
},
  "geometry": {"coordinates":[19.72472,40.77806],"type":"Point"}
}