{
  "type": "Feature",
  "properties": {
    "gn:admin1_code":"44",
    "gn:admin2_code":"14.0",
    "gn:asciiname":"Gradishte",
    "gn:cc2":"AL",
    "gn:country_code":"AL",
    "gn:dem":8,
    "gn:feature_class":"P",
    "gn:feature_code":"PPLA3",
    "gn:name":"Gradisht\u00eb",
    "gn:population":0,
    "gn:timezone":"Europe/Tirane",
    "iso:country":"AL",
    "name:ita_x_preferred":[
        "Gradisht\u00eb"
    ],
    "name:msa_x_preferred":[
        "Gradisht\u00eb"
    ],
    "name:pol_x_preferred":[
        "Gmina Gradisht\u00eb"
    ],
    "name:por_x_preferred":[
        "Gradisht\u00eb"
    ],
    "name:spa_x_preferred":[
        "Gradisht\u00eb"
    ],
    "name:tur_x_preferred":[
        "Gradi\u015fte"
    ],
    "name:und_x_variant":[
        "Qytez\u00eb",
        "Gradishti",
        "Gradiza",
        "Gradi\u0161ta",
        "Gradishta",
        "Gradisht"
    ],
    "name:vie_x_preferred":[
        "Gradisht\u00eb"
    ],
    "name:war_x_preferred":[
        "Gradisht\u00eb"
    ],
    "wof:name":"Gradishte",
    "wof:placetype":"locality"
},
  "geometry": {"coordinates":[19.58583,40.88806],"type":"Point"}
}