{
  "type": "Feature",
  "properties": {
    "gn:admin1_code":"47",
    "gn:asciiname":"Ishefaj",
    "gn:cc2":"AL",
    "gn:country_code":"AL",
    "gn:dem":542,
    "gn:feature_class":"P",
    "gn:feature_code":"PPL",
    "gn:name":"Ishefaj",
    "gn:population":0,
    "gn:timezone":"Europe/Tirane",
    "iso:country":"AL",
    "name:und_x_variant":[
        "Ishefai"
    ],
    "wof:name":"Ishefaj",
    "wof:placetype":"locality"
},
  "geometry": {"coordinates":[20.27167,42.20639],"type":"Point"}
}