{
  "type": "Feature",
  "properties": {
    "gn:admin1_code":"51",
    "gn:asciiname":"Gernec",
    "gn:cc2":"AL",
    "gn:country_code":"AL",
    "gn:dem":288,
    "gn:feature_class":"P",
    "gn:feature_code":"PPL",
    "gn:name":"G\u00ebrnec",
    "gn:population":0,
    "gn:timezone":"Europe/Tirane",
    "iso:country":"AL",
    "name:und_x_variant":[
        "Grenec",
        "Grenez",
        "Dirnec",
        "Grnec",
        "G\u00ebrneci",
        "G\u00ebrnec"
    ],
    "wof:name":"Gernec",
    "wof:placetype":"locality"
},
  "geometry": {"coordinates":[19.66861,40.44389],"type":"Point"}
}