{
  "type": "Feature",
  "properties": {
    "gn:admin1_code":"40",
    "gn:admin2_code":"22.0",
    "gn:asciiname":"Cepan",
    "gn:cc2":"AL",
    "gn:country_code":"AL",
    "gn:dem":817,
    "gn:feature_class":"P",
    "gn:feature_code":"PPLA3",
    "gn:name":"\u00c7epan",
    "gn:population":0,
    "gn:timezone":"Europe/Tirane",
    "iso:country":"AL",
    "name:und_x_variant":[
        "\u00c7epani",
        "\u00c7epan"
    ],
    "wof:name":"Cepan",
    "wof:placetype":"locality"
},
  "geometry": {"coordinates":[20.26056,40.42056],"type":"Point"}
}