{
  "type": "Feature",
  "properties": {
    "gn:admin1_code":"51",
    "gn:asciiname":"Dermish",
    "gn:cc2":"AL",
    "gn:country_code":"AL",
    "gn:dem":80,
    "gn:feature_class":"P",
    "gn:feature_code":"PPL",
    "gn:name":"D\u00ebrmish",
    "gn:population":0,
    "gn:timezone":"Europe/Tirane",
    "iso:country":"AL",
    "name:und_x_variant":[
        "D\u00ebrmishi",
        "D\u00ebrmish"
    ],
    "wof:name":"Dermish",
    "wof:placetype":"locality"
},
  "geometry": {"coordinates":[20.12194,39.84194],"type":"Point"}
}