{
  "type": "Feature",
  "properties": {
    "gn:admin1_code":"43",
    "gn:asciiname":"Serice",
    "gn:cc2":"AL",
    "gn:country_code":"AL",
    "gn:dem":410,
    "gn:feature_class":"P",
    "gn:feature_code":"PPL",
    "gn:name":"Seric\u00eb",
    "gn:population":0,
    "gn:timezone":"Europe/Tirane",
    "iso:country":"AL",
    "name:und_x_variant":[
        "Serica",
        "Servic\u00eb",
        "Seric\u00eb"
    ],
    "wof:name":"Serice",
    "wof:placetype":"locality"
},
  "geometry": {"coordinates":[20.18194,41.18611],"type":"Point"}
}