{
  "type": "Feature",
  "properties": {
    "gn:admin1_code":"49",
    "gn:asciiname":"Kodra e Lajthis",
    "gn:country_code":"AL",
    "gn:dem":795,
    "gn:feature_class":"P",
    "gn:feature_code":"PPL",
    "gn:name":"Kodra e Lajthis",
    "gn:population":0,
    "gn:timezone":"Europe/Tirane",
    "iso:country":"AL",
    "wof:name":"Kodra e Lajthis",
    "wof:placetype":"locality"
},
  "geometry": {"coordinates":[19.50139,42.39222],"type":"Point"}
}