{
  "type": "Feature",
  "properties": {
    "gn:admin1_code":"44",
    "gn:asciiname":"Margellic",
    "gn:cc2":"AL",
    "gn:country_code":"AL",
    "gn:dem":174,
    "gn:feature_class":"P",
    "gn:feature_code":"PPL",
    "gn:name":"Marg\u00eblli\u00e7",
    "gn:population":0,
    "gn:timezone":"Europe/Tirane",
    "iso:country":"AL",
    "name:und_x_variant":[
        "Marglli\u00e7i",
        "Marglli\u00e7",
        "Margli\u010d",
        "Marg\u00ebll\u00eb\u00e7",
        "Marg\u00eblli\u00e7i",
        "Marg\u00eblli\u00e7"
    ],
    "wof:name":"Margellic",
    "wof:placetype":"locality"
},
  "geometry": {"coordinates":[19.66111,40.67194],"type":"Point"}
}