{
  "type": "Feature",
  "properties": {
    "gn:admin1_code":"47",
    "gn:asciiname":"Ferth",
    "gn:country_code":"AL",
    "gn:dem":338,
    "gn:feature_class":"P",
    "gn:feature_code":"PPL",
    "gn:name":"Ferth",
    "gn:population":0,
    "gn:timezone":"Europe/Tirane",
    "iso:country":"AL",
    "wof:name":"Ferth",
    "wof:placetype":"locality"
},
  "geometry": {"coordinates":[20.45361,42.05972],"type":"Point"}
}