{
  "type": "Feature",
  "properties": {
    "gn:admin1_code":"49",
    "gn:asciiname":"Jubice",
    "gn:cc2":"AL",
    "gn:country_code":"AL",
    "gn:dem":22,
    "gn:feature_class":"P",
    "gn:feature_code":"PPL",
    "gn:name":"Jubic\u00eb",
    "gn:population":0,
    "gn:timezone":"Europe/Tirane",
    "iso:country":"AL",
    "name:ceb_x_preferred":[
        "Jubic\u00eb"
    ],
    "name:sqi_x_preferred":[
        "Jubic\u00eb"
    ],
    "name:swe_x_preferred":[
        "Jubic\u00eb"
    ],
    "name:und_x_variant":[
        "Jubica",
        "Jubic\u00eb"
    ],
    "wof:name":"Jubice",
    "wof:placetype":"locality"
},
  "geometry": {"coordinates":[19.38944,42.21861],"type":"Point"}
}