{
  "type": "Feature",
  "properties": {
    "gn:admin1_code":"49",
    "gn:asciiname":"Plet",
    "gn:country_code":"AL",
    "gn:dem":618,
    "gn:feature_class":"P",
    "gn:feature_code":"PPL",
    "gn:name":"Plet",
    "gn:population":0,
    "gn:timezone":"Europe/Tirane",
    "iso:country":"AL",
    "wof:name":"Plet",
    "wof:placetype":"locality"
},
  "geometry": {"coordinates":[19.81167,42.02333],"type":"Point"}
}