{
  "type": "Feature",
  "properties": {
    "gn:country":"AL",
    "gn:fcode":"PPLA3",
    "gn:pop":8282,
    "iso:country":"AL",
    "name:bul_x_preferred":[
        "\u041c\u0430\u043c\u0443\u0440\u0430\u0441"
    ],
    "name:ces_x_preferred":[
        "Mamurras"
    ],
    "name:deu_x_preferred":[
        "Mamurras"
    ],
    "name:eng_x_preferred":[
        "Mamurras"
    ],
    "name:fra_x_preferred":[
        "Mamurras"
    ],
    "name:ita_x_preferred":[
        "Mamurras"
    ],
    "name:lit_x_preferred":[
        "Mamurasas"
    ],
    "name:mkd_x_preferred":[
        "\u041c\u0430\u043c\u0443\u0440\u0430\u0441"
    ],
    "name:nld_x_preferred":[
        "Mamurras"
    ],
    "name:pol_x_preferred":[
        "Mamurras"
    ],
    "name:por_x_preferred":[
        "Mamurras"
    ],
    "name:ron_x_preferred":[
        "Mamurras"
    ],
    "name:rus_x_preferred":[
        "\u041c\u0430\u043c\u0443\u0440\u0440\u0430\u0441"
    ],
    "name:slk_x_preferred":[
        "Mamurras"
    ],
    "name:sqi_x_preferred":[
        "Mamurrasi"
    ],
    "name:tat_x_preferred":[
        "\u041c\u0430\u043c\u0443\u0440\u0440\u0430\u0441"
    ],
    "name:tur_x_preferred":[
        "Mamurras"
    ],
    "name:ukr_x_preferred":[
        "\u041c\u0430\u043c\u0443\u0440\u0440\u0430\u0448"
    ],
    "name:unk_x_variant":[
        "Murrizaj"
    ],
    "name:urd_x_preferred":[
        "\u0645\u0627\u0645\u0648\u0631\u0633\u06cc"
    ],
    "name:vie_x_preferred":[
        "Mamurras"
    ],
    "name:war_x_preferred":[
        "Mamurras"
    ],
    "name:zho_x_preferred":[
        "\u99ac\u7a46\u62c9\u897f"
    ],
    "qs:name":"Mamurras",
    "qs:photos_9r":0,
    "qs:photos_sr":0,
    "qs:pop_sr":"5",
    "wd:wordcount":62,
    "wof:name":"Mamurras",
    "wof:placetype":"locality",
    "wof:population":8282
},
  "geometry": {"coordinates":[19.69222,41.5775],"type":"Point"}
}