{
  "type": "Feature",
  "properties": {
    "gn:admin1_code":"43",
    "gn:asciiname":"Kuterman",
    "gn:cc2":"AL",
    "gn:country_code":"AL",
    "gn:dem":363,
    "gn:feature_class":"P",
    "gn:feature_code":"PPL",
    "gn:name":"Kut\u00ebrman",
    "gn:population":0,
    "gn:timezone":"Europe/Tirane",
    "iso:country":"AL",
    "name:mkd_x_preferred":[
        "\u041a\u0443\u0442\u0440\u043e\u043c\u0430\u043d"
    ],
    "name:und_x_variant":[
        "Cutrman",
        "Katurmani",
        "Kut\u00ebman",
        "Kut\u00ebrmani",
        "Kuturmani",
        "Kut\u00ebrman"
    ],
    "wof:name":"Kuterman",
    "wof:placetype":"locality"
},
  "geometry": {"coordinates":[20.25444,41.23833],"type":"Point"}
}