{
  "type": "Feature",
  "properties": {
    "gn:admin1_code":"44",
    "gn:asciiname":"Bashkim",
    "gn:cc2":"AL",
    "gn:country_code":"AL",
    "gn:dem":31,
    "gn:feature_class":"P",
    "gn:feature_code":"PPL",
    "gn:name":"Bashkim",
    "gn:population":0,
    "gn:timezone":"Europe/Tirane",
    "iso:country":"AL",
    "name:swe_x_preferred":[
        "Bashkim"
    ],
    "name:und_x_variant":[
        "Bashkimi"
    ],
    "wof:name":"Bashkim",
    "wof:placetype":"locality"
},
  "geometry": {"coordinates":[19.63333,40.71667],"type":"Point"}
}