{
  "type": "Feature",
  "properties": {
    "gn:admin1_code":"48",
    "gn:asciiname":"Rreza e Malit",
    "gn:country_code":"AL",
    "gn:dem":7,
    "gn:feature_class":"P",
    "gn:feature_code":"PPL",
    "gn:name":"Rr\u00ebza e Malit",
    "gn:population":0,
    "gn:timezone":"Europe/Tirane",
    "iso:country":"AL",
    "wof:name":"Rreza e Malit",
    "wof:placetype":"locality"
},
  "geometry": {"coordinates":[19.61,41.82389000000001],"type":"Point"}
}