{
  "type": "Feature",
  "properties": {
    "gn:admin1_code":"44",
    "gn:asciiname":"Ferras",
    "gn:cc2":"AL",
    "gn:country_code":"AL",
    "gn:dem":3,
    "gn:feature_class":"P",
    "gn:feature_code":"PPL",
    "gn:name":"Ferras",
    "gn:population":0,
    "gn:timezone":"Europe/Tirane",
    "iso:country":"AL",
    "name:und_x_variant":[
        "Ferasi",
        "Ferrasi",
        "Feras",
        "Ferras"
    ],
    "wof:name":"Ferras",
    "wof:placetype":"locality"
},
  "geometry": {"coordinates":[19.45778,40.64694],"type":"Point"}
}