{
  "type": "Feature",
  "properties": {
    "gn:admin1_code":"44",
    "gn:asciiname":"Ferras",
    "gn:cc2":"AL",
    "gn:country_code":"AL",
    "gn:dem":3,
    "gn:feature_class":"P",
    "gn:feature_code":"PPL",
    "gn:name":"Ferras",
    "gn:population":0,
    "gn:timezone":"Europe/Tirane",
    "iso:country":"AL",
    "name:azb_x_preferred":[
        "\u0641\u0631\u0627\u0633"
    ],
    "name:fas_x_preferred":[
        "\u0641\u0631\u0627\u0633"
    ],
    "name:fra_x_preferred":[
        "Ferras"
    ],
    "name:ita_x_preferred":[
        "Ferras"
    ],
    "name:por_x_preferred":[
        "Ferras"
    ],
    "name:spa_x_preferred":[
        "Ferras"
    ],
    "name:tha_x_preferred":[
        "\u0e40\u0e1f\u0e23\u0e4c\u0e23\u0e32\u0e2a\u0e4c"
    ],
    "name:tur_x_preferred":[
        "Ferras"
    ],
    "name:und_x_variant":[
        "Ferasi",
        "Ferrasi",
        "Feras",
        "Ferras"
    ],
    "name:zho_x_preferred":[
        "\u8d39\u62c9\u65af"
    ],
    "wof:name":"Ferras",
    "wof:placetype":"locality"
},
  "geometry": {"coordinates":[19.45778,40.64694],"type":"Point"}
}