{
  "type": "Feature",
  "properties": {
    "gn:admin1_code":"47",
    "gn:asciiname":"Tejmolle",
    "gn:cc2":"AL",
    "gn:country_code":"AL",
    "gn:dem":1093,
    "gn:feature_class":"P",
    "gn:feature_code":"PPL",
    "gn:name":"Tejmoll\u00eb",
    "gn:population":0,
    "gn:timezone":"Europe/Tirane",
    "iso:country":"AL",
    "name:und_x_variant":[
        "Tejmolla",
        "Tej-Mehalla",
        "Tejmall\u00eb",
        "Tejmalla"
    ],
    "wof:name":"Tejmolle",
    "wof:placetype":"locality"
},
  "geometry": {"coordinates":[20.28333,41.91667],"type":"Point"}
}