{
  "type": "Feature",
  "properties": {
    "gn:admin1_code":"43",
    "gn:asciiname":"Bratiles",
    "gn:country_code":"AL",
    "gn:dem":932,
    "gn:feature_class":"P",
    "gn:feature_code":"PPL",
    "gn:name":"Bratil\u00ebs",
    "gn:population":0,
    "gn:timezone":"Europe/Tirane",
    "iso:country":"AL",
    "wof:name":"Bratiles",
    "wof:placetype":"locality"
},
  "geometry": {"coordinates":[20.40639,40.99639000000001],"type":"Point"}
}