{
  "type": "Feature",
  "properties": {
    "gn:admin1_code":"44",
    "gn:asciiname":"Kadiaj",
    "gn:cc2":"AL",
    "gn:country_code":"AL",
    "gn:dem":9,
    "gn:feature_class":"P",
    "gn:feature_code":"PPL",
    "gn:name":"Kadiaj",
    "gn:population":0,
    "gn:timezone":"Europe/Tirane",
    "iso:country":"AL",
    "name:und_x_variant":[
        "Cazijani",
        "Kadias",
        "Kadijani",
        "Kadijan",
        "Kadijes",
        "Kadiaj"
    ],
    "wof:name":"Kadiaj",
    "wof:placetype":"locality"
},
  "geometry": {"coordinates":[19.71333,40.89306],"type":"Point"}
}