{
  "type": "Feature",
  "properties": {
    "gn:admin1_code":"44",
    "gn:asciiname":"Shulenj",
    "gn:country_code":"AL",
    "gn:dem":3,
    "gn:feature_class":"P",
    "gn:feature_code":"PPL",
    "gn:name":"Shulenj",
    "gn:population":0,
    "gn:timezone":"Europe/Tirane",
    "iso:country":"AL",
    "wof:name":"Shulenj",
    "wof:placetype":"locality"
},
  "geometry": {"coordinates":[19.53611,40.84],"type":"Point"}
}