{
  "type": "Feature",
  "properties": {
    "gn:admin1_code":"49",
    "gn:asciiname":"Kir",
    "gn:cc2":"AL",
    "gn:country_code":"AL",
    "gn:dem":892,
    "gn:feature_class":"P",
    "gn:feature_code":"PPL",
    "gn:name":"Kir",
    "gn:population":0,
    "gn:timezone":"Europe/Tirane",
    "iso:country":"AL",
    "name:und_x_variant":[
        "Kiri",
        "Kir"
    ],
    "wof:name":"Kir",
    "wof:placetype":"locality"
},
  "geometry": {"coordinates":[19.72111,42.24111],"type":"Point"}
}