{
  "type": "Feature",
  "properties": {
    "gn:admin1_code":"44",
    "gn:asciiname":"Seman",
    "gn:cc2":"AL",
    "gn:country_code":"AL",
    "gn:dem":4,
    "gn:feature_class":"P",
    "gn:feature_code":"PPL",
    "gn:name":"Seman",
    "gn:population":0,
    "gn:timezone":"Europe/Tirane",
    "iso:country":"AL",
    "name:ceb_x_preferred":[
        "Seman"
    ],
    "name:ces_x_preferred":[
        "Seman"
    ],
    "name:deu_x_preferred":[
        "Seman"
    ],
    "name:spa_x_preferred":[
        "Seman"
    ],
    "name:swe_x_preferred":[
        "Seman"
    ],
    "name:ukr_x_preferred":[
        "\u0421\u0435\u043c\u0430\u043d"
    ],
    "name:und_x_variant":[
        "Semani"
    ],
    "wof:name":"Seman",
    "wof:placetype":"locality"
},
  "geometry": {"coordinates":[19.47139,40.77944],"type":"Point"}
}