{
  "type": "Feature",
  "properties": {
    "gn:admin1_code":"51",
    "gn:asciiname":"Ftere",
    "gn:cc2":"AL",
    "gn:country_code":"AL",
    "gn:dem":375,
    "gn:feature_class":"P",
    "gn:feature_code":"PPL",
    "gn:name":"Fter\u00eb",
    "gn:population":0,
    "gn:timezone":"Europe/Tirane",
    "iso:country":"AL",
    "name:ceb_x_preferred":[
        "Fter\u00eb"
    ],
    "name:deu_x_preferred":[
        "Fterra"
    ],
    "name:mkd_x_preferred":[
        "\u0424\u0442\u0435\u0440\u0430"
    ],
    "name:sqi_x_preferred":[
        "Fterra"
    ],
    "name:swe_x_preferred":[
        "Fter\u00eb"
    ],
    "name:tur_x_preferred":[
        "\u0130fteran"
    ],
    "name:und_x_variant":[
        "Fterr\u00eb",
        "Milt Itan i Nestont",
        "Fterra",
        "Ftera",
        "Fter\u00eb"
    ],
    "wof:name":"Ftere",
    "wof:placetype":"locality"
},
  "geometry": {"coordinates":[19.89361,40.11444],"type":"Point"}
}