{
  "type": "Feature",
  "properties": {
    "gn:admin1_code":"45",
    "gn:asciiname":"Katundishte",
    "gn:cc2":"AL",
    "gn:country_code":"AL",
    "gn:dem":541,
    "gn:feature_class":"P",
    "gn:feature_code":"PPL",
    "gn:name":"Katundisht\u00eb",
    "gn:population":0,
    "gn:timezone":"Europe/Tirane",
    "iso:country":"AL",
    "name:und_x_variant":[
        "Katundisht",
        "Katundishta",
        "Kodzanishti",
        "Katundisht\u00eb"
    ],
    "wof:name":"Katundishte",
    "wof:placetype":"locality"
},
  "geometry": {"coordinates":[20.15361,40.33167],"type":"Point"}
}