{
  "type": "Feature",
  "properties": {
    "gn:admin1_code":"46",
    "gn:asciiname":"Mazreke-Opar",
    "gn:cc2":"AL",
    "gn:country_code":"AL",
    "gn:dem":1107,
    "gn:feature_class":"P",
    "gn:feature_code":"PPL",
    "gn:name":"Mazrek\u00eb-Opar",
    "gn:population":0,
    "gn:timezone":"Europe/Tirane",
    "iso:country":"AL",
    "name:und_x_variant":[
        "Mazrek\u00eb",
        "Misras-Mazreka",
        "Misiras-Mazrek\u00eb",
        "Misras-Mazrek\u00eb",
        "Mazrek\u00eb-Opar"
    ],
    "wof:name":"Mazreke-Opar",
    "wof:placetype":"locality"
},
  "geometry": {"coordinates":[20.42167,40.61028],"type":"Point"}
}