{
  "type": "Feature",
  "properties": {
    "gn:admin1_code":"40",
    "gn:asciiname":"Nishice",
    "gn:cc2":"AL",
    "gn:country_code":"AL",
    "gn:dem":846,
    "gn:feature_class":"P",
    "gn:feature_code":"PPL",
    "gn:name":"Nishic\u00eb",
    "gn:population":0,
    "gn:timezone":"Europe/Tirane",
    "iso:country":"AL",
    "name:und_x_variant":[
        "Niscizza",
        "Nivica",
        "Nikit",
        "Nishica",
        "Nishic\u00eb"
    ],
    "wof:name":"Nishice",
    "wof:placetype":"locality"
},
  "geometry": {"coordinates":[20.18333,40.46861],"type":"Point"}
}