{
  "type": "Feature",
  "properties": {
    "gn:admin1_code":"48",
    "gn:asciiname":"Tharr",
    "gn:cc2":"AL",
    "gn:country_code":"AL",
    "gn:dem":637,
    "gn:feature_class":"P",
    "gn:feature_code":"PPL",
    "gn:name":"Tharr",
    "gn:population":0,
    "gn:timezone":"Europe/Tirane",
    "iso:country":"AL",
    "name:und_x_variant":[
        "Tharri",
        "Tharr"
    ],
    "wof:name":"Tharr",
    "wof:placetype":"locality"
},
  "geometry": {"coordinates":[20.05,41.75],"type":"Point"}
}