{
  "type": "Feature",
  "properties": {
    "gn:admin1_code":"51",
    "gn:asciiname":"Grave",
    "gn:cc2":"AL",
    "gn:country_code":"AL",
    "gn:dem":165,
    "gn:feature_class":"P",
    "gn:feature_code":"PPL",
    "gn:name":"Grav\u00eb",
    "gn:population":0,
    "gn:timezone":"Europe/Tirane",
    "iso:country":"AL",
    "name:und_x_variant":[
        "Grava",
        "Grav\u00eb"
    ],
    "wof:name":"Grave",
    "wof:placetype":"locality"
},
  "geometry": {"coordinates":[20.16972,39.78722],"type":"Point"}
}