{
  "type": "Feature",
  "properties": {
    "gn:admin1_code":"49",
    "gn:asciiname":"Tabak Ajasme",
    "gn:country_code":"AL",
    "gn:dem":10,
    "gn:feature_class":"P",
    "gn:feature_code":"PPL",
    "gn:name":"Tabak Ajasm\u00eb",
    "gn:population":0,
    "gn:timezone":"Europe/Tirane",
    "iso:country":"AL",
    "wof:name":"Tabak Ajasme",
    "wof:placetype":"locality"
},
  "geometry": {"coordinates":[19.50667,42.04778],"type":"Point"}
}