{
  "type": "Feature",
  "properties": {
    "gn:admin1_code":"42",
    "gn:asciiname":"Gjuze",
    "gn:cc2":"AL",
    "gn:country_code":"AL",
    "gn:dem":171,
    "gn:feature_class":"P",
    "gn:feature_code":"PPL",
    "gn:name":"Gjuz\u00eb",
    "gn:population":0,
    "gn:timezone":"Europe/Tirane",
    "iso:country":"AL",
    "name:und_x_variant":[
        "Guzaj",
        "Gjuz",
        "Guza",
        "Gusa",
        "Gjuz\u00eb"
    ],
    "wof:name":"Gjuze",
    "wof:placetype":"locality"
},
  "geometry": {"coordinates":[19.56306,41.26944],"type":"Point"}
}