{
  "type": "Feature",
  "properties": {
    "gn:admin1_code":"44",
    "gn:asciiname":"Canakaj",
    "gn:cc2":"AL",
    "gn:country_code":"AL",
    "gn:dem":106,
    "gn:feature_class":"P",
    "gn:feature_code":"PPL",
    "gn:name":"\u00c7anakaj",
    "gn:population":0,
    "gn:timezone":"Europe/Tirane",
    "iso:country":"AL",
    "name:und_x_variant":[
        "Xhanakaj",
        "D\u017eanakaj",
        "\u00c7anaskaj",
        "\u00c7anakaj"
    ],
    "wof:name":"Canakaj",
    "wof:placetype":"locality"
},
  "geometry": {"coordinates":[19.77806,40.97861],"type":"Point"}
}