{
  "type": "Feature",
  "properties": {
    "gn:admin1_code":"44",
    "gn:asciiname":"Fieri i Ri",
    "gn:cc2":"AL",
    "gn:country_code":"AL",
    "gn:dem":13,
    "gn:feature_class":"P",
    "gn:feature_code":"PPL",
    "gn:name":"Fieri i Ri",
    "gn:population":0,
    "gn:timezone":"Europe/Tirane",
    "iso:country":"AL",
    "name:und_x_variant":[
        "Fier i Ri",
        "Fier Veis Bej",
        "Fi\u00ebrze",
        "Fjeri Veis Beut",
        "Fierza",
        "Fieri i Ri"
    ],
    "wof:name":"Fieri i Ri",
    "wof:placetype":"locality"
},
  "geometry": {"coordinates":[19.70639,40.85722],"type":"Point"}
}