{
  "type": "Feature",
  "properties": {
    "gn:admin1_code":"41",
    "gn:admin2_code":"2.0",
    "gn:asciiname":"Selishte",
    "gn:cc2":"AL",
    "gn:country_code":"AL",
    "gn:dem":743,
    "gn:feature_class":"P",
    "gn:feature_code":"PPLA3",
    "gn:name":"Selisht\u00eb",
    "gn:population":0,
    "gn:timezone":"Europe/Tirane",
    "iso:country":"AL",
    "name:mkd_x_preferred":[
        "\u0421\u0435\u043b\u0438\u0448\u0442\u0435"
    ],
    "name:und_x_variant":[
        "Selishta",
        "Selishta e Poshtme",
        "Selisht\u00eb"
    ],
    "wof:name":"Selishte",
    "wof:placetype":"locality"
},
  "geometry": {"coordinates":[20.27917,41.6275],"type":"Point"}
}