{
  "type": "Feature",
  "properties": {
    "gn:admin1_code":"44",
    "gn:asciiname":"Allprendaj",
    "gn:cc2":"AL",
    "gn:country_code":"AL",
    "gn:dem":87,
    "gn:feature_class":"P",
    "gn:feature_code":"PPL",
    "gn:name":"Allprendaj",
    "gn:population":0,
    "gn:timezone":"Europe/Tirane",
    "iso:country":"AL",
    "name:und_x_variant":[
        "Prende Sip\u00ebrme",
        "Allprendaj-Lushnje",
        "Hallprendaj-Lushnje",
        "Allprendaj Lushnja",
        "Halprende- e Lushnj\u00ebs",
        "Allprenaj",
        "Allprendja",
        "Allprendaj"
    ],
    "wof:name":"Allprendaj",
    "wof:placetype":"locality"
},
  "geometry": {"coordinates":[19.72639,40.97],"type":"Point"}
}