{
  "type": "Feature",
  "properties": {
    "gn:admin1_code":"40",
    "gn:asciiname":"Sheq",
    "gn:cc2":"AL",
    "gn:country_code":"AL",
    "gn:dem":22,
    "gn:feature_class":"P",
    "gn:feature_code":"PPL",
    "gn:name":"Sheq",
    "gn:population":0,
    "gn:timezone":"Europe/Tirane",
    "iso:country":"AL",
    "name:und_x_variant":[
        "Sheqi-Gajta",
        "Sheq-Gajda",
        "Sheq i Madhe",
        "Sheqigajt",
        "Sheq-Gajd\u00eb",
        "Sheq"
    ],
    "wof:name":"Sheq",
    "wof:placetype":"locality"
},
  "geometry": {"coordinates":[19.82833,40.83889],"type":"Point"}
}