{
  "type": "Feature",
  "properties": {
    "gn:country":"AL",
    "gn:fcode":"PPL",
    "gn:population":5,
    "iso:country":"AL",
    "name:eng_x_preferred":[
        "Biz\u00eb"
    ],
    "name:ita_x_preferred":[
        "Biz\u00eb"
    ],
    "name:nld_x_preferred":[
        "Biz\u00eb"
    ],
    "name:sqi_x_preferred":[
        "Biz\u00eb"
    ],
    "name:und_x_variant":[
        "Biza"
    ],
    "qs:name":"Biz\u00eb",
    "qs:photos_9r":0,
    "qs:photos_sr":0,
    "qs:pop_sr":"1",
    "wd:wordcount":51,
    "wof:name":"Biz\u00eb",
    "wof:placetype":"locality",
    "wof:population":5
},
  "geometry": {"coordinates":[20.19806,41.34083],"type":"Point"}
}