{
  "type": "Feature",
  "properties": {
    "gn:admin1_code":"51",
    "gn:asciiname":"Krongj",
    "gn:cc2":"AL",
    "gn:country_code":"AL",
    "gn:dem":297,
    "gn:feature_class":"P",
    "gn:feature_code":"PPL",
    "gn:name":"Krongj",
    "gn:population":0,
    "gn:timezone":"Europe/Tirane",
    "iso:country":"AL",
    "name:und_x_variant":[
        "Krongjia",
        "Kronji",
        "Krongja",
        "Krongje",
        "Cronghi",
        "Crogni",
        "Krongji",
        "Kronjgj",
        "Krongj"
    ],
    "wof:name":"Krongj",
    "wof:placetype":"locality"
},
  "geometry": {"coordinates":[20.17333,39.91306],"type":"Point"}
}