{
  "type": "Feature",
  "properties": {
    "gn:admin1_code":"40",
    "gn:asciiname":"Palec",
    "gn:cc2":"AL",
    "gn:country_code":"AL",
    "gn:dem":376,
    "gn:feature_class":"P",
    "gn:feature_code":"PPL",
    "gn:name":"Palec",
    "gn:population":0,
    "gn:timezone":"Europe/Tirane",
    "iso:country":"AL",
    "name:und_x_variant":[
        "Paleci",
        "Palec"
    ],
    "wof:name":"Palec",
    "wof:placetype":"locality"
},
  "geometry": {"coordinates":[20.07972,40.54111],"type":"Point"}
}