{
  "type": "Feature",
  "properties": {
    "gn:admin1_code":"43",
    "gn:asciiname":"Konaj",
    "gn:cc2":"AL",
    "gn:country_code":"AL",
    "gn:dem":392,
    "gn:feature_class":"P",
    "gn:feature_code":"PPL",
    "gn:name":"Konaj",
    "gn:population":0,
    "gn:timezone":"Europe/Tirane",
    "iso:country":"AL",
    "name:und_x_variant":[
        "Konit"
    ],
    "wof:name":"Konaj",
    "wof:placetype":"locality"
},
  "geometry": {"coordinates":[19.77444,41.07694],"type":"Point"}
}