{
  "type": "Feature",
  "properties": {
    "gn:country":"AL",
    "gn:fcode":"PPL",
    "gn:population":5,
    "iso:country":"AL",
    "name:deu_x_preferred":[
        "Stojka"
    ],
    "name:fra_x_preferred":[
        "St\u00f3jka"
    ],
    "name:pol_x_preferred":[
        "St\u00f3jka"
    ],
    "qs:name":"Stojka",
    "qs:photos_9r":0,
    "qs:photos_sr":0,
    "qs:pop_sr":"1",
    "wd:wordcount":48,
    "wof:name":"Stojka",
    "wof:placetype":"locality",
    "wof:population":5
},
  "geometry": {"coordinates":[20.39361,41.41917],"type":"Point"}
}