{
  "type": "Feature",
  "properties": {
    "gn:admin1_code":"45",
    "gn:asciiname":"Cacaj",
    "gn:country_code":"AL",
    "gn:dem":408,
    "gn:feature_class":"P",
    "gn:feature_code":"PPL",
    "gn:name":"Cacaj",
    "gn:population":0,
    "gn:timezone":"Europe/Tirane",
    "iso:country":"AL",
    "wof:name":"Cacaj",
    "wof:placetype":"locality"
},
  "geometry": {"coordinates":[19.97333,40.3875],"type":"Point"}
}