{
  "type": "Feature",
  "properties": {
    "gn:admin1_code":"43",
    "gn:asciiname":"Bujqes",
    "gn:cc2":"AL",
    "gn:country_code":"AL",
    "gn:dem":87,
    "gn:feature_class":"P",
    "gn:feature_code":"PPL",
    "gn:name":"Bujq\u00ebs",
    "gn:population":0,
    "gn:timezone":"Europe/Tirane",
    "iso:country":"AL",
    "name:und_x_variant":[
        "Buq\u00ebz",
        "Bugj\u00ebsi",
        "Buq\u00ebsi",
        "Bugj\u00ebzi",
        "Buq\u00ebs",
        "Bujqez",
        "Bujq\u00ebsi",
        "Bujq\u00ebs"
    ],
    "wof:name":"Bujqes",
    "wof:placetype":"locality"
},
  "geometry": {"coordinates":[20.0475,41.07611],"type":"Point"}
}