{
  "type": "Feature",
  "properties": {
    "gn:admin1_code":"43",
    "gn:asciiname":"Lleshaj",
    "gn:cc2":"AL",
    "gn:country_code":"AL",
    "gn:dem":841,
    "gn:feature_class":"P",
    "gn:feature_code":"PPL",
    "gn:name":"Lleshaj",
    "gn:population":0,
    "gn:timezone":"Europe/Tirane",
    "iso:country":"AL",
    "name:und_x_variant":[
        "Ano Poro\u00e7an",
        "Poro\u00e7ani iziu",
        "Poro\u00e7an i Sip\u00ebrm",
        "Porciani-sipenme",
        "Poro\u00e7ani i Sip\u00ebrm",
        "Poro\u00e7iani Sip\u00ebrme",
        "Lleshaj"
    ],
    "wof:name":"Lleshaj",
    "wof:placetype":"locality"
},
  "geometry": {"coordinates":[20.31583,40.93139],"type":"Point"}
}