{
  "type": "Feature",
  "properties": {
    "gn:admin1_code":"51",
    "gn:asciiname":"Kallarat",
    "gn:cc2":"AL",
    "gn:country_code":"AL",
    "gn:dem":270,
    "gn:feature_class":"P",
    "gn:feature_code":"PPL",
    "gn:name":"Kallarat",
    "gn:population":0,
    "gn:timezone":"Europe/Tirane",
    "iso:country":"AL",
    "name:und_x_variant":[
        "Kaljarat",
        "Kallarati",
        "Kalarat",
        "Kallarat"
    ],
    "wof:name":"Kallarat",
    "wof:placetype":"locality"
},
  "geometry": {"coordinates":[19.74111,40.20667],"type":"Point"}
}