{
  "type": "Feature",
  "properties": {
    "gn:admin1_code":"50",
    "gn:asciiname":"Germej",
    "gn:cc2":"AL",
    "gn:country_code":"AL",
    "gn:dem":60,
    "gn:feature_class":"P",
    "gn:feature_code":"PPL",
    "gn:name":"G\u00ebrmej",
    "gn:population":0,
    "gn:timezone":"Europe/Tirane",
    "iso:country":"AL",
    "name:und_x_variant":[
        "Grmaj",
        "Germ\u00ebnji",
        "G\u00ebrmenj",
        "G\u00ebrmaj",
        "G\u00ebrmej"
    ],
    "wof:name":"Germej",
    "wof:placetype":"locality"
},
  "geometry": {"coordinates":[19.63083,41.13889],"type":"Point"}
}