{
  "type": "Feature",
  "properties": {
    "gn:admin1_code":"43",
    "gn:asciiname":"Mexixe",
    "gn:cc2":"AL",
    "gn:country_code":"AL",
    "gn:dem":859,
    "gn:feature_class":"P",
    "gn:feature_code":"PPL",
    "gn:name":"M\u00ebxix\u00eb",
    "gn:population":0,
    "gn:timezone":"Europe/Tirane",
    "iso:country":"AL",
    "name:und_x_variant":[
        "M\u00ebxixa"
    ],
    "wof:name":"Mexixe",
    "wof:placetype":"locality"
},
  "geometry": {"coordinates":[20.25,41.28333],"type":"Point"}
}