{
  "type": "Feature",
  "properties": {
    "gn:admin1_code":"47",
    "gn:asciiname":"Gjonpapaj",
    "gn:country_code":"AL",
    "gn:dem":595,
    "gn:feature_class":"P",
    "gn:feature_code":"PPL",
    "gn:name":"Gjonpapaj",
    "gn:population":0,
    "gn:timezone":"Europe/Tirane",
    "iso:country":"AL",
    "wof:name":"Gjonpapaj",
    "wof:placetype":"locality"
},
  "geometry": {"coordinates":[20.17694,42.25833],"type":"Point"}
}