{
  "type": "Feature",
  "properties": {
    "gn:admin1_code":"51",
    "gn:asciiname":"Millone",
    "gn:cc2":"AL",
    "gn:country_code":"AL",
    "gn:dem":299,
    "gn:feature_class":"P",
    "gn:feature_code":"PPL",
    "gn:name":"Millon\u00eb",
    "gn:population":0,
    "gn:timezone":"Europe/Tirane",
    "iso:country":"AL",
    "name:und_x_variant":[
        "Milona",
        "Miljona"
    ],
    "wof:name":"Millone",
    "wof:placetype":"locality"
},
  "geometry": {"coordinates":[19.56306,40.39833],"type":"Point"}
}