{
  "type": "Feature",
  "properties": {
    "gn:admin1_code":"41",
    "gn:asciiname":"Ushtelence",
    "gn:cc2":"AL",
    "gn:country_code":"AL",
    "gn:dem":525,
    "gn:feature_class":"P",
    "gn:feature_code":"PPL",
    "gn:name":"Ushtelenc\u00eb",
    "gn:population":0,
    "gn:timezone":"Europe/Tirane",
    "iso:country":"AL",
    "name:und_x_variant":[
        "Ushtelenz\u00eb",
        "Ushtelenza",
        "Ushtelende",
        "Ushtelenca",
        "Ushtelenc\u00eb"
    ],
    "wof:name":"Ushtelence",
    "wof:placetype":"locality"
},
  "geometry": {"coordinates":[20.39167,41.68],"type":"Point"}
}