{
  "type": "Feature",
  "properties": {
    "gn:admin1_code":"44",
    "gn:asciiname":"Fushe",
    "gn:cc2":"AL",
    "gn:country_code":"AL",
    "gn:dem":1,
    "gn:feature_class":"P",
    "gn:feature_code":"PPL",
    "gn:name":"Fush\u00eb",
    "gn:population":0,
    "gn:timezone":"Europe/Tirane",
    "iso:country":"AL",
    "name:und_x_variant":[
        "Sh\u00ebnpjet\u00ebr",
        "Fusha",
        "Sh\u00ebnpjetri",
        "Shenpjetra",
        "Sh\u00ebnpjet\u00ebra",
        "Fush\u00eb"
    ],
    "wof:name":"Fushe",
    "wof:placetype":"locality"
},
  "geometry": {"coordinates":[19.44528,40.74861],"type":"Point"}
}