{
  "type": "Feature",
  "properties": {
    "gn:admin1_code":"44",
    "gn:asciiname":"Hajdaraj",
    "gn:cc2":"AL",
    "gn:country_code":"AL",
    "gn:dem":151,
    "gn:feature_class":"P",
    "gn:feature_code":"PPL",
    "gn:name":"Hajdaraj",
    "gn:population":0,
    "gn:timezone":"Europe/Tirane",
    "iso:country":"AL",
    "name:sqi_x_preferred":[
        "Hajdaraj"
    ],
    "name:und_x_variant":[
        "Bregas",
        "Hajdaraj-Lushnja",
        "Hajdaran-Lushnje",
        "Hajdarani Lushnj\u00eb"
    ],
    "wof:name":"Hajdaraj",
    "wof:placetype":"locality"
},
  "geometry": {"coordinates":[19.72861,40.96222],"type":"Point"}
}