{
  "type": "Feature",
  "properties": {
    "gn:admin1_code":"44",
    "gn:asciiname":"Peshtan-Bregas",
    "gn:cc2":"AL",
    "gn:country_code":"AL",
    "gn:dem":206,
    "gn:feature_class":"P",
    "gn:feature_code":"PPL",
    "gn:name":"Peshtan-Bregas",
    "gn:population":0,
    "gn:timezone":"Europe/Tirane",
    "iso:country":"AL",
    "name:und_x_variant":[
        "Bregas",
        "Bregasi",
        "Peshtan-Bregas"
    ],
    "wof:name":"Peshtan-Bregas",
    "wof:placetype":"locality"
},
  "geometry": {"coordinates":[19.53611,40.65611],"type":"Point"}
}