{
  "type": "Feature",
  "properties": {
    "gn:admin1_code":"49",
    "gn:asciiname":"Xhaferraj",
    "gn:cc2":"AL",
    "gn:country_code":"AL",
    "gn:dem":42,
    "gn:feature_class":"P",
    "gn:feature_code":"PPL",
    "gn:name":"Xhaferraj",
    "gn:population":0,
    "gn:timezone":"Europe/Tirane",
    "iso:country":"AL",
    "name:und_x_variant":[
        "Gjaferaj",
        "Oblik\u00eb",
        "Oblika Cafret",
        "Oblika",
        "Oblik\u00eb e Cafret",
        "Xhaferraj"
    ],
    "wof:name":"Xhaferraj",
    "wof:placetype":"locality"
},
  "geometry": {"coordinates":[19.44917,42.02889],"type":"Point"}
}