{
  "type": "Feature",
  "properties": {
    "gn:admin1_code":"49",
    "gn:asciiname":"Dajc",
    "gn:cc2":"AL",
    "gn:country_code":"AL",
    "gn:dem":843,
    "gn:feature_class":"P",
    "gn:feature_code":"PPL",
    "gn:name":"Daj\u00e7",
    "gn:population":0,
    "gn:timezone":"Europe/Tirane",
    "iso:country":"AL",
    "name:und_x_variant":[
        "Daj\u00e7a",
        "Daj\u00e7\u00eb",
        "Daj\u00e7"
    ],
    "wof:name":"Dajc",
    "wof:placetype":"locality"
},
  "geometry": {"coordinates":[19.65361,42.19528],"type":"Point"}
}