{
  "type": "Feature",
  "properties": {
    "gn:admin1_code":"40",
    "gn:asciiname":"Straficke",
    "gn:cc2":"AL",
    "gn:country_code":"AL",
    "gn:dem":835,
    "gn:feature_class":"P",
    "gn:feature_code":"PPL",
    "gn:name":"Strafick\u00eb",
    "gn:population":0,
    "gn:timezone":"Europe/Tirane",
    "iso:country":"AL",
    "name:und_x_variant":[
        "Straficka",
        "Strafic\u00eb",
        "Strafiska",
        "Strafick\u00eb"
    ],
    "wof:name":"Straficke",
    "wof:placetype":"locality"
},
  "geometry": {"coordinates":[20.30472,40.64167],"type":"Point"}
}