{
  "type": "Feature",
  "properties": {
    "gn:admin1_code":"42",
    "gn:asciiname":"Mazha e Madhe",
    "gn:cc2":"AL",
    "gn:country_code":"AL",
    "gn:dem":129,
    "gn:feature_class":"P",
    "gn:feature_code":"PPL",
    "gn:name":"Mazha e Madhe",
    "gn:population":0,
    "gn:timezone":"Europe/Tirane",
    "iso:country":"AL",
    "name:und_x_variant":[
        "Mazh\u00eb e Madhe",
        "Mazhaj e Madh\u00eb",
        "Mazhj\u00eb-e madhe",
        "Mazj e Male",
        "Mazhaj i Madh",
        "Mazha e Madhe"
    ],
    "wof:name":"Mazha e Madhe",
    "wof:placetype":"locality"
},
  "geometry": {"coordinates":[19.63417,41.47528],"type":"Point"}
}