{
  "type": "Feature",
  "properties": {
    "gn:admin1_code":"45",
    "gn:asciiname":"Kordhe",
    "gn:cc2":"AL",
    "gn:country_code":"AL",
    "gn:dem":105,
    "gn:feature_class":"P",
    "gn:feature_code":"PPL",
    "gn:name":"Kordh\u00eb",
    "gn:population":0,
    "gn:timezone":"Europe/Tirane",
    "iso:country":"AL",
    "name:und_x_variant":[
        "Kordha",
        "Kordh\u00eb"
    ],
    "wof:name":"Kordhe",
    "wof:placetype":"locality"
},
  "geometry": {"coordinates":[19.94,40.34306],"type":"Point"}
}