{
  "type": "Feature",
  "properties": {
    "iso:country":"AL",
    "name:bul_x_preferred":[
        "\u041c\u0430\u043c\u0443\u0440\u0430\u0441"
    ],
    "name:ces_x_preferred":[
        "Mamurras"
    ],
    "name:deu_x_preferred":[
        "Mamurras"
    ],
    "name:eng_x_preferred":[
        "Mamurras"
    ],
    "name:fra_x_preferred":[
        "Mamurras"
    ],
    "name:hbs_x_preferred":[
        "Op\u0161tina Streje\u015fti"
    ],
    "name:ita_x_preferred":[
        "Streje\u0219ti"
    ],
    "name:lit_x_preferred":[
        "Mamurasas"
    ],
    "name:mkd_x_preferred":[
        "\u041c\u0430\u043c\u0443\u0440\u0430\u0441"
    ],
    "name:msa_x_preferred":[
        "Streje\u015fti"
    ],
    "name:nld_x_preferred":[
        "Streje\u0219ti"
    ],
    "name:nld_x_variant":[
        "Mamurras"
    ],
    "name:pol_x_preferred":[
        "Mamurras"
    ],
    "name:por_x_preferred":[
        "Streje\u015fti"
    ],
    "name:ron_x_preferred":[
        "Comuna Streje\u0219ti"
    ],
    "name:ron_x_variant":[
        "Mamurras"
    ],
    "name:rus_x_preferred":[
        "\u041c\u0430\u043c\u0443\u0440\u0440\u0430\u0448"
    ],
    "name:slk_x_preferred":[
        "Mamurras"
    ],
    "name:sqi_x_preferred":[
        "Mamurrasi"
    ],
    "name:tat_x_preferred":[
        "\u041c\u0430\u043c\u0443\u0440\u0440\u0430\u0441"
    ],
    "name:tur_x_preferred":[
        "Mamurras"
    ],
    "name:ukr_x_preferred":[
        "\u0421\u0442\u0440\u0435\u0436\u0435\u0448\u0442\u044c"
    ],
    "name:urd_x_preferred":[
        "\u0645\u0627\u0645\u0648\u0631\u0633\u06cc"
    ],
    "name:vie_x_preferred":[
        "Strejesti"
    ],
    "name:vol_x_preferred":[
        "Streje\u015fti"
    ],
    "name:war_x_preferred":[
        "Mamurras"
    ],
    "name:zho_x_preferred":[
        "\u99ac\u7a46\u62c9\u897f"
    ],
    "qs:gn_pop":0,
    "qs:name":"Mamuras",
    "qs:name_adm0":"Shqip\u00ebri",
    "qs:name_adm1":"Lezhe",
    "qs:photos":7,
    "qs:photos_1k":1,
    "qs:photos_9k":1,
    "qs:photos_9r":1,
    "qs:photos_all":7,
    "qs:photos_sr":1,
    "qs:placetype":"Town",
    "qs:pop_sr":"0",
    "qs:woe_adm0":23424742,
    "wof:name":"Mamuras",
    "wof:placetype":"locality"
},
  "geometry": {"coordinates":[19.6669,41.562545],"type":"Point"}
}