{
  "type": "Feature",
  "properties": {
    "gn:admin1_code":"44",
    "gn:admin2_code":"14.0",
    "gn:asciiname":"Dushk",
    "gn:cc2":"AL",
    "gn:country_code":"AL",
    "gn:dem":50,
    "gn:feature_class":"P",
    "gn:feature_code":"PPLA3",
    "gn:name":"Dushk",
    "gn:population":0,
    "gn:timezone":"Europe/Tirane",
    "iso:country":"AL",
    "name:ita_x_preferred":[
        "Dushk"
    ],
    "name:msa_x_preferred":[
        "Dushk"
    ],
    "name:pol_x_preferred":[
        "Gmina Dushk"
    ],
    "name:por_x_preferred":[
        "Dushk"
    ],
    "name:spa_x_preferred":[
        "Dushk"
    ],
    "name:tur_x_preferred":[
        "Dushk"
    ],
    "name:und_x_variant":[
        "Dushku",
        "Dushk"
    ],
    "name:vie_x_preferred":[
        "Dushk"
    ],
    "name:war_x_preferred":[
        "Dushk"
    ],
    "wof:name":"Dushk",
    "wof:placetype":"locality"
},
  "geometry": {"coordinates":[19.75722,40.72667],"type":"Point"}
}