{
  "type": "Feature",
  "properties": {
    "gn:admin1_code":"49",
    "gn:asciiname":"Grizhe",
    "gn:cc2":"AL",
    "gn:country_code":"AL",
    "gn:dem":472,
    "gn:feature_class":"P",
    "gn:feature_code":"PPL",
    "gn:name":"Grizh\u00eb",
    "gn:population":0,
    "gn:timezone":"Europe/Tirane",
    "iso:country":"AL",
    "name:und_x_variant":[
        "Grizaj",
        "Grishaj",
        "Grizha"
    ],
    "wof:name":"Grizhe",
    "wof:placetype":"locality"
},
  "geometry": {"coordinates":[19.46667,42.26667],"type":"Point"}
}