{
  "type": "Feature",
  "properties": {
    "gn:admin1_code":"44",
    "gn:asciiname":"Selimaj",
    "gn:cc2":"AL",
    "gn:country_code":"AL",
    "gn:dem":433,
    "gn:feature_class":"P",
    "gn:feature_code":"PPL",
    "gn:name":"Selimaj",
    "gn:population":0,
    "gn:timezone":"Europe/Tirane",
    "iso:country":"AL",
    "name:und_x_variant":[
        "Cerila-Toska",
        "Tosk",
        "\u00c7erill\u00eb",
        "Tosk\u00eb",
        "Cerila-Toske",
        "Ceril\u00eb-Tosk\u00eb",
        "Selimaj"
    ],
    "wof:name":"Selimaj",
    "wof:placetype":"locality"
},
  "geometry": {"coordinates":[19.78861,40.61361],"type":"Point"}
}