{
  "type": "Feature",
  "properties": {
    "gn:admin1_code":"50",
    "gn:asciiname":"Cacabeze",
    "gn:cc2":"AL",
    "gn:country_code":"AL",
    "gn:dem":556,
    "gn:feature_class":"P",
    "gn:feature_code":"PPL",
    "gn:name":"Cacabez\u00eb",
    "gn:population":0,
    "gn:timezone":"Europe/Tirane",
    "iso:country":"AL",
    "name:und_x_variant":[
        "Carabez\u00eb",
        "Cacabeza",
        "Cacabez\u00eb"
    ],
    "wof:name":"Cacabeze",
    "wof:placetype":"locality"
},
  "geometry": {"coordinates":[19.86111,41.14861],"type":"Point"}
}