{
  "type": "Feature",
  "properties": {
    "gn:admin1_code":"44",
    "gn:asciiname":"Shpataj",
    "gn:country_code":"AL",
    "gn:dem":94,
    "gn:feature_class":"P",
    "gn:feature_code":"PPL",
    "gn:name":"Shpataj",
    "gn:population":0,
    "gn:timezone":"Europe/Tirane",
    "iso:country":"AL",
    "wof:name":"Shpataj",
    "wof:placetype":"locality"
},
  "geometry": {"coordinates":[19.65111,40.68472],"type":"Point"}
}