{
  "type": "Feature",
  "properties": {
    "gn:admin1_code":"41",
    "gn:asciiname":"Bresti i Poshtem",
    "gn:cc2":"AL",
    "gn:country_code":"AL",
    "gn:dem":503,
    "gn:feature_class":"P",
    "gn:feature_code":"PPL",
    "gn:name":"Bresti i Posht\u00ebm",
    "gn:population":0,
    "gn:timezone":"Europe/Tirane",
    "iso:country":"AL",
    "name:und_x_variant":[
        "Brest i Posht\u00ebm",
        "Bresti i Posht\u00ebr",
        "Bresti i Posht\u00ebm"
    ],
    "wof:name":"Bresti i Poshtem",
    "wof:placetype":"locality"
},
  "geometry": {"coordinates":[20.36917,41.71944000000001],"type":"Point"}
}