{
  "type": "Feature",
  "properties": {
    "gn:admin1_code":"51",
    "gn:asciiname":"Lubonje",
    "gn:cc2":"AL",
    "gn:country_code":"AL",
    "gn:dem":44,
    "gn:feature_class":"P",
    "gn:feature_code":"PPL",
    "gn:name":"Lubonj\u00eb",
    "gn:population":0,
    "gn:timezone":"Europe/Tirane",
    "iso:country":"AL",
    "name:und_x_variant":[
        "Lubonja",
        "Lub\u00ebnj\u00eb",
        "Ljubnj",
        "Lub\u00ebnja",
        "Libonia",
        "Lubonj\u00eb"
    ],
    "wof:name":"Lubonje",
    "wof:placetype":"locality"
},
  "geometry": {"coordinates":[19.57222,40.50778],"type":"Point"}
}