{
  "type": "Feature",
  "properties": {
    "gn:admin1_code":"50",
    "gn:asciiname":"Lalej",
    "gn:country_code":"AL",
    "gn:dem":384,
    "gn:feature_class":"P",
    "gn:feature_code":"PPL",
    "gn:name":"Lalej",
    "gn:population":0,
    "gn:timezone":"Europe/Tirane",
    "iso:country":"AL",
    "wof:name":"Lalej",
    "wof:placetype":"locality"
},
  "geometry": {"coordinates":[19.91667,41.31667],"type":"Point"}
}