{
  "type": "Feature",
  "properties": {
    "gn:admin1_code":"44",
    "gn:asciiname":"Vanaj",
    "gn:cc2":"AL",
    "gn:country_code":"AL",
    "gn:dem":4,
    "gn:feature_class":"P",
    "gn:feature_code":"PPL",
    "gn:name":"Vanaj",
    "gn:population":0,
    "gn:timezone":"Europe/Tirane",
    "iso:country":"AL",
    "name:und_x_variant":[
        "Vaunar",
        "Vanar",
        "Vanari",
        "Vanaj"
    ],
    "wof:name":"Vanaj",
    "wof:placetype":"locality"
},
  "geometry": {"coordinates":[19.55861,40.84472],"type":"Point"}
}