{
  "type": "Feature",
  "properties": {
    "gn:admin1_code":"43",
    "gn:asciiname":"Elezaj",
    "gn:country_code":"AL",
    "gn:dem":1085,
    "gn:feature_class":"P",
    "gn:feature_code":"PPL",
    "gn:name":"Elezaj",
    "gn:population":0,
    "gn:timezone":"Europe/Tirane",
    "iso:country":"AL",
    "wof:name":"Elezaj",
    "wof:placetype":"locality"
},
  "geometry": {"coordinates":[20.2975,40.88944],"type":"Point"}
}