{
  "type": "Feature",
  "properties": {
    "gn:admin1_code":"45",
    "gn:asciiname":"Ball",
    "gn:cc2":"AL",
    "gn:country_code":"AL",
    "gn:dem":781,
    "gn:feature_class":"P",
    "gn:feature_code":"PPL",
    "gn:name":"Ball",
    "gn:population":0,
    "gn:timezone":"Europe/Tirane",
    "iso:country":"AL",
    "name:und_x_variant":[
        "Balli",
        "Bali",
        "Ball"
    ],
    "wof:name":"Ball",
    "wof:placetype":"locality"
},
  "geometry": {"coordinates":[20.11028,40.38472],"type":"Point"}
}