{
  "type": "Feature",
  "properties": {
    "gn:admin1_code":"49",
    "gn:asciiname":"Lagej",
    "gn:country_code":"AL",
    "gn:dem":61,
    "gn:feature_class":"P",
    "gn:feature_code":"PPL",
    "gn:name":"Lagej",
    "gn:population":0,
    "gn:timezone":"Europe/Tirane",
    "iso:country":"AL",
    "wof:name":"Lagej",
    "wof:placetype":"locality"
},
  "geometry": {"coordinates":[19.42,42.26056],"type":"Point"}
}