{
  "type": "Feature",
  "properties": {
    "gn:admin1_code":"41",
    "gn:asciiname":"Kovashice",
    "gn:cc2":"AL",
    "gn:country_code":"AL",
    "gn:dem":517,
    "gn:feature_class":"P",
    "gn:feature_code":"PPL",
    "gn:name":"Kovashic\u00eb",
    "gn:population":0,
    "gn:timezone":"Europe/Tirane",
    "iso:country":"AL",
    "name:und_x_variant":[
        "Kovashica",
        "Kova\u00e7ica",
        "Kova\u00e7is\u00eb",
        "Koshavice",
        "Kvashica",
        "Kovashic\u00eb"
    ],
    "wof:name":"Kovashice",
    "wof:placetype":"locality"
},
  "geometry": {"coordinates":[20.44806,41.59806],"type":"Point"}
}