{
  "type": "Feature",
  "properties": {
    "gn:admin1_code":"40",
    "gn:admin2_code":"34.0",
    "gn:asciiname":"Kozare",
    "gn:cc2":"AL",
    "gn:country_code":"AL",
    "gn:dem":28,
    "gn:feature_class":"P",
    "gn:feature_code":"PPLA3",
    "gn:name":"Kozar\u00eb",
    "gn:population":0,
    "gn:timezone":"Europe/Tirane",
    "iso:country":"AL",
    "name:und_x_variant":[
        "Kozarja",
        "Kozara",
        "Kozar\u00eb"
    ],
    "wof:name":"Kozare",
    "wof:placetype":"locality"
},
  "geometry": {"coordinates":[19.90056,40.83083],"type":"Point"}
}