{
  "type": "Feature",
  "properties": {
    "gn:admin1_code":"49",
    "gn:asciiname":"Gjergoraj",
    "gn:country_code":"AL",
    "gn:dem":672,
    "gn:feature_class":"P",
    "gn:feature_code":"PPL",
    "gn:name":"Gjergoraj",
    "gn:population":0,
    "gn:timezone":"Europe/Tirane",
    "iso:country":"AL",
    "wof:name":"Gjergoraj",
    "wof:placetype":"locality"
},
  "geometry": {"coordinates":[19.69861,42.24806],"type":"Point"}
}