{
  "type": "Feature",
  "properties": {
    "gn:admin1_code":"51",
    "gn:asciiname":"Memoraq",
    "gn:cc2":"AL",
    "gn:country_code":"AL",
    "gn:dem":133,
    "gn:feature_class":"P",
    "gn:feature_code":"PPL",
    "gn:name":"Memoraq",
    "gn:population":0,
    "gn:timezone":"Europe/Tirane",
    "iso:country":"AL",
    "name:und_x_variant":[
        "Memordhi",
        "Memorachi",
        "Memoraqi",
        "Nemoraqi",
        "Meshorabi",
        "Memoraq"
    ],
    "wof:name":"Memoraq",
    "wof:placetype":"locality"
},
  "geometry": {"coordinates":[20.14222,39.84833],"type":"Point"}
}