{
  "type": "Feature",
  "properties": {
    "gn:admin1_code":"43",
    "gn:asciiname":"Molle",
    "gn:country_code":"AL",
    "gn:dem":792,
    "gn:feature_class":"P",
    "gn:feature_code":"PPL",
    "gn:name":"Moll\u00eb",
    "gn:population":0,
    "gn:timezone":"Europe/Tirane",
    "iso:country":"AL",
    "name:deu_x_preferred":[
        "Molle"
    ],
    "name:swe_x_preferred":[
        "Molle"
    ],
    "wof:name":"Molle",
    "wof:placetype":"locality"
},
  "geometry": {"coordinates":[20.32556,40.82111],"type":"Point"}
}