{
  "type": "Feature",
  "properties": {
    "gn:admin1_code":"46",
    "gn:asciiname":"Zvezde",
    "gn:cc2":"AL",
    "gn:country_code":"AL",
    "gn:dem":826,
    "gn:feature_class":"P",
    "gn:feature_code":"PPL",
    "gn:name":"Zvezd\u00eb",
    "gn:population":0,
    "gn:timezone":"Europe/Tirane",
    "iso:country":"AL",
    "name:mkd_x_preferred":[
        "\u0405\u0432\u0435\u0437\u0434\u0430"
    ],
    "name:und_x_variant":[
        "Svezda",
        "Zvezda",
        "Zvezhda",
        "Zvezd\u00eb"
    ],
    "wof:name":"Zvezde",
    "wof:placetype":"locality"
},
  "geometry": {"coordinates":[20.85806,40.73111],"type":"Point"}
}