{
  "type": "Feature",
  "properties": {
    "gn:admin1_code":"40",
    "gn:asciiname":"Malinat",
    "gn:cc2":"AL",
    "gn:country_code":"AL",
    "gn:dem":260,
    "gn:feature_class":"P",
    "gn:feature_code":"PPL",
    "gn:name":"Malinat",
    "gn:population":0,
    "gn:timezone":"Europe/Tirane",
    "iso:country":"AL",
    "name:und_x_variant":[
        "Malinati",
        "Malinit",
        "Malinat"
    ],
    "wof:name":"Malinat",
    "wof:placetype":"locality"
},
  "geometry": {"coordinates":[20.03278,40.61194],"type":"Point"}
}