{
  "type": "Feature",
  "properties": {
    "gn:admin1_code":"46",
    "gn:asciiname":"Memelisht",
    "gn:cc2":"AL",
    "gn:country_code":"AL",
    "gn:dem":718,
    "gn:feature_class":"P",
    "gn:feature_code":"PPL",
    "gn:name":"M\u00ebm\u00eblisht",
    "gn:population":0,
    "gn:timezone":"Europe/Tirane",
    "iso:country":"AL",
    "name:mkd_x_preferred":[
        "\u041c\u0430\u043c\u0443\u043b\u0438\u0448\u0442\u0430"
    ],
    "name:und_x_variant":[
        "M\u00ebmlisht",
        "Memlishta",
        "M\u00ebmlisht\u00eb",
        "Memelishti",
        "M\u00ebm\u00eblisht"
    ],
    "wof:name":"Memelisht",
    "wof:placetype":"locality"
},
  "geometry": {"coordinates":[20.6375,40.935],"type":"Point"}
}