{
  "type": "Feature",
  "properties": {
    "gn:admin1_code":"40",
    "gn:asciiname":"Teman",
    "gn:cc2":"AL",
    "gn:country_code":"AL",
    "gn:dem":523,
    "gn:feature_class":"P",
    "gn:feature_code":"PPL",
    "gn:name":"Teman",
    "gn:population":0,
    "gn:timezone":"Europe/Tirane",
    "iso:country":"AL",
    "name:ceb_x_preferred":[
        "Teman"
    ],
    "name:heb_x_preferred":[
        "\u05ea\u05d9\u05de\u05df"
    ],
    "name:swe_x_preferred":[
        "Teman"
    ],
    "name:und_x_variant":[
        "Temani",
        "Temon"
    ],
    "wof:name":"Teman",
    "wof:placetype":"locality"
},
  "geometry": {"coordinates":[20.03944,40.58111],"type":"Point"}
}