{
  "type": "Feature",
  "properties": {
    "gn:admin1_code":"40",
    "gn:asciiname":"Helmes",
    "gn:cc2":"AL",
    "gn:country_code":"AL",
    "gn:dem":1094,
    "gn:feature_class":"P",
    "gn:feature_code":"PPL",
    "gn:name":"Helm\u00ebs",
    "gn:population":0,
    "gn:timezone":"Europe/Tirane",
    "iso:country":"AL",
    "name:mkd_x_preferred":[
        "\u0425\u0435\u043b\u043c\u0435\u0441"
    ],
    "name:sqi_x_preferred":[
        "Helm\u00ebs"
    ],
    "name:tur_x_preferred":[
        "Helmes"
    ],
    "name:und_x_variant":[
        "Helmesi",
        "Helm\u00ebs"
    ],
    "wof:name":"Helmes",
    "wof:placetype":"locality"
},
  "geometry": {"coordinates":[20.41556,40.48111],"type":"Point"}
}