{
  "type": "Feature",
  "properties": {
    "gn:admin1_code":"48",
    "gn:asciiname":"Gurez",
    "gn:cc2":"AL",
    "gn:country_code":"AL",
    "gn:dem":4,
    "gn:feature_class":"P",
    "gn:feature_code":"PPL",
    "gn:name":"Gur\u00ebz",
    "gn:population":0,
    "gn:timezone":"Europe/Tirane",
    "iso:country":"AL",
    "name:und_x_variant":[
        "Gur\u00ebzi",
        "Gurr\u00ebs",
        "Gurz",
        "Gurz\u00eb",
        "Gurr\u00ebz",
        "Gurr\u00ebsi",
        "Gurr\u00ebzi",
        "Gur\u00ebz"
    ],
    "wof:name":"Gurez",
    "wof:placetype":"locality"
},
  "geometry": {"coordinates":[19.63639,41.66722],"type":"Point"}
}