{
  "type": "Feature",
  "properties": {
    "gn:admin1_code":"40",
    "gn:asciiname":"Galine",
    "gn:cc2":"AL",
    "gn:country_code":"AL",
    "gn:dem":487,
    "gn:feature_class":"P",
    "gn:feature_code":"PPL",
    "gn:name":"Galin\u00eb",
    "gn:population":0,
    "gn:timezone":"Europe/Tirane",
    "iso:country":"AL",
    "name:und_x_variant":[
        "Galina",
        "Galin\u00eb"
    ],
    "wof:name":"Galine",
    "wof:placetype":"locality"
},
  "geometry": {"coordinates":[19.87167,40.70278],"type":"Point"}
}