{
  "type": "Feature",
  "properties": {
    "gn:admin1_code":"50",
    "gn:asciiname":"Pinet",
    "gn:cc2":"AL",
    "gn:country_code":"AL",
    "gn:dem":144,
    "gn:feature_class":"P",
    "gn:feature_code":"PPL",
    "gn:name":"Pinet",
    "gn:population":0,
    "gn:timezone":"Europe/Tirane",
    "iso:country":"AL",
    "name:und_x_variant":[
        "Pineti",
        "Plnet",
        "Pinet"
    ],
    "wof:name":"Pinet",
    "wof:placetype":"locality"
},
  "geometry": {"coordinates":[19.64278,41.28556],"type":"Point"}
}