{
  "type": "Feature",
  "properties": {
    "gn:admin1_code":"48",
    "gn:asciiname":"Kashnjet",
    "gn:cc2":"AL",
    "gn:country_code":"AL",
    "gn:dem":440,
    "gn:feature_class":"P",
    "gn:feature_code":"PPL",
    "gn:name":"Kashnjet",
    "gn:population":0,
    "gn:timezone":"Europe/Tirane",
    "iso:country":"AL",
    "name:und_x_variant":[
        "Kashnjeti",
        "Kashnjet"
    ],
    "wof:name":"Kashnjet",
    "wof:placetype":"locality"
},
  "geometry": {"coordinates":[19.81389,41.91222],"type":"Point"}
}