{
  "type": "Feature",
  "properties": {
    "gn:admin1_code":"44",
    "gn:asciiname":"Sulaj",
    "gn:cc2":"AL",
    "gn:country_code":"AL",
    "gn:dem":2,
    "gn:feature_class":"P",
    "gn:feature_code":"PPL",
    "gn:name":"Sulaj",
    "gn:population":0,
    "gn:timezone":"Europe/Tirane",
    "iso:country":"AL",
    "name:und_x_variant":[
        "Sulaj Bufasi",
        "Sulajn",
        "Sulaj"
    ],
    "wof:name":"Sulaj",
    "wof:placetype":"locality"
},
  "geometry": {"coordinates":[19.50444,40.75806],"type":"Point"}
}