{
  "type": "Feature",
  "properties": {
    "gn:admin1_code":"49",
    "gn:asciiname":"Rras",
    "gn:cc2":"AL",
    "gn:country_code":"AL",
    "gn:dem":264,
    "gn:feature_class":"P",
    "gn:feature_code":"PPL",
    "gn:name":"Rras",
    "gn:population":0,
    "gn:timezone":"Europe/Tirane",
    "iso:country":"AL",
    "name:und_x_variant":[
        "Rrasi",
        "Rrasi eg\u00ebr",
        "Rras\u00eb",
        "Ras",
        "Ras i Eg\u00ebr",
        "Rras"
    ],
    "wof:name":"Rras",
    "wof:placetype":"locality"
},
  "geometry": {"coordinates":[19.985,41.9125],"type":"Point"}
}