{
  "type": "Feature",
  "properties": {
    "gn:admin1_code":"49",
    "gn:asciiname":"Pap",
    "gn:cc2":"AL",
    "gn:country_code":"AL",
    "gn:dem":454,
    "gn:feature_class":"P",
    "gn:feature_code":"PPL",
    "gn:name":"Pap",
    "gn:population":0,
    "gn:timezone":"Europe/Tirane",
    "iso:country":"AL",
    "name:und_x_variant":[
        "Papi",
        "Pap"
    ],
    "wof:name":"Pap",
    "wof:placetype":"locality"
},
  "geometry": {"coordinates":[19.92667,42.17333],"type":"Point"}
}