{
  "type": "Feature",
  "properties": {
    "gn:admin1_code":"43",
    "gn:asciiname":"Shark",
    "gn:country_code":"AL",
    "gn:dem":163,
    "gn:feature_class":"P",
    "gn:feature_code":"PPL",
    "gn:name":"Shark",
    "gn:population":0,
    "gn:timezone":"Europe/Tirane",
    "iso:country":"AL",
    "wof:name":"Shark",
    "wof:placetype":"locality"
},
  "geometry": {"coordinates":[19.94361,40.97],"type":"Point"}
}