{
  "type": "Feature",
  "properties": {
    "gn:admin1_code":"43",
    "gn:asciiname":"Nezhan",
    "gn:cc2":"AL",
    "gn:country_code":"AL",
    "gn:dem":663,
    "gn:feature_class":"P",
    "gn:feature_code":"PPL",
    "gn:name":"Nezhan",
    "gn:population":0,
    "gn:timezone":"Europe/Tirane",
    "iso:country":"AL",
    "name:und_x_variant":[
        "Nezani",
        "Nezhani",
        "Nezhaj",
        "Nezhari",
        "Nezhan"
    ],
    "wof:name":"Nezhan",
    "wof:placetype":"locality"
},
  "geometry": {"coordinates":[20.22917,40.97861],"type":"Point"}
}