{
  "type": "Feature",
  "properties": {
    "gn:admin1_code":"40",
    "gn:asciiname":"Kuc",
    "gn:cc2":"AL",
    "gn:country_code":"AL",
    "gn:dem":909,
    "gn:feature_class":"P",
    "gn:feature_code":"PPL",
    "gn:name":"Ku\u00e7",
    "gn:population":0,
    "gn:timezone":"Europe/Tirane",
    "iso:country":"AL",
    "name:und_x_variant":[
        "Ku\u00e7i",
        "Ku\u00e7"
    ],
    "wof:name":"Kuc",
    "wof:placetype":"locality"
},
  "geometry": {"coordinates":[20.32972,40.59944],"type":"Point"}
}