{
  "type": "Feature",
  "properties": {
    "gn:admin1_code":"49",
    "gn:asciiname":"Lumz",
    "gn:cc2":"AL",
    "gn:country_code":"AL",
    "gn:dem":525,
    "gn:feature_class":"P",
    "gn:feature_code":"PPL",
    "gn:name":"Lumz",
    "gn:population":0,
    "gn:timezone":"Europe/Tirane",
    "iso:country":"AL",
    "name:und_x_variant":[
        "Lumzi",
        "Lumz"
    ],
    "wof:name":"Lumz",
    "wof:placetype":"locality"
},
  "geometry": {"coordinates":[20.02222,42.02111],"type":"Point"}
}