{
  "type": "Feature",
  "properties": {
    "gn:admin1_code":"47",
    "gn:asciiname":"Qinamake",
    "gn:cc2":"AL",
    "gn:country_code":"AL",
    "gn:dem":485,
    "gn:feature_class":"P",
    "gn:feature_code":"PPL",
    "gn:name":"Qinamak\u00eb",
    "gn:population":0,
    "gn:timezone":"Europe/Tirane",
    "iso:country":"AL",
    "name:und_x_variant":[
        "\u00c7inemak",
        "Qinamak",
        "\u00c7inamak",
        "Qinamaku",
        "\u00c7iramaku",
        "Qinamak\u00eb"
    ],
    "wof:name":"Qinamake",
    "wof:placetype":"locality"
},
  "geometry": {"coordinates":[20.36944,42.01611],"type":"Point"}
}