{
  "type": "Feature",
  "properties": {
    "gn:admin1_code":"44",
    "gn:asciiname":"Afrimi i Ri",
    "gn:cc2":"AL",
    "gn:country_code":"AL",
    "gn:dem":11,
    "gn:feature_class":"P",
    "gn:feature_code":"PPL",
    "gn:name":"Afrimi i Ri",
    "gn:population":0,
    "gn:timezone":"Europe/Tirane",
    "iso:country":"AL",
    "name:und_x_variant":[
        "Qenas",
        "Afrim i Ri",
        "Afrimi i Ri"
    ],
    "wof:name":"Afrimi i Ri",
    "wof:placetype":"locality"
},
  "geometry": {"coordinates":[19.53028,40.73361],"type":"Point"}
}