{
  "type": "Feature",
  "properties": {
    "gn:admin1_code":"43",
    "gn:asciiname":"Porrepth",
    "gn:country_code":"AL",
    "gn:dem":514,
    "gn:feature_class":"P",
    "gn:feature_code":"PPL",
    "gn:name":"Porrepth",
    "gn:population":0,
    "gn:timezone":"Europe/Tirane",
    "iso:country":"AL",
    "wof:name":"Porrepth",
    "wof:placetype":"locality"
},
  "geometry": {"coordinates":[20.05194,40.93861],"type":"Point"}
}