{
  "type": "Feature",
  "properties": {
    "gn:admin1_code":"45",
    "gn:admin2_code":"6.0",
    "gn:asciiname":"Qestorat",
    "gn:cc2":"AL",
    "gn:country_code":"AL",
    "gn:dem":553,
    "gn:feature_class":"P",
    "gn:feature_code":"PPLA3",
    "gn:name":"Qestorat",
    "gn:population":0,
    "gn:timezone":"Europe/Tirane",
    "iso:country":"AL",
    "name:sqi_x_preferred":[
        "Qestorat"
    ],
    "name:und_x_variant":[
        "Chiesarat",
        "Khiesarat",
        "Qesarat",
        "Qestorati"
    ],
    "wof:name":"Qestorat",
    "wof:placetype":"locality"
},
  "geometry": {"coordinates":[20.19972000000001,40.1175],"type":"Point"}
}