{
  "type": "Feature",
  "properties": {
    "gn:admin1_code":"51",
    "gn:asciiname":"Rumanxe",
    "gn:cc2":"AL",
    "gn:country_code":"AL",
    "gn:dem":110,
    "gn:feature_class":"P",
    "gn:feature_code":"PPL",
    "gn:name":"Rumanx\u00eb",
    "gn:population":0,
    "gn:timezone":"Europe/Tirane",
    "iso:country":"AL",
    "name:und_x_variant":[
        "Romanza",
        "Rumanz\u00eb",
        "Rumanza",
        "Rumance",
        "Rumanxaj\u00eb",
        "Ramanxa",
        "Rumanxaja",
        "Rumanxa",
        "Rumanx\u00eb"
    ],
    "wof:name":"Rumanxe",
    "wof:placetype":"locality"
},
  "geometry": {"coordinates":[20.125,39.85667],"type":"Point"}
}