{
  "type": "Feature",
  "properties": {
    "gn:admin1_code":"48",
    "gn:asciiname":"Geziq",
    "gn:cc2":"AL",
    "gn:country_code":"AL",
    "gn:dem":365,
    "gn:feature_class":"P",
    "gn:feature_code":"PPL",
    "gn:name":"G\u00ebziq",
    "gn:population":0,
    "gn:timezone":"Europe/Tirane",
    "iso:country":"AL",
    "name:und_x_variant":[
        "Gziq",
        "Gzy\u00e7",
        "Goziqi",
        "Gziqi",
        "G\u00ebziqi",
        "G\u00ebziq"
    ],
    "wof:name":"Geziq",
    "wof:placetype":"locality"
},
  "geometry": {"coordinates":[19.91278,41.81056],"type":"Point"}
}