{
  "type": "Feature",
  "properties": {
    "gn:admin1_code":"49",
    "gn:asciiname":"Kcira e Eperme",
    "gn:country_code":"AL",
    "gn:dem":547,
    "gn:feature_class":"P",
    "gn:feature_code":"PPL",
    "gn:name":"K\u00e7ira e Ep\u00ebrme",
    "gn:population":0,
    "gn:timezone":"Europe/Tirane",
    "iso:country":"AL",
    "wof:name":"Kcira e Eperme",
    "wof:placetype":"locality"
},
  "geometry": {"coordinates":[19.80583,42.01583],"type":"Point"}
}