{
  "type": "Feature",
  "properties": {
    "gn:admin1_code":"44",
    "gn:asciiname":"Gur",
    "gn:cc2":"AL",
    "gn:country_code":"AL",
    "gn:dem":4,
    "gn:feature_class":"P",
    "gn:feature_code":"PPL",
    "gn:name":"Gur",
    "gn:population":0,
    "gn:timezone":"Europe/Tirane",
    "iso:country":"AL",
    "name:ceb_x_preferred":[
        "Gur"
    ],
    "name:deu_x_preferred":[
        "Gur"
    ],
    "name:fra_x_preferred":[
        "Gur"
    ],
    "name:pol_x_preferred":[
        "Gur"
    ],
    "name:rus_x_preferred":[
        "\u0413\u0443\u0440"
    ],
    "name:swe_x_preferred":[
        "Gur"
    ],
    "name:ukr_x_preferred":[
        "\u0413\u0443\u0440"
    ],
    "name:und_x_variant":[
        "Guri"
    ],
    "wof:name":"Gur",
    "wof:placetype":"locality"
},
  "geometry": {"coordinates":[19.535,40.89806],"type":"Point"}
}