{
  "type": "Feature",
  "properties": {
    "gn:admin1_code":"46",
    "gn:asciiname":"Lajthize",
    "gn:cc2":"AL",
    "gn:country_code":"AL",
    "gn:dem":917,
    "gn:feature_class":"P",
    "gn:feature_code":"PPL",
    "gn:name":"Lajthiz\u00eb",
    "gn:population":0,
    "gn:timezone":"Europe/Tirane",
    "iso:country":"AL",
    "name:bul_x_preferred":[
        "\u041b\u0435\u0441\u043a\u0430"
    ],
    "name:ell_x_preferred":[
        "\u039b\u03ad\u03c3\u03ba\u03b1"
    ],
    "name:ell_x_variant":[
        "\u039b\u03b1\u0390\u03b8\u03b9\u03c4\u03c3\u03b1"
    ],
    "name:mkd_x_preferred":[
        "\u041b\u0435\u0441\u043a\u0430"
    ],
    "name:sqi_x_preferred":[
        "Lajthiz\u00eb"
    ],
    "name:und_x_variant":[
        "Lezica",
        "Lajthiza",
        "Lajthiz\u00eb"
    ],
    "wof:name":"Lajthize",
    "wof:placetype":"locality"
},
  "geometry": {"coordinates":[20.88889,40.77778],"type":"Point"}
}