{
  "type": "Feature",
  "properties": {
    "gn:country":"AL",
    "gn:fcode":"PPL",
    "gn:population":5,
    "iso:country":"AL",
    "name:und_x_variant":[
        "M\u00ebxixa"
    ],
    "qs:name":"M\u00ebxix\u00eb",
    "qs:photos_9r":0,
    "qs:photos_sr":0,
    "qs:pop_sr":"1",
    "wof:name":"M\u00ebxix\u00eb",
    "wof:placetype":"locality",
    "wof:population":5
},
  "geometry": {"coordinates":[20.27583,41.32917],"type":"Point"}
}