{
  "type": "Feature",
  "properties": {
    "gn:admin1_code":"50",
    "gn:asciiname":"Damarkaj",
    "gn:cc2":"AL",
    "gn:country_code":"AL",
    "gn:dem":251,
    "gn:feature_class":"P",
    "gn:feature_code":"PPL",
    "gn:name":"Damarkaj",
    "gn:population":0,
    "gn:timezone":"Europe/Tirane",
    "iso:country":"AL",
    "name:sqi_x_preferred":[
        "Damarkaj"
    ],
    "name:und_x_variant":[
        "Domarkai",
        "Danmarkaj",
        "Domarkaj",
        "Demarkaj",
        "Dormakaj"
    ],
    "wof:name":"Damarkaj",
    "wof:placetype":"locality"
},
  "geometry": {"coordinates":[19.73583,41.12833],"type":"Point"}
}