{
  "type": "Feature",
  "properties": {
    "gn:admin1_code":"40",
    "gn:asciiname":"Ramanjat",
    "gn:country_code":"AL",
    "gn:dem":268,
    "gn:feature_class":"P",
    "gn:feature_code":"PPL",
    "gn:name":"Ramanjat",
    "gn:population":0,
    "gn:timezone":"Europe/Tirane",
    "iso:country":"AL",
    "wof:name":"Ramanjat",
    "wof:placetype":"locality"
},
  "geometry": {"coordinates":[19.90194,40.67194],"type":"Point"}
}