{
  "type": "Feature",
  "properties": {
    "gn:admin1_code":"45",
    "gn:asciiname":"Kamcisht",
    "gn:cc2":"AL",
    "gn:country_code":"AL",
    "gn:dem":607,
    "gn:feature_class":"P",
    "gn:feature_code":"PPL",
    "gn:name":"Kam\u00e7isht",
    "gn:population":0,
    "gn:timezone":"Europe/Tirane",
    "iso:country":"AL",
    "name:und_x_variant":[
        "Kam\u00e7ishti",
        "Kam\u00e7ishta",
        "Kamshishti",
        "Kam\u00e7ista",
        "Kam\u00e7isht"
    ],
    "wof:name":"Kamcisht",
    "wof:placetype":"locality"
},
  "geometry": {"coordinates":[19.92083,40.4475],"type":"Point"}
}