{
  "type": "Feature",
  "properties": {
    "gn:admin1_code":"48",
    "gn:asciiname":"Nderfane",
    "gn:cc2":"AL",
    "gn:country_code":"AL",
    "gn:dem":104,
    "gn:feature_class":"P",
    "gn:feature_code":"PPL",
    "gn:name":"Nd\u00ebrfan\u00eb",
    "gn:population":0,
    "gn:timezone":"Europe/Tirane",
    "iso:country":"AL",
    "name:und_x_variant":[
        "Nderfana",
        "Nd\u00ebrfan\u00eb"
    ],
    "wof:name":"Nderfane",
    "wof:placetype":"locality"
},
  "geometry": {"coordinates":[19.89194,41.81083],"type":"Point"}
}