{
  "type": "Feature",
  "properties": {
    "gn:admin1_code":"50",
    "gn:asciiname":"Kercukje",
    "gn:cc2":"AL",
    "gn:country_code":"AL",
    "gn:dem":312,
    "gn:feature_class":"P",
    "gn:feature_code":"PPL",
    "gn:name":"K\u00ebr\u00e7ukje",
    "gn:population":0,
    "gn:timezone":"Europe/Tirane",
    "iso:country":"AL",
    "name:und_x_variant":[
        "Kur\u00e7ukaj",
        "K\u00ebr\u00e7ukaj",
        "Kreukaj",
        "K\u00ebr\u00e7ukja",
        "K\u00ebr\u00e7ukje"
    ],
    "wof:name":"Kercukje",
    "wof:placetype":"locality"
},
  "geometry": {"coordinates":[19.63167,41.24472],"type":"Point"}
}