{
  "type": "Feature",
  "properties": {
    "gn:admin1_code":"47",
    "gn:asciiname":"Kurpal",
    "gn:cc2":"AL",
    "gn:country_code":"AL",
    "gn:dem":728,
    "gn:feature_class":"P",
    "gn:feature_code":"PPL",
    "gn:name":"Kurpal",
    "gn:population":0,
    "gn:timezone":"Europe/Tirane",
    "iso:country":"AL",
    "name:und_x_variant":[
        "Kurpali",
        "Gurpal\u00eb",
        "Kurpal"
    ],
    "wof:name":"Kurpal",
    "wof:placetype":"locality"
},
  "geometry": {"coordinates":[20.39639,42.29361],"type":"Point"}
}