{
  "type": "Feature",
  "properties": {
    "gn:admin1_code":"41",
    "gn:asciiname":"Draj-Rec",
    "gn:cc2":"AL",
    "gn:country_code":"AL",
    "gn:dem":370,
    "gn:feature_class":"P",
    "gn:feature_code":"PPL",
    "gn:name":"Draj-Re\u00e7",
    "gn:population":0,
    "gn:timezone":"Europe/Tirane",
    "iso:country":"AL",
    "name:und_x_variant":[
        "Draj\u00eb",
        "Draj-Re\u00e7i",
        "Draja",
        "Draj-Re\u00e7"
    ],
    "wof:name":"Draj-Rec",
    "wof:placetype":"locality"
},
  "geometry": {"coordinates":[20.33056,41.88194],"type":"Point"}
}