{
  "type": "Feature",
  "properties": {
    "gn:admin1_code":"46",
    "gn:admin2_code":"9.0",
    "gn:asciiname":"Pojan",
    "gn:country_code":"AL",
    "gn:dem":823,
    "gn:feature_class":"P",
    "gn:feature_code":"PPLA3",
    "gn:name":"Pojan",
    "gn:population":0,
    "gn:timezone":"Europe/Tirane",
    "iso:country":"AL",
    "name:hun_x_preferred":[
        "Pojan"
    ],
    "name:ita_x_preferred":[
        "Pojan"
    ],
    "name:mkd_x_preferred":[
        "\u041f\u043e\u043b\u0458\u0430\u043d\u0438"
    ],
    "name:msa_x_preferred":[
        "Pojan"
    ],
    "name:mwl_x_preferred":[
        "Pojan"
    ],
    "name:pol_x_preferred":[
        "Gmina Pojan"
    ],
    "name:por_x_preferred":[
        "Pojani"
    ],
    "name:rup_x_preferred":[
        "Poiani"
    ],
    "name:spa_x_preferred":[
        "Pojan"
    ],
    "name:sqi_x_preferred":[
        "Pojan"
    ],
    "name:tur_x_preferred":[
        "Pojan"
    ],
    "name:vie_x_preferred":[
        "Pojan"
    ],
    "name:war_x_preferred":[
        "Pojan"
    ],
    "wof:name":"Pojan",
    "wof:placetype":"locality"
},
  "geometry": {"coordinates":[20.8375,40.72583],"type":"Point"}
}