{
  "type": "Feature",
  "properties": {
    "gn:admin1_code":"40",
    "gn:asciiname":"Kikias",
    "gn:country_code":"AL",
    "gn:dem":26,
    "gn:feature_class":"P",
    "gn:feature_code":"PPL",
    "gn:name":"Kikias",
    "gn:population":0,
    "gn:timezone":"Europe/Tirane",
    "iso:country":"AL",
    "wof:name":"Kikias",
    "wof:placetype":"locality"
},
  "geometry": {"coordinates":[19.86333,40.79028],"type":"Point"}
}