{
  "type": "Feature",
  "properties": {
    "gn:admin1_code":"42",
    "gn:asciiname":"Luz",
    "gn:cc2":"AL",
    "gn:country_code":"AL",
    "gn:dem":28,
    "gn:feature_class":"P",
    "gn:feature_code":"PPL",
    "gn:name":"Luz",
    "gn:population":0,
    "gn:timezone":"Europe/Tirane",
    "iso:country":"AL",
    "name:por_x_preferred":[
        "Luz"
    ],
    "name:tam_x_preferred":[
        "\u0bb2\u0bc2\u0b9a\u0bc1"
    ],
    "name:und_x_variant":[
        "Ljuz",
        "Luzi",
        "Luz\u00eb",
        "Luzja",
        "Luz"
    ],
    "wof:name":"Luz",
    "wof:placetype":"locality"
},
  "geometry": {"coordinates":[19.69972000000001,41.49472],"type":"Point"}
}