{
  "type": "Feature",
  "properties": {
    "gn:admin1_code":"46",
    "gn:asciiname":"Maliq-Fshat",
    "gn:cc2":"AL",
    "gn:country_code":"AL",
    "gn:dem":862,
    "gn:feature_class":"P",
    "gn:feature_code":"PPL",
    "gn:name":"Maliq-Fshat",
    "gn:population":0,
    "gn:timezone":"Europe/Tirane",
    "iso:country":"AL",
    "name:und_x_variant":[
        "Maliqi",
        "Maliq-Fshat"
    ],
    "wof:name":"Maliq-Fshat",
    "wof:placetype":"locality"
},
  "geometry": {"coordinates":[20.68222,40.71139],"type":"Point"}
}