{
  "type": "Feature",
  "properties": {
    "gn:admin1_code":"45",
    "gn:asciiname":"Mamogjinaj",
    "gn:cc2":"AL",
    "gn:country_code":"AL",
    "gn:dem":272,
    "gn:feature_class":"P",
    "gn:feature_code":"PPL",
    "gn:name":"Mamogjinaj",
    "gn:population":0,
    "gn:timezone":"Europe/Tirane",
    "iso:country":"AL",
    "name:und_x_variant":[
        "Marhugjina",
        "Mamogjinaj"
    ],
    "wof:name":"Mamogjinaj",
    "wof:placetype":"locality"
},
  "geometry": {"coordinates":[19.825,40.37083],"type":"Point"}
}