{
  "type": "Feature",
  "properties": {
    "gn:admin1_code":"46",
    "gn:asciiname":"Shales",
    "gn:cc2":"AL",
    "gn:country_code":"AL",
    "gn:dem":1096,
    "gn:feature_class":"P",
    "gn:feature_code":"PPL",
    "gn:name":"Shal\u00ebs",
    "gn:population":0,
    "gn:timezone":"Europe/Tirane",
    "iso:country":"AL",
    "name:und_x_variant":[
        "Shal\u00ebsi",
        "Shal\u00ebs"
    ],
    "wof:name":"Shales",
    "wof:placetype":"locality"
},
  "geometry": {"coordinates":[20.65694,40.24361],"type":"Point"}
}