{
  "type": "Feature",
  "properties": {
    "gn:admin1_code":"43",
    "gn:asciiname":"Urucaj",
    "gn:country_code":"AL",
    "gn:dem":164,
    "gn:feature_class":"P",
    "gn:feature_code":"PPL",
    "gn:name":"Uru\u00e7aj",
    "gn:population":0,
    "gn:timezone":"Europe/Tirane",
    "iso:country":"AL",
    "wof:name":"Urucaj",
    "wof:placetype":"locality"
},
  "geometry": {"coordinates":[19.88278,40.99722],"type":"Point"}
}