{
  "type": "Feature",
  "properties": {
    "gn:admin1_code":"40",
    "gn:admin2_code":"1.0",
    "gn:asciiname":"Cukalat",
    "gn:cc2":"AL",
    "gn:country_code":"AL",
    "gn:dem":153,
    "gn:feature_class":"P",
    "gn:feature_code":"PPLA3",
    "gn:name":"Cukalat",
    "gn:population":0,
    "gn:timezone":"Europe/Tirane",
    "iso:country":"AL",
    "name:und_x_variant":[
        "Cukala",
        "Cukalati",
        "Cukelat",
        "Cukakat",
        "Cukaljat",
        "Cukelati",
        "Cukalat"
    ],
    "wof:name":"Cukalat",
    "wof:placetype":"locality"
},
  "geometry": {"coordinates":[19.79056,40.73028],"type":"Point"}
}