{
  "type": "Feature",
  "properties": {
    "gn:admin1_code":"40",
    "gn:admin2_code":"1.0",
    "gn:asciiname":"Cukalat",
    "gn:cc2":"AL",
    "gn:country_code":"AL",
    "gn:dem":153,
    "gn:feature_class":"P",
    "gn:feature_code":"PPLA3",
    "gn:name":"Cukalat",
    "gn:population":0,
    "gn:timezone":"Europe/Tirane",
    "iso:country":"AL",
    "name:hye_x_preferred":[
        "\u0554\u0578\u0582\u056f\u0561\u056c\u0561\u0569"
    ],
    "name:ita_x_preferred":[
        "Cukalat"
    ],
    "name:msa_x_preferred":[
        "Cukalat"
    ],
    "name:nno_x_preferred":[
        "Cukalat"
    ],
    "name:pol_x_preferred":[
        "Gmina Cukalat"
    ],
    "name:por_x_preferred":[
        "Cukalat"
    ],
    "name:spa_x_preferred":[
        "Cukalat"
    ],
    "name:tur_x_preferred":[
        "Cukalat"
    ],
    "name:und_x_variant":[
        "Cukala",
        "Cukalati",
        "Cukelat",
        "Cukakat",
        "Cukaljat",
        "Cukelati"
    ],
    "name:vie_x_preferred":[
        "Cukalat"
    ],
    "name:war_x_preferred":[
        "Cukalat"
    ],
    "wof:name":"Cukalat",
    "wof:placetype":"locality"
},
  "geometry": {"coordinates":[19.79056,40.73028],"type":"Point"}
}