{
  "type": "Feature",
  "properties": {
    "gn:admin1_code":"44",
    "gn:asciiname":"Ciflik",
    "gn:cc2":"AL",
    "gn:country_code":"AL",
    "gn:dem":13,
    "gn:feature_class":"P",
    "gn:feature_code":"PPL",
    "gn:name":"\u00c7iflik",
    "gn:population":0,
    "gn:timezone":"Europe/Tirane",
    "iso:country":"AL",
    "name:und_x_variant":[
        "\u00c7ifliku",
        "\u00c7iflik"
    ],
    "wof:name":"Ciflik",
    "wof:placetype":"locality"
},
  "geometry": {"coordinates":[19.75056,40.7625],"type":"Point"}
}