{
  "type": "Feature",
  "properties": {
    "gn:admin1_code":"50",
    "gn:asciiname":"Thartor",
    "gn:cc2":"AL",
    "gn:country_code":"AL",
    "gn:dem":422,
    "gn:feature_class":"P",
    "gn:feature_code":"PPL",
    "gn:name":"Thartor",
    "gn:population":0,
    "gn:timezone":"Europe/Tirane",
    "iso:country":"AL",
    "name:sqi_x_preferred":[
        "Thartor"
    ],
    "name:und_x_variant":[
        "Thartori",
        "Tharter",
        "Thartor"
    ],
    "wof:name":"Thartor",
    "wof:placetype":"locality"
},
  "geometry": {"coordinates":[19.70639,41.12972],"type":"Point"}
}