{
  "type": "Feature",
  "properties": {
    "gn:admin1_code":"40",
    "gn:asciiname":"Qorraj",
    "gn:cc2":"AL",
    "gn:country_code":"AL",
    "gn:dem":294,
    "gn:feature_class":"P",
    "gn:feature_code":"PPL",
    "gn:name":"Qorraj",
    "gn:population":0,
    "gn:timezone":"Europe/Tirane",
    "iso:country":"AL",
    "name:und_x_variant":[
        "Qoranj",
        "Qorraj"
    ],
    "wof:name":"Qorraj",
    "wof:placetype":"locality"
},
  "geometry": {"coordinates":[20.01472,40.64278],"type":"Point"}
}