{
  "type": "Feature",
  "properties": {
    "gn:admin1_code":"45",
    "gn:admin2_code":"6.0",
    "gn:asciiname":"Dervician",
    "gn:country_code":"AL",
    "gn:dem":177,
    "gn:feature_class":"P",
    "gn:feature_code":"PPLL",
    "gn:name":"Dervi\u00e7ian",
    "gn:population":211,
    "gn:timezone":"Europe/Tirane",
    "iso:country":"AL",
    "name:ell_x_preferred":[
        "\u0394\u03b5\u03c1\u03b2\u03b9\u03c4\u03c3\u03ac\u03bd\u03b7"
    ],
    "name:und_x_variant":[
        "Derviciani",
        "Dervi\u00e7an",
        "Dervi\u00e7ani",
        "Dervisciani",
        "Dervi\u00e7ian"
    ],
    "wof:name":"Dervician",
    "wof:placetype":"locality",
    "wof:population":211
},
  "geometry": {"coordinates":[20.17333,40.0325],"type":"Point"}
}