{
  "type": "Feature",
  "properties": {
    "gn:admin1_code":"50",
    "gn:asciiname":"Verri",
    "gn:cc2":"AL",
    "gn:country_code":"AL",
    "gn:dem":674,
    "gn:feature_class":"P",
    "gn:feature_code":"PPL",
    "gn:name":"Verri",
    "gn:population":0,
    "gn:timezone":"Europe/Tirane",
    "iso:country":"AL",
    "name:und_x_variant":[
        "Verria",
        "Verri"
    ],
    "wof:name":"Verri",
    "wof:placetype":"locality"
},
  "geometry": {"coordinates":[20.08722,41.32556],"type":"Point"}
}