{
  "type": "Feature",
  "properties": {
    "gn:admin1_code":"48",
    "gn:asciiname":"Spac",
    "gn:cc2":"AL",
    "gn:country_code":"AL",
    "gn:dem":529,
    "gn:feature_class":"P",
    "gn:feature_code":"PPL",
    "gn:name":"Spa\u00e7",
    "gn:population":0,
    "gn:timezone":"Europe/Tirane",
    "iso:country":"AL",
    "name:und_x_variant":[
        "Spa\u00e7i",
        "Spa\u00e7"
    ],
    "wof:name":"Spac",
    "wof:placetype":"locality"
},
  "geometry": {"coordinates":[20.04583,41.89833],"type":"Point"}
}