{
  "type": "Feature",
  "properties": {
    "gn:admin1_code":"43",
    "gn:asciiname":"Polis-Vale",
    "gn:cc2":"AL",
    "gn:country_code":"AL",
    "gn:dem":186,
    "gn:feature_class":"P",
    "gn:feature_code":"PPL",
    "gn:name":"Polis-Vale",
    "gn:population":0,
    "gn:timezone":"Europe/Tirane",
    "iso:country":"AL",
    "name:und_x_variant":[
        "Val\u00eb",
        "Polis Val\u00eb",
        "Polis-Vale"
    ],
    "wof:name":"Polis-Vale",
    "wof:placetype":"locality"
},
  "geometry": {"coordinates":[20.21528,41.15583],"type":"Point"}
}