{
  "type": "Feature",
  "properties": {
    "gn:admin1_code":"42",
    "gn:asciiname":"Hardhishte",
    "gn:cc2":"AL",
    "gn:country_code":"AL",
    "gn:dem":28,
    "gn:feature_class":"P",
    "gn:feature_code":"PPL",
    "gn:name":"Hardhisht\u00eb",
    "gn:population":0,
    "gn:timezone":"Europe/Tirane",
    "iso:country":"AL",
    "name:und_x_variant":[
        "Ardhisht\u00eb",
        "Hardhishta",
        "Ardhishta",
        "Hardhisht",
        "Hardisht\u00eb",
        "Hardhisht\u00eb"
    ],
    "wof:name":"Hardhishte",
    "wof:placetype":"locality"
},
  "geometry": {"coordinates":[19.57611,41.30556],"type":"Point"}
}