{
  "type": "Feature",
  "properties": {
    "gn:admin1_code":"44",
    "gn:asciiname":"Mehmet",
    "gn:cc2":"AL",
    "gn:country_code":"AL",
    "gn:dem":66,
    "gn:feature_class":"P",
    "gn:feature_code":"PPL",
    "gn:name":"Mehmet",
    "gn:population":0,
    "gn:timezone":"Europe/Tirane",
    "iso:country":"AL",
    "name:und_x_variant":[
        "Mehmeti",
        "Mehmet"
    ],
    "wof:name":"Mehmet",
    "wof:placetype":"locality"
},
  "geometry": {"coordinates":[19.58583,40.77389],"type":"Point"}
}