{
  "type": "Feature",
  "properties": {
    "gn:admin1_code":"45",
    "gn:asciiname":"Gjinkar",
    "gn:cc2":"AL",
    "gn:country_code":"AL",
    "gn:dem":311,
    "gn:feature_class":"P",
    "gn:feature_code":"PPL",
    "gn:name":"Gjinkar",
    "gn:population":3243,
    "gn:timezone":"Europe/Tirane",
    "iso:country":"AL",
    "name:und_x_variant":[
        "Petran",
        "Gjinakar",
        "Petrani",
        "Gjinkan-Petrani",
        "Petranit",
        "Gjinkar-Petran",
        "Petrani-Gjinkari",
        "Gjinkar"
    ],
    "wof:name":"Gjinkar",
    "wof:placetype":"locality",
    "wof:population":3243
},
  "geometry": {"coordinates":[20.40611,40.19944],"type":"Point"}
}