{
  "type": "Feature",
  "properties": {
    "gn:admin1_code":"44",
    "gn:asciiname":"Halilaj",
    "gn:cc2":"AL",
    "gn:country_code":"AL",
    "gn:dem":10,
    "gn:feature_class":"P",
    "gn:feature_code":"PPL",
    "gn:name":"Halilaj",
    "gn:population":0,
    "gn:timezone":"Europe/Tirane",
    "iso:country":"AL",
    "name:und_x_variant":[
        "Halilani",
        "Kalilaj",
        "Halilaj"
    ],
    "wof:name":"Halilaj",
    "wof:placetype":"locality"
},
  "geometry": {"coordinates":[19.63333,40.80222],"type":"Point"}
}