{
  "type": "Feature",
  "properties": {
    "gn:admin1_code":"46",
    "gn:asciiname":"Hadollar",
    "gn:cc2":"AL",
    "gn:country_code":"AL",
    "gn:dem":1135,
    "gn:feature_class":"P",
    "gn:feature_code":"PPL",
    "gn:name":"Hadollar",
    "gn:population":0,
    "gn:timezone":"Europe/Tirane",
    "iso:country":"AL",
    "name:und_x_variant":[
        "Sh\u00ebn Gjon",
        "Hadollar"
    ],
    "wof:name":"Hadollar",
    "wof:placetype":"locality"
},
  "geometry": {"coordinates":[20.46056,40.48417],"type":"Point"}
}