{
  "type": "Feature",
  "properties": {
    "gn:admin1_code":"45",
    "gn:asciiname":"Nepravishte",
    "gn:cc2":"AL",
    "gn:country_code":"AL",
    "gn:dem":391,
    "gn:feature_class":"P",
    "gn:feature_code":"PPL",
    "gn:name":"Nepravisht\u00eb",
    "gn:population":0,
    "gn:timezone":"Europe/Tirane",
    "iso:country":"AL",
    "name:und_x_variant":[
        "Vepravisht\u00eb e Poshtme",
        "Nepravista",
        "Nepravisht",
        "Nepravishta",
        "Nepravisht\u00eb"
    ],
    "wof:name":"Nepravishte",
    "wof:placetype":"locality"
},
  "geometry": {"coordinates":[20.27306,40.00083],"type":"Point"}
}