{
  "type": "Feature",
  "properties": {
    "gn:admin1_code":"51",
    "gn:admin2_code":"27.0",
    "gn:asciiname":"Brataj",
    "gn:cc2":"AL",
    "gn:country_code":"AL",
    "gn:dem":257,
    "gn:feature_class":"P",
    "gn:feature_code":"PPLA3",
    "gn:name":"Brataj",
    "gn:population":0,
    "gn:timezone":"Europe/Tirane",
    "iso:country":"AL",
    "name:ita_x_preferred":[
        "Brataj"
    ],
    "name:msa_x_preferred":[
        "Brataj"
    ],
    "name:pol_x_preferred":[
        "Brataj"
    ],
    "name:por_x_preferred":[
        "Brataj"
    ],
    "name:rus_x_preferred":[
        "\u0411\u0440\u0430\u0442\u0430\u0439"
    ],
    "name:tur_x_preferred":[
        "Brataj"
    ],
    "name:und_x_variant":[
        "Bratraj",
        "Brataj"
    ],
    "name:vie_x_preferred":[
        "Brataj"
    ],
    "name:war_x_preferred":[
        "Brataj"
    ],
    "wof:name":"Brataj",
    "wof:placetype":"locality"
},
  "geometry": {"coordinates":[19.66917,40.26778],"type":"Point"}
}