{
  "type": "Feature",
  "properties": {
    "gn:admin1_code":"48",
    "gn:asciiname":"Sherilaj",
    "gn:cc2":"AL",
    "gn:country_code":"AL",
    "gn:dem":306,
    "gn:feature_class":"P",
    "gn:feature_code":"PPL",
    "gn:name":"Sherilaj",
    "gn:population":0,
    "gn:timezone":"Europe/Tirane",
    "iso:country":"AL",
    "name:und_x_variant":[
        "Shevillaj",
        "Sherilaj"
    ],
    "wof:name":"Sherilaj",
    "wof:placetype":"locality"
},
  "geometry": {"coordinates":[19.81,41.85528],"type":"Point"}
}