{
  "type": "Feature",
  "properties": {
    "gn:admin1_code":"48",
    "gn:asciiname":"Kodermarlekaj",
    "gn:country_code":"AL",
    "gn:dem":0,
    "gn:feature_class":"P",
    "gn:feature_code":"PPL",
    "gn:name":"Kod\u00ebrmarlekaj",
    "gn:population":0,
    "gn:timezone":"Europe/Tirane",
    "iso:country":"AL",
    "wof:name":"Kodermarlekaj",
    "wof:placetype":"locality"
},
  "geometry": {"coordinates":[19.61611,41.76667],"type":"Point"}
}