{
  "type": "Feature",
  "properties": {
    "gn:admin1_code":"49",
    "gn:asciiname":"Lukaj",
    "gn:country_code":"AL",
    "gn:dem":815,
    "gn:feature_class":"P",
    "gn:feature_code":"PPL",
    "gn:name":"Lukaj",
    "gn:population":0,
    "gn:timezone":"Europe/Tirane",
    "iso:country":"AL",
    "wof:name":"Lukaj",
    "wof:placetype":"locality"
},
  "geometry": {"coordinates":[19.49167000000001,42.36444],"type":"Point"}
}