{
  "type": "Feature",
  "properties": {
    "gn:admin1_code":"45",
    "gn:asciiname":"Mashkullore",
    "gn:cc2":"AL",
    "gn:country_code":"AL",
    "gn:dem":438,
    "gn:feature_class":"P",
    "gn:feature_code":"PPL",
    "gn:name":"Mashkullor\u00eb",
    "gn:population":0,
    "gn:timezone":"Europe/Tirane",
    "iso:country":"AL",
    "name:und_x_variant":[
        "Masculori",
        "Mashkulleri",
        "Mashkullor",
        "Mashkullora",
        "Mashkullor\u00eb"
    ],
    "wof:name":"Mashkullore",
    "wof:placetype":"locality"
},
  "geometry": {"coordinates":[20.08667,40.1175],"type":"Point"}
}