{
  "type": "Feature",
  "properties": {
    "gn:admin1_code":"46",
    "gn:asciiname":"Diellas",
    "gn:cc2":"AL",
    "gn:country_code":"AL",
    "gn:dem":994,
    "gn:feature_class":"P",
    "gn:feature_code":"PPL",
    "gn:name":"Diellas",
    "gn:population":0,
    "gn:timezone":"Europe/Tirane",
    "iso:country":"AL",
    "name:mkd_x_preferred":[
        "\u0428\u0443\u043b\u0438\u043d"
    ],
    "name:und_x_variant":[
        "Sulin",
        "Djellas",
        "Shulini",
        "Djellasi",
        "Shulin",
        "Shullini",
        "Sciulin",
        "Suli",
        "Diellas"
    ],
    "wof:name":"Diellas",
    "wof:placetype":"locality"
},
  "geometry": {"coordinates":[20.91056,40.80222],"type":"Point"}
}