{
  "type": "Feature",
  "properties": {
    "gn:admin1_code":"44",
    "gn:admin2_code":"5.0",
    "gn:asciiname":"Dermenas",
    "gn:cc2":"AL",
    "gn:country_code":"AL",
    "gn:dem":4,
    "gn:feature_class":"P",
    "gn:feature_code":"PPLA3",
    "gn:name":"D\u00ebrm\u00ebnas",
    "gn:population":0,
    "gn:timezone":"Europe/Tirane",
    "iso:country":"AL",
    "name:und_x_variant":[
        "Dermena",
        "Derm\u00ebnasi",
        "Drmanas",
        "D\u00ebrm\u00ebnas",
        "Deremenas"
    ],
    "wof:name":"Dermenas",
    "wof:placetype":"locality"
},
  "geometry": {"coordinates":[19.49389,40.74556],"type":"Point"}
}