{
  "type": "Feature",
  "properties": {
    "gn:admin1_code":"44",
    "gn:asciiname":"Cukasi i Vjeter",
    "gn:cc2":"AL",
    "gn:country_code":"AL",
    "gn:dem":25,
    "gn:feature_class":"P",
    "gn:feature_code":"PPL",
    "gn:name":"\u00c7ukasi i Vjet\u00ebr",
    "gn:population":0,
    "gn:timezone":"Europe/Tirane",
    "iso:country":"AL",
    "name:und_x_variant":[
        "\u00c7ukas i Vjet\u00ebr",
        "\u00c7ukasi",
        "\u00c7ukas",
        "\u00c7ukasi i Vjet\u00ebr"
    ],
    "wof:name":"Cukasi i Vjeter",
    "wof:placetype":"locality"
},
  "geometry": {"coordinates":[19.78861,40.85083],"type":"Point"}
}