{
  "type": "Feature",
  "properties": {
    "gn:admin1_code":"43",
    "gn:asciiname":"Lipofnik",
    "gn:country_code":"AL",
    "gn:dem":580,
    "gn:feature_class":"P",
    "gn:feature_code":"PPL",
    "gn:name":"Lipofnik",
    "gn:population":0,
    "gn:timezone":"Europe/Tirane",
    "iso:country":"AL",
    "wof:name":"Lipofnik",
    "wof:placetype":"locality"
},
  "geometry": {"coordinates":[20.50667,41.07972],"type":"Point"}
}