{
  "type": "Feature",
  "properties": {
    "gn:admin1_code":"45",
    "gn:asciiname":"Lamaj",
    "gn:country_code":"AL",
    "gn:dem":693,
    "gn:feature_class":"P",
    "gn:feature_code":"PPL",
    "gn:name":"Lamaj",
    "gn:population":0,
    "gn:timezone":"Europe/Tirane",
    "iso:country":"AL",
    "wof:name":"Lamaj",
    "wof:placetype":"locality"
},
  "geometry": {"coordinates":[20.05556,40.40556],"type":"Point"}
}