{
  "type": "Feature",
  "properties": {
    "gn:admin1_code":"43",
    "gn:asciiname":"Shemat",
    "gn:country_code":"AL",
    "gn:dem":894,
    "gn:feature_class":"P",
    "gn:feature_code":"PPL",
    "gn:name":"Shemat",
    "gn:population":0,
    "gn:timezone":"Europe/Tirane",
    "iso:country":"AL",
    "wof:name":"Shemat",
    "wof:placetype":"locality"
},
  "geometry": {"coordinates":[20.24611,40.99083],"type":"Point"}
}