{
  "type": "Feature",
  "properties": {
    "gn:admin1_code":"46",
    "gn:asciiname":"Krickove",
    "gn:cc2":"AL",
    "gn:country_code":"AL",
    "gn:dem":678,
    "gn:feature_class":"P",
    "gn:feature_code":"PPL",
    "gn:name":"Kri\u00e7kov\u00eb",
    "gn:population":0,
    "gn:timezone":"Europe/Tirane",
    "iso:country":"AL",
    "name:und_x_variant":[
        "Kri\u00e7shova",
        "Kri\u00e7kova",
        "Kri\u00e7kov\u00eb"
    ],
    "wof:name":"Krickove",
    "wof:placetype":"locality"
},
  "geometry": {"coordinates":[20.52,40.98306],"type":"Point"}
}