{
  "type": "Feature",
  "properties": {
    "gn:admin1_code":"40",
    "gn:asciiname":"Veliaj",
    "gn:country_code":"AL",
    "gn:dem":746,
    "gn:feature_class":"P",
    "gn:feature_code":"PPL",
    "gn:name":"Veliaj",
    "gn:population":0,
    "gn:timezone":"Europe/Tirane",
    "iso:country":"AL",
    "wof:name":"Veliaj",
    "wof:placetype":"locality"
},
  "geometry": {"coordinates":[20.03389,40.54556],"type":"Point"}
}