{
  "type": "Feature",
  "properties": {
    "gn:admin1_code":"51",
    "gn:asciiname":"Lenge",
    "gn:cc2":"AL",
    "gn:country_code":"AL",
    "gn:dem":259,
    "gn:feature_class":"P",
    "gn:feature_code":"PPL",
    "gn:name":"Leng\u00eb",
    "gn:population":0,
    "gn:timezone":"Europe/Tirane",
    "iso:country":"AL",
    "name:und_x_variant":[
        "Lenga",
        "Leng\u00eb"
    ],
    "wof:name":"Lenge",
    "wof:placetype":"locality"
},
  "geometry": {"coordinates":[19.70778,40.21333],"type":"Point"}
}