{
  "type": "Feature",
  "properties": {
    "gn:admin1_code":"41",
    "gn:asciiname":"Kercishti i Poshtem",
    "gn:cc2":"AL",
    "gn:country_code":"AL",
    "gn:dem":742,
    "gn:feature_class":"P",
    "gn:feature_code":"PPL",
    "gn:name":"K\u00ebr\u00e7ishti i Posht\u00ebm",
    "gn:population":0,
    "gn:timezone":"Europe/Tirane",
    "iso:country":"AL",
    "name:und_x_variant":[
        "Dolna Kr\u010di\u0161ta",
        "Ker\u00e7ishta e Posth\u00ebr",
        "Ker\u00e7ishte e Posht\u00ebme",
        "K\u00ebr\u00e7isht i Posht\u00ebm",
        "K\u00ebr\u00e7ishti i Posht\u00ebm"
    ],
    "wof:name":"Kercishti i Poshtem",
    "wof:placetype":"locality"
},
  "geometry": {"coordinates":[20.50611,41.58611],"type":"Point"}
}