{
  "type": "Feature",
  "properties": {
    "gn:admin1_code":"43",
    "gn:asciiname":"Hasnjok",
    "gn:cc2":"AL",
    "gn:country_code":"AL",
    "gn:dem":601,
    "gn:feature_class":"P",
    "gn:feature_code":"PPL",
    "gn:name":"Hasnjok",
    "gn:population":0,
    "gn:timezone":"Europe/Tirane",
    "iso:country":"AL",
    "name:und_x_variant":[
        "Hasnjak",
        "Hasnjoku",
        "Hasnjok"
    ],
    "wof:name":"Hasnjok",
    "wof:placetype":"locality"
},
  "geometry": {"coordinates":[19.85028,41.10667],"type":"Point"}
}