{
  "type": "Feature",
  "properties": {
    "gn:admin1_code":"43",
    "gn:asciiname":"Selte",
    "gn:cc2":"AL",
    "gn:country_code":"AL",
    "gn:dem":683,
    "gn:feature_class":"P",
    "gn:feature_code":"PPL",
    "gn:name":"Selt\u00eb",
    "gn:population":0,
    "gn:timezone":"Europe/Tirane",
    "iso:country":"AL",
    "name:und_x_variant":[
        "Sel\u00e7\u00eb",
        "Selta",
        "Selt\u00eb"
    ],
    "wof:name":"Selte",
    "wof:placetype":"locality"
},
  "geometry": {"coordinates":[20.21806,40.96167],"type":"Point"}
}